Workbook
Name CompanyList: Company_List!$A$3:$A$207
Name DecisionList: Settings!$D$8:$D$10
Name DocumentList: Settings!$I$8:$I$12
Name QuarterList: Settings!$G$8:$G$12
Name RaterList: Settings!$A$8:$A$14
Name SectionList: Settings!$H$8:$H$11
Name TickerList: Company_List!$B$3:$B$207
Name YearList: Settings!$F$8:$F$14

Sheet Start_Here
A1: Start here
A3: What this workbook is | B3: The complete dataset and results for the model arm of the Citibank Applied Research Project. 361 model readings and 420 human readings, with every reported figure and its source.
A4: Read these four tabs first | B4: Results_Summary for every figure with its definition. Charts_Corrected for the figures. Efficiency_Corrected for cost and time. Confusion_Matrices for where the errors are.
A5: The one thing to understand before reading any number | B5: Accuracy is reported two ways from the same correct calls. SELECTIVITY asks whether the model was right when it committed to a direction, and reads 62.4% on 109 graded frozen events. COVERAGE asks whether it captured the available directional information, counts every HOLD on a moving event as a miss, and reads 46.9% on 145. Both are correct. Quoting one without the other is misleading.
A6: Three event sets, and which to quote | B6: FROZEN is 232 events and is the pre-registered primary. Lead with it. EXTENSION is 93 events across 20 companies added on 2026-08-14 and is descriptive only, since it yielded 18 graded events. COMBINED is all 325 and is a robustness check. Every figure in Results_Summary shows all three side by side.
A7: The sample is small and most comparisons are untestable | B7: Every frozen accuracy claim rests on 109 graded events, with a minimum detectable effect of roughly ±11 percentage points. The extension rests on 18, and is smaller again. A non-significant comparison here is underpowered rather than null, and the distinction matters.
A8: Thresholds were fitted in sample | B8: The deployed HOLD thresholds were chosen by maximising a compounded return the study no longer reports, on the full dataset with all events seen, and were not pre-registered. Every threshold-dependent figure carries that qualification. The walk-forward tab tests it.
A9: Two definitions of combined | B9: Main figures use COMBINED-FULL at 325 events. The baseline frontier uses COMBINED-EVAL at 279, because the baselines required a dev split for threshold fitting. Never compare a frontier figure against a non-frontier figure without checking which.
A10: Which tabs are working records rather than results | B10: The provenance and protocol tabs are working records rather than results. Corrections_Log, Findings, Anchor_Audit, Price_Basis_Note and the two superseded re-pricing tabs are referenced in several places but are NOT present in this workbook — they live in the repo. Summary, Charts and Efficiency are the original sheets, retained unchanged; they use the coverage convention and the Charts floor line sits on a different denominator from its bars. Use the corrected equivalents instead.
A11: Before you use it | B11: Open in Excel and press Ctrl+Alt+F9 to force a full recalculation. Several tabs are formula-driven and use XLOOKUP, which does not evaluate outside Excel.
A13: Prepared 14 August 2026; corrections applied through 24 August 2026. Figures on the corrected release_date anchor, frozen set N=232.

Sheet Results_Summary
A1: Results Summary — all three event sets
A2: Every figure appears on three sets. FROZEN (highlighted) is the pre-registered primary at 232 events and is what the written analysis leads with. EXTENSION is the 93 events added on 2026-08-14 across 20 companies the model arm had never scored, and is descriptive only at 18 graded events. COMBINED is all 325 events and is a robustness check, not a replacement. Accuracy is reported under two conventions because they answer different questions and neither travels alone.
A4: Headline result
A5: Metric | B5: FROZEN (primary) | C5: EXTENSION | D5: COMBINED | E5: Definition
A6: Selectivity accuracy | B6: 62.4% (68/109) | C6: 72.2% (13/18) | D6: 63.8% (81/127) | E6: Model committed to a direction AND |return| > 2%
A7: Majority-direction floor | B7: 54.1% | C7: 61.1% | D7: 55.1% | E7: Always predicting the majority realised direction, same denominator
A8: Margin over floor | B8: +8.3pp | C8: +11.1pp | D8: +8.7pp | E8: Accuracy minus its own floor
A9: Coverage accuracy | B9: 46.9% (68/145) | C9: 38.2% (13/34) | D9: 45.3% (81/179) | E9: All events with |return| > 2%; every HOLD counts as a miss
A10: Coverage floor | B10: 54.5% | C10: 50.0% | D10: — | E10: Majority direction on the coverage denominator
A11: Score-return rank correlation | B11: rho 0.2565, p=0.0001 | C11: rho 0.2715 | D11: — | E11: Spearman, blended score against realised overnight return. No threshold, no band, no selection
A12: Mean net per trade | B12: 1.7963% | C12: 1.4885% | D12: 1.7225% | E12: After 10bps round-trip cost
A13: Summed total return | B13: +303.80% | C13: +41.46% | D13: — | E13: Sum of independent per-trade returns. Not compounded, not an achievable balance. NOTE: on the N=233 / 169-trade vintage, not the corrected N=232 / 168 (Corrected_Metrics!F16).
A14: t-statistic on mean net | B14: 3.676 | C14: 1.362 | D14: — | E14: mean / sd × sqrt(n). Not a Sharpe ratio. NOTE: n=169 trades on the N=233 vintage (Corrected_Metrics!D17).
A15: Information ratio per trade | B15: 0.2828 | C15: 0.241 | D15: — | E15: mean / sd, unscaled. NOTE: n=169 trades on the N=233 vintage (Corrected_Metrics!D18).
A16: The two accuracy conventions are not in conflict and come from the same correct calls. Selectivity asks whether the model was right when it committed. Coverage asks whether it captured the available directional information, and it did not, because it stayed silent on 36 frozen events and 16 extension events that moved more than 2%. Quote neither without the other.
A18: Effective sample funnel
A19: Step | B19: FROZEN | C19: EXTENSION | D19: COMBINED | E19: Note
A20: Total scored | B20: 268 | C20: 93 | D20: 361 | E20: Events read by the model
A21: Excluded | B21: 36 | C21: 0 | D21: 36 | E21: 25 worksheet contamination, 1 misattributed document, 1 look-ahead document, 9 timing unresolved
A22: Clean universe | B22: 232 | C22: 93 | D22: 325 | E22: The reported universe
A23: Traded (BUY or SELL) | B23: 168 | C23: 53 | D23: 221 | E23: Trade rate 72.4% frozen against 57.0% extension
A24: Graded directionally | B24: 109 | C24: 18 | D24: 127 | E24: |return| > 2%, inside the pre-registered neutral band otherwise
A25: Correct | B25: 68 | C25: 13 | D25: 81
A26: Every accuracy claim rests on 109 graded events for the frozen set and 18 for the extension. The unpaired minimum detectable effect is roughly ±11pp on the frozen set, and the extension is smaller again, so the extension cannot test accuracy and its figures are descriptive only. The extension trade rate of 57.0% is itself a finding: the model held on 47.1% of extension events that moved more than 2% (16 of 34), against 24.8% on the frozen set (36 of 145).
A28: Signal decay by horizon (FROZEN)
A29: Horizon | B29: Mean net/trade | C29: Accuracy | D29: rho | E29: p (rho) | F29: Graded n
A30: Overnight | B30: 1.7963% | C30: 62.4% | D30: 0.2565 | E30: 0.0001 | F30: 109
A31: 1 day | B31: 1.1832% | C31: 60.2% | D31: 0.1952 | E31: 0.0028 | F31: 113
A32: 3 days | B32: 0.8296% | C32: 52.6% | D32: 0.1353 | E32: 0.0395 | F32: 114
A33: 5 days | B33: 0.9369% | C33: 51.9% | D33: 0.0972 | E33: 0.1401 | F33: 106
A34: 10 days | B34: 1.4455% | C34: 57.0% | D34: 0.0951 | E34: 0.1488 | F34: 114
A35: Mean net per trade declines from 1.80% overnight to a trough of 0.83% at three days and partially recovers by ten (1.45%); the bootstrap interval touches zero at three and five days. The overnight window remains the measured choice; the recovery at ten days leaves longer-horizon drift an open question rather than ruled out. Note that the excess-over-SPY column in returns_matrix.csv is a separate per-event diagnostic and is not monotonic; its shape reflects SPY’s own multi-horizon pattern across those entry dates, not the model.
A37: Human arm versus model (FROZEN)
A38: Comparison | B38: Human | C38: Model | D38: Difference | E38: p | F38: MDE | G38: n
A39: Direction-only, both committed | B39: 57.6% | C39: 58.8% | D39: +1.2pp | E39: 0.889 | F39: ±21pp | G39: 85
A40: Versus always-DOWN floor 52.9% | B40: +4.7pp | C40: +5.9pp | D40: — | E40: 0.224 / 0.164 | F40: — | G40: 85
A41: SELL calls | B41: 72.7% | C41: 69.2% | D41: — | E41: 0.026 / 0.038 | F41: — | G41: 22 / 26
A42: BUY calls | B42: 52.4% | C42: 54.2% | D42: — | E42: 0.401 / 0.301 | F42: — | G42: 63 / 59
A43: Cohen’s kappa | B43: 0.1391 | D43: CI 0.049 to 0.229 | E43: — | F43: — | G43: 170
A44: Neither arm beats the naive floor by a testable margin and the difference between them is untestable rather than absent. Both clear chance on SELL calls and neither clears chance on BUY. Against the base rate rather than 50% the SELL margins soften to p=0.060 and 0.087. Kappa near zero means the two arms are close to independent, which is why their agreement carries no information about accuracy.
A46: Decision mix
A47: Call | B47: Human (170 paired) | C47: Model (170 paired) | D47: Model (EXTENSION) | E47: Note
A48: BUY | B48: 55.9% | C48: 42.4% | D48: 44.1% | E48: Human arm is directionally optimistic
A49: HOLD | B49: 23.5% | C49: 31.2% | D49: 43.0% | E49: Model holds far more, and more still on the extension
A50: SELL | B50: 20.6% | C50: 26.5% | D50: 12.9% | E50: Two arms with opposite dispositions
A52: Section ablation (Item C)
A53: Arm | B53: FROZEN accuracy | C53: FROZEN cost/correct | D53: EXTENSION accuracy | E53: Mean tokens
A54: Full bundle | B54: 64.6% | C54: $0.0369 | D54: 40.7% | E54: 30096
A55: Press release | B55: 64.9% | C55: $0.0225 | D55: 45.5% | E55: 13030
A56: Prepared remarks | B56: 64.4% | C56: $0.0187 | D56: 41.7% | E56: 10287
A57: Q&A only | B57: 69.2% | C57: $0.0220 | D57: 34.6% | E57: 13163
A58: Accuracy differences sit inside the paired MDE of about ±12pp on the frozen set. At the promoted constants on the corrected returns no arm separates from the full bundle: the largest inclusive paired gap is the press release at −3.1pp (p=0.53, n=49), and when both arms commit on a moved event they agree far more often than they differ. Prepared remarks reproduces the full-bundle signal on 87.4% of events (104/119) at roughly a third of the tokens, which remains the deployment answer: indistinguishable accuracy at lower cost. The extension ablation rests on 19 graded events among its 56 four-arm events (corrected returns) and is descriptive only.
A60: Baseline frontier — coverage convention
A61: Method | B61: FROZEN | C61: EXTENSION | D61: COMBINED-EVAL | E61: Note
A62: Majority direction (floor) | B62: 54.6% | C62: 50.0% | D62: 53.6% | E62: Always predicting the majority realised direction
A63: Deployed model | B63: 48.7% | C63: 38.2% | D63: 46.4% | E63: HOLD counted as wrong
A64: FinBERT | B64: 17.6% | C64: 14.7% | D64: 17.0% | E64: ProsusAI/finbert, chunk-weighted
A65: Loughran-McDonald | B65: 3.4% | C65: 2.9% | D65: 3.3% | E65: Word-count dictionary
A66: Graded n | B66: 119 | C66: 34 | D66: 153 | E66: Denominator for the column above
A67: Coverage convention throughout: every graded event is in the denominator regardless of the model’s call, so the model reads 48.7%, 38.2% and 46.4% rather than the 62.4% and 72.2% selectivity headlines. COMBINED-EVAL is 279 events, the frozen eval split of 186 plus the 93 extension events, because the baselines required a dev split for threshold fitting and cannot use the full 325. Do not compare a frontier figure against a non-frontier figure without that distinction. On the corrected basis every baseline sits below its floor in every column, and the earlier reversal story is gone: FinBERT now trades 31% of extension events against the model’s 57%, and its extension coverage (14.7%) sits far below the model’s 38.2%.
A69: Walk-forward (Item E)
A70: Objective | B70: FROZEN degenerate | C70: COMBINED degenerate | D70: Pooled OOS (frozen) | E70: Note
A71: Mean net per trade | B71: 4/4 | C71: 4/4 | D71: 5 trades, 50.0% | E71: Fits the same extreme thresholds (+0.50/−0.50) in all four windows on both sets (frozen training n 99–229, combined 138–320). Not converging
A72: Directional accuracy | B72: 1/4 | C72: 1/4 | D72: 38 trades, 65.4% | E72: Test trades thin as the fitted thresholds drift extreme: 19/12/5/2 across the frozen windows
A73: Pooled OOS floor | B73: — | C73: 65.4% | D73: gap +0.0pp | E73: Floor ties the pooled accuracy exactly (both 17/26), so the pooled OOS carries no margin at all
A74: The two objectives behave differently and that is the finding. Mean-net maximisation is structurally drawn to a wide band because trading rarely maximises the mean, so it will not become estimable by adding data. Directional accuracy is sample-limited and improving, plausibly estimable somewhere around 400 to 500 events on the observed trajectory, which is an extrapolation from two points rather than an estimate. All events were seen before the analysis, so this is retrospective validation and not out-of-sample in the pre-registered sense.
A76: Cost and execution
A77: Metric | B77: Value | C77: Basis | D77: Source
A78: Break-even round-trip cost | B78: 189.63 bps | C78: Mean net per trade, N=232 corrected anchor | D78: ext9_cost_grid_n233.json
A79: Deployed cost assumption | B79: 10 bps | C79: Round trip, zero slippage | D79: Settings!B4
A80: Extension scoring cost | B80: $0.77146 | C80: 93 events, measured per call | D80: first_run_costs.jsonl
A81: Extension ablation cost | B81: $1.72383 | C81: 298 calls across four arms | D81: section_ablation_extension_results.csv
A82: Per-event token cost is recorded for both sets. The frozen figures come from api_cost_ledger.csv and the extension figures from the per-issuer first_run_costs.jsonl files, which the ledger builder did not visit until it was corrected on 2026-08-14. No externally-cited realistic desk cost exists in this project, so no claim is made about whether the break-even exceeds realistic trading costs.
A84: Stated asymmetries between the sets
A85: Item | B85: FROZEN | C85: EXTENSION | D85: Consequence
A86: Ensemble consistency runs | B86: YES | C86: NO | D86: Output-stability claims apply to the frozen set only
A87: Document coverage | B87: 86.6% with a transcript | C87: 98.9% with a transcript | D87: The extension is better documented, so coverage cannot explain any shortfall
A88: Events excluded from the paired comparison | B88: 0 | C88: 3 | D88: Heineken FQ3 2025, Shell FQ3 and FQ4 2025, not like for like
A89: Trade rate | B89: 72.4% | C89: 57.0% | D89: The extension held on 47.1% of events that moved (16 of 34), against 24.8% frozen (36 of 145)
A91: Human arm performance by rater (frozen and extension combined)
A92: Rater | B92: Trades | C92: Correct | D92: Wrong | E92: Flat | F92: Accuracy | G92: Mean net per trade
A93: Abdul | B93: 48 | C93: 26 | D93: 9 | E93: 13 | F93: 0.542 | G93: 0.02167
A94: Anna | B94: 49 | C94: 18 | D94: 16 | E94: 15 | F94: 0.367 | G94: 0.01594
A95: David | B95: 56 | C95: 13 | D95: 30 | E95: 13 | F95: 0.232 | G95: -0.02429
A96: Dragos | B96: 65 | C96: 14 | D96: 16 | E96: 35 | F96: 0.215 | G96: -0.00227
A97: Meriem | B97: 36 | C97: 14 | D97: 10 | E97: 12 | F97: 0.389 | G97: 0.01232
A98: Nigel | B98: 52 | C98: 12 | D98: 16 | E98: 24 | F98: 0.231 | G98: -0.00599
A99: Each rater read between 36 and 65 traded events, so every figure rests on a small sample and the spread between raters is largely noise rather than skill. On roughly 50 trades apiece the intervals overlap comfortably and no ranking should be read into the order. A pooled human figure is not reported because raters read overlapping events, so pooling counts shared events several times and reflects the mix of rater coverage rather than event economics. Accuracy here counts flat outcomes in the denominator.

Sheet Charts_Corrected
A1: Charts — three event sets
A2: Charts on the corrected release_date anchor. Each floor is computed on the same denominator as the bars it sits against. FROZEN is the pre-registered primary; EXTENSION is descriptive only at 18 graded events. The legacy Charts sheet is retained unchanged and uses the coverage convention with a mismatched floor.
A4: 1. Selectivity accuracy against its floor, all three sets
A5: Set | B5: Accuracy | C5: Majority-direction floor
A6: Frozen (n=109) | B6: =B78/B77 | C6: =VALUE(Corrected_Metrics!B11)
A7: Extension (n=18) | B7: 0.722 | C7: 0.611
A8: Combined (n=127) | B8: =D78/D77 | C8: 0.551
A12: 2. Coverage accuracy against its floor
A13: Set | B13: Accuracy | C13: Coverage floor
A14: Frozen (n=145) | B14: =VALUE(Corrected_Metrics!B13) | C14: =VALUE(Corrected_Metrics!B14)
A15: Extension (n=34) | B15: 0.382 | C15: 0.5
A16: Combined (n=179) | B16: =Sector_Breakdown!E29/Sector_Breakdown!D29 | C16: 0.536
A20: 3. Rank correlation decays with horizon (frozen)
A21: Horizon | B21: Rank correlation (rho)
A22: Overnight | B22: 0.257
A23: 1 day | B23: 0.1952
A24: 3 days | B24: 0.1353
A25: 5 days | B25: 0.0972
A26: 10 days | B26: 0.0951
A30: 4. Accuracy and return decay with horizon (frozen)
A31: Horizon | B31: Accuracy | C31: Mean net per trade
A32: Overnight | B32: 0.624 | C32: 0.01796
A33: 1 day | B33: 0.602 | C33: 0.01183
A34: 3 days | B34: 0.526 | C34: 0.00830
A35: 5 days | B35: 0.519 | C35: 0.00937
A36: 10 days | B36: 0.570 | C36: 0.01446
A40: 5. Directional accuracy by call type (170-paired subset; graded on returns_matrix overnight, ±2% band; floor = base rate of that direction among the 97 graded paired events)
A41: Call | B41: Human | C41: Model | D41: Floor for that call
A42: BUY | B42: 0.491 | C42: 0.512 | D42: 0.392
A43: SELL | B43: 0.739 | C43: 0.808 | D43: 0.608
A47: 6. Section ablation — accuracy and cost (frozen)
A48: Arm | B48: Accuracy | C48: Cost per correct call
A49: Full bundle | B49: 0.646 | C49: 0.0369
A50: Press release | B50: 0.649 | C50: 0.0225
A51: Prepared remarks | B51: 0.644 | C51: 0.0187
A52: Q&A only | B52: 0.692 | C52: 0.022
A56: 7. Baseline frontier — conventions differ by column: see notes on the header row
A57: Method | B57: Frozen | C57: Extension | D57: Combined-eval
A58: Majority floor | B58: =VALUE(Corrected_Metrics!B90) | C58: 0.5 | D58: 0.536
A59: Deployed model | B59: =VALUE(Corrected_Metrics!B96) | C59: 0.382 | D59: 0.464
A60: FinBERT | B60: =VALUE(Corrected_Metrics!B94) | C60: 0.147 | D60: 0.17
A61: Loughran-McDonald | B61: =VALUE(Corrected_Metrics!B92) | C61: 0.029 | D61: 0.033
A65: 8. Decision mix — how often each arm commits
A66: Call | B66: Human (170 paired) | C66: Model (170 paired) | D66: Model extension
A67: BUY | B67: 0.559 | C67: 0.424 | D67: 0.441
A68: HOLD | B68: 0.235 | C68: 0.312 | D68: 0.43
A69: SELL | B69: 0.206 | C69: 0.265 | D69: 0.129
A73: 9. Effective sample funnel, all three sets
A74: Step | B74: Frozen | C74: Extension | D74: Combined
A75: Clean universe | B75: 232 | C75: 93 | D75: 325
A76: Traded | B76: 168 | C76: 53 | D76: 221
A77: Graded | B77: 109 | C77: 18 | D77: 127
A78: Correct | B78: 68 | C78: 13 | D78: 81

Sheet Trader_View
A1: Trader view — the operational questions
A2: The cuts a desk asks for before deploying a signal: does conviction predict reliability, what does the return distribution look like, where is the left tail, does the edge concentrate in large moves, and how does the accuracy-versus-coverage trade-off behave across the whole band rather than at one threshold. All figures are the frozen 232-event universe unless stated.
A4: 1. Does conviction predict reliability?
A5: Score band | B5: Graded n | C5: Correct | D5: Accuracy
A6: SELL, below −0.30 | B6: 18 | C6: 13 | D6: 0.722
A7: SELL, −0.30 to −0.15 | B7: 9 | C7: 7 | D7: 0.778
A8: SELL, −0.15 to −0.10 | B8: 7 | C8: 6 | D8: 0.857
A9: BUY, +0.20 to +0.35 | B9: 43 | C9: 21 | D9: 0.488
A10: BUY, +0.35 to +0.45 | B10: 14 | C10: 9 | D10: 0.643
A11: BUY, above +0.45 | B11: 18 | C11: 12 | D11: 0.667
A13: The two sides behave differently. On the BUY side accuracy rises with conviction, 48.8% to 64.3% to 66.7%, which is what a desk would want for position sizing. On the SELL side it falls as conviction strengthens, 85.7% to 77.8% to 72.2%, so a strong sell signal is no more reliable than a marginal one — though the −0.15 to −0.10 band holds only seven events. The usable statement is unchanged: conviction is weakly informative on BUY calls and uninformative on SELL calls. These six bands tile all 109 graded traded events at the deployed thresholds (+0.20/−0.10), and the counts sum to the 68/109 = 62.4% selectivity headline.
A15: 2. What does the return distribution look like?
A16: Bucket | B16: Trades
A17: Loss worse than −10% | B17: 1
A18: −10% to −5% | B18: 17
A19: −5% to 0% | B19: 48
A20: 0% to +5% | B20: 62
A21: +5% to +10% | B21: 25
A22: Above +10% | B22: 15
A24: Statistic | B24: Value
A25: Mean net per trade | B25: 1.7963%
A26: Median net per trade | B26: +0.950%
A27: Best trade | B27: +32.06%
A28: Worst trade | B28: −14.62%
A29: Losing trades | B29: 66 of 168 (39.3%)
A30: Losses worse than 5% | B30: 18 trades
A31: Losses worse than 10% | B31: 1 trade
A33: The mean sits above the median, so the average is pulled up by the right tail, but not dominated by it: removing the single best trade moves the mean from +1.7963% to +1.615%. Thirty-nine per cent of trades lose money and one loses more than 10%, which is the exposure a desk would size against. This is a positive expectancy with a fat right tail rather than a high win rate.
A35: 3. Does the edge concentrate in large moves?
A36: Move size | B36: Graded n | C36: Accuracy | D36: Mean net per trade
A37: 2% to 5% | B37: 49 | C37: 0.531 | D37: 0.0009
A38: 5% to 10% | B38: 44 | C38: 0.614 | D38: 0.0153
A39: Above 10% | B39: 16 | C39: 0.938 | D39: 0.1398
A41: This is the strongest operational finding in the study. On events that moved more than 10% the model was right 93.8% of the time at a mean of +13.98% per trade, against 53.1% and +0.09% on 2 to 5% moves. The signal is most reliable precisely where the money is. The caveat is that 16 events cannot carry a strong claim and the direction of causation is open: large moves may simply be easier to read because the document language is less ambiguous.
A43: 4. The accuracy-versus-coverage trade-off across the whole band
A44: HOLD band | B44: Graded n | C44: Accuracy
A45: ±0% | B45: 167 | C45: 0.611
A46: ±1% | B46: 137 | C46: 0.620
A47: ±2% (pre-registered) | B47: 109 | C47: 0.624
A48: ±3% | B48: 82 | C48: 0.671
A49: ±4% | B49: 70 | C49: 0.671
A50: ±5% | B50: 60 | C50: 0.7
A52: Accuracy rises monotonically as the band widens and the graded count falls, from 61.1% on 167 events at no band to 70.0% on 60 events at ±5%. The pre-registered ±2% sits low on that curve, so the choice was conservative rather than flattering: a wider band would have produced a higher headline. Showing the whole curve rather than one point is the direct answer to the objection that the band was fitted, since the shape holds at every threshold.
A54: 5. Mean net per trade across the three sets
A55: Set | B55: Trades | C55: Mean net per trade
A56: Frozen | B56: 168 | C56: 0.017963
A57: Extension | B57: 53 | C57: 0.014885
A58: Combined | B58: 221 | C58: 0.017225
A60: 6. Mean net per trade, model against each rater
A61: Arm | B61: Trades | C61: Mean net per trade | D61: Unweighted mean of the six rater means — the model row is excluded from this average; not a pooled human figure
A62: Model | B62: 168 | C62: 0.017963 | D62: 0.00309
A63: Abdul | B63: 48 | C63: 0.02123
A64: Meriem | B64: 36 | C64: 0.01309
A65: Anna | B65: 49 | C65: 0.01183
A66: Dragos | B66: 65 | C66: -0.00247
A67: Nigel | B67: 52 | C67: 5e-05
A68: David | B68: 56 | C68: -0.02522
A70: Each rater traded between 36 and 65 events, so the spread across raters is largely noise and no ranking should be read into the order. The model sits inside the human range rather than above it, which is the honest reading: one rater beat it and five did not, on samples too small to separate. No pooled human figure is shown, since raters read overlapping events and pooling would count shared events several times. Rater means are on the re-priced basis (column AK); trades without a re-priced price stay in the trade count but drop from the mean — Nigel: 34 of 52 priced (the ALV.DE, STAN.L, DELL, PLTR and WDAY rows have no re-priced prices). Disney FQ1 2025 stays in Meriem’s row: the human arm keeps all 420 readings (see A92 on Accuracy_Conventions).

Sheet Efficiency_Corrected
A1: Efficiency — corrected figures
A2: Cost and time on the corrected anchor. Model cost is measured per call from the API logs. Human time is recorded reading time per event. The two are different currencies and the comparison is indicative rather than a like-for-like unit cost.
A4: Cost per correct directional call, by section arm (frozen)
A5: Arm | B5: Cost per correct call | C5: Mean tokens
A6: Full bundle | B6: 0.0369 | C6: 30096
A7: Press release | B7: 0.0225 | C7: 13030
A8: Prepared remarks | B8: 0.0187 | C8: 10287
A9: Q&A only | B9: 0.022 | C9: 13163
A13: Human reading time by information set
A14: Information set | B14: Mean minutes | C14: Readings
A15: Press release only | B15: 15 | C15: 19
A16: Guidance only | B16: 18.7 | C16: 29
A17: Presentation only | B17: 19.8 | C17: 23
A18: Financials only | B18: 20.3 | C18: 32
A19: Q&A only | B19: 29.4 | C19: 33
A20: Full document | B20: 29.8 | C20: 190
A21: Transcript only | B21: 33.5 | C21: 94
A25: API cost and break-even
A26: Item | B26: Value | C26: Basis
A27: Extension scoring total | B27: $0.77146 | C27: 93 events, measured per call
A28: Extension ablation total | B28: $1.72383 | C28: 298 calls across four arms
A29: Break-even round trip | B29: 189.63 bps | C29: Mean net per trade, N=232
A30: Deployed cost assumption | B30: 10 bps | C30: Round trip, zero slippage
A32: Per-event token cost is recorded for both sets. Frozen figures come from api_cost_ledger.csv. Extension figures come from the per-issuer first_run_costs.jsonl files, which the ledger builder did not visit until it was corrected on 2026-08-14: it built its issuer list from the frozen naming convention and never matched the extension output folders, so the ledger showed nothing for those 93 events while the data sat on disk. The figures are measured, not allocated averages. No externally-cited realistic desk cost exists in this project, so no claim is made about whether the break-even exceeds realistic trading costs.
A34: Model against human: two currencies, reported separately
A35: Measure | B35: Model arm | C35: Human arm | D35: Note
A36: Correct directional calls | B36: 68 | C36: 155 | D36: Model on 109 graded events; human on 420 readings, re-priced correctness (col AJ; 20 rows carry no re-priced flag)
A37: Total cost | B37: $1.14 | C37: 195.3 hours | D37: API spend against recorded reading time
A38: Per correct call | B38: $0.0369 | C38: 75.6 minutes | D38: The two headline unit figures
A39: Per document | B39: $0.0096 | C39: 27.9 minutes | D39: Mean across all readings
A40: Fastest unit | B40: $0.0187 (prepared remarks) | C40: 17.2 minutes (fastest rater) | D40: Cheapest arm is also the fastest, at 12.09 s median on the extension
A42: Deliberately not converted to a common currency. Turning reading time into money requires choosing an hourly rate, and any resulting ROI figure would inherit that choice rather than measure anything. The two facts stand on their own: the model produces a correct directional call for about three and a half cents, and a human takes about seventy-five minutes. A sensitivity block follows for anyone who wants the conversion, with the rate stated rather than assumed.
A44: Sensitivity: human cost per correct call at various hourly rates
A45: Hourly rate | B45: Cost per correct call | C45: Multiple of model cost
A46: £25 | B46: £31.29 | C46: 848×
A47: £50 | B47: £62.58 | C47: 1,696×
A48: £75 | B48: £93.88 | C48: 2,544×
A49: £100 | B49: £125.17 | C49: 3,392×
A50: £150 | B50: £187.75 | C50: 5,088×
A52: At 75.6 minutes per correct call, the human unit cost is the hourly rate multiplied by 1.260. The multiple against the model assumes $0.0369 per correct call at parity between pound and dollar, so treat it as an order of magnitude rather than a figure. The point is the scale of the gap, which holds across every plausible rate, not the precise number at any one of them.
A54: Time against the decision window
A55: Measure | B55: Value | C55: Note
A56: Overnight decision window | B56: roughly 15 hours | C56: Release-day close to next-session open
A57: Model time per document | B57: 15.0 s median | C57: Real per-call latency, 624 calls; IQR 12.95 to 17.31 s
A58: Human mean per document | B58: 27.9 minutes | C58: Recorded reading time
A59: Human total across the corpus | B59: 195.3 hours | C59: 420 readings across six raters
A60: Documents a human could read in the window | B60: roughly 32 | C60: At the mean reading time, without breaks
A62: The operational argument the model wins outright. A desk covering thirty companies reporting on the same evening cannot read them all by the open; the model can. Note that per-event model runtime was not logged, so the seconds figure is an observation rather than a measurement, and the human times carry an unexplained anomaly: transcript-only reads averaged 33.5 minutes against 29.8 for full-document reads, which is counterintuitive and unresolved.
A64: Model latency — measured, not assumed
A65: Group | B65: Calls | C65: Mean (s) | D65: Median (s) | E65: Q1 (s) | F65: Q3 (s) | G65: Range (s)
A66: All micro-layer calls | B66: 624 | C66: 15.92 | D66: 15 | E66: 12.95 | F66: 17.31 | G66: 7.52 to 126.99
A67: Frozen events | B67: 523 | C67: 15.86 | D67: 15.1 | E67: 13.03 | F67: 17.82 | G67: 7.52 to 100.65
A68: Extension events | B68: 101 | C68: 16.23 | D68: 14.25 | E68: 12.82 | F68: 15.68 | G68: 9.89 to 126.99
A70: Per-call latency was logged throughout in the per-issuer run logs and was never surfaced. The legacy Efficiency tab uses an 8-second placeholder that appears in no committed file, and the 212x and 118x speed multiples on that tab were computed from it. Both are superseded by the figures here. Source: model_latency_2026-08-15.csv, drawn from outputs/p2_*/logs/first_run_costs.jsonl across all 91 issuers, success calls only.
A72: Speed against the human arm, stated as a range
A73: Comparison | B73: Human | C73: Model | D73: Multiple | E73: Basis
A74: Per document, full-document readers | B74: 29.8 min (1,788 s) | C74: 12.95 to 17.31 s | D74: 103x to 138x | E74: Human full arm against the model interquartile range
A75: Per document, all information sets | B75: 27.9 min (1,674 s) | C75: 12.95 to 17.31 s | D75: 97x to 129x | E75: Human pooled mean against the same range
A76: Per correct directional call | B76: 149.2 min | C76: 2.0 min (122.0 s) | D76: about 73x | E76: Human full-document arm: 5,668 min over 38 graded-correct readings (re-priced basis); model 8,293 s over 68 correct
A78: Reported as a range because latency varies by a factor of six across calls, from 7.5 to 127 seconds, so a single point figure would mislead. The per-correct-call multiple is roughly half the per-document one, because the model holds more often and therefore produces fewer correct calls per unit of time. That is the harder and fairer comparison. Note that the two arms cover different events, so this is an efficiency comparison rather than a like-for-like race.
A80: Latency by section arm — the cheaper arm is also the faster one
A81: Arm | B81: Frozen mean (s) | C81: Frozen median (s) | D81: Extension mean (s) | E81: Extension median (s)
A82: Full bundle | B82: 16.36 | C82: 15.31 | D82: 17.53 | E82: 15.41
A83: Press release | B83: 14.14 | C83: 13.07 | D83: 13.32 | E83: 13.03
A84: Prepared remarks | B84: 15.34 | C84: 13.99 | D84: 12.52 | E84: 12.09
A85: Q&A only | B85: 13.47 | C85: 13.19 | D85: 13.73 | E85: 13.21
A87: Prepared remarks and press release run 2 to 3 seconds faster than the full bundle, so the cheaper arm is cheaper in tokens, cheaper per correct call and faster. Three independent reasons pointing the same way. Two outliers above 200 seconds were excluded as probable network timeouts and are named in the source file.
A89: Why latency barely tracks document length
A90: Measure | B90: Value
A91: Rank correlation, tokens against latency | B91: 0.4414
A92: Fitted intercept | B92: 14.08 s
A93: Fitted slope | B93: 0.077 s per 1,000 tokens
A94: Predicted at 10,000 tokens | B94: 14.85 s
A95: Predicted at 30,000 tokens | B95: 16.38 s
A96: Predicted at 50,000 tokens | B96: 17.91 s
A98: Most of the 14-second baseline is network and queue overhead rather than reading, so a 30,000-token full bundle is only about 1.5 seconds slower than a 13,000-token press release. Two consequences worth stating: the speed advantage does not erode with document length, so it holds for long filings as well as short releases; and the 2 to 3 second gap between section arms is mostly a token-count effect rather than anything about the sections themselves.

Sheet Confusion_Matrices
A2: (a) Model call vs realised outcome — N=232 clean events, pre-registered ±2% overnight band
B4: Outcome UP (ret>2%) | C4: Outcome FLAT (|ret|≤2%) | D4: Outcome DOWN (ret<-2%) | E4: Row total | F4: Precision (correct/called_dir) | G4: Recall (correct/realised_dir)
A5: Call BUY | B5: =COUNTIFS(LLM_Data_Entry!$BA$3:$BA$354,"YES",LLM_Data_Entry!$H$3:$H$354,"BUY",LLM_Data_Entry!$Q$3:$Q$354,"UP") | C5: =COUNTIFS(LLM_Data_Entry!$BA$3:$BA$354,"YES",LLM_Data_Entry!$H$3:$H$354,"BUY",LLM_Data_Entry!$Q$3:$Q$354,"FLAT") | D5: =COUNTIFS(LLM_Data_Entry!$BA$3:$BA$354,"YES",LLM_Data_Entry!$H$3:$H$354,"BUY",LLM_Data_Entry!$Q$3:$Q$354,"DOWN") | E5: =SUM(B5:D5) | F5: =B5&"/"&E5
A6: Call HOLD | B6: =COUNTIFS(LLM_Data_Entry!$BA$3:$BA$354,"YES",LLM_Data_Entry!$H$3:$H$354,"HOLD",LLM_Data_Entry!$Q$3:$Q$354,"UP") | C6: =COUNTIFS(LLM_Data_Entry!$BA$3:$BA$354,"YES",LLM_Data_Entry!$H$3:$H$354,"HOLD",LLM_Data_Entry!$Q$3:$Q$354,"FLAT") | D6: =COUNTIFS(LLM_Data_Entry!$BA$3:$BA$354,"YES",LLM_Data_Entry!$H$3:$H$354,"HOLD",LLM_Data_Entry!$Q$3:$Q$354,"DOWN") | E6: =SUM(B6:D6) | F6: =C6&"/"&E6
A7: Call SELL | B7: =COUNTIFS(LLM_Data_Entry!$BA$3:$BA$354,"YES",LLM_Data_Entry!$H$3:$H$354,"SELL",LLM_Data_Entry!$Q$3:$Q$354,"UP") | C7: =COUNTIFS(LLM_Data_Entry!$BA$3:$BA$354,"YES",LLM_Data_Entry!$H$3:$H$354,"SELL",LLM_Data_Entry!$Q$3:$Q$354,"FLAT") | D7: =COUNTIFS(LLM_Data_Entry!$BA$3:$BA$354,"YES",LLM_Data_Entry!$H$3:$H$354,"SELL",LLM_Data_Entry!$Q$3:$Q$354,"DOWN") | E7: =SUM(B7:D7) | F7: =D7&"/"&E7
A8: Col total | B8: =SUM(B5:B7) | C8: =SUM(C5:C7) | D8: =SUM(D5:D7) | E8: =SUM(B8:D8)
A9: Recall (correct/total_in_direction) | B9: =B5&"/"&B8 | C9: =C6&"/"&C8 | D9: =D7&"/"&D8
A10: ="Note: BUY-called-DOWN and SELL-called-UP are the costly directional errors. HOLD row against UP and DOWN is the coverage gap ("&(B6+D6)&" events that moved but were passed on). Matrix (a) is computed live from LLM_Data_Entry (In Clean Universe = YES); it previously held figures from a superseded threshold vintage that did not tie to the funnel."
A12: (b) Human arm vs realised outcome — N=170 paired events (section=All, first_rater=YES, in_llm=YES, exclusions applied)
B14: Outcome UP (ret>2%) | C14: Outcome FLAT (|ret|≤2%) | D14: Outcome DOWN (ret<-2%) | E14: Row total
A15: Call BUY | B15: 27 | C15: 40 | D15: 28 | E15: 95
A16: Call HOLD | B16: 5 | C16: 20 | D16: 15 | E16: 40
A17: Call SELL | B17: 6 | C17: 12 | D17: 17 | E17: 35
A18: Col total | B18: 38 | C18: 72 | D18: 60 | E18: 170
A19: Source: human_decisions_export_2026-08-12.csv + returns_matrix.csv
A21: (c) Human vs model agreement — N=170 paired events. Source: kappa_near_independence.csv (the committed CSV still holds the pre-exclusion 171-pair grid; this grid is that crosstab less DIS_FQ1_2025, verified against the paired rows in Human_Data_Entry and by re-running the script at the deployed constants)
A23: Human call \ LLM call | B23: LLM BUY | C23: LLM HOLD | D23: LLM SELL | E23: Row total
A24: Human BUY | B24: 53 | C24: 32 | D24: 10 | E24: =SUM(B24:D24)
A25: Human HOLD | B25: 13 | C25: 8 | D25: 19 | E25: =SUM(B25:D25)
A26: Human SELL | B26: 6 | C26: 13 | D26: 16 | E26: =SUM(B26:D26)
A28: Kappa | B28: 0.1391
A29: 90% CI | B29: [0.049, 0.229]
A30: Observed agreement | B30: 0.4529
A31: Expected agreement | B31: 0.3645

Sheet Item_C_Ablation
A1: PER-ARM ACCURACY AND COST
A2: event_set | B2: arm | C2: n_calls | D2: n_graded | E2: n_correct | F2: accuracy_hold_excluded | G2: mean_tokens_per_call | H2: total_cost_usd | I2: cost_per_call_usd | J2: cost_per_correct_usd
A3: four_arm_n119 | B3: full_bundle | C3: 119 | D3: 48 | E3: 31 | F3: =E3/D3 | G3: 30096 | H3: 1.1441 | I3: 0.0096 | J3: =H3/E3
A4: four_arm_n119 | B4: press_release | C4: 119 | D4: 37 | E4: 24 | F4: =E4/D4 | G4: 13030 | H4: 0.5394 | I4: 0.0045 | J4: =H4/E4
A5: four_arm_n119 | B5: prepared_remarks | C5: 119 | D5: 45 | E5: 29 | F5: =E5/D5 | G5: 10287 | H5: 0.5412 | I5: 0.0045 | J5: =H5/E5
A6: four_arm_n119 | B6: qa_only | C6: 119 | D6: 39 | E6: 27 | F6: =E6/D6 | G6: 13163 | H6: 0.5952 | I6: 0.005 | J6: =H6/E6
A7: all_n200 | B7: full_bundle | C7: 200 | D7: 70 | E7: 46 | F7: =E7/D7 | G7: 33130 | H7: 2.1166 | I7: 0.0106 | J7: =H7/E7
A8: all_n200 | B8: press_release | C8: 200 | D8: 56 | E8: 35 | F8: =E8/D8 | G8: 15298 | H8: 1.0149 | I8: 0.0051 | J8: =H8/E8
A9: all_n200 | B9: prepared_remarks | C9: 119 | D9: 45 | E9: 29 | F9: =E9/D9 | G9: 10287 | H9: 0.5412 | I9: 0.0045 | J9: =H9/E9
A10: all_n200 | B10: qa_only | C10: 119 | D10: 39 | E10: 27 | F10: =E10/D10 | G10: 13163 | H10: 0.5952 | I10: 0.005 | J10: =H10/E10
A12: Note: figures from section_ablation_cost_per_correct.csv DATA ROWS ONLY. four_arm_n119 = events where all 4 arms scored. all_n200 = full scored set for full_bundle and press_release.
A14: PAIRED DIFFERENCES VS FULL BUNDLE
A15: comparison | B15: set | C15: method | D15: n_paired | E15: point_diff | F15: ci_low | G15: ci_high | H15: p_value | I15: metric | J15: note
A16: press_release vs full_bundle | B16: four_arm | C16: strict (both graded) | D16: 36 | E16: 0.0278 | F16: 0.0 | G16: 0.0833 | H16: 0.7162 | I16: accuracy_overnight | J16: On the 36 both-graded events the press release is +2.8pp (p=0.72); the old zero-information identity did not survive the corrected returns
A17: press_release vs full_bundle | B17: four_arm | C17: inclusive (either graded, ungraded=0.5) | D17: 49 | E17: -0.0306 | F17: -0.1020 | G17: 0.0408 | H17: 0.5346 | I17: accuracy_overnight | J17: Full bundle +3.1pp inclusive (p=0.53) — inside the ±12pp paired MDE
A18: prepared_remarks vs full_bundle | B18: four_arm | C18: strict (both graded) | D18: 43 | E18: -0.0233 | F18: -0.0698 | G18: 0.0 | H18: 0.7284 | I18: accuracy_overnight
A19: prepared_remarks vs full_bundle | B19: four_arm | C19: inclusive (either graded, ungraded=0.5) | D19: 50 | E19: -0.0100 | F19: -0.0700 | G19: 0.0400 | H19: 0.8994 | I19: accuracy_overnight
A20: qa_only vs full_bundle | B20: four_arm | C20: strict (both graded) | D20: 38 | E20: 0.0263 | F20: -0.0526 | G20: 0.1053 | H20: 0.7804 | I20: accuracy_overnight
A21: qa_only vs full_bundle | B21: four_arm | C21: inclusive (either graded, ungraded=0.5) | D21: 49 | E21: 0.0102 | F21: -0.0714 | G21: 0.0918 | H21: 0.9390 | I21: accuracy_overnight
A23: Paired MDE ~±12pp. At the promoted constants on the corrected returns no arm separates from the full bundle: the largest inclusive gap is −3.1pp at p=0.53 (press release, n=49). The 2026-08-13 values (−6.8pp at p=0.055 on 66 pairs) came from pre-correction returns at the superseded thresholds and reproduce from no committed input under any pairing convention.
A24: Prepared remarks agrees with the full bundle on 87.4% of signals (104/119) at ~10k tokens.

Sheet Walk_Forward
A2: DEGENERACY FINDING
A4: n_windows | B4: 4
A5: min_trades_floor | B5: 5
A6: objectives_tried | B6: ['mean_net_per_trade', 'directional_accuracy']
A7: degeneracy_finding | B7: {'mean_net_degenerate': 4, 'accuracy_degenerate': 1, 'total_windows': 4, 'both_degenerate': True}
A8: mean_net_objective_n_degenerate | B8: 4
A9: accuracy_objective_n_degenerate | B9: 1
A11: IN-SAMPLE DEPLOYED THRESHOLDS
A13: hold_upper | B13: 0.2
A14: hold_lower | B14: -0.1
A15: n_trades | B15: 168
A16: n_graded | B16: 109
A17: n_correct | B17: 68
A18: accuracy | B18: 0.6239
A19: mean_net_pct | B19: 1.7963
A21: DEV / EVAL SPLIT
A23: Split rule | B23: Sort 232 clean events by release_date (returns_matrix.csv), earliest 20% (46) = dev, remaining 80% (186) = eval.
A24: Eval: accuracy | B24: 63.0% (58/92) | C24: floor=54.6% (65/119 graded) | D24: margin +8.4pp | E24: p=0.064 | F24: MDE ±14.4pp
A25: Dev: accuracy | B25: 58.8% (10/17) | C25: floor=53.8% (14/26 graded) | D25: margin +5.0pp | E25: NOT significant (p=0.436) | F25: MDE ±27.8pp — underpowered
A26: Source | B26: frontier_table.csv, surviving_findings.md
A27: NOT out-of-sample | B27: Dev/eval split applied post hoc to data thresholds were fitted on. Eval 63.0% is in-sample on a subset.
A28: Floor convention (2026-08-21): the dev/eval floors above are computed on all graded events while accuracy is on traded events. On a matched traded-only denominator the dev floor is 11/17 = 64.7% — above the dev accuracy of 58.8% — while eval survives its matched floor (48/92 = 52.2% vs 63.0%). Separately: the MDE figures ±14.4pp/±27.8pp here (and ±10.8pp on Corrected_Metrics) are unreproduced literals from experiments/build_workbook.py, recorded as such (Q3a).
A29: CROSS-ISSUER GENERALISATION (RECONSTRUCTED)
A31: note | B31: Cross-issuer generalisation test: 29 issuers (with clean events in N=232) scored after the N=161 threshold sweep, zero issuer overlap with the 40 in-sweep issuers. 2 further post-sweep issuers (Allianz, Lenovo) are fully timing-excluded. Both subsets span overlapping date ranges (interleaved, not sequential) — this tests issuer transfer, not temporal generalisation. RECONSTRUCTED: sweep membership inferred from issuer ordering and count match (n_documents=161), not from a recorded event list. 453 single-swap alternatives also produce 161.
A33: subset | B33: n_events | C33: n_trades | D33: n_graded | E33: n_correct | F33: accuracy | G33: mean_net_pct | H33: floor | I33: margin | J33: p | K33: mde
A34: in_sweep | B34: 131 | C34: 87 | D34: 50 | E34: 29 | F34: 0.58 | G34: 0.59
A35: post_sweep | B35: 101 | C35: 81 | D35: 59 | E35: 39 | F35: 0.661 | G35: 3.092 | H35: 0.5254 | I35: 13.6 | J35: 0.0244 | K35: 19.5
A37: CAVEATS (three)
A38: 1. RECONSTRUCTED | B38: Sweep membership inferred from issuer ordering and count match (n=161). 453 single-swap alternatives also give n=161.
A39: 2. ISSUER TRANSFER ONLY | B39: Both subsets overlap in time. Tests whether thresholds transfer to new companies, not new time periods. Does NOT corroborate temporal generalisation.
A40: 3. NOMINALLY SIGNIFICANT, STILL UNDERPOWERED | B40: p=0.0244 clears 0.05 nominally; MDE=±19.5pp — the subset stays underpowered and the RECONSTRUCTED caveat above still applies, so treat as suggestive.

Sheet Accuracy_Conventions
A1: Accuracy Conventions — Coverage vs Selectivity
A2: Coverage accuracy = YES / all events (HOLDs counted as failures when stock moved, credited as correct when stock stayed flat). Selectivity accuracy = correct direction / (traded-and-graded events only: BUY or SELL call AND |ret_overnight| > 2%). Neither figure travels alone: selectivity inflates when the HOLD rate is high, because the model can selectively avoid hard calls. The FLAT convention gives the LLM an advantage in the paired comparison because the LLM holds 31.2% of events vs the human arm's 23.5% (N=170 paired subset): when the LLM holds and the stock stays flat, it earns a YES; a human BUY/SELL on the same event would earn a NO. See methodology_flat_convention.md for full derivation.
A3: CROSS-CHECK NOTE (figures below are at the SUPERSEDED 0.55/0.45 constants, which is what was investigated on 2026-08-13; at the deployed 0.80/0.20 the arm reads 68/109 = 62.4%): the selectivity formula (H=BUY/SELL, Q=UP/DOWN) gives 61/94 = 64.9% for the LLM arm. The repo authoritative figure is 62/95 = 65.3% (from item_e_walkforward.json, run 20260812_183842). Discrepancy = 1 event. Cause: one event's |ret_overnight| is below the ±2% band in the current returns_matrix but was apparently above it in the ext2 run. The formula definition is correct; the 0.4pp deviation is documented here.
A5: COVERAGE ACCURACY (YES / all events)
A6: Denominator: all events for the arm (including HOLDs) | F6: Floor: majority direction / all events
A7: Arm | B7: n (denom) | C7: YES | D7: Accuracy | E7: Floor n_DOWN | F7: Floor prob | G7: p-value (1-sided) | H7: MDE (±, 90%) | I7: HOLD count | J7: HOLD rate | K7: Traded
A8: LLM (DeepSeek) | B8: =COUNTIFS(LLM_Data_Entry!$F$3:$F$430,"LLM",LLM_Data_Entry!$R$3:$R$430,"<>") | C8: =COUNTIFS(LLM_Data_Entry!$F$3:$F$430,"LLM",LLM_Data_Entry!$R$3:$R$430,"YES") | D8: =IF(B8=0,"",C8/B8) | E8: =COUNTIFS(LLM_Data_Entry!$F$3:$F$430,"LLM",LLM_Data_Entry!$Q$3:$Q$430,"DOWN") | F8: =IF(B8=0,"",E8/B8) | G8: =IFERROR(1 - _xlfn.SINGLE(_xlfn.BINOM.DIST(C8 - 1, B8, F8, TRUE)), "") | H8: =IFERROR(2*1.645*SQRT(F8*(1-F8)/B8),"") | I8: =COUNTIFS(LLM_Data_Entry!$F$3:$F$430,"LLM",LLM_Data_Entry!$H$3:$H$430,"HOLD") | J8: =IFERROR(I8/(I8+K8),"") | K8: =COUNTIFS(LLM_Data_Entry!$F$3:$F$430,"LLM",LLM_Data_Entry!$H$3:$H$430,"BUY")+COUNTIFS(LLM_Data_Entry!$F$3:$F$430,"LLM",LLM_Data_Entry!$H$3:$H$430,"SELL")
A9: Human (All) | B9: =COUNTIF(Human_Data_Entry!$S$3:$S$524,"YES")+COUNTIF(Human_Data_Entry!$S$3:$S$524,"NO") | C9: =COUNTIF(Human_Data_Entry!$S$3:$S$524,"YES") | D9: =IF(B9=0,"",C9/B9) | E9: =COUNTIF(Human_Data_Entry!$R$3:$R$524,"DOWN") | F9: =IF(B9=0,"",E9/B9) | G9: =IFERROR(1 - _xlfn.SINGLE(_xlfn.BINOM.DIST(C9 - 1, B9, F9, TRUE)), "") | H9: =IFERROR(2*1.645*SQRT(F9*(1-F9)/B9),"") | I9: =COUNTIF(Human_Data_Entry!$J$3:$J$524,"HOLD") | J9: =IFERROR(I9/(I9+K9),"") | K9: =COUNTIF(Human_Data_Entry!$J$3:$J$524,"BUY")+COUNTIF(Human_Data_Entry!$J$3:$J$524,"SELL")
A10: =Settings!$A$8 | B10: =COUNTIFS(Human_Data_Entry!$G$3:$G$524,A10,Human_Data_Entry!$S$3:$S$524,"<>") | C10: =COUNTIFS(Human_Data_Entry!$G$3:$G$524,A10,Human_Data_Entry!$S$3:$S$524,"YES") | D10: =IF(B10=0,"",C10/B10) | E10: =COUNTIFS(Human_Data_Entry!$G$3:$G$524,A10,Human_Data_Entry!$R$3:$R$524,"DOWN") | F10: =IF(B10=0,"",E10/B10) | G10: =IFERROR(1 - _xlfn.SINGLE(_xlfn.BINOM.DIST(C10 - 1, B10, F10, TRUE)), "") | H10: =IFERROR(2*1.645*SQRT(F10*(1-F10)/B10),"") | I10: =COUNTIFS(Human_Data_Entry!$G$3:$G$524,A10,Human_Data_Entry!$J$3:$J$524,"HOLD") | J10: =IFERROR(I10/(I10+K10),"") | K10: =COUNTIFS(Human_Data_Entry!$G$3:$G$524,A10,Human_Data_Entry!$J$3:$J$524,"BUY")+COUNTIFS(Human_Data_Entry!$G$3:$G$524,A10,Human_Data_Entry!$J$3:$J$524,"SELL")
A11: =Settings!$A$9 | B11: =COUNTIFS(Human_Data_Entry!$G$3:$G$524,A11,Human_Data_Entry!$S$3:$S$524,"<>") | C11: =COUNTIFS(Human_Data_Entry!$G$3:$G$524,A11,Human_Data_Entry!$S$3:$S$524,"YES") | D11: =IF(B11=0,"",C11/B11) | E11: =COUNTIFS(Human_Data_Entry!$G$3:$G$524,A11,Human_Data_Entry!$R$3:$R$524,"DOWN") | F11: =IF(B11=0,"",E11/B11) | G11: =IFERROR(1 - _xlfn.SINGLE(_xlfn.BINOM.DIST(C11 - 1, B11, F11, TRUE)), "") | H11: =IFERROR(2*1.645*SQRT(F11*(1-F11)/B11),"") | I11: =COUNTIFS(Human_Data_Entry!$G$3:$G$524,A11,Human_Data_Entry!$J$3:$J$524,"HOLD") | J11: =IFERROR(I11/(I11+K11),"") | K11: =COUNTIFS(Human_Data_Entry!$G$3:$G$524,A11,Human_Data_Entry!$J$3:$J$524,"BUY")+COUNTIFS(Human_Data_Entry!$G$3:$G$524,A11,Human_Data_Entry!$J$3:$J$524,"SELL")
A12: =Settings!$A$10 | B12: =COUNTIFS(Human_Data_Entry!$G$3:$G$524,A12,Human_Data_Entry!$S$3:$S$524,"<>") | C12: =COUNTIFS(Human_Data_Entry!$G$3:$G$524,A12,Human_Data_Entry!$S$3:$S$524,"YES") | D12: =IF(B12=0,"",C12/B12) | E12: =COUNTIFS(Human_Data_Entry!$G$3:$G$524,A12,Human_Data_Entry!$R$3:$R$524,"DOWN") | F12: =IF(B12=0,"",E12/B12) | G12: =IFERROR(1 - _xlfn.SINGLE(_xlfn.BINOM.DIST(C12 - 1, B12, F12, TRUE)), "") | H12: =IFERROR(2*1.645*SQRT(F12*(1-F12)/B12),"") | I12: =COUNTIFS(Human_Data_Entry!$G$3:$G$524,A12,Human_Data_Entry!$J$3:$J$524,"HOLD") | J12: =IFERROR(I12/(I12+K12),"") | K12: =COUNTIFS(Human_Data_Entry!$G$3:$G$524,A12,Human_Data_Entry!$J$3:$J$524,"BUY")+COUNTIFS(Human_Data_Entry!$G$3:$G$524,A12,Human_Data_Entry!$J$3:$J$524,"SELL")
A13: =Settings!$A$11 | B13: =COUNTIFS(Human_Data_Entry!$G$3:$G$524,A13,Human_Data_Entry!$S$3:$S$524,"<>") | C13: =COUNTIFS(Human_Data_Entry!$G$3:$G$524,A13,Human_Data_Entry!$S$3:$S$524,"YES") | D13: =IF(B13=0,"",C13/B13) | E13: =COUNTIFS(Human_Data_Entry!$G$3:$G$524,A13,Human_Data_Entry!$R$3:$R$524,"DOWN") | F13: =IF(B13=0,"",E13/B13) | G13: =IFERROR(1 - _xlfn.SINGLE(_xlfn.BINOM.DIST(C13 - 1, B13, F13, TRUE)), "") | H13: =IFERROR(2*1.645*SQRT(F13*(1-F13)/B13),"") | I13: =COUNTIFS(Human_Data_Entry!$G$3:$G$524,A13,Human_Data_Entry!$J$3:$J$524,"HOLD") | J13: =IFERROR(I13/(I13+K13),"") | K13: =COUNTIFS(Human_Data_Entry!$G$3:$G$524,A13,Human_Data_Entry!$J$3:$J$524,"BUY")+COUNTIFS(Human_Data_Entry!$G$3:$G$524,A13,Human_Data_Entry!$J$3:$J$524,"SELL")
A14: =Settings!$A$12 | B14: =COUNTIFS(Human_Data_Entry!$G$3:$G$524,A14,Human_Data_Entry!$S$3:$S$524,"<>") | C14: =COUNTIFS(Human_Data_Entry!$G$3:$G$524,A14,Human_Data_Entry!$S$3:$S$524,"YES") | D14: =IF(B14=0,"",C14/B14) | E14: =COUNTIFS(Human_Data_Entry!$G$3:$G$524,A14,Human_Data_Entry!$R$3:$R$524,"DOWN") | F14: =IF(B14=0,"",E14/B14) | G14: =IFERROR(1 - _xlfn.SINGLE(_xlfn.BINOM.DIST(C14 - 1, B14, F14, TRUE)), "") | H14: =IFERROR(2*1.645*SQRT(F14*(1-F14)/B14),"") | I14: =COUNTIFS(Human_Data_Entry!$G$3:$G$524,A14,Human_Data_Entry!$J$3:$J$524,"HOLD") | J14: =IFERROR(I14/(I14+K14),"") | K14: =COUNTIFS(Human_Data_Entry!$G$3:$G$524,A14,Human_Data_Entry!$J$3:$J$524,"BUY")+COUNTIFS(Human_Data_Entry!$G$3:$G$524,A14,Human_Data_Entry!$J$3:$J$524,"SELL")
A15: =Settings!$A$13 | B15: =COUNTIFS(Human_Data_Entry!$G$3:$G$524,A15,Human_Data_Entry!$S$3:$S$524,"<>") | C15: =COUNTIFS(Human_Data_Entry!$G$3:$G$524,A15,Human_Data_Entry!$S$3:$S$524,"YES") | D15: =IF(B15=0,"",C15/B15) | E15: =COUNTIFS(Human_Data_Entry!$G$3:$G$524,A15,Human_Data_Entry!$R$3:$R$524,"DOWN") | F15: =IF(B15=0,"",E15/B15) | G15: =IFERROR(1 - _xlfn.SINGLE(_xlfn.BINOM.DIST(C15 - 1, B15, F15, TRUE)), "") | H15: =IFERROR(2*1.645*SQRT(F15*(1-F15)/B15),"") | I15: =COUNTIFS(Human_Data_Entry!$G$3:$G$524,A15,Human_Data_Entry!$J$3:$J$524,"HOLD") | J15: =IFERROR(I15/(I15+K15),"") | K15: =COUNTIFS(Human_Data_Entry!$G$3:$G$524,A15,Human_Data_Entry!$J$3:$J$524,"BUY")+COUNTIFS(Human_Data_Entry!$G$3:$G$524,A15,Human_Data_Entry!$J$3:$J$524,"SELL")
A16: =Settings!$A$14 | B16: =COUNTIFS(Human_Data_Entry!$G$3:$G$524,A16,Human_Data_Entry!$S$3:$S$524,"<>") | C16: =COUNTIFS(Human_Data_Entry!$G$3:$G$524,A16,Human_Data_Entry!$S$3:$S$524,"YES") | D16: =IF(B16=0,"",C16/B16) | E16: =COUNTIFS(Human_Data_Entry!$G$3:$G$524,A16,Human_Data_Entry!$R$3:$R$524,"DOWN") | F16: =IF(B16=0,"",E16/B16) | G16: =IFERROR(1 - _xlfn.SINGLE(_xlfn.BINOM.DIST(C16 - 1, B16, F16, TRUE)), "") | H16: =IFERROR(2*1.645*SQRT(F16*(1-F16)/B16),"") | I16: =COUNTIFS(Human_Data_Entry!$G$3:$G$524,A16,Human_Data_Entry!$J$3:$J$524,"HOLD") | J16: =IFERROR(I16/(I16+K16),"") | K16: =COUNTIFS(Human_Data_Entry!$G$3:$G$524,A16,Human_Data_Entry!$J$3:$J$524,"BUY")+COUNTIFS(Human_Data_Entry!$G$3:$G$524,A16,Human_Data_Entry!$J$3:$J$524,"SELL")
A18: SELECTIVITY ACCURACY (correct / traded-and-graded events)
A19: Denominator: events where arm committed (BUY/SELL) AND |ret_overnight| > 2% | F19: Floor: DOWN outcomes / graded denominator
A20: Arm | B20: n (denom) | C20: YES | D20: Accuracy | E20: Floor n_DOWN | F20: Floor prob | G20: p-value (1-sided) | H20: MDE (±, 90%) | I20: HOLD count | J20: HOLD rate | K20: Traded
A21: LLM (DeepSeek) | B21: =COUNTIFS(LLM_Data_Entry!$F$3:$F$430,"LLM",LLM_Data_Entry!$H$3:$H$430,"BUY",LLM_Data_Entry!$Q$3:$Q$430,"UP")+COUNTIFS(LLM_Data_Entry!$F$3:$F$430,"LLM",LLM_Data_Entry!$H$3:$H$430,"BUY",LLM_Data_Entry!$Q$3:$Q$430,"DOWN")+COUNTIFS(LLM_Data_Entry!$F$3:$F$430,"LLM",LLM_Data_Entry!$H$3:$H$430,"SELL",LLM_Data_Entry!$Q$3:$Q$430,"UP")+COUNTIFS(LLM_Data_Entry!$F$3:$F$430,"LLM",LLM_Data_Entry!$H$3:$H$430,"SELL",LLM_Data_Entry!$Q$3:$Q$430,"DOWN") | C21: =COUNTIFS(LLM_Data_Entry!$F$3:$F$430,"LLM",LLM_Data_Entry!$H$3:$H$430,"BUY",LLM_Data_Entry!$Q$3:$Q$430,"UP")+COUNTIFS(LLM_Data_Entry!$F$3:$F$430,"LLM",LLM_Data_Entry!$H$3:$H$430,"SELL",LLM_Data_Entry!$Q$3:$Q$430,"DOWN") | D21: =IF(B21=0,"",C21/B21) | E21: =COUNTIFS(LLM_Data_Entry!$F$3:$F$430,"LLM",LLM_Data_Entry!$H$3:$H$430,"BUY",LLM_Data_Entry!$Q$3:$Q$430,"DOWN")+COUNTIFS(LLM_Data_Entry!$F$3:$F$430,"LLM",LLM_Data_Entry!$H$3:$H$430,"SELL",LLM_Data_Entry!$Q$3:$Q$430,"DOWN") | F21: =IF(B21=0,"",E21/B21) | G21: =IFERROR(1 - _xlfn.SINGLE(_xlfn.BINOM.DIST(C21 - 1, B21, F21, TRUE)), "") | H21: =IFERROR(2*1.645*SQRT(F21*(1-F21)/B21),"") | I21: =COUNTIFS(LLM_Data_Entry!$F$3:$F$430,"LLM",LLM_Data_Entry!$H$3:$H$430,"HOLD") | J21: =IFERROR(I21/(I21+K21),"") | K21: =COUNTIFS(LLM_Data_Entry!$F$3:$F$430,"LLM",LLM_Data_Entry!$H$3:$H$430,"BUY")+COUNTIFS(LLM_Data_Entry!$F$3:$F$430,"LLM",LLM_Data_Entry!$H$3:$H$430,"SELL")
A22: Human (All) | B22: =COUNTIFS(Human_Data_Entry!$J$3:$J$524,"BUY",Human_Data_Entry!$R$3:$R$524,"UP")+COUNTIFS(Human_Data_Entry!$J$3:$J$524,"BUY",Human_Data_Entry!$R$3:$R$524,"DOWN")+COUNTIFS(Human_Data_Entry!$J$3:$J$524,"SELL",Human_Data_Entry!$R$3:$R$524,"UP")+COUNTIFS(Human_Data_Entry!$J$3:$J$524,"SELL",Human_Data_Entry!$R$3:$R$524,"DOWN") | C22: =COUNTIFS(Human_Data_Entry!$J$3:$J$524,"BUY",Human_Data_Entry!$R$3:$R$524,"UP")+COUNTIFS(Human_Data_Entry!$J$3:$J$524,"SELL",Human_Data_Entry!$R$3:$R$524,"DOWN") | D22: =IF(B22=0,"",C22/B22) | E22: =COUNTIFS(Human_Data_Entry!$J$3:$J$524,"BUY",Human_Data_Entry!$R$3:$R$524,"DOWN")+COUNTIFS(Human_Data_Entry!$J$3:$J$524,"SELL",Human_Data_Entry!$R$3:$R$524,"DOWN") | F22: =IF(B22=0,"",E22/B22) | G22: =IFERROR(1 - _xlfn.SINGLE(_xlfn.BINOM.DIST(C22 - 1, B22, F22, TRUE)), "") | H22: =IFERROR(2*1.645*SQRT(F22*(1-F22)/B22),"") | I22: =COUNTIF(Human_Data_Entry!$J$3:$J$524,"HOLD") | J22: =IFERROR(I22/(I22+K22),"") | K22: =COUNTIF(Human_Data_Entry!$J$3:$J$524,"BUY")+COUNTIF(Human_Data_Entry!$J$3:$J$524,"SELL")
A23: =Settings!$A$8 | B23: =COUNTIFS(Human_Data_Entry!$G$3:$G$524,A23,Human_Data_Entry!$J$3:$J$524,"BUY",Human_Data_Entry!$R$3:$R$524,"UP")+COUNTIFS(Human_Data_Entry!$G$3:$G$524,A23,Human_Data_Entry!$J$3:$J$524,"BUY",Human_Data_Entry!$R$3:$R$524,"DOWN")+COUNTIFS(Human_Data_Entry!$G$3:$G$524,A23,Human_Data_Entry!$J$3:$J$524,"SELL",Human_Data_Entry!$R$3:$R$524,"UP")+COUNTIFS(Human_Data_Entry!$G$3:$G$524,A23,Human_Data_Entry!$J$3:$J$524,"SELL",Human_Data_Entry!$R$3:$R$524,"DOWN") | C23: =COUNTIFS(Human_Data_Entry!$G$3:$G$524,A23,Human_Data_Entry!$J$3:$J$524,"BUY",Human_Data_Entry!$R$3:$R$524,"UP")+COUNTIFS(Human_Data_Entry!$G$3:$G$524,A23,Human_Data_Entry!$J$3:$J$524,"SELL",Human_Data_Entry!$R$3:$R$524,"DOWN") | D23: =IF(B23=0,"",C23/B23) | E23: =COUNTIFS(Human_Data_Entry!$G$3:$G$524,A23,Human_Data_Entry!$J$3:$J$524,"BUY",Human_Data_Entry!$R$3:$R$524,"DOWN")+COUNTIFS(Human_Data_Entry!$G$3:$G$524,A23,Human_Data_Entry!$J$3:$J$524,"SELL",Human_Data_Entry!$R$3:$R$524,"DOWN") | F23: =IF(B23=0,"",E23/B23) | G23: =IFERROR(1 - _xlfn.SINGLE(_xlfn.BINOM.DIST(C23 - 1, B23, F23, TRUE)), "") | H23: =IFERROR(2*1.645*SQRT(F23*(1-F23)/B23),"") | I23: =COUNTIFS(Human_Data_Entry!$G$3:$G$524,A23,Human_Data_Entry!$J$3:$J$524,"HOLD") | J23: =IFERROR(I23/(I23+K23),"") | K23: =COUNTIFS(Human_Data_Entry!$G$3:$G$524,A23,Human_Data_Entry!$J$3:$J$524,"BUY")+COUNTIFS(Human_Data_Entry!$G$3:$G$524,A23,Human_Data_Entry!$J$3:$J$524,"SELL")
A24: =Settings!$A$9 | B24: =COUNTIFS(Human_Data_Entry!$G$3:$G$524,A24,Human_Data_Entry!$J$3:$J$524,"BUY",Human_Data_Entry!$R$3:$R$524,"UP")+COUNTIFS(Human_Data_Entry!$G$3:$G$524,A24,Human_Data_Entry!$J$3:$J$524,"BUY",Human_Data_Entry!$R$3:$R$524,"DOWN")+COUNTIFS(Human_Data_Entry!$G$3:$G$524,A24,Human_Data_Entry!$J$3:$J$524,"SELL",Human_Data_Entry!$R$3:$R$524,"UP")+COUNTIFS(Human_Data_Entry!$G$3:$G$524,A24,Human_Data_Entry!$J$3:$J$524,"SELL",Human_Data_Entry!$R$3:$R$524,"DOWN") | C24: =COUNTIFS(Human_Data_Entry!$G$3:$G$524,A24,Human_Data_Entry!$J$3:$J$524,"BUY",Human_Data_Entry!$R$3:$R$524,"UP")+COUNTIFS(Human_Data_Entry!$G$3:$G$524,A24,Human_Data_Entry!$J$3:$J$524,"SELL",Human_Data_Entry!$R$3:$R$524,"DOWN") | D24: =IF(B24=0,"",C24/B24) | E24: =COUNTIFS(Human_Data_Entry!$G$3:$G$524,A24,Human_Data_Entry!$J$3:$J$524,"BUY",Human_Data_Entry!$R$3:$R$524,"DOWN")+COUNTIFS(Human_Data_Entry!$G$3:$G$524,A24,Human_Data_Entry!$J$3:$J$524,"SELL",Human_Data_Entry!$R$3:$R$524,"DOWN") | F24: =IF(B24=0,"",E24/B24) | G24: =IFERROR(1 - _xlfn.SINGLE(_xlfn.BINOM.DIST(C24 - 1, B24, F24, TRUE)), "") | H24: =IFERROR(2*1.645*SQRT(F24*(1-F24)/B24),"") | I24: =COUNTIFS(Human_Data_Entry!$G$3:$G$524,A24,Human_Data_Entry!$J$3:$J$524,"HOLD") | J24: =IFERROR(I24/(I24+K24),"") | K24: =COUNTIFS(Human_Data_Entry!$G$3:$G$524,A24,Human_Data_Entry!$J$3:$J$524,"BUY")+COUNTIFS(Human_Data_Entry!$G$3:$G$524,A24,Human_Data_Entry!$J$3:$J$524,"SELL")
A25: =Settings!$A$10 | B25: =COUNTIFS(Human_Data_Entry!$G$3:$G$524,A25,Human_Data_Entry!$J$3:$J$524,"BUY",Human_Data_Entry!$R$3:$R$524,"UP")+COUNTIFS(Human_Data_Entry!$G$3:$G$524,A25,Human_Data_Entry!$J$3:$J$524,"BUY",Human_Data_Entry!$R$3:$R$524,"DOWN")+COUNTIFS(Human_Data_Entry!$G$3:$G$524,A25,Human_Data_Entry!$J$3:$J$524,"SELL",Human_Data_Entry!$R$3:$R$524,"UP")+COUNTIFS(Human_Data_Entry!$G$3:$G$524,A25,Human_Data_Entry!$J$3:$J$524,"SELL",Human_Data_Entry!$R$3:$R$524,"DOWN") | C25: =COUNTIFS(Human_Data_Entry!$G$3:$G$524,A25,Human_Data_Entry!$J$3:$J$524,"BUY",Human_Data_Entry!$R$3:$R$524,"UP")+COUNTIFS(Human_Data_Entry!$G$3:$G$524,A25,Human_Data_Entry!$J$3:$J$524,"SELL",Human_Data_Entry!$R$3:$R$524,"DOWN") | D25: =IF(B25=0,"",C25/B25) | E25: =COUNTIFS(Human_Data_Entry!$G$3:$G$524,A25,Human_Data_Entry!$J$3:$J$524,"BUY",Human_Data_Entry!$R$3:$R$524,"DOWN")+COUNTIFS(Human_Data_Entry!$G$3:$G$524,A25,Human_Data_Entry!$J$3:$J$524,"SELL",Human_Data_Entry!$R$3:$R$524,"DOWN") | F25: =IF(B25=0,"",E25/B25) | G25: =IFERROR(1 - _xlfn.SINGLE(_xlfn.BINOM.DIST(C25 - 1, B25, F25, TRUE)), "") | H25: =IFERROR(2*1.645*SQRT(F25*(1-F25)/B25),"") | I25: =COUNTIFS(Human_Data_Entry!$G$3:$G$524,A25,Human_Data_Entry!$J$3:$J$524,"HOLD") | J25: =IFERROR(I25/(I25+K25),"") | K25: =COUNTIFS(Human_Data_Entry!$G$3:$G$524,A25,Human_Data_Entry!$J$3:$J$524,"BUY")+COUNTIFS(Human_Data_Entry!$G$3:$G$524,A25,Human_Data_Entry!$J$3:$J$524,"SELL")
A26: =Settings!$A$11 | B26: =COUNTIFS(Human_Data_Entry!$G$3:$G$524,A26,Human_Data_Entry!$J$3:$J$524,"BUY",Human_Data_Entry!$R$3:$R$524,"UP")+COUNTIFS(Human_Data_Entry!$G$3:$G$524,A26,Human_Data_Entry!$J$3:$J$524,"BUY",Human_Data_Entry!$R$3:$R$524,"DOWN")+COUNTIFS(Human_Data_Entry!$G$3:$G$524,A26,Human_Data_Entry!$J$3:$J$524,"SELL",Human_Data_Entry!$R$3:$R$524,"UP")+COUNTIFS(Human_Data_Entry!$G$3:$G$524,A26,Human_Data_Entry!$J$3:$J$524,"SELL",Human_Data_Entry!$R$3:$R$524,"DOWN") | C26: =COUNTIFS(Human_Data_Entry!$G$3:$G$524,A26,Human_Data_Entry!$J$3:$J$524,"BUY",Human_Data_Entry!$R$3:$R$524,"UP")+COUNTIFS(Human_Data_Entry!$G$3:$G$524,A26,Human_Data_Entry!$J$3:$J$524,"SELL",Human_Data_Entry!$R$3:$R$524,"DOWN") | D26: =IF(B26=0,"",C26/B26) | E26: =COUNTIFS(Human_Data_Entry!$G$3:$G$524,A26,Human_Data_Entry!$J$3:$J$524,"BUY",Human_Data_Entry!$R$3:$R$524,"DOWN")+COUNTIFS(Human_Data_Entry!$G$3:$G$524,A26,Human_Data_Entry!$J$3:$J$524,"SELL",Human_Data_Entry!$R$3:$R$524,"DOWN") | F26: =IF(B26=0,"",E26/B26) | G26: =IFERROR(1 - _xlfn.SINGLE(_xlfn.BINOM.DIST(C26 - 1, B26, F26, TRUE)), "") | H26: =IFERROR(2*1.645*SQRT(F26*(1-F26)/B26),"") | I26: =COUNTIFS(Human_Data_Entry!$G$3:$G$524,A26,Human_Data_Entry!$J$3:$J$524,"HOLD") | J26: =IFERROR(I26/(I26+K26),"") | K26: =COUNTIFS(Human_Data_Entry!$G$3:$G$524,A26,Human_Data_Entry!$J$3:$J$524,"BUY")+COUNTIFS(Human_Data_Entry!$G$3:$G$524,A26,Human_Data_Entry!$J$3:$J$524,"SELL")
A27: =Settings!$A$12 | B27: =COUNTIFS(Human_Data_Entry!$G$3:$G$524,A27,Human_Data_Entry!$J$3:$J$524,"BUY",Human_Data_Entry!$R$3:$R$524,"UP")+COUNTIFS(Human_Data_Entry!$G$3:$G$524,A27,Human_Data_Entry!$J$3:$J$524,"BUY",Human_Data_Entry!$R$3:$R$524,"DOWN")+COUNTIFS(Human_Data_Entry!$G$3:$G$524,A27,Human_Data_Entry!$J$3:$J$524,"SELL",Human_Data_Entry!$R$3:$R$524,"UP")+COUNTIFS(Human_Data_Entry!$G$3:$G$524,A27,Human_Data_Entry!$J$3:$J$524,"SELL",Human_Data_Entry!$R$3:$R$524,"DOWN") | C27: =COUNTIFS(Human_Data_Entry!$G$3:$G$524,A27,Human_Data_Entry!$J$3:$J$524,"BUY",Human_Data_Entry!$R$3:$R$524,"UP")+COUNTIFS(Human_Data_Entry!$G$3:$G$524,A27,Human_Data_Entry!$J$3:$J$524,"SELL",Human_Data_Entry!$R$3:$R$524,"DOWN") | D27: =IF(B27=0,"",C27/B27) | E27: =COUNTIFS(Human_Data_Entry!$G$3:$G$524,A27,Human_Data_Entry!$J$3:$J$524,"BUY",Human_Data_Entry!$R$3:$R$524,"DOWN")+COUNTIFS(Human_Data_Entry!$G$3:$G$524,A27,Human_Data_Entry!$J$3:$J$524,"SELL",Human_Data_Entry!$R$3:$R$524,"DOWN") | F27: =IF(B27=0,"",E27/B27) | G27: =IFERROR(1 - _xlfn.SINGLE(_xlfn.BINOM.DIST(C27 - 1, B27, F27, TRUE)), "") | H27: =IFERROR(2*1.645*SQRT(F27*(1-F27)/B27),"") | I27: =COUNTIFS(Human_Data_Entry!$G$3:$G$524,A27,Human_Data_Entry!$J$3:$J$524,"HOLD") | J27: =IFERROR(I27/(I27+K27),"") | K27: =COUNTIFS(Human_Data_Entry!$G$3:$G$524,A27,Human_Data_Entry!$J$3:$J$524,"BUY")+COUNTIFS(Human_Data_Entry!$G$3:$G$524,A27,Human_Data_Entry!$J$3:$J$524,"SELL")
A28: =Settings!$A$13 | B28: =COUNTIFS(Human_Data_Entry!$G$3:$G$524,A28,Human_Data_Entry!$J$3:$J$524,"BUY",Human_Data_Entry!$R$3:$R$524,"UP")+COUNTIFS(Human_Data_Entry!$G$3:$G$524,A28,Human_Data_Entry!$J$3:$J$524,"BUY",Human_Data_Entry!$R$3:$R$524,"DOWN")+COUNTIFS(Human_Data_Entry!$G$3:$G$524,A28,Human_Data_Entry!$J$3:$J$524,"SELL",Human_Data_Entry!$R$3:$R$524,"UP")+COUNTIFS(Human_Data_Entry!$G$3:$G$524,A28,Human_Data_Entry!$J$3:$J$524,"SELL",Human_Data_Entry!$R$3:$R$524,"DOWN") | C28: =COUNTIFS(Human_Data_Entry!$G$3:$G$524,A28,Human_Data_Entry!$J$3:$J$524,"BUY",Human_Data_Entry!$R$3:$R$524,"UP")+COUNTIFS(Human_Data_Entry!$G$3:$G$524,A28,Human_Data_Entry!$J$3:$J$524,"SELL",Human_Data_Entry!$R$3:$R$524,"DOWN") | D28: =IF(B28=0,"",C28/B28) | E28: =COUNTIFS(Human_Data_Entry!$G$3:$G$524,A28,Human_Data_Entry!$J$3:$J$524,"BUY",Human_Data_Entry!$R$3:$R$524,"DOWN")+COUNTIFS(Human_Data_Entry!$G$3:$G$524,A28,Human_Data_Entry!$J$3:$J$524,"SELL",Human_Data_Entry!$R$3:$R$524,"DOWN") | F28: =IF(B28=0,"",E28/B28) | G28: =IFERROR(1 - _xlfn.SINGLE(_xlfn.BINOM.DIST(C28 - 1, B28, F28, TRUE)), "") | H28: =IFERROR(2*1.645*SQRT(F28*(1-F28)/B28),"") | I28: =COUNTIFS(Human_Data_Entry!$G$3:$G$524,A28,Human_Data_Entry!$J$3:$J$524,"HOLD") | J28: =IFERROR(I28/(I28+K28),"") | K28: =COUNTIFS(Human_Data_Entry!$G$3:$G$524,A28,Human_Data_Entry!$J$3:$J$524,"BUY")+COUNTIFS(Human_Data_Entry!$G$3:$G$524,A28,Human_Data_Entry!$J$3:$J$524,"SELL")
A29: =Settings!$A$14 | B29: =COUNTIFS(Human_Data_Entry!$G$3:$G$524,A29,Human_Data_Entry!$J$3:$J$524,"BUY",Human_Data_Entry!$R$3:$R$524,"UP")+COUNTIFS(Human_Data_Entry!$G$3:$G$524,A29,Human_Data_Entry!$J$3:$J$524,"BUY",Human_Data_Entry!$R$3:$R$524,"DOWN")+COUNTIFS(Human_Data_Entry!$G$3:$G$524,A29,Human_Data_Entry!$J$3:$J$524,"SELL",Human_Data_Entry!$R$3:$R$524,"UP")+COUNTIFS(Human_Data_Entry!$G$3:$G$524,A29,Human_Data_Entry!$J$3:$J$524,"SELL",Human_Data_Entry!$R$3:$R$524,"DOWN") | C29: =COUNTIFS(Human_Data_Entry!$G$3:$G$524,A29,Human_Data_Entry!$J$3:$J$524,"BUY",Human_Data_Entry!$R$3:$R$524,"UP")+COUNTIFS(Human_Data_Entry!$G$3:$G$524,A29,Human_Data_Entry!$J$3:$J$524,"SELL",Human_Data_Entry!$R$3:$R$524,"DOWN") | D29: =IF(B29=0,"",C29/B29) | E29: =COUNTIFS(Human_Data_Entry!$G$3:$G$524,A29,Human_Data_Entry!$J$3:$J$524,"BUY",Human_Data_Entry!$R$3:$R$524,"DOWN")+COUNTIFS(Human_Data_Entry!$G$3:$G$524,A29,Human_Data_Entry!$J$3:$J$524,"SELL",Human_Data_Entry!$R$3:$R$524,"DOWN") | F29: =IF(B29=0,"",E29/B29) | G29: =IFERROR(1 - _xlfn.SINGLE(_xlfn.BINOM.DIST(C29 - 1, B29, F29, TRUE)), "") | H29: =IFERROR(2*1.645*SQRT(F29*(1-F29)/B29),"") | I29: =COUNTIFS(Human_Data_Entry!$G$3:$G$524,A29,Human_Data_Entry!$J$3:$J$524,"HOLD") | J29: =IFERROR(I29/(I29+K29),"") | K29: =COUNTIFS(Human_Data_Entry!$G$3:$G$524,A29,Human_Data_Entry!$J$3:$J$524,"BUY")+COUNTIFS(Human_Data_Entry!$G$3:$G$524,A29,Human_Data_Entry!$J$3:$J$524,"SELL")
A30: CHART NOTE: The two floor-level series ('Coverage floor' and 'Selectivity floor') are rendered as bars, not horizontal lines, because openpyxl cannot produce a clean bar+line combo chart without raw XML manipulation. To convert to horizontal lines: open in Excel → right-click each floor series → Change Series Chart Type → Line. The coverage and selectivity bars show accuracy; floor bars show the naive majority-direction baseline for the matching denominator.
A31: Chart data (feeds accuracy comparison chart below)
A32: Arm | B32: Coverage acc | C32: Selectivity acc | D32: Coverage floor | E32: Selectivity floor
A33: LLM | B33: =D8 | C33: =D21 | D33: =F8 | E33: =F21
A34: Human (All) | B34: =D9 | C34: =D22 | D34: =F9 | E34: =F22
A60: KEY DISTINCTION: Coverage (47%) and selectivity (62%) are not both correct — they measure different things on different denominators. Coverage penalises every HOLD call; selectivity credits only committed events that moved. Quoting one without the other is misleading. The repo's headline accuracy figure is selectivity (68/109 = 62.4%, from item_e_walkforward.json); the workbook Summary and Figure 1 show coverage (47% for LLM). Both are real; neither is the whole story.
A63: RECORD (2026-08-13 basis, derived 2026-08-21) — Human arm, the 295 rows then marked Price Basis Corrected = YES. The cells in rows 66–74 were live COUNTIFS formulas that silently tracked the BS column as it grew to 405, so the earlier claim here that the figures had 'NOT been re-run' was wrong — and no 295-era values were ever frozen in any committed vintage. The human values below are now typed records derived from the committed 2026-08-13 workbook vintage (raw prices and scores, same formula semantics). Current 405-row tables: rows 94–101. Ledger L9.
A64: Human cells below are typed record values (2026-08-13 basis, 295 corrected rows, original-price correctness). LLM cells remain live single-basis formulas — their inputs did not change. For current human figures use rows 94–101; comparing the two shows the effect of the re-anchoring completed since.
A66: Coverage (2026-08-13 record: 295 corrected rows)
A67: Arm | B67: YES | C67: N | D67: Accuracy | E67: Floor (always-DOWN) | F67: p-value | G67: MDE
A68: Human (all raters, 295 corrected) | B68: 106 | C68: 295 | D68: 0.3593 | E68: 0.3695 | F68: 0.6619 | G68: =IFERROR(2*1.645*SQRT(E68*(1-E68)/C68),"")
A69: LLM (single basis, unchanged) | B69: =COUNTIFS(LLM_Data_Entry!$F$3:$F$430,"LLM",LLM_Data_Entry!$R$3:$R$430,"YES") | C69: =COUNTIFS(LLM_Data_Entry!$F$3:$F$430,"LLM",LLM_Data_Entry!$R$3:$R$430,"<>") | D69: =IFERROR(B69/C69,"") | E69: =IFERROR(COUNTIFS(LLM_Data_Entry!$F$3:$F$430,"LLM",LLM_Data_Entry!$Q$3:$Q$430,"DOWN")/COUNTIFS(LLM_Data_Entry!$F$3:$F$430,"LLM",LLM_Data_Entry!$R$3:$R$430,"<>"),"") | F69: =IFERROR(1 - _xlfn.SINGLE(_xlfn.BINOM.DIST(B69 - 1, C69, E69, TRUE)), "") | G69: =IFERROR(2*1.645*SQRT(E69*(1-E69)/C69),"")
A71: Selectivity (2026-08-13 record: 295 corrected rows)
A72: Arm | B72: Correct | C72: N (traded+graded) | D72: Accuracy | E72: Floor (always-DOWN) | F72: p-value | G72: MDE
A73: Human (all raters, 295 corrected) | B73: 78 | C73: 159 | D73: 0.4906 | E73: 0.5472 | F73: 0.9347 | G73: =IFERROR(2*1.645*SQRT(E73*(1-E73)/C73),"")
A74: LLM (single basis, unchanged) | B74: =COUNTIFS(LLM_Data_Entry!$F$3:$F$430,"LLM",LLM_Data_Entry!$H$3:$H$430,"BUY",LLM_Data_Entry!$Q$3:$Q$430,"UP")+COUNTIFS(LLM_Data_Entry!$F$3:$F$430,"LLM",LLM_Data_Entry!$H$3:$H$430,"SELL",LLM_Data_Entry!$Q$3:$Q$430,"DOWN") | C74: =COUNTIFS(LLM_Data_Entry!$F$3:$F$430,"LLM",LLM_Data_Entry!$H$3:$H$430,"BUY",LLM_Data_Entry!$Q$3:$Q$430,"UP")+COUNTIFS(LLM_Data_Entry!$F$3:$F$430,"LLM",LLM_Data_Entry!$H$3:$H$430,"BUY",LLM_Data_Entry!$Q$3:$Q$430,"DOWN")+COUNTIFS(LLM_Data_Entry!$F$3:$F$430,"LLM",LLM_Data_Entry!$H$3:$H$430,"SELL",LLM_Data_Entry!$Q$3:$Q$430,"UP")+COUNTIFS(LLM_Data_Entry!$F$3:$F$430,"LLM",LLM_Data_Entry!$H$3:$H$430,"SELL",LLM_Data_Entry!$Q$3:$Q$430,"DOWN") | D74: =IFERROR(B74/C74,"") | E74: =IFERROR((COUNTIFS(LLM_Data_Entry!$F$3:$F$430,"LLM",LLM_Data_Entry!$H$3:$H$430,"BUY",LLM_Data_Entry!$Q$3:$Q$430,"DOWN")+COUNTIFS(LLM_Data_Entry!$F$3:$F$430,"LLM",LLM_Data_Entry!$H$3:$H$430,"SELL",LLM_Data_Entry!$Q$3:$Q$430,"DOWN"))/(COUNTIFS(LLM_Data_Entry!$F$3:$F$430,"LLM",LLM_Data_Entry!$H$3:$H$430,"BUY",LLM_Data_Entry!$Q$3:$Q$430,"UP")+COUNTIFS(LLM_Data_Entry!$F$3:$F$430,"LLM",LLM_Data_Entry!$H$3:$H$430,"BUY",LLM_Data_Entry!$Q$3:$Q$430,"DOWN")+COUNTIFS(LLM_Data_Entry!$F$3:$F$430,"LLM",LLM_Data_Entry!$H$3:$H$430,"SELL",LLM_Data_Entry!$Q$3:$Q$430,"UP")+COUNTIFS(LLM_Data_Entry!$F$3:$F$430,"LLM",LLM_Data_Entry!$H$3:$H$430,"SELL",LLM_Data_Entry!$Q$3:$Q$430,"DOWN")),"") | F74: =IFERROR(1 - _xlfn.SINGLE(_xlfn.BINOM.DIST(B74 - 1, C74, E74, TRUE)), "") | G74: =IFERROR(2*1.645*SQRT(E74*(1-E74)/C74),"")
A76: Interpretation: the record above (2026-08-13 basis) against the current tables in rows 94–101 shows what the re-anchoring completed since then did to the human figures. Report the current rows when citing human-arm accuracy from this workbook, and say which basis is being quoted.
A78: N=232 CLEAN UNIVERSE — LLM ONLY (In Clean Universe = YES, 36 excluded events removed)
A79: The 36 excluded events (25 worksheet contamination, 1 SPOT misattribution, 1 look-ahead document, 9 timing unresolved) may inflate N=268 figures. N=232 uses only clean events. LLM values are static from authoritative repo artifacts — they are NOT formula-driven in this section. Human figures require the Price Basis Corrected filter (see rows 63+ above).
A80: COVERAGE (N=232)
A81: Arm | B81: n (denom) | C81: YES (correct) | D81: Accuracy | E81: Note | F81: Source
A82: LLM (DeepSeek, N=232) | B82: 145 | C82: 68 | D82: 46.9% (68/145) | E82: Coverage = correct / all graded events (|ret|>2%), HOLD counted wrong when stock moved | F82: ext2_holding_curve.csv / frontier_table.csv (run 20260812_183842)
A84: SELECTIVITY (N=232) — PRIMARY HEADLINE
A85: Arm | B85: n (denom) | C85: Correct | D85: Accuracy | E85: Floor (always-DOWN) | F85: Source
A86: LLM (DeepSeek, N=232) | B86: 109 | C86: 68 | D86: 62.4% (68/109) | E86: 54.1% (59/109) — always-DOWN floor on N=232 (from item_e_walkforward.json) | F86: item_e_walkforward.json (run 20260812_183842) — AUTHORITATIVE
A88: RECONCILIATION RESOLVED 2026-08-13 (at the SUPERSEDED 0.55/0.45 constants; the KHC price fix below still stands, but the closing claim that the sheet formula reproduces 62/95 is true only at those constants - at the deployed 0.80/0.20 it reproduces 68/109 = 62.4%): The 1-event discrepancy (formula 61/94 vs authoritative 62/95) was caused by KHC_FQ1_2025 (Kraft Heinz, FQ4 2025, doc_id KHC_FQ1_2025). Its next_day_open was blank (a missing-price sentinel) in the pre-correction workbook. With next_day_open=blank, the formula returned actual_pct_change=0.0%, direction=FLAT — excluding KHC from the selectivity denominator. In returns_matrix.csv, ret_overnight=−0.0442 (−4.4177%), |ret|>2%, so KHC belongs in the graded set. Decision=SELL, actual direction=DOWN → prediction_correct=YES. Fixed 2026-08-13: next_day_open=23.80 (returns_matrix entry_close 24.9 × (1−0.044177)). After this fix the LLM_Data_Entry formula reproduces 62/95=65.3% exactly; the static figures in rows 85-86 above are correct and verified.
A89: RECONCILIATION NOTE (recorded at the N=233 vintage; rows 82/86 above carry the current N=232 figures): 47.3% (coverage) and 62.7% (selectivity) describe the same deployed model on the same N=233 events but use different denominators. Coverage denominator=146 (all events where |ret|>2%); selectivity denominator=110 (model committed BUY/SELL AND |ret|>2%). Neither figure is wrong; both must be cited together. The 62.7% is the project headline; the 47.3% provides the fuller picture that penalises HOLD decisions.
A91: HUMAN-ARM COVERAGE LIMITATION (N=420 total rows; 405 corrected, 15 uncorrected — see A92)
A92: Price-basis status (live count, 2026-08-21): 405 of 420 Human_Data_Entry rows carry Price_Basis_Corrected = YES. The 15 remaining rows are 15 unique human-only events that do not appear in the LLM returns_matrix; for each, the recorded reason (column BT) is 'EDGAR lookup deferred — manual verification required'. Human-arm accuracy figures should be reported on the corrected subset with the uncorrected full-sample figure alongside. Earlier counts in this cell (~295/~120/~109) described the 2026-08-13 state and are superseded.
A94: HUMAN ARM — CURRENT (2026-08-21): 405 corrected rows (Price Basis Corrected = YES), re-priced correctness (columns AH/AI/AJ). 16 of the 405 carry no re-priced outcome (the ALV.DE / STAN.L / DELL / PLTR / WDAY family) and drop from denominators. Typed as gated values; formula equivalent is COUNTIFS over AJ/AI/BS. Group decision Q10. (Efficiency_Corrected D36's '20 rows' counts all 420: these 16 plus 4 of the 15 uncorrected human-only rows; the other 11 uncorrected rows do carry re-priced outcomes.)
A95: Coverage (405-corrected rows, re-priced)
A96: Arm | B96: YES (correct) | C96: N | D96: Accuracy | E96: Floor (always-DOWN) | F96: p-value
A97: Human (all raters, 405 corrected) | B97: 151 | C97: 389 | D97: 0.3882 | E97: 0.3265 | F97: 0.006
A98: LLM comparison: rows 69 and 74 above (single basis, unchanged)
A99: Selectivity (405-corrected rows, re-priced)
A100: Arm | B100: YES (correct) | C100: N | D100: Accuracy | E100: Floor (always-DOWN) | F100: p-value
A101: Human (all raters, 405 corrected) | B101: 94 | C101: 186 | D101: 0.5054 | E101: 0.5376 | F101: 0.8305

Sheet Sector_Breakdown
A1: Set B is thin outside Technology (n_graded=15) and Consumer (n_graded=13). Energy, Utilities and Materials are below the n_graded<3 threshold and no accuracy is reported for them. Do not compare Set B sector accuracy against Set A without noting the sample-size difference.
A3: sector | B3: event_set | C3: n_events | D3: n_graded | E3: n_correct_coverage | F3: accuracy_coverage | G3: notes
A4: Technology | B4: Set A — N=232 frozen | C4: 36 | D4: 31 | E4: 13 | F4: 0.419 | G4: "Includes AAPL AVGO DELL IBM LNVGY MU MSFT ORCL PLTR UBER WDAY (broad Technology grouping)"
A5: Consumer | B5: Set A — N=232 frozen | C5: 86 | D5: 49 | E5: 23 | F5: 0.469 | G5: "Largest sector by N. Includes ABNB BKNG CMG COST CL EXPE F GIS HLT KHC KO LOW LULU MAR MCD NKE PEP PUM.DE RMSP.XC SBUX TGT TSLA WMT etc."
A6: Financials | B6: Set A — N=232 frozen | C6: 49 | D6: 22 | E6: 9 | F6: 0.409 | G6: "Includes BAC BCS C COIN GS HOOD JPM MET PYPL SCHW STAN.L V AXP ALV.DE"
A7: Industrials | B7: Set A — N=232 frozen | C7: 26 | D7: 17 | E7: 9 | F7: 0.529 | G7: "Includes AMKBY BA CAT DAL FDX LMT SIE.DE UAL"
A8: Communication Services | B8: Set A — N=232 frozen | C8: 18 | D8: 17 | E8: 7 | F8: 0.412 | G8: "Includes CMCSA DIS META NFLX PINS (note: META/NFLX worksheet-excluded pairs removed)"
A9: Healthcare | B9: Set A — N=232 frozen | C9: 14 | D9: 9 | E9: 7 | F9: 0.778 | G9: "Includes CVS JNJ NVO PFE UNH; n_graded=9 — interpret cautiously"
A10: Materials | B10: Set A — N=232 frozen | C10: 3 | D10: 0 | E10: 0 | F10: n<3 | G10: "LIN only in clean set; 0 graded events in ±2% band"
A11: Total | B11: Set A — N=232 frozen | C11: 232 | D11: 145 | E11: 68 | F11: =E11/D11 | G11: "Coverage accuracy: 68/145. Selectivity (HOLD-excluded | H11: n=109 graded+traded): 62.4% (68/109)."
A12: Technology | B12: Set B — N=93 extension | C12: 18 | D12: 15 | E12: 8 | F12: 53.3% | G12: "ADBE DDOG INTC SHOP SONY; n_graded=15 — largest graded count in Set B"
A13: Consumer | B13: Set B — N=93 extension | C13: 26 | D13: 13 | E13: 1 | F13: 7.7% | G13: "CL COST EBAY HD HEIA.AS NSRGY RMSP.XC; n_graded=13"
A14: Utilities | B14: Set B — N=93 extension | C14: 13 | D14: 1 | E14: 1 | F14: n<3 | G14: "DUK only (13 events); DUK_FQ2_2025 graded after the 8-K acceptance-time dateline correction"
A15: Energy | B15: Set B — N=93 extension | C15: 21 | D15: 1 | E15: 1 | F15: n<3 | G15: "CVX XOM SHEL; only 1 graded event in ±2% band"
A16: Financials | B16: Set B — N=93 extension | C16: 8 | D16: 2 | E16: 1 | F16: n<3 | G16: "AXP MA; only 2 graded events — not reportable"
A17: Materials | B17: Set B — N=93 extension | C17: 3 | D17: 2 | E17: 1 | F17: n<3 | G17: "FCX; only 2 graded events — not reportable"
A18: Industrials | B18: Set B — N=93 extension | C18: 4 | D18: 0 | E18: 0 | F18: — | G18: "UNP; 0 graded events"
A19: Total | B19: Set B — N=93 extension | C19: 93 | D19: 34 | E19: 13 | F19: =E19/D19 | G19: "Coverage accuracy: 13/34. Selectivity (HOLD-excluded, n=18 graded+traded): 72.2% (13/18). Extension is pure eval."
A20: Technology | B20: Set C — N=325 combined | C20: 54 | D20: 46 | E20: 21 | F20: 45.7% | G20: "Set A (36/31/13) + Set B (18/15/8)"
A21: Consumer | B21: Set C — N=325 combined | C21: 112 | D21: 62 | E21: 24 | F21: 38.7% | G21: "Set A (86/49/23) + Set B (26/13/1)"
A22: Financials | B22: Set C — N=325 combined | C22: 57 | D22: 24 | E22: 10 | F22: 41.7% | G22: "Set A (49/22/9) + Set B (8/2/1)"
A23: Industrials | B23: Set C — N=325 combined | C23: 30 | D23: 17 | E23: 9 | F23: 52.9% | G23: "Set A (26/17/9) + Set B (4/0/0)"
A24: Communication Services | B24: Set C — N=325 combined | C24: 18 | D24: 17 | E24: 7 | F24: 41.2% | G24: "Set A only (18/17/7); no Set B events in this sector"
A25: Healthcare | B25: Set C — N=325 combined | C25: 14 | D25: 9 | E25: 7 | F25: 77.8% | G25: "Set A only (14/9/7); n_graded=9 — interpret cautiously"
A26: Energy | B26: Set C — N=325 combined | C26: 21 | D26: 1 | E26: 1 | F26: n<3 | G26: "Set B only (21/1/1)"
A27: Utilities | B27: Set C — N=325 combined | C27: 13 | D27: 1 | E27: 1 | F27: n<3 | G27: "Set B only (13/1/1)"
A28: Materials | B28: Set C — N=325 combined | C28: 6 | D28: 2 | E28: 1 | F28: n<3 | G28: "Set A (3/0/0) + Set B (3/2/1)"
A29: Total | B29: Set C — N=325 combined | C29: 325 | D29: 179 | E29: 81 | F29: =E29/D29 | G29: "Coverage accuracy: 81/179. In-sample walk-forward accuracy on graded+traded: 63.8% (81/127, deployed thresholds)."
A31: Set B is thin outside Technology (n_graded=15) and Consumer (n_graded=13). Energy, Utilities and Materials fall below the n_graded<3 threshold and no accuracy is reported for them. The counts themselves are the finding: the extension broadened sector coverage but the low-volatility sectors it added rarely breach the ±2% band, so they contribute coverage rather than graded events.
A34: A fuller sector analysis across four cuts — Spearman rank correlation, calibration of mean score against
A35: mean realised return, score dispersion against hold rate, and BUY versus SELL asymmetry — is in
A36: outputs/global/summary/sector_analysis_2026-08-15.md and its accompanying CSV. The signal is positive in
A37: every estimable sector rather than concentrated in one. Only four sectors in the frozen set carry enough
A38: events for both a correlation and a directional estimate, and most cells fall below the reporting
A39: threshold. Note that the fuller analysis uses the SECTORS dict as its canonical taxonomy, which classifies
A40: four CVS Health events as Healthcare where this tab places them in Consumer; both sum to 232; under the
A41: canonical taxonomy Healthcare reads 18/12/9 (75.0%) and Consumer 82/46/21 (45.7%) against this tab's 14/9/7 (77.8%) and 86/49/23 (46.9%).

Sheet Corrected_Metrics
A1: metric_name | B1: value | C1: unit | D1: n | E1: denominator_definition | F1: event_set | G1: convention | H1: ci_low | I1: ci_high | J1: ci_level | K1: p_value | L1: mde | M1: test_used | N1: threshold_dependent | O1: source_file | P1: notes
A2: total_events_scored | B2: 268 | C2: events | D2: 268 | F2: N=268 phase2 scored events | N2: FALSE | O2: effective_sample_funnel.md
A3: excluded_worksheet | B3: 25 | C3: events | D3: 268 | F3: N=268 | N3: FALSE | O3: worksheet_leak_flags.csv | P3: LLM input included human rater worksheet
A4: excluded_bad_document | B4: 2 | C4: events | N4: FALSE | O4: effective_sample_funnel.md | P4: SPOT_FQ1_2026 misattribution; DIS_FQ1_2025 look-ahead (excluded 2026-08-24)
A5: excluded_timing | B5: 9 | C5: events | N5: FALSE | O5: effective_sample_funnel.md | P5: 9 non-US issuers, timing unresolved
A6: clean_universe | B6: 232 | C6: events | F6: N=232 clean universe | N6: FALSE | O6: effective_sample_funnel.md
A7: traded_events | B7: 168 | C7: events | E7: Model called BUY or SELL | F7: N=232 clean universe | N7: TRUE | O7: ext2_holding_curve.csv
A8: graded_events | B8: 109 | C8: events | E8: |ret_overnight| > 2% AND traded | F8: N=232 clean universe | G8: pre-registered ±2% overnight band | N8: TRUE | O8: ext2_holding_curve.csv
A9: selectivity_accuracy | B9: 62.4% | C9: percent | D9: 109 | E9: model traded AND |ret_overnight|>2% | F9: N=232 clean universe | G9: HOLD-excluded, pre-registered ±2% band | K9: 0.050 | L9: ±10.8pp | M9: binomial vs always-DOWN floor 54.1% | N9: TRUE | O9: ext2_holding_curve.csv | P9: 68/109; margin +8.3pp vs floor 54.1% (59/109 always-DOWN); the ±10.8pp MDE is an unreproduced literal hardcoded in experiments/build_workbook.py beside the superseded n=95 basis — no candidate formula reproduces the ±10.8/±14.4/±27.8 family on any basis (recorded 2026-08-21, Q3a)
A10: selectivity_accuracy_numerator | B10: 68/109 | D10: 109 | F10: N=232 clean universe | N10: TRUE | O10: ext2_holding_curve.csv
A11: selectivity_floor_always_down | B11: 54.1% | C11: percent | D11: 109 | E11: always-DOWN (predict SELL every event) on graded set | F11: N=232 clean universe | G11: 59/109 graded events have negative return | N11: FALSE | O11: ext2_holding_curve.csv
A12: selectivity_margin_vs_floor | B12: +8.3pp | C12: pp | D12: 109 | K12: 0.050 | L12: ±10.8pp | M12: binomial one-sided greater vs always-DOWN 59/109 | N12: TRUE | O12: ext2_holding_curve.csv | P12: The ±10.8pp MDE is an unreproduced literal hardcoded in experiments/build_workbook.py beside the superseded n=95 basis — no candidate formula reproduces the ±10.8/±14.4/±27.8 family on any basis (recorded 2026-08-21, Q3a)
A13: coverage_accuracy | B13: 46.9% | C13: percent | D13: 145 | E13: all events with |ret_overnight|>2% (model traded or not) | F13: N=232 clean universe | G13: HOLD=wrong, pre-registered ±2% band | N13: FALSE | O13: ext2_holding_curve.csv | P13: 68/145; floor=54.5% (79/145 always-DOWN); margin -7.6pp. Model missed 36 events that moved.
A14: coverage_floor_always_down | B14: 54.5% | C14: percent | D14: 145 | E14: all events with |ret_overnight|>2% | F14: N=232 clean universe | N14: FALSE | P14: 79/145 events have negative return
A15: mean_net_per_trade_overnight | B15: 1.7963% | C15: percent | D15: 168 | E15: traded events | F15: N=232 clean universe | G15: overnight, 10bps round-trip cost, 0bps short borrow | H15: 1.00% | I15: 2.63% | J15: 90% | N15: TRUE | O15: ext2_holding_curve.csv | P15: +1.798% per trade
A16: summed_total_return | B16: +301.78% | C16: percent (order-dependent) | D16: 168 | F16: N=232 clean universe | N16: TRUE | O16: item_e_handoff.md | P16: Order-dependent compounded equity curve, not an achievable balance. Mean net per trade is the primary P&L metric. Value from item_e_handoff.md (+303.80% on N=233); corrected-basis value gated 2026-08-21 (+303.80% reproduced exactly on N=233/169 from the same chain first)
A17: t_statistic_per_trade | B17: 3.652 | D17: 168 | E17: traded events | F17: N=232 clean universe | G17: mean_net/pstdev(nets)*sqrt(N_traded) — NOT a time-series Sharpe | N17: TRUE | O17: item_e_handoff.md | P17: Grows mechanically with sample size. Do not label as Sharpe.
A18: info_ratio_per_trade | B18: 0.2817 | D18: 168 | N18: TRUE | O18: item_e_handoff.md | P18: mean_net / pstdev(nets), unscaled by sqrt(N)
A19: spearman_rho_overnight | B19: 0.2565 | D19: 232 | F19: N=232 clean universe | G19: overnight return, 0.02 band (pre-registered) | K19: 0.0001 | M19: Spearman rank correlation, blended score vs ret_overnight | N19: FALSE | O19: ext2_holding_curve.csv
A20: mean_net_per_trade_overnight | B20: 1.7963% | C20: percent | D20: 168 | F20: N=232 clean universe | H20: 1.0009% | I20: 2.6281% | J20: 90% | N20: FALSE | O20: ext2_holding_curve.csv
A21: accuracy_overnight | B21: 62.4% | C21: percent | D21: 109 | E21: |ret_overnight|>band | N21: TRUE | O21: ext2_holding_curve.csv
A22: spearman_rho_1d | B22: 0.1952 | D22: 232 | F22: N=232 clean universe | G22: 1d return, 0.022497 band (recalibrated) | K22: 0.0028 | M22: Spearman rank correlation, blended score vs ret_overnight | N22: FALSE | O22: ext2_holding_curve.csv
A23: mean_net_per_trade_1d | B23: 1.1832% | C23: percent | D23: 168 | F23: N=232 clean universe | H23: 0.3271% | I23: 2.0805% | J23: 90% | N23: FALSE | O23: ext2_holding_curve.csv
A24: accuracy_1d | B24: 60.2% | C24: percent | D24: 113 | E24: |ret_1d|>band | N24: TRUE | O24: ext2_holding_curve.csv
A25: spearman_rho_3d | B25: 0.1353 | D25: 232 | F25: N=232 clean universe | G25: 3d return, 0.025207 band (recalibrated) | K25: 0.0395 | M25: Spearman rank correlation, blended score vs ret_overnight | N25: FALSE | O25: ext2_holding_curve.csv
A26: mean_net_per_trade_3d | B26: 0.8296% | C26: percent | D26: 168 | F26: N=232 clean universe | H26: -0.0720% | I26: 1.7674% | J26: 90% | N26: FALSE | O26: ext2_holding_curve.csv
A27: accuracy_3d | B27: 52.6% | C27: percent | D27: 114 | E27: |ret_3d|>band | N27: TRUE | O27: ext2_holding_curve.csv
A28: spearman_rho_5d | B28: 0.0972 | D28: 232 | F28: N=232 clean universe | G28: 5d return, 0.027189 band (recalibrated) | K28: 0.1401 | M28: Spearman rank correlation, blended score vs ret_overnight | N28: FALSE | O28: ext2_holding_curve.csv
A29: mean_net_per_trade_5d | B29: 0.9369% | C29: percent | D29: 168 | F29: N=232 clean universe | H29: -0.0341% | I29: 1.9485% | J29: 90% | N29: FALSE | O29: ext2_holding_curve.csv
A30: accuracy_5d | B30: 51.9% | C30: percent | D30: 106 | E30: |ret_5d|>band | N30: TRUE | O30: ext2_holding_curve.csv
A31: spearman_rho_10d | B31: 0.0951 | D31: 232 | F31: N=232 clean universe | G31: 10d return, 0.035159 band (recalibrated) | K31: 0.1488 | M31: Spearman rank correlation, blended score vs ret_overnight | N31: FALSE | O31: ext2_holding_curve.csv
A32: mean_net_per_trade_10d | B32: 1.4455% | C32: percent | D32: 168 | F32: N=232 clean universe | H32: 0.2807% | I32: 2.6466% | J32: 90% | N32: FALSE | O32: ext2_holding_curve.csv
A33: accuracy_10d | B33: 57.0% | C33: percent | D33: 114 | E33: |ret_10d|>band | N33: TRUE | O33: ext2_holding_curve.csv
A34: majority_direction_floor_full_sample | B34: 54.1% | C34: percent | D34: 109 | E34: always-DOWN on graded events (|ret_overnight|>2%, traded) | F34: N=232 clean universe, graded events only | G34: 59/109 graded events have negative return | N34: FALSE | O34: ext2_holding_curve.csv
A35: cohens_kappa_human_vs_llm | B35: 0.1391 | D35: 170 | E35: paired events with both human and LLM BUY/HOLD/SELL call | F35: N=170 paired events (section=All, first_rater=YES, in_llm=YES, exclusions applied) | G35: 3x3 BUY/HOLD/SELL vs BUY/HOLD/SELL, no return grading | H35: 0.049 | I35: 0.229 | J35: 90% | M35: bootstrap 10000 resamples, seed 20260709 | N35: FALSE | O35: kappa_near_independence.csv
A36: call_count_human_buy | B36: 95 | C36: count | D36: 170 | F36: N=170 paired events | N36: FALSE | O36: human_vs_llm_statistics.csv
A37: call_frac_human_buy | B37: 0.5588 | C37: fraction | D37: 170 | N37: FALSE | O37: human_vs_llm_statistics.csv
A38: call_count_human_hold | B38: 40 | C38: count | D38: 170 | F38: N=170 paired events | N38: FALSE | O38: human_vs_llm_statistics.csv
A39: call_frac_human_hold | B39: 0.2353 | C39: fraction | D39: 170 | N39: FALSE | O39: human_vs_llm_statistics.csv
A40: call_count_human_sell | B40: 35 | C40: count | D40: 170 | F40: N=170 paired events | N40: FALSE | O40: human_vs_llm_statistics.csv
A41: call_frac_human_sell | B41: 0.2059 | C41: fraction | D41: 170 | N41: FALSE | O41: human_vs_llm_statistics.csv
A42: call_count_llm_buy | B42: 72 | C42: count | D42: 170 | F42: N=170 paired events | N42: FALSE | O42: human_vs_llm_statistics.csv
A43: call_frac_llm_buy | B43: 0.4235 | C43: fraction | D43: 170 | N43: FALSE | O43: human_vs_llm_statistics.csv
A44: call_count_llm_hold | B44: 53 | C44: count | D44: 170 | F44: N=170 paired events | N44: FALSE | O44: human_vs_llm_statistics.csv
A45: call_frac_llm_hold | B45: 0.3118 | C45: fraction | D45: 170 | N45: FALSE | O45: human_vs_llm_statistics.csv
A46: call_count_llm_sell | B46: 45 | C46: count | D46: 170 | F46: N=170 paired events | N46: FALSE | O46: human_vs_llm_statistics.csv
A47: call_frac_llm_sell | B47: 0.2647 | C47: fraction | D47: 170 | N47: FALSE | O47: human_vs_llm_statistics.csv
A48: direction_only_n | B48: 85 | C48: events | F48: N=85 events where both arms called BUY or SELL | N48: FALSE | O48: human_vs_llm_statistics.csv
A49: direction_human_sign_accuracy | B49: 0.5765 | C49: fraction | D49: 85 | F49: N=85 direction-only | G49: sign accuracy, no band filter | N49: FALSE | O49: human_vs_llm_statistics.csv | P49: 49/85
A50: direction_llm_sign_accuracy | B50: 0.5882 | C50: fraction | D50: 85 | N50: FALSE | O50: human_vs_llm_statistics.csv | P50: 50/85
A51: direction_llm_minus_human_pp | B51: 1.2 | C51: pp | D51: 85 | H51: -5.9 | I51: 8.2 | J51: 90% | K51: 0.889 | M51: bootstrap paired 10000 resamples seed 20260709 | N51: FALSE | O51: human_vs_llm_statistics.csv
A52: direction_floor_always_down_strict | B52: 52.9% | C52: percent | D52: 85 | E52: 45/85 events with ret_overnight < 0 (strict negative) | F52: N=85 direction-only | G52: ret < 0 strictly; excludes PUM.DE_FQ4_2025 (ret=0) | N52: FALSE | O52: human_vs_llm_statistics.csv
A53: direction_floor_always_down_incl_zero | B53: 54.1% | C53: percent | D53: 85 | E53: 46/85 events with ret_overnight <= 0 (includes zero-return PUM.DE_FQ4_2025) | F53: N=85 direction-only | G53: ret <= 0; used for per-direction base-rate in finding #7 | N53: FALSE | O53: human_vs_llm_statistics.csv | P53: PUM.DE_FQ4_2025 has ret_overnight=0.0 exactly
A54: direction_human_vs_always_down_p | B54: 0.224 | D54: 85 | K54: — | M54: binomial one-sided greater vs always-DOWN 45/85 | N54: FALSE | O54: human_vs_llm_statistics.csv
A55: direction_llm_vs_always_down_p | B55: 0.164 | D55: 85 | K55: — | M55: binomial one-sided greater vs always-DOWN 45/85 | N55: FALSE | O55: human_vs_llm_statistics.csv
A56: direction_human_buy_accuracy | B56: 52.4% | C56: percent | D56: 63 | E56: human BUY calls among N=85 direction-only events | F56: N=85 direction-only | G56: sign accuracy, no band | K56: 0.401 | M56: binomial one-sided greater vs 50%; vs base-rate p=0.182 (base_rate=0.4588) | N56: FALSE | O56: human_vs_llm_direction_decomposition.csv | P56: 33/63, vs_50pct_margin=2.4pp
A57: direction_human_sell_accuracy | B57: 72.7% | C57: percent | D57: 22 | E57: human SELL calls among N=85 direction-only events | F57: N=85 direction-only | G57: sign accuracy, no band | K57: 0.026 | M57: binomial one-sided greater vs 50%; vs base-rate p=0.060 (base_rate=0.5412) | N57: FALSE | O57: human_vs_llm_direction_decomposition.csv | P57: 16/22, vs_50pct_margin=22.7pp
A58: direction_llm_buy_accuracy | B58: 54.2% | C58: percent | D58: 59 | E58: llm BUY calls among N=85 direction-only events | F58: N=85 direction-only | G58: sign accuracy, no band | K58: 0.301 | M58: binomial one-sided greater vs 50%; vs base-rate p=0.124 (base_rate=0.4588) | N58: FALSE | O58: human_vs_llm_direction_decomposition.csv | P58: 32/59, vs_50pct_margin=4.2pp
A59: direction_llm_sell_accuracy | B59: 69.2% | C59: percent | D59: 26 | E59: llm SELL calls among N=85 direction-only events | F59: N=85 direction-only | G59: sign accuracy, no band | K59: 0.038 | M59: binomial one-sided greater vs 50%; vs base-rate p=0.087 (base_rate=0.5412) | N59: FALSE | O59: human_vs_llm_direction_decomposition.csv | P59: 18/26, vs_50pct_margin=19.2pp
A60: item_c_four_arm_n119_full_bundle_accuracy | B60: 64.6% | C60: percent | D60: 48 | E60: graded events (|ret|>2%) in four_arm_n119 | F60: four_arm_n119 | G60: HOLD-excluded, ±2% overnight band | N60: TRUE | O60: section_ablation_cost_per_correct.csv | P60: 31/48; calls=119; mean_tokens=30096
A61: item_c_four_arm_n119_full_bundle_cost_per_correct | B61: $0.0369 | C61: USD per correct call | D61: 31 | F61: four_arm_n119 | N61: TRUE | O61: section_ablation_cost_per_correct.csv | P61: total_cost=$1.1441; total_tokens=3581446
A62: item_c_four_arm_n119_full_bundle_mean_tokens | B62: 30096 | C62: tokens per call | F62: four_arm_n119 | N62: FALSE | O62: section_ablation_cost_per_correct.csv
A63: item_c_four_arm_n119_press_release_accuracy | B63: 64.9% | C63: percent | D63: 37 | E63: graded events (|ret|>2%) in four_arm_n119 | F63: four_arm_n119 | G63: HOLD-excluded, ±2% overnight band | N63: TRUE | O63: section_ablation_cost_per_correct.csv | P63: 24/37; calls=119; mean_tokens=13030
A64: item_c_four_arm_n119_press_release_cost_per_correct | B64: $0.0225 | C64: USD per correct call | D64: 24 | F64: four_arm_n119 | N64: TRUE | O64: section_ablation_cost_per_correct.csv | P64: total_cost=$0.5394; total_tokens=1550583
A65: item_c_four_arm_n119_press_release_mean_tokens | B65: 13030 | C65: tokens per call | F65: four_arm_n119 | N65: FALSE | O65: section_ablation_cost_per_correct.csv
A66: item_c_four_arm_n119_prepared_remarks_accuracy | B66: 64.4% | C66: percent | D66: 45 | E66: graded events (|ret|>2%) in four_arm_n119 | F66: four_arm_n119 | G66: HOLD-excluded, ±2% overnight band | N66: TRUE | O66: section_ablation_cost_per_correct.csv | P66: 29/45; calls=119; mean_tokens=10287
A67: item_c_four_arm_n119_prepared_remarks_cost_per_correct | B67: $0.0187 | C67: USD per correct call | D67: 29 | F67: four_arm_n119 | N67: TRUE | O67: section_ablation_cost_per_correct.csv | P67: total_cost=$0.5412; total_tokens=1224173
A68: item_c_four_arm_n119_prepared_remarks_mean_tokens | B68: 10287 | C68: tokens per call | F68: four_arm_n119 | N68: FALSE | O68: section_ablation_cost_per_correct.csv
A69: item_c_four_arm_n119_qa_only_accuracy | B69: 69.2% | C69: percent | D69: 39 | E69: graded events (|ret|>2%) in four_arm_n119 | F69: four_arm_n119 | G69: HOLD-excluded, ±2% overnight band | N69: TRUE | O69: section_ablation_cost_per_correct.csv | P69: 27/39; calls=119; mean_tokens=13163
A70: item_c_four_arm_n119_qa_only_cost_per_correct | B70: $0.0220 | C70: USD per correct call | D70: 27 | F70: four_arm_n119 | N70: TRUE | O70: section_ablation_cost_per_correct.csv | P70: total_cost=$0.5952; total_tokens=1566442
A71: item_c_four_arm_n119_qa_only_mean_tokens | B71: 13163 | C71: tokens per call | F71: four_arm_n119 | N71: FALSE | O71: section_ablation_cost_per_correct.csv
A72: item_c_all_n200_full_bundle_accuracy | B72: 65.7% | C72: percent | D72: 70 | E72: graded events (|ret|>2%) in all_n200 | F72: all_n200 | G72: HOLD-excluded, ±2% overnight band | N72: TRUE | O72: section_ablation_cost_per_correct.csv | P72: 46/70; calls=200; mean_tokens=33130
A73: item_c_all_n200_full_bundle_cost_per_correct | B73: $0.0460 | C73: USD per correct call | D73: 46 | F73: all_n200 | N73: TRUE | O73: section_ablation_cost_per_correct.csv | P73: total_cost=$2.1166; total_tokens=6626021
A74: item_c_all_n200_full_bundle_mean_tokens | B74: 33130 | C74: tokens per call | F74: all_n200 | N74: FALSE | O74: section_ablation_cost_per_correct.csv
A75: item_c_all_n200_press_release_accuracy | B75: 62.5% | C75: percent | D75: 56 | E75: graded events (|ret|>2%) in all_n200 | F75: all_n200 | G75: HOLD-excluded, ±2% overnight band | N75: TRUE | O75: section_ablation_cost_per_correct.csv | P75: 35/56; calls=200; mean_tokens=15298
A76: item_c_all_n200_press_release_cost_per_correct | B76: $0.0290 | C76: USD per correct call | D76: 35 | F76: all_n200 | N76: TRUE | O76: section_ablation_cost_per_correct.csv | P76: total_cost=$1.0149; total_tokens=3059630
A77: item_c_all_n200_press_release_mean_tokens | B77: 15298 | C77: tokens per call | F77: all_n200 | N77: FALSE | O77: section_ablation_cost_per_correct.csv
A78: item_c_all_n200_prepared_remarks_accuracy | B78: 64.4% | C78: percent | D78: 45 | E78: graded events (|ret|>2%) in all_n200 | F78: all_n200 | G78: HOLD-excluded, ±2% overnight band | N78: TRUE | O78: section_ablation_cost_per_correct.csv | P78: 29/45; calls=119; mean_tokens=10287
A79: item_c_all_n200_prepared_remarks_cost_per_correct | B79: $0.0187 | C79: USD per correct call | D79: 29 | F79: all_n200 | N79: TRUE | O79: section_ablation_cost_per_correct.csv | P79: total_cost=$0.5412; total_tokens=1224173
A80: item_c_all_n200_prepared_remarks_mean_tokens | B80: 10287 | C80: tokens per call | F80: all_n200 | N80: FALSE | O80: section_ablation_cost_per_correct.csv
A81: item_c_all_n200_qa_only_accuracy | B81: 69.2% | C81: percent | D81: 39 | E81: graded events (|ret|>2%) in all_n200 | F81: all_n200 | G81: HOLD-excluded, ±2% overnight band | N81: TRUE | O81: section_ablation_cost_per_correct.csv | P81: 27/39; calls=119; mean_tokens=13163
A82: item_c_all_n200_qa_only_cost_per_correct | B82: $0.0220 | C82: USD per correct call | D82: 27 | F82: all_n200 | N82: TRUE | O82: section_ablation_cost_per_correct.csv | P82: total_cost=$0.5952; total_tokens=1566442
A83: item_c_all_n200_qa_only_mean_tokens | B83: 13163 | C83: tokens per call | F83: all_n200 | N83: FALSE | O83: section_ablation_cost_per_correct.csv
A84: item_c_paired_press_release_vs_full_bundle_strict_(both_graded) | B84: 0.0278 | C84: fraction diff | D84: 36 | F84: four_arm | G84: strict (both graded) | H84: 0.0 | I84: 0.0833 | K84: 1.0 | N84: TRUE | O84: section_ablation_paired_diffs.csv | P84: On the 36 both-graded events the press release is +2.8pp (p=0.72); the old zero-information identity did not survive the corrected returns
A85: item_c_paired_press_release_vs_full_bundle_inclusive_(either_graded_ungraded=0.5) | B85: -0.0306 | C85: fraction diff | D85: 49 | F85: four_arm | G85: inclusive (either graded, ungraded=0.5) | H85: -0.1020 | I85: 0.0408 | K85: 0.0548 | N85: TRUE | O85: section_ablation_paired_diffs.csv | P85: Full bundle +3.1pp inclusive (p=0.53) — inside the ±12pp paired MDE
A86: item_c_paired_prepared_remarks_vs_full_bundle_strict_(both_graded) | B86: -0.0233 | C86: fraction diff | D86: 43 | F86: four_arm | G86: strict (both graded) | H86: -0.0698 | I86: 0.0 | K86: 0.7284 | N86: TRUE | O86: section_ablation_paired_diffs.csv
A87: item_c_paired_prepared_remarks_vs_full_bundle_inclusive_(either_graded_ungraded=0.5) | B87: -0.0100 | C87: fraction diff | D87: 50 | F87: four_arm | G87: inclusive (either graded, ungraded=0.5) | H87: -0.0700 | I87: 0.0400 | K87: 0.201 | N87: TRUE | O87: section_ablation_paired_diffs.csv
A88: item_c_paired_qa_only_vs_full_bundle_strict_(both_graded) | B88: 0.0263 | C88: fraction diff | D88: 38 | F88: four_arm | G88: strict (both graded) | H88: -0.0526 | I88: 0.1053 | K88: 0.7934 | N88: TRUE | O88: section_ablation_paired_diffs.csv | P88: recomputed 2026-08-21 at the promoted constants on corrected returns (flag C); the 2026-08-13 paired artifact was stale twice over and reproduces from no committed input — same note serves row 89
A89: item_c_paired_qa_only_vs_full_bundle_inclusive_(either_graded_ungraded=0.5) | B89: 0.0102 | C89: fraction diff | D89: 49 | F89: four_arm | G89: inclusive (either graded, ungraded=0.5) | H89: -0.0714 | I89: 0.0918 | K89: 0.2686 | N89: TRUE | O89: section_ablation_paired_diffs.csv
A90: frontier_Majority-class_HOLD_accuracy_flat_excluded | B90: 54.6% | C90: percent | D90: 119 | E90: graded events, FLAT-excluded | F90: eval split (186 events, 119 graded) | H90: 0.471 | I90: 0.622 | J90: 90% | N90: FALSE | O90: frontier_table.csv | P90: Always predicts HOLD; 0 trades. FLAT-excluded: always-DOWN = 65/119.
A91: frontier_Majority-class_HOLD_accuracy_flat_wrong | B91: 36.0% | C91: percent | D91: 186 | E91: all eval events, HOLD=wrong | F91: eval split (186 events) | N91: FALSE | O91: frontier_table.csv
A92: frontier_Loughran-McDonald_(LM)_accuracy_flat_excluded | B92: 3.4% | C92: percent | D92: 119 | E92: graded events, FLAT-excluded | F92: eval split (186 events, 119 graded) | H92: — | I92: — | J92: 90% | N92: FALSE | O92: frontier_table.csv | P92: pysentiment2 word-count score, no API cost. FLAT-excluded: 4/119.
A93: frontier_Loughran-McDonald_(LM)_accuracy_flat_wrong | B93: 37.6% | C93: percent | D93: 186 | E93: all eval events, HOLD=wrong | F93: eval split (186 events) | N93: FALSE | O93: frontier_table.csv
A94: frontier_FinBERT_(ProsusAI_finbert)_accuracy_flat_excluded | B94: 17.6% | C94: percent | D94: 119 | E94: graded events, FLAT-excluded | F94: eval split (186 events, 119 graded) | H94: — | I94: — | J94: 90% | N94: FALSE | O94: frontier_table.csv | P94: 512-token chunks, token-weighted avg; local compute only. FLAT-excluded: 21/119.
A95: frontier_FinBERT_(ProsusAI_finbert)_accuracy_flat_wrong | B95: 32.8% | C95: percent | D95: 186 | E95: all eval events, HOLD=wrong | F95: eval split (186 events) | N95: FALSE | O95: frontier_table.csv
A96: frontier_Deployed_model_(DeepSeek_0.80_0.20_micro_macro)_accuracy_flat_excluded | B96: 48.7% | C96: percent | D96: 119 | E96: graded events, FLAT-excluded | F96: eval split (186 events, 119 graded) | H96: 0.412 | I96: 0.563 | J96: 90% | N96: FALSE | O96: frontier_table.csv | P96: Structured output with evidence quotes; API cost per document. FLAT-excluded: 51/119.
A97: frontier_Deployed_model_(DeepSeek_0.80_0.20_micro_macro)_accuracy_flat_wrong | B97: 41.9% | C97: percent | D97: 186 | E97: all eval events, HOLD=wrong | F97: eval split (186 events) | N97: FALSE | O97: frontier_table.csv
A98: walkforward_n_windows | B98: 4 | N98: FALSE | O98: item_e_walkforward.json
A99: walkforward_degeneracy_finding | B99: {'mean_net_degenerate': 4, 'accuracy_degenerate': 1, 'total_windows': 4, 'both_degenerate': True} | N99: FALSE | O99: item_e_walkforward.json | P99: Both mean-net and accuracy objectives tried; both degenerate
A100: walkforward_mean_net_objective_degenerate_windows | F100: walk-forward mean_net_objective | N100: FALSE | O100: item_e_walkforward.json
...

Sheet Human_Data_Entry
A1: HUMAN ARM CORRECTED. Prices M to P re-anchored on release_date from EDGAR filing dates, 2026-08-13. 295 of 420 rows re-anchored; 125 remain on original report_date basis (human-only events not in LLM universe — see column 'Price Basis Corrected'). Columns Q to U and the Summary, Charts and Efficiency sheets recalculate from these. Original basis retained in Master_Data_LOCKED_2026-08-13.xlsx. See Corrections_Log. | W1: Derived from Time (mins). Do not type here. | X1: HELPER KEY | DO NOT EDIT HERE | AB1: SECTION C — re-priced on the declared basis. Values, not formulas. Nothing to the left of here has been changed. | AL1: SECTION D - provenance and classification. Phase is looked up from Company_List column G. Source File is blank where no document matched the event both uniquely and strongly enough to cite, and Source Basis says which. Nothing to the left of here was changed.
A2: Company | B2: Ticker | C2: Year | D2: Quarter | E2: Document | F2: Section | G2: Rater | H2: Type (Human/LLM) | I2: Sentiment Score (−1 to +1) | J2: Decision (BUY/HOLD/SELL) | K2: Time (mins) | L2: Document Date | M2: Prior Closing Date | N2: Prior Close ($) | O2: Next Opening Date | P2: Next Day Open ($) | Q2: Actual % Change | R2: Actual Direction | S2: Prediction Correct? | T2: Position | U2: Net P&L | V2: Notes / Risks Flagged | W2: Time (sec) | X2: Event Key | Y2: LLM Decision | Z2: LLM Correct? | AA2: Helper columns for the Efficiency sheet. Do not type here. | AB2: Re-priced basis | AC2: Re-priced listing | AD2: Re-priced prior close date | AE2: Re-priced prior close | AF2: Re-priced next open date | AG2: Re-priced next open | AH2: Re-priced % change | AI2: Re-priced direction | AJ2: Re-priced correct? | AK2: Re-priced net P&L | AL2: Phase | AM2: Source File | AN2: Source URL | AO2: Source Basis | AP2: In LLM Universe | AQ2: First Rater for Event | AR2: In Window | AS2: Information Set | AT2: Net P&L on trades (helper) | AU2: Net P&L on trades, re-priced (helper) | AV2: Conviction weight (helper) | AW2: Conviction-weighted P&L (helper) | AX2: Conviction weight, re-priced (helper) | AY2: Event Set | AZ2: Sector | BA2: Pass | BB2: Passes Recorded | BC2: First Reading for Rater-Event | BD2: Pass 1 Minutes | BE2: Pass 2 Minutes | BF2: Pass 1 Score | BG2: Peeked | BH2: AI Declared | BI2: Expectation (written before reading) | BJ2: Rater Record | BK2: Decisions Agree | BL2: Peeked - Basis | BM2: Source Documents Cited | BN2: Source Publisher | BO2: Source Licence Class | BP2: Source Is SEC Periodic Filing | BQ2: Source In Provenance Manifest | BR2: Document Date - Basis | BS2: Price Basis Corrected | BT2: Not Corrected Reason
A3: Netflix | B3: =IF(A3="","",_xlfn.XLOOKUP(A3, Company_List!$A:$A, Company_List!$B:$B, "")) | C3: 2026 | D3: Q1 | E3: All | F3: All | G3: Anna | H3: Human | I3: 0.5 | J3: =IF(OR(I3="",Settings!$B$6=""),"",IF(I3>Settings!$B$6,"BUY",IF(I3<-Settings!$B$6,"SELL","HOLD"))) | K3: 38 | L3: 46128 | M3: 46128 | N3: 107.79 | O3: 46129 | P3: 96.37 | Q3: =IF(OR(N3="",P3=""),"",ROUND((P3-N3)/N3,4)) | R3: =IF(OR(N3="",P3=""),"",IF(Q3>Settings!$B$3/100,"UP",IF(Q3<-Settings!$B$3/100,"DOWN","FLAT"))) | S3: =IF(OR(N3="",P3="",J3=""),"",IF(OR(AND(J3="BUY",R3="UP"),AND(J3="SELL",R3="DOWN"),AND(J3="HOLD",R3="FLAT")),"YES","NO")) | T3: =IF(J3="","",IF(J3="BUY",1,IF(J3="SELL",-1,0))) | U3: =IFERROR(IF(OR(J3="",N3="",P3=""),"",IF(T3=0,0,T3*Q3-Settings!$B$4/10000-IF(T3<0,Settings!$B$5/10000,0))),"") | W3: =IF($K3="","",$K3*60) | X3: =IF($A3="","",$A3&"|"&$C3&"|"&$D3) | Y3: =IFERROR(IF($X3="","",INDEX(LLM_Data_Entry!$H$3:$H$548,MATCH($X3,INDEX(LLM_Data_Entry!$A$3:$A$548&"|"&LLM_Data_Entry!$C$3:$C$548&"|"&LLM_Data_Entry!$D$3:$D$548,0),0))),"") | Z3: =IFERROR(IF($X3="","",INDEX(LLM_Data_Entry!$R$3:$R$548,MATCH($X3,INDEX(LLM_Data_Entry!$A$3:$A$548&"|"&LLM_Data_Entry!$C$3:$C$548&"|"&LLM_Data_Entry!$D$3:$D$548,0),0))),"") | AB3: price signal — only this window shows an abnormal move | AC3: NFLX | AD3: 2026-04-16 | AE3: 107.79 | AF3: 2026-04-17 | AG3: 96.37 | AH3: -0.10594673 | AI3: DOWN | AJ3: NO | AK3: -0.106947 | AL3: =IF($A3="","",IFERROR(INDEX(Company_List!$G$3:$G$207,MATCH($A3,Company_List!$A$3:$A$207,0)),"unassigned")) | AM3: Phase 2/Netflix/Netflix-Inc-_Earnings-Call_2026-04-16T00_00_00_English-1.pdf | AO3: unique filename match | AP3: =IF($A3="","",IF(COUNTIFS(LLM_Data_Entry!$A$3:$A$548,$A3)>0,"YES","NO")) | AQ3: =IF($A3="","",IF(COUNTIFS($A$3:$A3,$A3,$C$3:$C3,$C3,$D$3:$D3,$D3)=1,"YES","NO")) | AR3: =IF($A3="","",IF(AND($C3&"-"&$D3>=Settings!$B$19,$C3&"-"&$D3<=Settings!$B$20),"IN","OUT")) | AS3: =IF($A3="","",IF($F3="Financial Results","financials",IF($F3="Outlook/Guidance","guidance",IF($F3="Transcript Q&A","qanda",IF($F3="","unrecorded",IF($E3="All","full",IF($E3="","unrecorded",LOWER($E3)&" only"))))))) | AT3: =IF(AND(OR($J3="BUY",$J3="SELL"),ISNUMBER($U3)),$U3,"") | AU3: =IF(AND(OR($J3="BUY",$J3="SELL"),ISNUMBER($AK3)),$AK3,"") | AV3: =IF(ISNUMBER($AT3),ABS(IF(ISNUMBER($I3),$I3,0)-Settings!$B$24),"") | AW3: =IF(ISNUMBER($AV3),$AV3*$AT3,"") | AX3: =IF(ISNUMBER($AU3),ABS(IF(ISNUMBER($I3),$I3,0)-Settings!$B$24),"") | AY3: FROZEN | AZ3: =IF($A3="","",IFERROR(INDEX(Company_List!$H$3:$H$207,MATCH($A3,Company_List!$A$3:$A$207,0)),"unassigned")) | BC3: =IF($A3="","",IF(COUNTIFS($A$3:$A3,$A3,$C$3:$C3,$C3,$D$3:$D3,$D3,$G$3:$G3,$G3)=1,1,0)) | BG3: no | BK3: =IF(OR($H3<>"Human",$S3="",$J3="",$Y3="",$Z3=""),"",IF(EXACT(UPPER($J3),UPPER($Y3)),1,0)) | BL3: assumed - no rater record | BM3: 1 | BN3: S&P Global Market Intelligence (Capital IQ) | BO3: licensed vendor | BP3: no | BQ3: no | BS3: YES
A4: Netflix | B4: =IF(A4="","",_xlfn.XLOOKUP(A4, Company_List!$A:$A, Company_List!$B:$B, "")) | C4: 2025 | D4: Q2 | E4: All | F4: All | G4: Anna | H4: Human | I4: 0.2 | J4: =IF(OR(I4="",Settings!$B$6=""),"",IF(I4>Settings!$B$6,"BUY",IF(I4<-Settings!$B$6,"SELL","HOLD"))) | K4: 26 | L4: 45855 | M4: 45855 | N4: 127.417 | O4: 45856 | P4: 124.2 | Q4: =IF(OR(N4="",P4=""),"",ROUND((P4-N4)/N4,4)) | R4: =IF(OR(N4="",P4=""),"",IF(Q4>Settings!$B$3/100,"UP",IF(Q4<-Settings!$B$3/100,"DOWN","FLAT"))) | S4: =IF(OR(N4="",P4="",J4=""),"",IF(OR(AND(J4="BUY",R4="UP"),AND(J4="SELL",R4="DOWN"),AND(J4="HOLD",R4="FLAT")),"YES","NO")) | T4: =IF(J4="","",IF(J4="BUY",1,IF(J4="SELL",-1,0))) | U4: =IFERROR(IF(OR(J4="",N4="",P4=""),"",IF(T4=0,0,T4*Q4-Settings!$B$4/10000-IF(T4<0,Settings!$B$5/10000,0))),"") | W4: =IF($K4="","",$K4*60) | X4: =IF($A4="","",$A4&"|"&$C4&"|"&$D4) | Y4: =IFERROR(IF($X4="","",INDEX(LLM_Data_Entry!$H$3:$H$548,MATCH($X4,INDEX(LLM_Data_Entry!$A$3:$A$548&"|"&LLM_Data_Entry!$C$3:$C$548&"|"&LLM_Data_Entry!$D$3:$D$548,0),0))),"") | Z4: =IFERROR(IF($X4="","",INDEX(LLM_Data_Entry!$R$3:$R$548,MATCH($X4,INDEX(LLM_Data_Entry!$A$3:$A$548&"|"&LLM_Data_Entry!$C$3:$C$548&"|"&LLM_Data_Entry!$D$3:$D$548,0),0))),"") | AB4: price signal — only this window shows an abnormal move | AC4: NFLX | AD4: 2025-07-17 | AE4: 127.417 | AF4: 2025-07-18 | AG4: 124.196 | AH4: -0.025279209 | AI4: DOWN | AJ4: NO | AK4: 0 | AL4: =IF($A4="","",IFERROR(INDEX(Company_List!$G$3:$G$207,MATCH($A4,Company_List!$A$3:$A$207,0)),"unassigned")) | AM4: Phase 2/Netflix/2025-Q2/NFLX-2025-Q2-press-release-SEC-EX-99-1.htm | AN4: https://www.sec.gov/Archives/edgar/data/1065280/000106528025000322/ex991_q225.htm | AO4: manifest | AP4: =IF($A4="","",IF(COUNTIFS(LLM_Data_Entry!$A$3:$A$548,$A4)>0,"YES","NO")) | AQ4: =IF($A4="","",IF(COUNTIFS($A$3:$A4,$A4,$C$3:$C4,$C4,$D$3:$D4,$D4)=1,"YES","NO")) | AR4: =IF($A4="","",IF(AND($C4&"-"&$D4>=Settings!$B$19,$C4&"-"&$D4<=Settings!$B$20),"IN","OUT")) | AS4: =IF($A4="","",IF($F4="Financial Results","financials",IF($F4="Outlook/Guidance","guidance",IF($F4="Transcript Q&A","qanda",IF($F4="","unrecorded",IF($E4="All","full",IF($E4="","unrecorded",LOWER($E4)&" only"))))))) | AT4: =IF(AND(OR($J4="BUY",$J4="SELL"),ISNUMBER($U4)),$U4,"") | AU4: =IF(AND(OR($J4="BUY",$J4="SELL"),ISNUMBER($AK4)),$AK4,"") | AV4: =IF(ISNUMBER($AT4),ABS(IF(ISNUMBER($I4),$I4,0)-Settings!$B$24),"") | AW4: =IF(ISNUMBER($AV4),$AV4*$AT4,"") | AX4: =IF(ISNUMBER($AU4),ABS(IF(ISNUMBER($I4),$I4,0)-Settings!$B$24),"") | AY4: FROZEN | AZ4: =IF($A4="","",IFERROR(INDEX(Company_List!$H$3:$H$207,MATCH($A4,Company_List!$A$3:$A$207,0)),"unassigned")) | BC4: =IF($A4="","",IF(COUNTIFS($A$3:$A4,$A4,$C$3:$C4,$C4,$D$3:$D4,$D4,$G$3:$G4,$G4)=1,1,0)) | BG4: no | BK4: =IF(OR($H4<>"Human",$S4="",$J4="",$Y4="",$Z4=""),"",IF(EXACT(UPPER($J4),UPPER($Y4)),1,0)) | BL4: assumed - no rater record | BM4: 1 | BN4: not publisher-identified | BO4: not publisher-identified | BP4: no | BQ4: yes | BS4: YES
A5: Netflix | B5: =IF(A5="","",_xlfn.XLOOKUP(A5, Company_List!$A:$A, Company_List!$B:$B, "")) | C5: 2025 | D5: Q3 | E5: All | F5: All | G5: Anna | H5: Human | I5: -0.2 | J5: =IF(OR(I5="",Settings!$B$6=""),"",IF(I5>Settings!$B$6,"BUY",IF(I5<-Settings!$B$6,"SELL","HOLD"))) | K5: 24 | L5: 45951 | M5: 45951 | N5: 124.135 | O5: 45952 | P5: 114.29 | Q5: =IF(OR(N5="",P5=""),"",ROUND((P5-N5)/N5,4)) | R5: =IF(OR(N5="",P5=""),"",IF(Q5>Settings!$B$3/100,"UP",IF(Q5<-Settings!$B$3/100,"DOWN","FLAT"))) | S5: =IF(OR(N5="",P5="",J5=""),"",IF(OR(AND(J5="BUY",R5="UP"),AND(J5="SELL",R5="DOWN"),AND(J5="HOLD",R5="FLAT")),"YES","NO")) | T5: =IF(J5="","",IF(J5="BUY",1,IF(J5="SELL",-1,0))) | U5: =IFERROR(IF(OR(J5="",N5="",P5=""),"",IF(T5=0,0,T5*Q5-Settings!$B$4/10000-IF(T5<0,Settings!$B$5/10000,0))),"") | W5: =IF($K5="","",$K5*60) | X5: =IF($A5="","",$A5&"|"&$C5&"|"&$D5) | Y5: =IFERROR(IF($X5="","",INDEX(LLM_Data_Entry!$H$3:$H$548,MATCH($X5,INDEX(LLM_Data_Entry!$A$3:$A$548&"|"&LLM_Data_Entry!$C$3:$C$548&"|"&LLM_Data_Entry!$D$3:$D$548,0),0))),"") | Z5: =IFERROR(IF($X5="","",INDEX(LLM_Data_Entry!$R$3:$R$548,MATCH($X5,INDEX(LLM_Data_Entry!$A$3:$A$548&"|"&LLM_Data_Entry!$C$3:$C$548&"|"&LLM_Data_Entry!$D$3:$D$548,0),0))),"") | AB5: release date + stated time in the document (rater worksheet) | AC5: NFLX | AD5: 2025-10-21 | AE5: 124.135 | AF5: 2025-10-22 | AG5: 114.29 | AH5: -0.079308824 | AI5: DOWN | AJ5: NO | AK5: 0 | AL5: =IF($A5="","",IFERROR(INDEX(Company_List!$G$3:$G$207,MATCH($A5,Company_List!$A$3:$A$207,0)),"unassigned")) | AM5: Phase 2/Netflix/2025-Q3/NFLX-2025-Q3-press-release-SEC-EX-99-1.htm | AN5: https://www.sec.gov/Archives/edgar/data/1065280/000106528025000404/ex991_q325.htm | AO5: manifest | AP5: =IF($A5="","",IF(COUNTIFS(LLM_Data_Entry!$A$3:$A$548,$A5)>0,"YES","NO")) | AQ5: =IF($A5="","",IF(COUNTIFS($A$3:$A5,$A5,$C$3:$C5,$C5,$D$3:$D5,$D5)=1,"YES","NO")) | AR5: =IF($A5="","",IF(AND($C5&"-"&$D5>=Settings!$B$19,$C5&"-"&$D5<=Settings!$B$20),"IN","OUT")) | AS5: =IF($A5="","",IF($F5="Financial Results","financials",IF($F5="Outlook/Guidance","guidance",IF($F5="Transcript Q&A","qanda",IF($F5="","unrecorded",IF($E5="All","full",IF($E5="","unrecorded",LOWER($E5)&" only"))))))) | AT5: =IF(AND(OR($J5="BUY",$J5="SELL"),ISNUMBER($U5)),$U5,"") | AU5: =IF(AND(OR($J5="BUY",$J5="SELL"),ISNUMBER($AK5)),$AK5,"") | AV5: =IF(ISNUMBER($AT5),ABS(IF(ISNUMBER($I5),$I5,0)-Settings!$B$24),"") | AW5: =IF(ISNUMBER($AV5),$AV5*$AT5,"") | AX5: =IF(ISNUMBER($AU5),ABS(IF(ISNUMBER($I5),$I5,0)-Settings!$B$24),"") | AY5: FROZEN | AZ5: =IF($A5="","",IFERROR(INDEX(Company_List!$H$3:$H$207,MATCH($A5,Company_List!$A$3:$A$207,0)),"unassigned")) | BC5: =IF($A5="","",IF(COUNTIFS($A$3:$A5,$A5,$C$3:$C5,$C5,$D$3:$D5,$D5,$G$3:$G5,$G5)=1,1,0)) | BG5: no | BK5: =IF(OR($H5<>"Human",$S5="",$J5="",$Y5="",$Z5=""),"",IF(EXACT(UPPER($J5),UPPER($Y5)),1,0)) | BL5: assumed - no rater record | BM5: 1 | BN5: not publisher-identified | BO5: not publisher-identified | BP5: no | BQ5: yes | BS5: YES
A6: Netflix | B6: =IF(A6="","",_xlfn.XLOOKUP(A6, Company_List!$A:$A, Company_List!$B:$B, "")) | C6: 2025 | D6: Q4 | E6: All | F6: All | G6: Anna | H6: Human | I6: 0.6 | J6: =IF(OR(I6="",Settings!$B$6=""),"",IF(I6>Settings!$B$6,"BUY",IF(I6<-Settings!$B$6,"SELL","HOLD"))) | K6: 25 | L6: 46042 | M6: 46042 | N6: 87.26 | O6: 46043 | P6: 82.52 | Q6: =IF(OR(N6="",P6=""),"",ROUND((P6-N6)/N6,4)) | R6: =IF(OR(N6="",P6=""),"",IF(Q6>Settings!$B$3/100,"UP",IF(Q6<-Settings!$B$3/100,"DOWN","FLAT"))) | S6: =IF(OR(N6="",P6="",J6=""),"",IF(OR(AND(J6="BUY",R6="UP"),AND(J6="SELL",R6="DOWN"),AND(J6="HOLD",R6="FLAT")),"YES","NO")) | T6: =IF(J6="","",IF(J6="BUY",1,IF(J6="SELL",-1,0))) | U6: =IFERROR(IF(OR(J6="",N6="",P6=""),"",IF(T6=0,0,T6*Q6-Settings!$B$4/10000-IF(T6<0,Settings!$B$5/10000,0))),"") | W6: =IF($K6="","",$K6*60) | X6: =IF($A6="","",$A6&"|"&$C6&"|"&$D6) | Y6: =IFERROR(IF($X6="","",INDEX(LLM_Data_Entry!$H$3:$H$548,MATCH($X6,INDEX(LLM_Data_Entry!$A$3:$A$548&"|"&LLM_Data_Entry!$C$3:$C$548&"|"&LLM_Data_Entry!$D$3:$D$548,0),0))),"") | Z6: =IFERROR(IF($X6="","",INDEX(LLM_Data_Entry!$R$3:$R$548,MATCH($X6,INDEX(LLM_Data_Entry!$A$3:$A$548&"|"&LLM_Data_Entry!$C$3:$C$548&"|"&LLM_Data_Entry!$D$3:$D$548,0),0))),"") | AB6: release date + stated time in the document (rater worksheet) | AC6: NFLX | AD6: 2026-01-20 | AE6: 87.26 | AF6: 2026-01-21 | AG6: 82.52 | AH6: -0.054320478 | AI6: DOWN | AJ6: NO | AK6: -0.05532 | AL6: =IF($A6="","",IFERROR(INDEX(Company_List!$G$3:$G$207,MATCH($A6,Company_List!$A$3:$A$207,0)),"unassigned")) | AM6: Phase 2/Netflix/2025-Q4/NFLX-2025-Q4-press-release-SEC-EX-99-1.htm | AN6: https://www.sec.gov/Archives/edgar/data/1065280/000106528026000033/ex991_q425.htm | AO6: manifest | AP6: =IF($A6="","",IF(COUNTIFS(LLM_Data_Entry!$A$3:$A$548,$A6)>0,"YES","NO")) | AQ6: =IF($A6="","",IF(COUNTIFS($A$3:$A6,$A6,$C$3:$C6,$C6,$D$3:$D6,$D6)=1,"YES","NO")) | AR6: =IF($A6="","",IF(AND($C6&"-"&$D6>=Settings!$B$19,$C6&"-"&$D6<=Settings!$B$20),"IN","OUT")) | AS6: =IF($A6="","",IF($F6="Financial Results","financials",IF($F6="Outlook/Guidance","guidance",IF($F6="Transcript Q&A","qanda",IF($F6="","unrecorded",IF($E6="All","full",IF($E6="","unrecorded",LOWER($E6)&" only"))))))) | AT6: =IF(AND(OR($J6="BUY",$J6="SELL"),ISNUMBER($U6)),$U6,"") | AU6: =IF(AND(OR($J6="BUY",$J6="SELL"),ISNUMBER($AK6)),$AK6,"") | AV6: =IF(ISNUMBER($AT6),ABS(IF(ISNUMBER($I6),$I6,0)-Settings!$B$24),"") | AW6: =IF(ISNUMBER($AV6),$AV6*$AT6,"") | AX6: =IF(ISNUMBER($AU6),ABS(IF(ISNUMBER($I6),$I6,0)-Settings!$B$24),"") | AY6: FROZEN | AZ6: =IF($A6="","",IFERROR(INDEX(Company_List!$H$3:$H$207,MATCH($A6,Company_List!$A$3:$A$207,0)),"unassigned")) | BC6: =IF($A6="","",IF(COUNTIFS($A$3:$A6,$A6,$C$3:$C6,$C6,$D$3:$D6,$D6,$G$3:$G6,$G6)=1,1,0)) | BG6: no | BK6: =IF(OR($H6<>"Human",$S6="",$J6="",$Y6="",$Z6=""),"",IF(EXACT(UPPER($J6),UPPER($Y6)),1,0)) | BL6: assumed - no rater record | BM6: 1 | BN6: not publisher-identified | BO6: not publisher-identified | BP6: no | BQ6: yes | BS6: YES
A7: Netflix | B7: =IF(A7="","",_xlfn.XLOOKUP(A7, Company_List!$A:$A, Company_List!$B:$B, "")) | C7: 2026 | D7: Q1 | E7: All | F7: All | G7: Meriem | H7: Human | I7: 0.6 | J7: =IF(OR(I7="",Settings!$B$6=""),"",IF(I7>Settings!$B$6,"BUY",IF(I7<-Settings!$B$6,"SELL","HOLD"))) | K7: 35 | L7: 46128 | M7: 46128 | N7: 107.79 | O7: 46129 | P7: 96.37 | Q7: =IF(OR(N7="",P7=""),"",ROUND((P7-N7)/N7,4)) | R7: =IF(OR(N7="",P7=""),"",IF(Q7>Settings!$B$3/100,"UP",IF(Q7<-Settings!$B$3/100,"DOWN","FLAT"))) | S7: =IF(OR(N7="",P7="",J7=""),"",IF(OR(AND(J7="BUY",R7="UP"),AND(J7="SELL",R7="DOWN"),AND(J7="HOLD",R7="FLAT")),"YES","NO")) | T7: =IF(J7="","",IF(J7="BUY",1,IF(J7="SELL",-1,0))) | U7: =IFERROR(IF(OR(J7="",N7="",P7=""),"",IF(T7=0,0,T7*Q7-Settings!$B$4/10000-IF(T7<0,Settings!$B$5/10000,0))),"") | W7: =IF($K7="","",$K7*60) | X7: =IF($A7="","",$A7&"|"&$C7&"|"&$D7) | Y7: =IFERROR(IF($X7="","",INDEX(LLM_Data_Entry!$H$3:$H$548,MATCH($X7,INDEX(LLM_Data_Entry!$A$3:$A$548&"|"&LLM_Data_Entry!$C$3:$C$548&"|"&LLM_Data_Entry!$D$3:$D$548,0),0))),"") | Z7: =IFERROR(IF($X7="","",INDEX(LLM_Data_Entry!$R$3:$R$548,MATCH($X7,INDEX(LLM_Data_Entry!$A$3:$A$548&"|"&LLM_Data_Entry!$C$3:$C$548&"|"&LLM_Data_Entry!$D$3:$D$548,0),0))),"") | AB7: price signal — only this window shows an abnormal move | AC7: NFLX | AD7: 2026-04-16 | AE7: 107.79 | AF7: 2026-04-17 | AG7: 96.37 | AH7: -0.10594673 | AI7: DOWN | AJ7: NO | AK7: -0.106947 | AL7: =IF($A7="","",IFERROR(INDEX(Company_List!$G$3:$G$207,MATCH($A7,Company_List!$A$3:$A$207,0)),"unassigned")) | AM7: Phase 2/Netflix/Netflix-Inc-_Earnings-Call_2026-04-16T00_00_00_English-1.pdf | AO7: unique filename match | AP7: =IF($A7="","",IF(COUNTIFS(LLM_Data_Entry!$A$3:$A$548,$A7)>0,"YES","NO")) | AQ7: =IF($A7="","",IF(COUNTIFS($A$3:$A7,$A7,$C$3:$C7,$C7,$D$3:$D7,$D7)=1,"YES","NO")) | AR7: =IF($A7="","",IF(AND($C7&"-"&$D7>=Settings!$B$19,$C7&"-"&$D7<=Settings!$B$20),"IN","OUT")) | AS7: =IF($A7="","",IF($F7="Financial Results","financials",IF($F7="Outlook/Guidance","guidance",IF($F7="Transcript Q&A","qanda",IF($F7="","unrecorded",IF($E7="All","full",IF($E7="","unrecorded",LOWER($E7)&" only"))))))) | AT7: =IF(AND(OR($J7="BUY",$J7="SELL"),ISNUMBER($U7)),$U7,"") | AU7: =IF(AND(OR($J7="BUY",$J7="SELL"),ISNUMBER($AK7)),$AK7,"") | AV7: =IF(ISNUMBER($AT7),ABS(IF(ISNUMBER($I7),$I7,0)-Settings!$B$24),"") | AW7: =IF(ISNUMBER($AV7),$AV7*$AT7,"") | AX7: =IF(ISNUMBER($AU7),ABS(IF(ISNUMBER($I7),$I7,0)-Settings!$B$24),"") | AY7: FROZEN | AZ7: =IF($A7="","",IFERROR(INDEX(Company_List!$H$3:$H$207,MATCH($A7,Company_List!$A$3:$A$207,0)),"unassigned")) | BC7: =IF($A7="","",IF(COUNTIFS($A$3:$A7,$A7,$C$3:$C7,$C7,$D$3:$D7,$D7,$G$3:$G7,$G7)=1,1,0)) | BG7: no | BK7: =IF(OR($H7<>"Human",$S7="",$J7="",$Y7="",$Z7=""),"",IF(EXACT(UPPER($J7),UPPER($Y7)),1,0)) | BL7: assumed - no rater record | BM7: 1 | BN7: S&P Global Market Intelligence (Capital IQ) | BO7: licensed vendor | BP7: no | BQ7: no | BS7: YES
A8: Netflix | B8: =IF(A8="","",_xlfn.XLOOKUP(A8, Company_List!$A:$A, Company_List!$B:$B, "")) | C8: 2025 | D8: Q2 | E8: All | F8: All | G8: Meriem | H8: Human | I8: 0.7 | J8: =IF(OR(I8="",Settings!$B$6=""),"",IF(I8>Settings!$B$6,"BUY",IF(I8<-Settings!$B$6,"SELL","HOLD"))) | K8: 55 | L8: 45855 | M8: 45855 | N8: 127.417 | O8: 45856 | P8: 124.2 | Q8: =IF(OR(N8="",P8=""),"",ROUND((P8-N8)/N8,4)) | R8: =IF(OR(N8="",P8=""),"",IF(Q8>Settings!$B$3/100,"UP",IF(Q8<-Settings!$B$3/100,"DOWN","FLAT"))) | S8: =IF(OR(N8="",P8="",J8=""),"",IF(OR(AND(J8="BUY",R8="UP"),AND(J8="SELL",R8="DOWN"),AND(J8="HOLD",R8="FLAT")),"YES","NO")) | T8: =IF(J8="","",IF(J8="BUY",1,IF(J8="SELL",-1,0))) | U8: =IFERROR(IF(OR(J8="",N8="",P8=""),"",IF(T8=0,0,T8*Q8-Settings!$B$4/10000-IF(T8<0,Settings!$B$5/10000,0))),"") | W8: =IF($K8="","",$K8*60) | X8: =IF($A8="","",$A8&"|"&$C8&"|"&$D8) | Y8: =IFERROR(IF($X8="","",INDEX(LLM_Data_Entry!$H$3:$H$548,MATCH($X8,INDEX(LLM_Data_Entry!$A$3:$A$548&"|"&LLM_Data_Entry!$C$3:$C$548&"|"&LLM_Data_Entry!$D$3:$D$548,0),0))),"") | Z8: =IFERROR(IF($X8="","",INDEX(LLM_Data_Entry!$R$3:$R$548,MATCH($X8,INDEX(LLM_Data_Entry!$A$3:$A$548&"|"&LLM_Data_Entry!$C$3:$C$548&"|"&LLM_Data_Entry!$D$3:$D$548,0),0))),"") | AB8: price signal — only this window shows an abnormal move | AC8: NFLX | AD8: 2025-07-17 | AE8: 127.417 | AF8: 2025-07-18 | AG8: 124.196 | AH8: -0.025279209 | AI8: DOWN | AJ8: NO | AK8: -0.026279 | AL8: =IF($A8="","",IFERROR(INDEX(Company_List!$G$3:$G$207,MATCH($A8,Company_List!$A$3:$A$207,0)),"unassigned")) | AM8: Phase 2/Netflix/2025-Q2/NFLX-2025-Q2-press-release-SEC-EX-99-1.htm | AN8: https://www.sec.gov/Archives/edgar/data/1065280/000106528025000322/ex991_q225.htm | AO8: manifest | AP8: =IF($A8="","",IF(COUNTIFS(LLM_Data_Entry!$A$3:$A$548,$A8)>0,"YES","NO")) | AQ8: =IF($A8="","",IF(COUNTIFS($A$3:$A8,$A8,$C$3:$C8,$C8,$D$3:$D8,$D8)=1,"YES","NO")) | AR8: =IF($A8="","",IF(AND($C8&"-"&$D8>=Settings!$B$19,$C8&"-"&$D8<=Settings!$B$20),"IN","OUT")) | AS8: =IF($A8="","",IF($F8="Financial Results","financials",IF($F8="Outlook/Guidance","guidance",IF($F8="Transcript Q&A","qanda",IF($F8="","unrecorded",IF($E8="All","full",IF($E8="","unrecorded",LOWER($E8)&" only"))))))) | AT8: =IF(AND(OR($J8="BUY",$J8="SELL"),ISNUMBER($U8)),$U8,"") | AU8: =IF(AND(OR($J8="BUY",$J8="SELL"),ISNUMBER($AK8)),$AK8,"") | AV8: =IF(ISNUMBER($AT8),ABS(IF(ISNUMBER($I8),$I8,0)-Settings!$B$24),"") | AW8: =IF(ISNUMBER($AV8),$AV8*$AT8,"") | AX8: =IF(ISNUMBER($AU8),ABS(IF(ISNUMBER($I8),$I8,0)-Settings!$B$24),"") | AY8: FROZEN | AZ8: =IF($A8="","",IFERROR(INDEX(Company_List!$H$3:$H$207,MATCH($A8,Company_List!$A$3:$A$207,0)),"unassigned")) | BC8: =IF($A8="","",IF(COUNTIFS($A$3:$A8,$A8,$C$3:$C8,$C8,$D$3:$D8,$D8,$G$3:$G8,$G8)=1,1,0)) | BG8: no | BK8: =IF(OR($H8<>"Human",$S8="",$J8="",$Y8="",$Z8=""),"",IF(EXACT(UPPER($J8),UPPER($Y8)),1,0)) | BL8: assumed - no rater record | BM8: 1 | BN8: not publisher-identified | BO8: not publisher-identified | BP8: no | BQ8: yes | BS8: YES
A9: Netflix | B9: =IF(A9="","",_xlfn.XLOOKUP(A9, Company_List!$A:$A, Company_List!$B:$B, "")) | C9: 2025 | D9: Q3 | E9: All | F9: All | G9: Meriem | H9: Human | I9: -0.5 | J9: =IF(OR(I9="",Settings!$B$6=""),"",IF(I9>Settings!$B$6,"BUY",IF(I9<-Settings!$B$6,"SELL","HOLD"))) | K9: 38 | L9: 45951 | M9: 45951 | N9: 124.135 | O9: 45952 | P9: 114.29 | Q9: =IF(OR(N9="",P9=""),"",ROUND((P9-N9)/N9,4)) | R9: =IF(OR(N9="",P9=""),"",IF(Q9>Settings!$B$3/100,"UP",IF(Q9<-Settings!$B$3/100,"DOWN","FLAT"))) | S9: =IF(OR(N9="",P9="",J9=""),"",IF(OR(AND(J9="BUY",R9="UP"),AND(J9="SELL",R9="DOWN"),AND(J9="HOLD",R9="FLAT")),"YES","NO")) | T9: =IF(J9="","",IF(J9="BUY",1,IF(J9="SELL",-1,0))) | U9: =IFERROR(IF(OR(J9="",N9="",P9=""),"",IF(T9=0,0,T9*Q9-Settings!$B$4/10000-IF(T9<0,Settings!$B$5/10000,0))),"") | W9: =IF($K9="","",$K9*60) | X9: =IF($A9="","",$A9&"|"&$C9&"|"&$D9) | Y9: =IFERROR(IF($X9="","",INDEX(LLM_Data_Entry!$H$3:$H$548,MATCH($X9,INDEX(LLM_Data_Entry!$A$3:$A$548&"|"&LLM_Data_Entry!$C$3:$C$548&"|"&LLM_Data_Entry!$D$3:$D$548,0),0))),"") | Z9: =IFERROR(IF($X9="","",INDEX(LLM_Data_Entry!$R$3:$R$548,MATCH($X9,INDEX(LLM_Data_Entry!$A$3:$A$548&"|"&LLM_Data_Entry!$C$3:$C$548&"|"&LLM_Data_Entry!$D$3:$D$548,0),0))),"") | AB9: release date + stated time in the document (rater worksheet) | AC9: NFLX | AD9: 2025-10-21 | AE9: 124.135 | AF9: 2025-10-22 | AG9: 114.29 | AH9: -0.079308824 | AI9: DOWN | AJ9: YES | AK9: 0.078309 | AL9: =IF($A9="","",IFERROR(INDEX(Company_List!$G$3:$G$207,MATCH($A9,Company_List!$A$3:$A$207,0)),"unassigned")) | AM9: Phase 2/Netflix/2025-Q3/NFLX-2025-Q3-press-release-SEC-EX-99-1.htm | AN9: https://www.sec.gov/Archives/edgar/data/1065280/000106528025000404/ex991_q325.htm | AO9: manifest | AP9: =IF($A9="","",IF(COUNTIFS(LLM_Data_Entry!$A$3:$A$548,$A9)>0,"YES","NO")) | AQ9: =IF($A9="","",IF(COUNTIFS($A$3:$A9,$A9,$C$3:$C9,$C9,$D$3:$D9,$D9)=1,"YES","NO")) | AR9: =IF($A9="","",IF(AND($C9&"-"&$D9>=Settings!$B$19,$C9&"-"&$D9<=Settings!$B$20),"IN","OUT")) | AS9: =IF($A9="","",IF($F9="Financial Results","financials",IF($F9="Outlook/Guidance","guidance",IF($F9="Transcript Q&A","qanda",IF($F9="","unrecorded",IF($E9="All","full",IF($E9="","unrecorded",LOWER($E9)&" only"))))))) | AT9: =IF(AND(OR($J9="BUY",$J9="SELL"),ISNUMBER($U9)),$U9,"") | AU9: =IF(AND(OR($J9="BUY",$J9="SELL"),ISNUMBER($AK9)),$AK9,"") | AV9: =IF(ISNUMBER($AT9),ABS(IF(ISNUMBER($I9),$I9,0)-Settings!$B$24),"") | AW9: =IF(ISNUMBER($AV9),$AV9*$AT9,"") | AX9: =IF(ISNUMBER($AU9),ABS(IF(ISNUMBER($I9),$I9,0)-Settings!$B$24),"") | AY9: FROZEN | AZ9: =IF($A9="","",IFERROR(INDEX(Company_List!$H$3:$H$207,MATCH($A9,Company_List!$A$3:$A$207,0)),"unassigned")) | BC9: =IF($A9="","",IF(COUNTIFS($A$3:$A9,$A9,$C$3:$C9,$C9,$D$3:$D9,$D9,$G$3:$G9,$G9)=1,1,0)) | BG9: no | BK9: =IF(OR($H9<>"Human",$S9="",$J9="",$Y9="",$Z9=""),"",IF(EXACT(UPPER($J9),UPPER($Y9)),1,0)) | BL9: assumed - no rater record | BM9: 1 | BN9: not publisher-identified | BO9: not publisher-identified | BP9: no | BQ9: yes | BS9: YES
A10: Netflix | B10: =IF(A10="","",_xlfn.XLOOKUP(A10, Company_List!$A:$A, Company_List!$B:$B, "")) | C10: 2025 | D10: Q4 | E10: All | F10: All | G10: Meriem | H10: Human | I10: 0.2 | J10: =IF(OR(I10="",Settings!$B$6=""),"",IF(I10>Settings!$B$6,"BUY",IF(I10<-Settings!$B$6,"SELL","HOLD"))) | K10: 40 | L10: 46042 | M10: 46042 | N10: 87.26 | O10: 46043 | P10: 82.52 | Q10: =IF(OR(N10="",P10=""),"",ROUND((P10-N10)/N10,4)) | R10: =IF(OR(N10="",P10=""),"",IF(Q10>Settings!$B$3/100,"UP",IF(Q10<-Settings!$B$3/100,"DOWN","FLAT"))) | S10: =IF(OR(N10="",P10="",J10=""),"",IF(OR(AND(J10="BUY",R10="UP"),AND(J10="SELL",R10="DOWN"),AND(J10="HOLD",R10="FLAT")),"YES","NO")) | T10: =IF(J10="","",IF(J10="BUY",1,IF(J10="SELL",-1,0))) | U10: =IFERROR(IF(OR(J10="",N10="",P10=""),"",IF(T10=0,0,T10*Q10-Settings!$B$4/10000-IF(T10<0,Settings!$B$5/10000,0))),"") | W10: =IF($K10="","",$K10*60) | X10: =IF($A10="","",$A10&"|"&$C10&"|"&$D10) | Y10: =IFERROR(IF($X10="","",INDEX(LLM_Data_Entry!$H$3:$H$548,MATCH($X10,INDEX(LLM_Data_Entry!$A$3:$A$548&"|"&LLM_Data_Entry!$C$3:$C$548&"|"&LLM_Data_Entry!$D$3:$D$548,0),0))),"") | Z10: =IFERROR(IF($X10="","",INDEX(LLM_Data_Entry!$R$3:$R$548,MATCH($X10,INDEX(LLM_Data_Entry!$A$3:$A$548&"|"&LLM_Data_Entry!$C$3:$C$548&"|"&LLM_Data_Entry!$D$3:$D$548,0),0))),"") | AB10: release date + stated time in the document (rater worksheet) | AC10: NFLX | AD10: 2026-01-20 | AE10: 87.26 | AF10: 2026-01-21 | AG10: 82.52 | AH10: -0.054320478 | AI10: DOWN | AJ10: NO | AK10: 0 | AL10: =IF($A10="","",IFERROR(INDEX(Company_List!$G$3:$G$207,MATCH($A10,Company_List!$A$3:$A$207,0)),"unassigned")) | AM10: Phase 2/Netflix/2025-Q4/NFLX-2025-Q4-press-release-SEC-EX-99-1.htm | AN10: https://www.sec.gov/Archives/edgar/data/1065280/000106528026000033/ex991_q425.htm | AO10: manifest | AP10: =IF($A10="","",IF(COUNTIFS(LLM_Data_Entry!$A$3:$A$548,$A10)>0,"YES","NO")) | AQ10: =IF($A10="","",IF(COUNTIFS($A$3:$A10,$A10,$C$3:$C10,$C10,$D$3:$D10,$D10)=1,"YES","NO")) | AR10: =IF($A10="","",IF(AND($C10&"-"&$D10>=Settings!$B$19,$C10&"-"&$D10<=Settings!$B$20),"IN","OUT")) | AS10: =IF($A10="","",IF($F10="Financial Results","financials",IF($F10="Outlook/Guidance","guidance",IF($F10="Transcript Q&A","qanda",IF($F10="","unrecorded",IF($E10="All","full",IF($E10="","unrecorded",LOWER($E10)&" only"))))))) | AT10: =IF(AND(OR($J10="BUY",$J10="SELL"),ISNUMBER($U10)),$U10,"") | AU10: =IF(AND(OR($J10="BUY",$J10="SELL"),ISNUMBER($AK10)),$AK10,"") | AV10: =IF(ISNUMBER($AT10),ABS(IF(ISNUMBER($I10),$I10,0)-Settings!$B$24),"") | AW10: =IF(ISNUMBER($AV10),$AV10*$AT10,"") | AX10: =IF(ISNUMBER($AU10),ABS(IF(ISNUMBER($I10),$I10,0)-Settings!$B$24),"") | AY10: FROZEN | AZ10: =IF($A10="","",IFERROR(INDEX(Company_List!$H$3:$H$207,MATCH($A10,Company_List!$A$3:$A$207,0)),"unassigned")) | BC10: =IF($A10="","",IF(COUNTIFS($A$3:$A10,$A10,$C$3:$C10,$C10,$D$3:$D10,$D10,$G$3:$G10,$G10)=1,1,0)) | BG10: no | BK10: =IF(OR($H10<>"Human",$S10="",$J10="",$Y10="",$Z10=""),"",IF(EXACT(UPPER($J10),UPPER($Y10)),1,0)) | BL10: assumed - no rater record | BM10: 1 | BN10: not publisher-identified | BO10: not publisher-identified | BP10: no | BQ10: yes | BS10: YES
A11: Netflix | B11: =IF(A11="","",_xlfn.XLOOKUP(A11, Company_List!$A:$A, Company_List!$B:$B, "")) | C11: 2025 | D11: Q1 | E11: All | F11: All | G11: Dragos | H11: Human | I11: 0.65 | J11: =IF(OR(I11="",Settings!$B$6=""),"",IF(I11>Settings!$B$6,"BUY",IF(I11<-Settings!$B$6,"SELL","HOLD"))) | K11: 42 | L11: 45764 | M11: 45764 | N11: 97.303 | O11: 45765 | P11: 98.44 | Q11: =IF(OR(N11="",P11=""),"",ROUND((P11-N11)/N11,4)) | R11: =IF(OR(N11="",P11=""),"",IF(Q11>Settings!$B$3/100,"UP",IF(Q11<-Settings!$B$3/100,"DOWN","FLAT"))) | S11: =IF(OR(N11="",P11="",J11=""),"",IF(OR(AND(J11="BUY",R11="UP"),AND(J11="SELL",R11="DOWN"),AND(J11="HOLD",R11="FLAT")),"YES","NO")) | T11: =IF(J11="","",IF(J11="BUY",1,IF(J11="SELL",-1,0))) | U11: =IFERROR(IF(OR(J11="",N11="",P11=""),"",IF(T11=0,0,T11*Q11-Settings!$B$4/10000-IF(T11<0,Settings!$B$5/10000,0))),"") | V11: CORRECTION: replaces my existing row currently mislabeled '2025 Q4' (it holds this Q1 data). Clean beat, margin expansion, guide tracking above midpoint; valuation full. Sealed 29 Jun, ±1% band (correct under my sealed band). | W11: =IF($K11="","",$K11*60) | X11: =IF($A11="","",$A11&"|"&$C11&"|"&$D11) | Y11: =IFERROR(IF($X11="","",INDEX(LLM_Data_Entry!$H$3:$H$548,MATCH($X11,INDEX(LLM_Data_Entry!$A$3:$A$548&"|"&LLM_Data_Entry!$C$3:$C$548&"|"&LLM_Data_Entry!$D$3:$D$548,0),0))),"") | Z11: =IFERROR(IF($X11="","",INDEX(LLM_Data_Entry!$R$3:$R$548,MATCH($X11,INDEX(LLM_Data_Entry!$A$3:$A$548&"|"&LLM_Data_Entry!$C$3:$C$548&"|"&LLM_Data_Entry!$D$3:$D$548,0),0))),"") | AB11: release date + stated time in the document (rater worksheet) | AC11: NFLX | AD11: 2025-04-17 | AE11: 97.303 | AF11: 2025-04-21 | AG11: 98.44 | AH11: 0.011685159 | AI11: FLAT | AJ11: NO | AK11: 0.010685 | AL11: =IF($A11="","",IFERROR(INDEX(Company_List!$G$3:$G$207,MATCH($A11,Company_List!$A$3:$A$207,0)),"unassigned")) | AM11: Phase 2/Netflix/2025-Q1/NFLX-2025-Q1-press-release-SEC-EX-99-1.htm | AN11: https://www.sec.gov/Archives/edgar/data/1065280/000106528025000175/ex991_q125.htm | AO11: manifest | AP11: =IF($A11="","",IF(COUNTIFS(LLM_Data_Entry!$A$3:$A$548,$A11)>0,"YES","NO")) | AQ11: =IF($A11="","",IF(COUNTIFS($A$3:$A11,$A11,$C$3:$C11,$C11,$D$3:$D11,$D11)=1,"YES","NO")) | AR11: =IF($A11="","",IF(AND($C11&"-"&$D11>=Settings!$B$19,$C11&"-"&$D11<=Settings!$B$20),"IN","OUT")) | AS11: =IF($A11="","",IF($F11="Financial Results","financials",IF($F11="Outlook/Guidance","guidance",IF($F11="Transcript Q&A","qanda",IF($F11="","unrecorded",IF($E11="All","full",IF($E11="","unrecorded",LOWER($E11)&" only"))))))) | AT11: =IF(AND(OR($J11="BUY",$J11="SELL"),ISNUMBER($U11)),$U11,"") | AU11: =IF(AND(OR($J11="BUY",$J11="SELL"),ISNUMBER($AK11)),$AK11,"") | AV11: =IF(ISNUMBER($AT11),ABS(IF(ISNUMBER($I11),$I11,0)-Settings!$B$24),"") | AW11: =IF(ISNUMBER($AV11),$AV11*$AT11,"") | AX11: =IF(ISNUMBER($AU11),ABS(IF(ISNUMBER($I11),$I11,0)-Settings!$B$24),"") | AY11: FROZEN | AZ11: =IF($A11="","",IFERROR(INDEX(Company_List!$H$3:$H$207,MATCH($A11,Company_List!$A$3:$A$207,0)),"unassigned")) | BC11: =IF($A11="","",IF(COUNTIFS($A$3:$A11,$A11,$C$3:$C11,$C11,$D$3:$D11,$D11,$G$3:$G11,$G11)=1,1,0)) | BG11: no | BK11: =IF(OR($H11<>"Human",$S11="",$J11="",$Y11="",$Z11=""),"",IF(EXACT(UPPER($J11),UPPER($Y11)),1,0)) | BL11: assumed - no rater record | BM11: 1 | BN11: not publisher-identified | BO11: not publisher-identified | BP11: no | BQ11: yes | BS11: YES
A12: Netflix | B12: =IF(A12="","",_xlfn.XLOOKUP(A12, Company_List!$A:$A, Company_List!$B:$B, "")) | C12: 2025 | D12: Q2 | E12: All | F12: All | G12: Dragos | H12: Human | I12: 0.55 | J12: =IF(OR(I12="",Settings!$B$6=""),"",IF(I12>Settings!$B$6,"BUY",IF(I12<-Settings!$B$6,"SELL","HOLD"))) | K12: 38 | L12: 45855 | M12: 45855 | N12: 127.417 | O12: 45856 | P12: 124.2 | Q12: =IF(OR(N12="",P12=""),"",ROUND((P12-N12)/N12,4)) | R12: =IF(OR(N12="",P12=""),"",IF(Q12>Settings!$B$3/100,"UP",IF(Q12<-Settings!$B$3/100,"DOWN","FLAT"))) | S12: =IF(OR(N12="",P12="",J12=""),"",IF(OR(AND(J12="BUY",R12="UP"),AND(J12="SELL",R12="DOWN"),AND(J12="HOLD",R12="FLAT")),"YES","NO")) | T12: =IF(J12="","",IF(J12="BUY",1,IF(J12="SELL",-1,0))) | U12: =IFERROR(IF(OR(J12="",N12="",P12=""),"",IF(T12=0,0,T12*Q12-Settings!$B$4/10000-IF(T12<0,Settings!$B$5/10000,0))),"") | V12: Beat-and-raise but raise mostly FX; H2 margin step-down guided; stock priced for perfection. NOTE: my sealed next-day open is 124.20 (-2.53%); sheet's existing Q2 rows show 129.92 - flag to Anna/Ben. | W12: =IF($K12="","",$K12*60) | X12: =IF($A12="","",$A12&"|"&$C12&"|"&$D12) | Y12: =IFERROR(IF($X12="","",INDEX(LLM_Data_Entry!$H$3:$H$548,MATCH($X12,INDEX(LLM_Data_Entry!$A$3:$A$548&"|"&LLM_Data_Entry!$C$3:$C$548&"|"&LLM_Data_Entry!$D$3:$D$548,0),0))),"") | Z12: =IFERROR(IF($X12="","",INDEX(LLM_Data_Entry!$R$3:$R$548,MATCH($X12,INDEX(LLM_Data_Entry!$A$3:$A$548&"|"&LLM_Data_Entry!$C$3:$C$548&"|"&LLM_Data_Entry!$D$3:$D$548,0),0))),"") | AB12: price signal — only this window shows an abnormal move | AC12: NFLX | AD12: 2025-07-17 | AE12: 127.417 | AF12: 2025-07-18 | AG12: 124.196 | AH12: -0.025279209 | AI12: DOWN | AJ12: NO | AK12: -0.026279 | AL12: =IF($A12="","",IFERROR(INDEX(Company_List!$G$3:$G$207,MATCH($A12,Company_List!$A$3:$A$207,0)),"unassigned")) | AM12: Phase 2/Netflix/2025-Q2/NFLX-2025-Q2-press-release-SEC-EX-99-1.htm | AN12: https://www.sec.gov/Archives/edgar/data/1065280/000106528025000322/ex991_q225.htm | AO12: manifest | AP12: =IF($A12="","",IF(COUNTIFS(LLM_Data_Entry!$A$3:$A$548,$A12)>0,"YES","NO")) | AQ12: =IF($A12="","",IF(COUNTIFS($A$3:$A12,$A12,$C$3:$C12,$C12,$D$3:$D12,$D12)=1,"YES","NO")) | AR12: =IF($A12="","",IF(AND($C12&"-"&$D12>=Settings!$B$19,$C12&"-"&$D12<=Settings!$B$20),"IN","OUT")) | AS12: =IF($A12="","",IF($F12="Financial Results","financials",IF($F12="Outlook/Guidance","guidance",IF($F12="Transcript Q&A","qanda",IF($F12="","unrecorded",IF($E12="All","full",IF($E12="","unrecorded",LOWER($E12)&" only"))))))) | AT12: =IF(AND(OR($J12="BUY",$J12="SELL"),ISNUMBER($U12)),$U12,"") | AU12: =IF(AND(OR($J12="BUY",$J12="SELL"),ISNUMBER($AK12)),$AK12,"") | AV12: =IF(ISNUMBER($AT12),ABS(IF(ISNUMBER($I12),$I12,0)-Settings!$B$24),"") | AW12: =IF(ISNUMBER($AV12),$AV12*$AT12,"") | AX12: =IF(ISNUMBER($AU12),ABS(IF(ISNUMBER($I12),$I12,0)-Settings!$B$24),"") | AY12: FROZEN | AZ12: =IF($A12="","",IFERROR(INDEX(Company_List!$H$3:$H$207,MATCH($A12,Company_List!$A$3:$A$207,0)),"unassigned")) | BC12: =IF($A12="","",IF(COUNTIFS($A$3:$A12,$A12,$C$3:$C12,$C12,$D$3:$D12,$D12,$G$3:$G12,$G12)=1,1,0)) | BG12: no | BK12: =IF(OR($H12<>"Human",$S12="",$J12="",$Y12="",$Z12=""),"",IF(EXACT(UPPER($J12),UPPER($Y12)),1,0)) | BL12: attested - the note states the score was sealed | BM12: 1 | BN12: not publisher-identified | BO12: not publisher-identified | BP12: no | BQ12: yes | BS12: YES
A13: Netflix | B13: =IF(A13="","",_xlfn.XLOOKUP(A13, Company_List!$A:$A, Company_List!$B:$B, "")) | C13: 2025 | D13: Q3 | E13: All | F13: All | G13: Dragos | H13: Human | I13: 0.45 | J13: =IF(OR(I13="",Settings!$B$6=""),"",IF(I13>Settings!$B$6,"BUY",IF(I13<-Settings!$B$6,"SELL","HOLD"))) | K13: 55 | L13: 45951 | M13: 45951 | N13: 124.135 | O13: 45952 | P13: 114.29 | Q13: =IF(OR(N13="",P13=""),"",ROUND((P13-N13)/N13,4)) | R13: =IF(OR(N13="",P13=""),"",IF(Q13>Settings!$B$3/100,"UP",IF(Q13<-Settings!$B$3/100,"DOWN","FLAT"))) | S13: =IF(OR(N13="",P13="",J13=""),"",IF(OR(AND(J13="BUY",R13="UP"),AND(J13="SELL",R13="DOWN"),AND(J13="HOLD",R13="FLAT")),"YES","NO")) | T13: =IF(J13="","",IF(J13="BUY",1,IF(J13="SELL",-1,0))) | U13: =IFERROR(IF(OR(J13="",N13="",P13=""),"",IF(T13=0,0,T13*Q13-Settings!$B$4/10000-IF(T13<0,Settings!$B$5/10000,0))),"") | V13: Headline EPS miss (Brazil CIDE tax charge), guidance vacuum until January, rich valuation - sold first, reasoned later. | W13: =IF($K13="","",$K13*60) | X13: =IF($A13="","",$A13&"|"&$C13&"|"&$D13) | Y13: =IFERROR(IF($X13="","",INDEX(LLM_Data_Entry!$H$3:$H$548,MATCH($X13,INDEX(LLM_Data_Entry!$A$3:$A$548&"|"&LLM_Data_Entry!$C$3:$C$548&"|"&LLM_Data_Entry!$D$3:$D$548,0),0))),"") | Z13: =IFERROR(IF($X13="","",INDEX(LLM_Data_Entry!$R$3:$R$548,MATCH($X13,INDEX(LLM_Data_Entry!$A$3:$A$548&"|"&LLM_Data_Entry!$C$3:$C$548&"|"&LLM_Data_Entry!$D$3:$D$548,0),0))),"") | AB13: release date + stated time in the document (rater worksheet) | AC13: NFLX | AD13: 2025-10-21 | AE13: 124.135 | AF13: 2025-10-22 | AG13: 114.29 | AH13: -0.079308824 | AI13: DOWN | AJ13: NO | AK13: -0.080309 | AL13: =IF($A13="","",IFERROR(INDEX(Company_List!$G$3:$G$207,MATCH($A13,Company_List!$A$3:$A$207,0)),"unassigned")) | AM13: Phase 2/Netflix/2025-Q3/NFLX-2025-Q3-press-release-SEC-EX-99-1.htm | AN13: https://www.sec.gov/Archives/edgar/data/1065280/000106528025000404/ex991_q325.htm | AO13: manifest | AP13: =IF($A13="","",IF(COUNTIFS(LLM_Data_Entry!$A$3:$A$548,$A13)>0,"YES","NO")) | AQ13: =IF($A13="","",IF(COUNTIFS($A$3:$A13,$A13,$C$3:$C13,$C13,$D$3:$D13,$D13)=1,"YES","NO")) | AR13: =IF($A13="","",IF(AND($C13&"-"&$D13>=Settings!$B$19,$C13&"-"&$D13<=Settings!$B$20),"IN","OUT")) | AS13: =IF($A13="","",IF($F13="Financial Results","financials",IF($F13="Outlook/Guidance","guidance",IF($F13="Transcript Q&A","qanda",IF($F13="","unrecorded",IF($E13="All","full",IF($E13="","unrecorded",LOWER($E13)&" only"))))))) | AT13: =IF(AND(OR($J13="BUY",$J13="SELL"),ISNUMBER($U13)),$U13,"") | AU13: =IF(AND(OR($J13="BUY",$J13="SELL"),ISNUMBER($AK13)),$AK13,"") | AV13: =IF(ISNUMBER($AT13),ABS(IF(ISNUMBER($I13),$I13,0)-Settings!$B$24),"") | AW13: =IF(ISNUMBER($AV13),$AV13*$AT13,"") | AX13: =IF(ISNUMBER($AU13),ABS(IF(ISNUMBER($I13),$I13,0)-Settings!$B$24),"") | AY13: FROZEN | AZ13: =IF($A13="","",IFERROR(INDEX(Company_List!$H$3:$H$207,MATCH($A13,Company_List!$A$3:$A$207,0)),"unassigned")) | BC13: =IF($A13="","",IF(COUNTIFS($A$3:$A13,$A13,$C$3:$C13,$C13,$D$3:$D13,$D13,$G$3:$G13,$G13)=1,1,0)) | BG13: no | BK13: =IF(OR($H13<>"Human",$S13="",$J13="",$Y13="",$Z13=""),"",IF(EXACT(UPPER($J13),UPPER($Y13)),1,0)) | BL13: assumed - no rater record | BM13: 1 | BN13: not publisher-identified | BO13: not publisher-identified | BP13: no | BQ13: yes | BS13: YES
A14: Netflix | B14: =IF(A14="","",_xlfn.XLOOKUP(A14, Company_List!$A:$A, Company_List!$B:$B, "")) | C14: 2025 | D14: Q4 | E14: All | F14: All | G14: Dragos | H14: Human | I14: 0.6 | J14: =IF(OR(I14="",Settings!$B$6=""),"",IF(I14>Settings!$B$6,"BUY",IF(I14<-Settings!$B$6,"SELL","HOLD"))) | K14: 45 | L14: 46042 | M14: 46042 | N14: 87.26 | O14: 46043 | P14: 82.52 | Q14: =IF(OR(N14="",P14=""),"",ROUND((P14-N14)/N14,4)) | R14: =IF(OR(N14="",P14=""),"",IF(Q14>Settings!$B$3/100,"UP",IF(Q14<-Settings!$B$3/100,"DOWN","FLAT"))) | S14: =IF(OR(N14="",P14="",J14=""),"",IF(OR(AND(J14="BUY",R14="UP"),AND(J14="SELL",R14="DOWN"),AND(J14="HOLD",R14="FLAT")),"YES","NO")) | T14: =IF(J14="","",IF(J14="BUY",1,IF(J14="SELL",-1,0))) | U14: =IFERROR(IF(OR(J14="",N14="",P14=""),"",IF(T14=0,0,T14*Q14-Settings!$B$4/10000-IF(T14<0,Settings!$B$5/10000,0))),"") | V14: Clean beat + $51B 2026 guide, but growth decelerating 16%->14% and WBD deal overhang; I under-weighted the forward risk. | W14: =IF($K14="","",$K14*60) | X14: =IF($A14="","",$A14&"|"&$C14&"|"&$D14) | Y14: =IFERROR(IF($X14="","",INDEX(LLM_Data_Entry!$H$3:$H$548,MATCH($X14,INDEX(LLM_Data_Entry!$A$3:$A$548&"|"&LLM_Data_Entry!$C$3:$C$548&"|"&LLM_Data_Entry!$D$3:$D$548,0),0))),"") | Z14: =IFERROR(IF($X14="","",INDEX(LLM_Data_Entry!$R$3:$R$548,MATCH($X14,INDEX(LLM_Data_Entry!$A$3:$A$548&"|"&LLM_Data_Entry!$C$3:$C$548&"|"&LLM_Data_Entry!$D$3:$D$548,0),0))),"") | AB14: release date + stated time in the document (rater worksheet) | AC14: NFLX | AD14: 2026-01-20 | AE14: 87.26 | AF14: 2026-01-21 | AG14: 82.52 | AH14: -0.054320478 | AI14: DOWN | AJ14: NO | AK14: -0.05532 | AL14: =IF($A14="","",IFERROR(INDEX(Company_List!$G$3:$G$207,MATCH($A14,Company_List!$A$3:$A$207,0)),"unassigned")) | AM14: Phase 2/Netflix/2025-Q4/NFLX-2025-Q4-press-release-SEC-EX-99-1.htm | AN14: https://www.sec.gov/Archives/edgar/data/1065280/000106528026000033/ex991_q425.htm | AO14: manifest | AP14: =IF($A14="","",IF(COUNTIFS(LLM_Data_Entry!$A$3:$A$548,$A14)>0,"YES","NO")) | AQ14: =IF($A14="","",IF(COUNTIFS($A$3:$A14,$A14,$C$3:$C14,$C14,$D$3:$D14,$D14)=1,"YES","NO")) | AR14: =IF($A14="","",IF(AND($C14&"-"&$D14>=Settings!$B$19,$C14&"-"&$D14<=Settings!$B$20),"IN","OUT")) | AS14: =IF($A14="","",IF($F14="Financial Results","financials",IF($F14="Outlook/Guidance","guidance",IF($F14="Transcript Q&A","qanda",IF($F14="","unrecorded",IF($E14="All","full",IF($E14="","unrecorded",LOWER($E14)&" only"))))))) | AT14: =IF(AND(OR($J14="BUY",$J14="SELL"),ISNUMBER($U14)),$U14,"") | AU14: =IF(AND(OR($J14="BUY",$J14="SELL"),ISNUMBER($AK14)),$AK14,"") | AV14: =IF(ISNUMBER($AT14),ABS(IF(ISNUMBER($I14),$I14,0)-Settings!$B$24),"") | AW14: =IF(ISNUMBER($AV14),$AV14*$AT14,"") | AX14: =IF(ISNUMBER($AU14),ABS(IF(ISNUMBER($I14),$I14,0)-Settings!$B$24),"") | AY14: FROZEN | AZ14: =IF($A14="","",IFERROR(INDEX(Company_List!$H$3:$H$207,MATCH($A14,Company_List!$A$3:$A$207,0)),"unassigned")) | BC14: =IF($A14="","",IF(COUNTIFS($A$3:$A14,$A14,$C$3:$C14,$C14,$D$3:$D14,$D14,$G$3:$G14,$G14)=1,1,0)) | BG14: no | BK14: =IF(OR($H14<>"Human",$S14="",$J14="",$Y14="",$Z14=""),"",IF(EXACT(UPPER($J14),UPPER($Y14)),1,0)) | BL14: assumed - no rater record | BM14: 1 | BN14: not publisher-identified | BO14: not publisher-identified | BP14: no | BQ14: yes | BS14: YES
A15: Nvidia | B15: =IF(A15="","",_xlfn.XLOOKUP(A15, Company_List!$A:$A, Company_List!$B:$B, "")) | C15: 2025 | D15: Q1 | E15: All | F15: All | G15: Dragos | H15: Human | I15: 0.55 | J15: =IF(OR(I15="",Settings!$B$6=""),"",IF(I15>Settings!$B$6,"BUY",IF(I15<-Settings!$B$6,"SELL","HOLD"))) | K15: 50 | L15: 45714 | M15: 45714 | N15: 131.28 | O15: 45715 | P15: 135 | Q15: =IF(OR(N15="",P15=""),"",ROUND((P15-N15)/N15,4)) | R15: =IF(OR(N15="",P15=""),"",IF(Q15>Settings!$B$3/100,"UP",IF(Q15<-Settings!$B$3/100,"DOWN","FLAT"))) | S15: =IF(OR(N15="",P15="",J15=""),"",IF(OR(AND(J15="BUY",R15="UP"),AND(J15="SELL",R15="DOWN"),AND(J15="HOLD",R15="FLAT")),"YES","NO")) | T15: =IF(J15="","",IF(J15="BUY",1,IF(J15="SELL",-1,0))) | U15: =IFERROR(IF(OR(J15="",N15="",P15=""),"",IF(T15=0,0,T15*Q15-Settings!$B$4/10000-IF(T15<0,Settings!$B$5/10000,0))),"") | V15: NVIDIA fiscal Q4 FY25, released 26 Feb 2025 (calendar label by release date). Beat on every line but margin-trough guide (71%), growth 262%->65%, tariffs unknown. Opened +2.8% then closed -8.5% - overnight window called it BUY. | W15: =IF($K15="","",$K15*60) | X15: =IF($A15="","",$A15&"|"&$C15&"|"&$D15) | Y15: =IFERROR(IF($X15="","",INDEX(LLM_Data_Entry!$H$3:$H$548,MATCH($X15,INDEX(LLM_Data_Entry!$A$3:$A$548&"|"&LLM_Data_Entry!$C$3:$C$548&"|"&LLM_Data_Entry!$D$3:$D$548,0),0))),"") | Z15: =IFERROR(IF($X15="","",INDEX(LLM_Data_Entry!$R$3:$R$548,MATCH($X15,INDEX(LLM_Data_Entry!$A$3:$A$548&"|"&LLM_Data_Entry!$C$3:$C$548&"|"&LLM_Data_Entry!$D$3:$D$548,0),0))),"") | AB15: release date + stated time in the document (rater worksheet) | AC15: NVDA | AD15: 2025-02-26 | AE15: 131.0842 | AF15: 2025-02-27 | AG15: 134.7987 | AH15: 0.028336475 | AI15: UP | AJ15: YES | AK15: 0.027336 | AL15: =IF($A15="","",IFERROR(INDEX(Company_List!$G$3:$G$207,MATCH($A15,Company_List!$A$3:$A$207,0)),"unassigned")) | AM15: Phase 2/Nvidia/Q2 2025/NVDA-Q1FY26-press-release-SEC-EX99-1.htm; Phase 2/Nvidia/Q2 2025/NVDA-Q1FY26-earnings-call-transcript-AlphaStreet.html; Phase 2/Nvidia/Q2 2025/NVDA-Q1FY26-CFO-commentary-SEC-EX99-2.htm; Phase 2/Nvidia/Q1 2025/NVDA-Q4FY25-press-release-SEC-EX99-1.htm; Phase 2/Nvidia/Q1 2025/NVDA-Q4FY25-earnings-call-transcript-MotleyFool.html; Phase 2/Nvidia/Q1 2025/NVDA-Q4FY25-CFO-commentary-SEC-EX99-2.htm | AO15: whole bundle (Document = All) | AP15: =IF($A15="","",IF(COUNTIFS(LLM_Data_Entry!$A$3:$A$548,$A15)>0,"YES","NO")) | AQ15: =IF($A15="","",IF(COUNTIFS($A$3:$A15,$A15,$C$3:$C15,$C15,$D$3:$D15,$D15)=1,"YES","NO")) | AR15: =IF($A15="","",IF(AND($C15&"-"&$D15>=Settings!$B$19,$C15&"-"&$D15<=Settings!$B$20),"IN","OUT")) | AS15: =IF($A15="","",IF($F15="Financial Results","financials",IF($F15="Outlook/Guidance","guidance",IF($F15="Transcript Q&A","qanda",IF($F15="","unrecorded",IF($E15="All","full",IF($E15="","unrecorded",LOWER($E15)&" only"))))))) | AT15: =IF(AND(OR($J15="BUY",$J15="SELL"),ISNUMBER($U15)),$U15,"") | AU15: =IF(AND(OR($J15="BUY",$J15="SELL"),ISNUMBER($AK15)),$AK15,"") | AV15: =IF(ISNUMBER($AT15),ABS(IF(ISNUMBER($I15),$I15,0)-Settings!$B$24),"") | AW15: =IF(ISNUMBER($AV15),$AV15*$AT15,"") | AX15: =IF(ISNUMBER($AU15),ABS(IF(ISNUMBER($I15),$I15,0)-Settings!$B$24),"") | AY15: FROZEN | AZ15: =IF($A15="","",IFERROR(INDEX(Company_List!$H$3:$H$207,MATCH($A15,Company_List!$A$3:$A$207,0)),"unassigned")) | BC15: =IF($A15="","",IF(COUNTIFS($A$3:$A15,$A15,$C$3:$C15,$C15,$D$3:$D15,$D15,$G$3:$G15,$G15)=1,1,0)) | BG15: no | BK15: =IF(OR($H15<>"Human",$S15="",$J15="",$Y15="",$Z15=""),"",IF(EXACT(UPPER($J15),UPPER($Y15)),1,0)) | BL15: assumed - blind unless stated otherwise; the note names the realised move (query E-a, settled 10 Aug 2026) | BM15: 6 | BN15: The Motley Fool | BO15: free to read, copyright asserted | BP15: no | BQ15: yes | BS15: YES
A16: Nvidia | B16: =IF(A16="","",_xlfn.XLOOKUP(A16, Company_List!$A:$A, Company_List!$B:$B, "")) | C16: 2025 | D16: Q2 | E16: All | F16: All | G16: Dragos | H16: Human | I16: 0.35 | J16: =IF(OR(I16="",Settings!$B$6=""),"",IF(I16>Settings!$B$6,"BUY",IF(I16<-Settings!$B$6,"SELL","HOLD"))) | K16: 48 | L16: 45805 | M16: 45805 | N16: 134.81 | O16: 45806 | P16: 142.25 | Q16: =IF(OR(N16="",P16=""),"",ROUND((P16-N16)/N16,4)) | R16: =IF(OR(N16="",P16=""),"",IF(Q16>Settings!$B$3/100,"UP",IF(Q16<-Settings!$B$3/100,"DOWN","FLAT"))) | S16: =IF(OR(N16="",P16="",J16=""),"",IF(OR(AND(J16="BUY",R16="UP"),AND(J16="SELL",R16="DOWN"),AND(J16="HOLD",R16="FLAT")),"YES","NO")) | T16: =IF(J16="","",IF(J16="BUY",1,IF(J16="SELL",-1,0))) | U16: =IFERROR(IF(OR(J16="",N16="",P16=""),"",IF(T16=0,0,T16*Q16-Settings!$B$4/10000-IF(T16<0,Settings!$B$5/10000,0))),"") | V16: NVIDIA fiscal Q1 FY26, released 28 May 2025. Ugly headline (China/H20 charge) but underlying demand intact; market looked through it. | W16: =IF($K16="","",$K16*60) | X16: =IF($A16="","",$A16&"|"&$C16&"|"&$D16) | Y16: =IFERROR(IF($X16="","",INDEX(LLM_Data_Entry!$H$3:$H$548,MATCH($X16,INDEX(LLM_Data_Entry!$A$3:$A$548&"|"&LLM_Data_Entry!$C$3:$C$548&"|"&LLM_Data_Entry!$D$3:$D$548,0),0))),"") | Z16: =IFERROR(IF($X16="","",INDEX(LLM_Data_Entry!$R$3:$R$548,MATCH($X16,INDEX(LLM_Data_Entry!$A$3:$A$548&"|"&LLM_Data_Entry!$C$3:$C$548&"|"&LLM_Data_Entry!$D$3:$D$548,0),0))),"") | AB16: release date + stated time in the document (rater worksheet) | AC16: NVDA | AD16: 2025-05-28 | AE16: 134.6213 | AF16: 2025-05-29 | AG16: 142.0509 | AH16: 0.055188774 | AI16: UP | AJ16: YES | AK16: 0.054189 | AL16: =IF($A16="","",IFERROR(INDEX(Company_List!$G$3:$G$207,MATCH($A16,Company_List!$A$3:$A$207,0)),"unassigned")) | AM16: Phase 2/Nvidia/Q3 2025/NVDA-Q2FY26-press-release-SEC-EX99-1.htm; Phase 2/Nvidia/Q3 2025/NVDA-Q2FY26-earnings-call-transcript-AlphaStreet.html; Phase 2/Nvidia/Q3 2025/NVDA-Q2FY26-CFO-commentary-SEC-EX99-2.htm; Phase 2/Nvidia/Q2 2025/NVDA-Q1FY26-press-release-SEC-EX99-1.htm; Phase 2/Nvidia/Q2 2025/NVDA-Q1FY26-earnings-call-transcript-AlphaStreet.html; Phase 2/Nvidia/Q2 2025/NVDA-Q1FY26-CFO-commentary-SEC-EX99-2.htm | AO16: whole bundle (Document = All) | AP16: =IF($A16="","",IF(COUNTIFS(LLM_Data_Entry!$A$3:$A$548,$A16)>0,"YES","NO")) | AQ16: =IF($A16="","",IF(COUNTIFS($A$3:$A16,$A16,$C$3:$C16,$C16,$D$3:$D16,$D16)=1,"YES","NO")) | AR16: =IF($A16="","",IF(AND($C16&"-"&$D16>=Settings!$B$19,$C16&"-"&$D16<=Settings!$B$20),"IN","OUT")) | AS16: =IF($A16="","",IF($F16="Financial Results","financials",IF($F16="Outlook/Guidance","guidance",IF($F16="Transcript Q&A","qanda",IF($F16="","unrecorded",IF($E16="All","full",IF($E16="","unrecorded",LOWER($E16)&" only"))))))) | AT16: =IF(AND(OR($J16="BUY",$J16="SELL"),ISNUMBER($U16)),$U16,"") | AU16: =IF(AND(OR($J16="BUY",$J16="SELL"),ISNUMBER($AK16)),$AK16,"") | AV16: =IF(ISNUMBER($AT16),ABS(IF(ISNUMBER($I16),$I16,0)-Settings!$B$24),"") | AW16: =IF(ISNUMBER($AV16),$AV16*$AT16,"") | AX16: =IF(ISNUMBER($AU16),ABS(IF(ISNUMBER($I16),$I16,0)-Settings!$B$24),"") | AY16: FROZEN | AZ16: =IF($A16="","",IFERROR(INDEX(Company_List!$H$3:$H$207,MATCH($A16,Company_List!$A$3:$A$207,0)),"unassigned")) | BC16: =IF($A16="","",IF(COUNTIFS($A$3:$A16,$A16,$C$3:$C16,$C16,$D$3:$D16,$D16,$G$3:$G16,$G16)=1,1,0)) | BG16: no | BK16: =IF(OR($H16<>"Human",$S16="",$J16="",$Y16="",$Z16=""),"",IF(EXACT(UPPER($J16),UPPER($Y16)),1,0)) | BL16: assumed - no rater record | BM16: 6 | BN16: not publisher-identified | BO16: not publisher-identified | BP16: no | BQ16: yes | BS16: YES
A17: Nvidia | B17: =IF(A17="","",_xlfn.XLOOKUP(A17, Company_List!$A:$A, Company_List!$B:$B, "")) | C17: 2025 | D17: Q3 | E17: All | F17: All | G17: Dragos | H17: Human | I17: 0.6 | J17: =IF(OR(I17="",Settings!$B$6=""),"",IF(I17>Settings!$B$6,"BUY",IF(I17<-Settings!$B$6,"SELL","HOLD"))) | K17: 40 | L17: 45896 | M17: 45896 | N17: 181.6 | O17: 45897 | P17: 180.82 | Q17: =IF(OR(N17="",P17=""),"",ROUND((P17-N17)/N17,4)) | R17: =IF(OR(N17="",P17=""),"",IF(Q17>Settings!$B$3/100,"UP",IF(Q17<-Settings!$B$3/100,"DOWN","FLAT"))) | S17: =IF(OR(N17="",P17="",J17=""),"",IF(OR(AND(J17="BUY",R17="UP"),AND(J17="SELL",R17="DOWN"),AND(J17="HOLD",R17="FLAT")),"YES","NO")) | T17: =IF(J17="","",IF(J17="BUY",1,IF(J17="SELL",-1,0))) | U17: =IFERROR(IF(OR(J17="",N17="",P17=""),"",IF(T17=0,0,T17*Q17-Settings!$B$4/10000-IF(T17<0,Settings!$B$5/10000,0))),"") | V17: NVIDIA fiscal Q2 FY26, released 27 Aug 2025. Strong records but reaction flat (-0.43%) - correct call was HOLD. | W17: =IF($K17="","",$K17*60) | X17: =IF($A17="","",$A17&"|"&$C17&"|"&$D17) | Y17: =IFERROR(IF($X17="","",INDEX(LLM_Data_Entry!$H$3:$H$548,MATCH($X17,INDEX(LLM_Data_Entry!$A$3:$A$548&"|"&LLM_Data_Entry!$C$3:$C$548&"|"&LLM_Data_Entry!$D$3:$D$548,0),0))),"") | Z17: =IFERROR(IF($X17="","",INDEX(LLM_Data_Entry!$R$3:$R$548,MATCH($X17,INDEX(LLM_Data_Entry!$A$3:$A$548&"|"&LLM_Data_Entry!$C$3:$C$548&"|"&LLM_Data_Entry!$D$3:$D$548,0),0))),"") | AB17: release date + stated time in the document (rater worksheet) | AC17: NVDA | AD17: 2025-08-27 | AE17: 181.3585 | AF17: 2025-08-28 | AG17: 180.5795 | AH17: -0.0042951987 | AI17: FLAT | AJ17: NO | AK17: -0.005295 | AL17: =IF($A17="","",IFERROR(INDEX(Company_List!$G$3:$G$207,MATCH($A17,Company_List!$A$3:$A$207,0)),"unassigned")) | AM17: Phase 2/Nvidia/Q4 2025/NVDA-Q3FY26-press-release-SEC-EX99-1.htm; Phase 2/Nvidia/Q4 2025/NVDA-Q3FY26-earnings-call-transcript-MotleyFool.html; Phase 2/Nvidia/Q4 2025/NVDA-Q3FY26-CFO-commentary-SEC-EX99-2.htm; Phase 2/Nvidia/Q3 2025/NVDA-Q2FY26-press-release-SEC-EX99-1.htm; Phase 2/Nvidia/Q3 2025/NVDA-Q2FY26-earnings-call-transcript-AlphaStreet.html; Phase 2/Nvidia/Q3 2025/NVDA-Q2FY26-CFO-commentary-SEC-EX99-2.htm | AO17: whole bundle (Document = All) | AP17: =IF($A17="","",IF(COUNTIFS(LLM_Data_Entry!$A$3:$A$548,$A17)>0,"YES","NO")) | AQ17: =IF($A17="","",IF(COUNTIFS($A$3:$A17,$A17,$C$3:$C17,$C17,$D$3:$D17,$D17)=1,"YES","NO")) | AR17: =IF($A17="","",IF(AND($C17&"-"&$D17>=Settings!$B$19,$C17&"-"&$D17<=Settings!$B$20),"IN","OUT")) | AS17: =IF($A17="","",IF($F17="Financial Results","financials",IF($F17="Outlook/Guidance","guidance",IF($F17="Transcript Q&A","qanda",IF($F17="","unrecorded",IF($E17="All","full",IF($E17="","unrecorded",LOWER($E17)&" only"))))))) | AT17: =IF(AND(OR($J17="BUY",$J17="SELL"),ISNUMBER($U17)),$U17,"") | AU17: =IF(AND(OR($J17="BUY",$J17="SELL"),ISNUMBER($AK17)),$AK17,"") | AV17: =IF(ISNUMBER($AT17),ABS(IF(ISNUMBER($I17),$I17,0)-Settings!$B$24),"") | AW17: =IF(ISNUMBER($AV17),$AV17*$AT17,"") | AX17: =IF(ISNUMBER($AU17),ABS(IF(ISNUMBER($I17),$I17,0)-Settings!$B$24),"") | AY17: FROZEN | AZ17: =IF($A17="","",IFERROR(INDEX(Company_List!$H$3:$H$207,MATCH($A17,Company_List!$A$3:$A$207,0)),"unassigned")) | BC17: =IF($A17="","",IF(COUNTIFS($A$3:$A17,$A17,$C$3:$C17,$C17,$D$3:$D17,$D17,$G$3:$G17,$G17)=1,1,0)) | BG17: no | BK17: =IF(OR($H17<>"Human",$S17="",$J17="",$Y17="",$Z17=""),"",IF(EXACT(UPPER($J17),UPPER($Y17)),1,0)) | BL17: assumed - blind unless stated otherwise; the note names the realised move (query E-a, settled 10 Aug 2026) | BM17: 6 | BN17: The Motley Fool | BO17: free to read, copyright asserted | BP17: no | BQ17: yes | BS17: YES
A18: Nvidia | B18: =IF(A18="","",_xlfn.XLOOKUP(A18, Company_List!$A:$A, Company_List!$B:$B, "")) | C18: 2025 | D18: Q4 | E18: All | F18: All | G18: Dragos | H18: Human | I18: 0.75 | J18: =IF(OR(I18="",Settings!$B$6=""),"",IF(I18>Settings!$B$6,"BUY",IF(I18<-Settings!$B$6,"SELL","HOLD"))) | K18: 44 | L18: 45980 | M18: 45980 | N18: 186.52 | O18: 45981 | P18: 195.95 | Q18: =IF(OR(N18="",P18=""),"",ROUND((P18-N18)/N18,4)) | R18: =IF(OR(N18="",P18=""),"",IF(Q18>Settings!$B$3/100,"UP",IF(Q18<-Settings!$B$3/100,"DOWN","FLAT"))) | S18: =IF(OR(N18="",P18="",J18=""),"",IF(OR(AND(J18="BUY",R18="UP"),AND(J18="SELL",R18="DOWN"),AND(J18="HOLD",R18="FLAT")),"YES","NO")) | T18: =IF(J18="","",IF(J18="BUY",1,IF(J18="SELL",-1,0))) | U18: =IFERROR(IF(OR(J18="",N18="",P18=""),"",IF(T18=0,0,T18*Q18-Settings!$B$4/10000-IF(T18<0,Settings!$B$5/10000,0))),"") | V18: NVIDIA fiscal Q3 FY26, released 19 Nov 2025. Strongest print of the four; +5.1% overnight. | W18: =IF($K18="","",$K18*60) | X18: =IF($A18="","",$A18&"|"&$C18&"|"&$D18) | Y18: =IFERROR(IF($X18="","",INDEX(LLM_Data_Entry!$H$3:$H$548,MATCH($X18,INDEX(LLM_Data_Entry!$A$3:$A$548&"|"&LLM_Data_Entry!$C$3:$C$548&"|"&LLM_Data_Entry!$D$3:$D$548,0),0))),"") | Z18: =IFERROR(IF($X18="","",INDEX(LLM_Data_Entry!$R$3:$R$548,MATCH($X18,INDEX(LLM_Data_Entry!$A$3:$A$548&"|"&LLM_Data_Entry!$C$3:$C$548&"|"&LLM_Data_Entry!$D$3:$D$548,0),0))),"") | AB18: release date + stated time in the document (rater worksheet) | AC18: NVDA | AD18: 2025-11-19 | AE18: 186.2824 | AF18: 2025-11-20 | AG18: 195.7004 | AH18: 0.050557553 | AI18: UP | AJ18: YES | AK18: 0.049558 | AL18: =IF($A18="","",IFERROR(INDEX(Company_List!$G$3:$G$207,MATCH($A18,Company_List!$A$3:$A$207,0)),"unassigned")) | AM18: Phase 2/Nvidia/Q4 2025/NVDA-Q3FY26-press-release-SEC-EX99-1.htm; Phase 2/Nvidia/Q4 2025/NVDA-Q3FY26-earnings-call-transcript-MotleyFool.html; Phase 2/Nvidia/Q4 2025/NVDA-Q3FY26-CFO-commentary-SEC-EX99-2.htm; Phase 2/Nvidia/Q1 2025/NVDA-Q4FY25-press-release-SEC-EX99-1.htm; Phase 2/Nvidia/Q1 2025/NVDA-Q4FY25-earnings-call-transcript-MotleyFool.html; Phase 2/Nvidia/Q1 2025/NVDA-Q4FY25-CFO-commentary-SEC-EX99-2.htm | AO18: whole bundle (Document = All) | AP18: =IF($A18="","",IF(COUNTIFS(LLM_Data_Entry!$A$3:$A$548,$A18)>0,"YES","NO")) | AQ18: =IF($A18="","",IF(COUNTIFS($A$3:$A18,$A18,$C$3:$C18,$C18,$D$3:$D18,$D18)=1,"YES","NO")) | AR18: =IF($A18="","",IF(AND($C18&"-"&$D18>=Settings!$B$19,$C18&"-"&$D18<=Settings!$B$20),"IN","OUT")) | AS18: =IF($A18="","",IF($F18="Financial Results","financials",IF($F18="Outlook/Guidance","guidance",IF($F18="Transcript Q&A","qanda",IF($F18="","unrecorded",IF($E18="All","full",IF($E18="","unrecorded",LOWER($E18)&" only"))))))) | AT18: =IF(AND(OR($J18="BUY",$J18="SELL"),ISNUMBER($U18)),$U18,"") | AU18: =IF(AND(OR($J18="BUY",$J18="SELL"),ISNUMBER($AK18)),$AK18,"") | AV18: =IF(ISNUMBER($AT18),ABS(IF(ISNUMBER($I18),$I18,0)-Settings!$B$24),"") | AW18: =IF(ISNUMBER($AV18),$AV18*$AT18,"") | AX18: =IF(ISNUMBER($AU18),ABS(IF(ISNUMBER($I18),$I18,0)-Settings!$B$24),"") | AY18: FROZEN | AZ18: =IF($A18="","",IFERROR(INDEX(Company_List!$H$3:$H$207,MATCH($A18,Company_List!$A$3:$A$207,0)),"unassigned")) | BC18: =IF($A18="","",IF(COUNTIFS($A$3:$A18,$A18,$C$3:$C18,$C18,$D$3:$D18,$D18,$G$3:$G18,$G18)=1,1,0)) | BG18: no | BK18: =IF(OR($H18<>"Human",$S18="",$J18="",$Y18="",$Z18=""),"",IF(EXACT(UPPER($J18),UPPER($Y18)),1,0)) | BL18: assumed - no rater record | BM18: 6 | BN18: The Motley Fool | BO18: free to read, copyright asserted | BP18: no | BQ18: yes | BS18: YES
A19: Boeing | B19: =IF(A19="","",_xlfn.XLOOKUP(A19, Company_List!$A:$A, Company_List!$B:$B, "")) | C19: 2025 | D19: Q1 | E19: All | F19: All | G19: Nigel | H19: Human | I19: -0.5 | J19: =IF(OR(I19="",Settings!$B$6=""),"",IF(I19>Settings!$B$6,"BUY",IF(I19<-Settings!$B$6,"SELL","HOLD"))) | K19: 32 | L19: 45770 | M19: 45769 | N19: 162.52 | O19: 45770 | P19: 174 | Q19: =IF(OR(N19="",P19=""),"",ROUND((P19-N19)/N19,4)) | R19: =IF(OR(N19="",P19=""),"",IF(Q19>Settings!$B$3/100,"UP",IF(Q19<-Settings!$B$3/100,"DOWN","FLAT"))) | S19: =IF(OR(N19="",P19="",J19=""),"",IF(OR(AND(J19="BUY",R19="UP"),AND(J19="SELL",R19="DOWN"),AND(J19="HOLD",R19="FLAT")),"YES","NO")) | T19: =IF(J19="","",IF(J19="BUY",1,IF(J19="SELL",-1,0))) | U19: =IFERROR(IF(OR(J19="",N19="",P19=""),"",IF(T19=0,0,T19*Q19-Settings!$B$4/10000-IF(T19<0,Settings!$B$5/10000,0))),"") | V19: Recovery plan working as intended though a long road remains; revenue up but operating margin lower and not yet convincing; outlook resting on planned diversification; tariffs a growing concern especially around China deals, with possible supply chain knock-on; more conservative forward plans. Heavy uncertainty, cautious tone. | W19: =IF($K19="","",$K19*60) | X19: =IF($A19="","",$A19&"|"&$C19&"|"&$D19) | Y19: =IFERROR(IF($X19="","",INDEX(LLM_Data_Entry!$H$3:$H$548,MATCH($X19,INDEX(LLM_Data_Entry!$A$3:$A$548&"|"&LLM_Data_Entry!$C$3:$C$548&"|"&LLM_Data_Entry!$D$3:$D$548,0),0))),"") | Z19: =IFERROR(IF($X19="","",INDEX(LLM_Data_Entry!$R$3:$R$548,MATCH($X19,INDEX(LLM_Data_Entry!$A$3:$A$548&"|"&LLM_Data_Entry!$C$3:$C$548&"|"&LLM_Data_Entry!$D$3:$D$548,0),0))),"") | AB19: price signal | AC19: BA | AD19: 2025-04-22 | AE19: 162.52 | AF19: 2025-04-23 | AG19: 174 | AH19: 0.070637434 | AI19: UP | AJ19: NO | AK19: -0.071637 | AL19: =IF($A19="","",IFERROR(INDEX(Company_List!$G$3:$G$207,MATCH($A19,Company_List!$A$3:$A$207,0)),"unassigned")) | AM19: Phase 2/Boeing/Q1/Transcript-Q1-2025-Earnings-Call.pdf | AO19: unique filename match | AP19: =IF($A19="","",IF(COUNTIFS(LLM_Data_Entry!$A$3:$A$548,$A19)>0,"YES","NO")) | AQ19: =IF($A19="","",IF(COUNTIFS($A$3:$A19,$A19,$C$3:$C19,$C19,$D$3:$D19,$D19)=1,"YES","NO")) | AR19: =IF($A19="","",IF(AND($C19&"-"&$D19>=Settings!$B$19,$C19&"-"&$D19<=Settings!$B$20),"IN","OUT")) | AS19: =IF($A19="","",IF($F19="Financial Results","financials",IF($F19="Outlook/Guidance","guidance",IF($F19="Transcript Q&A","qanda",IF($F19="","unrecorded",IF($E19="All","full",IF($E19="","unrecorded",LOWER($E19)&" only"))))))) | AT19: =IF(AND(OR($J19="BUY",$J19="SELL"),ISNUMBER($U19)),$U19,"") | AU19: =IF(AND(OR($J19="BUY",$J19="SELL"),ISNUMBER($AK19)),$AK19,"") | AV19: =IF(ISNUMBER($AT19),ABS(IF(ISNUMBER($I19),$I19,0)-Settings!$B$24),"") | AW19: =IF(ISNUMBER($AV19),$AV19*$AT19,"") | AX19: =IF(ISNUMBER($AU19),ABS(IF(ISNUMBER($I19),$I19,0)-Settings!$B$24),"") | AY19: FROZEN | AZ19: =IF($A19="","",IFERROR(INDEX(Company_List!$H$3:$H$207,MATCH($A19,Company_List!$A$3:$A$207,0)),"unassigned")) | BC19: =IF($A19="","",IF(COUNTIFS($A$3:$A19,$A19,$C$3:$C19,$C19,$D$3:$D19,$D19,$G$3:$G19,$G19)=1,1,0)) | BG19: no | BK19: =IF(OR($H19<>"Human",$S19="",$J19="",$Y19="",$Z19=""),"",IF(EXACT(UPPER($J19),UPPER($Y19)),1,0)) | BL19: assumed - no rater record | BM19: 1 | BN19: FactSet CallStreet | BO19: licensed vendor | BP19: no | BQ19: no | BS19: YES
A20: Boeing | B20: =IF(A20="","",_xlfn.XLOOKUP(A20, Company_List!$A:$A, Company_List!$B:$B, "")) | C20: 2025 | D20: Q2 | E20: All | F20: All | G20: Nigel | H20: Human | I20: 0.6 | J20: =IF(OR(I20="",Settings!$B$6=""),"",IF(I20>Settings!$B$6,"BUY",IF(I20<-Settings!$B$6,"SELL","HOLD"))) | K20: 28 | L20: 45867 | M20: 45866 | N20: 236.41 | O20: 45867 | P20: 239.5 | Q20: =IF(OR(N20="",P20=""),"",ROUND((P20-N20)/N20,4)) | R20: =IF(OR(N20="",P20=""),"",IF(Q20>Settings!$B$3/100,"UP",IF(Q20<-Settings!$B$3/100,"DOWN","FLAT"))) | S20: =IF(OR(N20="",P20="",J20=""),"",IF(OR(AND(J20="BUY",R20="UP"),AND(J20="SELL",R20="DOWN"),AND(J20="HOLD",R20="FLAT")),"YES","NO")) | T20: =IF(J20="","",IF(J20="BUY",1,IF(J20="SELL",-1,0))) | U20: =IFERROR(IF(OR(J20="",N20="",P20=""),"",IF(T20=0,0,T20*Q20-Settings!$B$4/10000-IF(T20<0,Settings!$B$5/10000,0))),"") | V20: Demand growing and finances healthier with stronger revenues; production plan improving as intended; contract wins in defence and space; tariff worries easing and geopolitical risk stabilising; 737 deliveries below last year but in line with the action plan. Improving tone. | W20: =IF($K20="","",$K20*60) | X20: =IF($A20="","",$A20&"|"&$C20&"|"&$D20) | Y20: =IFERROR(IF($X20="","",INDEX(LLM_Data_Entry!$H$3:$H$548,MATCH($X20,INDEX(LLM_Data_Entry!$A$3:$A$548&"|"&LLM_Data_Entry!$C$3:$C$548&"|"&LLM_Data_Entry!$D$3:$D$548,0),0))),"") | Z20: =IFERROR(IF($X20="","",INDEX(LLM_Data_Entry!$R$3:$R$548,MATCH($X20,INDEX(LLM_Data_Entry!$A$3:$A$548&"|"&LLM_Data_Entry!$C$3:$C$548&"|"&LLM_Data_Entry!$D$3:$D$548,0),0))),"") | AB20: price signal | AC20: BA | AD20: 2025-07-28 | AE20: 236.41 | AF20: 2025-07-29 | AG20: 239.5 | AH20: 0.013070496 | AI20: FLAT | AJ20: NO | AK20: 0.01207 | AL20: =IF($A20="","",IFERROR(INDEX(Company_List!$G$3:$G$207,MATCH($A20,Company_List!$A$3:$A$207,0)),"unassigned")) | AM20: Phase 2/Boeing/2025-Q2/BA-2025-Q2-press-release-SEC-EX-99-1.htm | AN20: https://www.sec.gov/Archives/edgar/data/12927/000001292725000058/a202506jun308kprex991.htm | AO20: manifest | AP20: =IF($A20="","",IF(COUNTIFS(LLM_Data_Entry!$A$3:$A$548,$A20)>0,"YES","NO")) | AQ20: =IF($A20="","",IF(COUNTIFS($A$3:$A20,$A20,$C$3:$C20,$C20,$D$3:$D20,$D20)=1,"YES","NO")) | AR20: =IF($A20="","",IF(AND($C20&"-"&$D20>=Settings!$B$19,$C20&"-"&$D20<=Settings!$B$20),"IN","OUT")) | AS20: =IF($A20="","",IF($F20="Financial Results","financials",IF($F20="Outlook/Guidance","guidance",IF($F20="Transcript Q&A","qanda",IF($F20="","unrecorded",IF($E20="All","full",IF($E20="","unrecorded",LOWER($E20)&" only"))))))) | AT20: =IF(AND(OR($J20="BUY",$J20="SELL"),ISNUMBER($U20)),$U20,"") | AU20: =IF(AND(OR($J20="BUY",$J20="SELL"),ISNUMBER($AK20)),$AK20,"") | AV20: =IF(ISNUMBER($AT20),ABS(IF(ISNUMBER($I20),$I20,0)-Settings!$B$24),"") | AW20: =IF(ISNUMBER($AV20),$AV20*$AT20,"") | AX20: =IF(ISNUMBER($AU20),ABS(IF(ISNUMBER($I20),$I20,0)-Settings!$B$24),"") | AY20: FROZEN | AZ20: =IF($A20="","",IFERROR(INDEX(Company_List!$H$3:$H$207,MATCH($A20,Company_List!$A$3:$A$207,0)),"unassigned")) | BC20: =IF($A20="","",IF(COUNTIFS($A$3:$A20,$A20,$C$3:$C20,$C20,$D$3:$D20,$D20,$G$3:$G20,$G20)=1,1,0)) | BG20: no | BK20: =IF(OR($H20<>"Human",$S20="",$J20="",$Y20="",$Z20=""),"",IF(EXACT(UPPER($J20),UPPER($Y20)),1,0)) | BL20: assumed - no rater record | BM20: 1 | BN20: not publisher-identified | BO20: not publisher-identified | BP20: no | BQ20: yes | BS20: YES
A21: Boeing | B21: =IF(A21="","",_xlfn.XLOOKUP(A21, Company_List!$A:$A, Company_List!$B:$B, "")) | C21: 2025 | D21: Q3 | E21: All | F21: All | G21: Nigel | H21: Human | I21: -0.1 | J21: =IF(OR(I21="",Settings!$B$6=""),"",IF(I21>Settings!$B$6,"BUY",IF(I21<-Settings!$B$6,"SELL","HOLD"))) | K21: 26 | L21: 45959 | M21: 45958 | N21: 223.33 | O21: 45959 | P21: 221.36 | Q21: =IF(OR(N21="",P21=""),"",ROUND((P21-N21)/N21,4)) | R21: =IF(OR(N21="",P21=""),"",IF(Q21>Settings!$B$3/100,"UP",IF(Q21<-Settings!$B$3/100,"DOWN","FLAT"))) | S21: =IF(OR(N21="",P21="",J21=""),"",IF(OR(AND(J21="BUY",R21="UP"),AND(J21="SELL",R21="DOWN"),AND(J21="HOLD",R21="FLAT")),"YES","NO")) | T21: =IF(J21="","",IF(J21="BUY",1,IF(J21="SELL",-1,0))) | U21: =IFERROR(IF(OR(J21="",N21="",P21=""),"",IF(T21=0,0,T21*Q21-Settings!$B$4/10000-IF(T21<0,Settings!$B$5/10000,0))),"") | V21: Good progress on the 737 programme though 777X production delayed; US Space Force contract secured; KPIs being met and demand still strong; finances healthier; supply chain still tough but stable. Steady tone. | W21: =IF($K21="","",$K21*60) | X21: =IF($A21="","",$A21&"|"&$C21&"|"&$D21) | Y21: =IFERROR(IF($X21="","",INDEX(LLM_Data_Entry!$H$3:$H$548,MATCH($X21,INDEX(LLM_Data_Entry!$A$3:$A$548&"|"&LLM_Data_Entry!$C$3:$C$548&"|"&LLM_Data_Entry!$D$3:$D$548,0),0))),"") | Z21: =IFERROR(IF($X21="","",INDEX(LLM_Data_Entry!$R$3:$R$548,MATCH($X21,INDEX(LLM_Data_Entry!$A$3:$A$548&"|"&LLM_Data_Entry!$C$3:$C$548&"|"&LLM_Data_Entry!$D$3:$D$548,0),0))),"") | AB21: release time published by the issuer | AC21: BA | AD21: 2025-10-28 | AE21: 223.33 | AF21: 2025-10-29 | AG21: 221.36 | AH21: -0.0088210316 | AI21: FLAT | AJ21: YES | AK21: 0 | AL21: =IF($A21="","",IFERROR(INDEX(Company_List!$G$3:$G$207,MATCH($A21,Company_List!$A$3:$A$207,0)),"unassigned")) | AM21: Phase 2/Boeing/2025-Q3/BA-2025-Q3-press-release-SEC-EX-99-1.htm | AN21: https://www.sec.gov/Archives/edgar/data/12927/000162828025046915/a202509sep308kprex991.htm | AO21: manifest | AP21: =IF($A21="","",IF(COUNTIFS(LLM_Data_Entry!$A$3:$A$548,$A21)>0,"YES","NO")) | AQ21: =IF($A21="","",IF(COUNTIFS($A$3:$A21,$A21,$C$3:$C21,$C21,$D$3:$D21,$D21)=1,"YES","NO")) | AR21: =IF($A21="","",IF(AND($C21&"-"&$D21>=Settings!$B$19,$C21&"-"&$D21<=Settings!$B$20),"IN","OUT")) | AS21: =IF($A21="","",IF($F21="Financial Results","financials",IF($F21="Outlook/Guidance","guidance",IF($F21="Transcript Q&A","qanda",IF($F21="","unrecorded",IF($E21="All","full",IF($E21="","unrecorded",LOWER($E21)&" only"))))))) | AT21: =IF(AND(OR($J21="BUY",$J21="SELL"),ISNUMBER($U21)),$U21,"") | AU21: =IF(AND(OR($J21="BUY",$J21="SELL"),ISNUMBER($AK21)),$AK21,"") | AV21: =IF(ISNUMBER($AT21),ABS(IF(ISNUMBER($I21),$I21,0)-Settings!$B$24),"") | AW21: =IF(ISNUMBER($AV21),$AV21*$AT21,"") | AX21: =IF(ISNUMBER($AU21),ABS(IF(ISNUMBER($I21),$I21,0)-Settings!$B$24),"") | AY21: FROZEN | AZ21: =IF($A21="","",IFERROR(INDEX(Company_List!$H$3:$H$207,MATCH($A21,Company_List!$A$3:$A$207,0)),"unassigned")) | BC21: =IF($A21="","",IF(COUNTIFS($A$3:$A21,$A21,$C$3:$C21,$C21,$D$3:$D21,$D21,$G$3:$G21,$G21)=1,1,0)) | BG21: no | BK21: =IF(OR($H21<>"Human",$S21="",$J21="",$Y21="",$Z21=""),"",IF(EXACT(UPPER($J21),UPPER($Y21)),1,0)) | BL21: assumed - no rater record | BM21: 1 | BN21: not publisher-identified | BO21: not publisher-identified | BP21: no | BQ21: yes | BS21: YES
A22: Boeing | B22: =IF(A22="","",_xlfn.XLOOKUP(A22, Company_List!$A:$A, Company_List!$B:$B, "")) | C22: 2025 | D22: Q4 | E22: All | F22: All | G22: Nigel | H22: Human | I22: 0.7 | J22: =IF(OR(I22="",Settings!$B$6=""),"",IF(I22>Settings!$B$6,"BUY",IF(I22<-Settings!$B$6,"SELL","HOLD"))) | K22: 18 | L22: 46049 | M22: 46048 | N22: 248.43 | O22: 46049 | P22: 242.5 | Q22: =IF(OR(N22="",P22=""),"",ROUND((P22-N22)/N22,4)) | R22: =IF(OR(N22="",P22=""),"",IF(Q22>Settings!$B$3/100,"UP",IF(Q22<-Settings!$B$3/100,"DOWN","FLAT"))) | S22: =IF(OR(N22="",P22="",J22=""),"",IF(OR(AND(J22="BUY",R22="UP"),AND(J22="SELL",R22="DOWN"),AND(J22="HOLD",R22="FLAT")),"YES","NO")) | T22: =IF(J22="","",IF(J22="BUY",1,IF(J22="SELL",-1,0))) | U22: =IFERROR(IF(OR(J22="",N22="",P22=""),"",IF(T22=0,0,T22*Q22-Settings!$B$4/10000-IF(T22<0,Settings!$B$5/10000,0))),"") | V22: Highest order totals and good progress on delivery plans; leaner production and supply chain; KPIs being met; further defence deals secured; Jeppesen sale completed; finances healthy. Confident tone. | W22: =IF($K22="","",$K22*60) | X22: =IF($A22="","",$A22&"|"&$C22&"|"&$D22) | Y22: =IFERROR(IF($X22="","",INDEX(LLM_Data_Entry!$H$3:$H$548,MATCH($X22,INDEX(LLM_Data_Entry!$A$3:$A$548&"|"&LLM_Data_Entry!$C$3:$C$548&"|"&LLM_Data_Entry!$D$3:$D$548,0),0))),"") | Z22: =IFERROR(IF($X22="","",INDEX(LLM_Data_Entry!$R$3:$R$548,MATCH($X22,INDEX(LLM_Data_Entry!$A$3:$A$548&"|"&LLM_Data_Entry!$C$3:$C$548&"|"&LLM_Data_Entry!$D$3:$D$548,0),0))),"") | AB22: recorded price identified against every pulled series | AC22: BA | AD22: 2026-01-26 | AE22: 248.43 | AF22: 2026-01-27 | AG22: 242.5 | AH22: -0.023869875 | AI22: DOWN | AJ22: NO | AK22: -0.02487 | AL22: =IF($A22="","",IFERROR(INDEX(Company_List!$G$3:$G$207,MATCH($A22,Company_List!$A$3:$A$207,0)),"unassigned")) | AM22: Phase 2/Boeing/2025-Q4/BA-2025-Q4-press-release-SEC-EX-99-1.htm | AN22: https://www.sec.gov/Archives/edgar/data/12927/000162828026003518/a202512dec318kprex991.htm | AO22: manifest | AP22: =IF($A22="","",IF(COUNTIFS(LLM_Data_Entry!$A$3:$A$548,$A22)>0,"YES","NO")) | AQ22: =IF($A22="","",IF(COUNTIFS($A$3:$A22,$A22,$C$3:$C22,$C22,$D$3:$D22,$D22)=1,"YES","NO")) | AR22: =IF($A22="","",IF(AND($C22&"-"&$D22>=Settings!$B$19,$C22&"-"&$D22<=Settings!$B$20),"IN","OUT")) | AS22: =IF($A22="","",IF($F22="Financial Results","financials",IF($F22="Outlook/Guidance","guidance",IF($F22="Transcript Q&A","qanda",IF($F22="","unrecorded",IF($E22="All","full",IF($E22="","unrecorded",LOWER($E22)&" only"))))))) | AT22: =IF(AND(OR($J22="BUY",$J22="SELL"),ISNUMBER($U22)),$U22,"") | AU22: =IF(AND(OR($J22="BUY",$J22="SELL"),ISNUMBER($AK22)),$AK22,"") | AV22: =IF(ISNUMBER($AT22),ABS(IF(ISNUMBER($I22),$I22,0)-Settings!$B$24),"") | AW22: =IF(ISNUMBER($AV22),$AV22*$AT22,"") | AX22: =IF(ISNUMBER($AU22),ABS(IF(ISNUMBER($I22),$I22,0)-Settings!$B$24),"") | AY22: FROZEN | AZ22: =IF($A22="","",IFERROR(INDEX(Company_List!$H$3:$H$207,MATCH($A22,Company_List!$A$3:$A$207,0)),"unassigned")) | BC22: =IF($A22="","",IF(COUNTIFS($A$3:$A22,$A22,$C$3:$C22,$C22,$D$3:$D22,$D22,$G$3:$G22,$G22)=1,1,0)) | BG22: no | BK22: =IF(OR($H22<>"Human",$S22="",$J22="",$Y22="",$Z22=""),"",IF(EXACT(UPPER($J22),UPPER($Y22)),1,0)) | BL22: assumed - no rater record | BM22: 1 | BN22: not publisher-identified | BO22: not publisher-identified | BP22: no | BQ22: yes | BS22: YES
A23: Disney | B23: =IF(A23="","",_xlfn.XLOOKUP(A23, Company_List!$A:$A, Company_List!$B:$B, "")) | C23: 2025 | D23: Q1 | E23: All | F23: All | G23: Meriem | H23: Human | I23: 0.4 | J23: =IF(OR(I23="",Settings!$B$6=""),"",IF(I23>Settings!$B$6,"BUY",IF(I23<-Settings!$B$6,"SELL","HOLD"))) | K23: 60 | L23: 45693 | M23: 45692 | N23: 113.3 | O23: 45693 | P23: 115.7 | Q23: =IF(OR(N23="",P23=""),"",ROUND((P23-N23)/N23,4)) | R23: =IF(OR(N23="",P23=""),"",IF(Q23>Settings!$B$3/100,"UP",IF(Q23<-Settings!$B$3/100,"DOWN","FLAT"))) | S23: =IF(OR(N23="",P23="",J23=""),"",IF(OR(AND(J23="BUY",R23="UP"),AND(J23="SELL",R23="DOWN"),AND(J23="HOLD",R23="FLAT")),"YES","NO")) | T23: =IF(J23="","",IF(J23="BUY",1,IF(J23="SELL",-1,0))) | U23: =IFERROR(IF(OR(J23="",N23="",P23=""),"",IF(T23=0,0,T23*Q23-Settings!$B$4/10000-IF(T23<0,Settings!$B$5/10000,0))),"") | W23: =IF($K23="","",$K23*60) | X23: =IF($A23="","",$A23&"|"&$C23&"|"&$D23) | Y23: =IFERROR(IF($X23="","",INDEX(LLM_Data_Entry!$H$3:$H$548,MATCH($X23,INDEX(LLM_Data_Entry!$A$3:$A$548&"|"&LLM_Data_Entry!$C$3:$C$548&"|"&LLM_Data_Entry!$D$3:$D$548,0),0))),"") | Z23: =IFERROR(IF($X23="","",INDEX(LLM_Data_Entry!$R$3:$R$548,MATCH($X23,INDEX(LLM_Data_Entry!$A$3:$A$548&"|"&LLM_Data_Entry!$C$3:$C$548&"|"&LLM_Data_Entry!$D$3:$D$548,0),0))),"") | AB23: release date + stated time | AC23: DIS | AD23: 2025-02-04 | AE23: 111.2086 | AF23: 2025-02-05 | AG23: 113.5643 | AH23: 0.021182588 | AI23: UP | AJ23: YES | AK23: 0.020183 | AL23: =IF($A23="","",IFERROR(INDEX(Company_List!$G$3:$G$207,MATCH($A23,Company_List!$A$3:$A$207,0)),"unassigned")) | AM23: Phase 2/Disney/q1-fy25-earnings-transcriptpdf.pdf | AO23: unique filename match | AP23: =IF($A23="","",IF(COUNTIFS(LLM_Data_Entry!$A$3:$A$548,$A23)>0,"YES","NO")) | AQ23: =IF($A23="","",IF(COUNTIFS($A$3:$A23,$A23,$C$3:$C23,$C23,$D$3:$D23,$D23)=1,"YES","NO")) | AR23: =IF($A23="","",IF(AND($C23&"-"&$D23>=Settings!$B$19,$C23&"-"&$D23<=Settings!$B$20),"IN","OUT")) | AS23: =IF($A23="","",IF($F23="Financial Results","financials",IF($F23="Outlook/Guidance","guidance",IF($F23="Transcript Q&A","qanda",IF($F23="","unrecorded",IF($E23="All","full",IF($E23="","unrecorded",LOWER($E23)&" only"))))))) | AT23: =IF(AND(OR($J23="BUY",$J23="SELL"),ISNUMBER($U23)),$U23,"") | AU23: =IF(AND(OR($J23="BUY",$J23="SELL"),ISNUMBER($AK23)),$AK23,"") | AV23: =IF(ISNUMBER($AT23),ABS(IF(ISNUMBER($I23),$I23,0)-Settings!$B$24),"") | AW23: =IF(ISNUMBER($AV23),$AV23*$AT23,"") | AX23: =IF(ISNUMBER($AU23),ABS(IF(ISNUMBER($I23),$I23,0)-Settings!$B$24),"") | AY23: FROZEN | AZ23: =IF($A23="","",IFERROR(INDEX(Company_List!$H$3:$H$207,MATCH($A23,Company_List!$A$3:$A$207,0)),"unassigned")) | BC23: =IF($A23="","",IF(COUNTIFS($A$3:$A23,$A23,$C$3:$C23,$C23,$D$3:$D23,$D23,$G$3:$G23,$G23)=1,1,0)) | BG23: no | BK23: =IF(OR($H23<>"Human",$S23="",$J23="",$Y23="",$Z23=""),"",IF(EXACT(UPPER($J23),UPPER($Y23)),1,0)) | BL23: assumed - no rater record | BM23: 1 | BN23: The Motley Fool | BO23: free to read, copyright asserted | BP23: no | BQ23: no | BS23: YES
A24: Disney | B24: =IF(A24="","",_xlfn.XLOOKUP(A24, Company_List!$A:$A, Company_List!$B:$B, "")) | C24: 2025 | D24: Q3 | E24: All | F24: All | G24: Meriem | H24: Human | I24: 0.5 | J24: =IF(OR(I24="",Settings!$B$6=""),"",IF(I24>Settings!$B$6,"BUY",IF(I24<-Settings!$B$6,"SELL","HOLD"))) | K24: 45 | L24: 45875 | M24: 45874 | N24: 118.32 | O24: 45875 | P24: 115.78 | Q24: =IF(OR(N24="",P24=""),"",ROUND((P24-N24)/N24,4)) | R24: =IF(OR(N24="",P24=""),"",IF(Q24>Settings!$B$3/100,"UP",IF(Q24<-Settings!$B$3/100,"DOWN","FLAT"))) | S24: =IF(OR(N24="",P24="",J24=""),"",IF(OR(AND(J24="BUY",R24="UP"),AND(J24="SELL",R24="DOWN"),AND(J24="HOLD",R24="FLAT")),"YES","NO")) | T24: =IF(J24="","",IF(J24="BUY",1,IF(J24="SELL",-1,0))) | U24: =IFERROR(IF(OR(J24="",N24="",P24=""),"",IF(T24=0,0,T24*Q24-Settings!$B$4/10000-IF(T24<0,Settings!$B$5/10000,0))),"") | W24: =IF($K24="","",$K24*60) | X24: =IF($A24="","",$A24&"|"&$C24&"|"&$D24) | Y24: =IFERROR(IF($X24="","",INDEX(LLM_Data_Entry!$H$3:$H$548,MATCH($X24,INDEX(LLM_Data_Entry!$A$3:$A$548&"|"&LLM_Data_Entry!$C$3:$C$548&"|"&LLM_Data_Entry!$D$3:$D$548,0),0))),"") | Z24: =IFERROR(IF($X24="","",INDEX(LLM_Data_Entry!$R$3:$R$548,MATCH($X24,INDEX(LLM_Data_Entry!$A$3:$A$548&"|"&LLM_Data_Entry!$C$3:$C$548&"|"&LLM_Data_Entry!$D$3:$D$548,0),0))),"") | AB24: price signal — only this window shows an abnormal move | AC24: DIS | AD24: 2025-08-05 | AE24: 116.6312 | AF24: 2025-08-06 | AG24: 114.1274 | AH24: -0.021467297 | AI24: DOWN | AJ24: NO | AK24: -0.022467 | AL24: =IF($A24="","",IFERROR(INDEX(Company_List!$G$3:$G$207,MATCH($A24,Company_List!$A$3:$A$207,0)),"unassigned")) | AM24: Phase 2/Disney/q3-fy25-earnings-transcript.pdf | AO24: unique filename match | AP24: =IF($A24="","",IF(COUNTIFS(LLM_Data_Entry!$A$3:$A$548,$A24)>0,"YES","NO")) | AQ24: =IF($A24="","",IF(COUNTIFS($A$3:$A24,$A24,$C$3:$C24,$C24,$D$3:$D24,$D24)=1,"YES","NO")) | AR24: =IF($A24="","",IF(AND($C24&"-"&$D24>=Settings!$B$19,$C24&"-"&$D24<=Settings!$B$20),"IN","OUT")) | AS24: =IF($A24="","",IF($F24="Financial Results","financials",IF($F24="Outlook/Guidance","guidance",IF($F24="Transcript Q&A","qanda",IF($F24="","unrecorded",IF($E24="All","full",IF($E24="","unrecorded",LOWER($E24)&" only"))))))) | AT24: =IF(AND(OR($J24="BUY",$J24="SELL"),ISNUMBER($U24)),$U24,"") | AU24: =IF(AND(OR($J24="BUY",$J24="SELL"),ISNUMBER($AK24)),$AK24,"") | AV24: =IF(ISNUMBER($AT24),ABS(IF(ISNUMBER($I24),$I24,0)-Settings!$B$24),"") | AW24: =IF(ISNUMBER($AV24),$AV24*$AT24,"") | AX24: =IF(ISNUMBER($AU24),ABS(IF(ISNUMBER($I24),$I24,0)-Settings!$B$24),"") | AY24: FROZEN | AZ24: =IF($A24="","",IFERROR(INDEX(Company_List!$H$3:$H$207,MATCH($A24,Company_List!$A$3:$A$207,0)),"unassigned")) | BC24: =IF($A24="","",IF(COUNTIFS($A$3:$A24,$A24,$C$3:$C24,$C24,$D$3:$D24,$D24,$G$3:$G24,$G24)=1,1,0)) | BG24: no | BK24: =IF(OR($H24<>"Human",$S24="",$J24="",$Y24="",$Z24=""),"",IF(EXACT(UPPER($J24),UPPER($Y24)),1,0)) | BL24: assumed - no rater record | BM24: 1 | BN24: not publisher-identified | BO24: not publisher-identified | BP24: no | BQ24: no | BS24: YES
A25: Disney | B25: =IF(A25="","",_xlfn.XLOOKUP(A25, Company_List!$A:$A, Company_List!$B:$B, "")) | C25: 2025 | D25: Q4 | E25: All | F25: All | G25: Meriem | H25: Human | I25: 0.6 | J25: =IF(OR(I25="",Settings!$B$6=""),"",IF(I25>Settings!$B$6,"BUY",IF(I25<-Settings!$B$6,"SELL","HOLD"))) | K25: 60 | L25: 45974 | M25: 45973 | N25: 116.65 | O25: 45974 | P25: 108.89 | Q25: =IF(OR(N25="",P25=""),"",ROUND((P25-N25)/N25,4)) | R25: =IF(OR(N25="",P25=""),"",IF(Q25>Settings!$B$3/100,"UP",IF(Q25<-Settings!$B$3/100,"DOWN","FLAT"))) | S25: =IF(OR(N25="",P25="",J25=""),"",IF(OR(AND(J25="BUY",R25="UP"),AND(J25="SELL",R25="DOWN"),AND(J25="HOLD",R25="FLAT")),"YES","NO")) | T25: =IF(J25="","",IF(J25="BUY",1,IF(J25="SELL",-1,0))) | U25: =IFERROR(IF(OR(J25="",N25="",P25=""),"",IF(T25=0,0,T25*Q25-Settings!$B$4/10000-IF(T25<0,Settings!$B$5/10000,0))),"") | W25: =IF($K25="","",$K25*60) | X25: =IF($A25="","",$A25&"|"&$C25&"|"&$D25) | Y25: =IFERROR(IF($X25="","",INDEX(LLM_Data_Entry!$H$3:$H$548,MATCH($X25,INDEX(LLM_Data_Entry!$A$3:$A$548&"|"&LLM_Data_Entry!$C$3:$C$548&"|"&LLM_Data_Entry!$D$3:$D$548,0),0))),"") | Z25: =IFERROR(IF($X25="","",INDEX(LLM_Data_Entry!$R$3:$R$548,MATCH($X25,INDEX(LLM_Data_Entry!$A$3:$A$548&"|"&LLM_Data_Entry!$C$3:$C$548&"|"&LLM_Data_Entry!$D$3:$D$548,0),0))),"") | AB25: price signal — only this window shows an abnormal move | AC25: DIS | AD25: 2025-11-12 | AE25: 114.985 | AF25: 2025-11-13 | AG25: 107.3358 | AH25: -0.066523851 | AI25: DOWN | AJ25: NO | AK25: -0.067524 | AL25: =IF($A25="","",IFERROR(INDEX(Company_List!$G$3:$G$207,MATCH($A25,Company_List!$A$3:$A$207,0)),"unassigned")) | AM25: Phase 2/Disney/q4-fy25-earnings-transcript.pdf | AO25: unique filename match | AP25: =IF($A25="","",IF(COUNTIFS(LLM_Data_Entry!$A$3:$A$548,$A25)>0,"YES","NO")) | AQ25: =IF($A25="","",IF(COUNTIFS($A$3:$A25,$A25,$C$3:$C25,$C25,$D$3:$D25,$D25)=1,"YES","NO")) | AR25: =IF($A25="","",IF(AND($C25&"-"&$D25>=Settings!$B$19,$C25&"-"&$D25<=Settings!$B$20),"IN","OUT")) | AS25: =IF($A25="","",IF($F25="Financial Results","financials",IF($F25="Outlook/Guidance","guidance",IF($F25="Transcript Q&A","qanda",IF($F25="","unrecorded",IF($E25="All","full",IF($E25="","unrecorded",LOWER($E25)&" only"))))))) | AT25: =IF(AND(OR($J25="BUY",$J25="SELL"),ISNUMBER($U25)),$U25,"") | AU25: =IF(AND(OR($J25="BUY",$J25="SELL"),ISNUMBER($AK25)),$AK25,"") | AV25: =IF(ISNUMBER($AT25),ABS(IF(ISNUMBER($I25),$I25,0)-Settings!$B$24),"") | AW25: =IF(ISNUMBER($AV25),$AV25*$AT25,"") | AX25: =IF(ISNUMBER($AU25),ABS(IF(ISNUMBER($I25),$I25,0)-Settings!$B$24),"") | AY25: FROZEN | AZ25: =IF($A25="","",IFERROR(INDEX(Company_List!$H$3:$H$207,MATCH($A25,Company_List!$A$3:$A$207,0)),"unassigned")) | BC25: =IF($A25="","",IF(COUNTIFS($A$3:$A25,$A25,$C$3:$C25,$C25,$D$3:$D25,$D25,$G$3:$G25,$G25)=1,1,0)) | BG25: no | BK25: =IF(OR($H25<>"Human",$S25="",$J25="",$Y25="",$Z25=""),"",IF(EXACT(UPPER($J25),UPPER($Y25)),1,0)) | BL25: assumed - no rater record | BM25: 1 | BN25: not publisher-identified | BO25: not publisher-identified | BP25: no | BQ25: no | BS25: YES
A26: Netflix | B26: =IF(A26="","",_xlfn.XLOOKUP(A26, Company_List!$A:$A, Company_List!$B:$B, "")) | C26: 2025 | D26: Q3 | E26: Transcript | F26: All | G26: David | H26: Human | I26: 0.5 | J26: =IF(OR(I26="",Settings!$B$6=""),"",IF(I26>Settings!$B$6,"BUY",IF(I26<-Settings!$B$6,"SELL","HOLD"))) | K26: 62 | L26: 45951 | M26: 45951 | N26: 124.135 | O26: 45952 | P26: 114.29 | Q26: =IF(OR(N26="",P26=""),"",ROUND((P26-N26)/N26,4)) | R26: =IF(OR(N26="",P26=""),"",IF(Q26>Settings!$B$3/100,"UP",IF(Q26<-Settings!$B$3/100,"DOWN","FLAT"))) | S26: =IF(OR(N26="",P26="",J26=""),"",IF(OR(AND(J26="BUY",R26="UP"),AND(J26="SELL",R26="DOWN"),AND(J26="HOLD",R26="FLAT")),"YES","NO")) | T26: =IF(J26="","",IF(J26="BUY",1,IF(J26="SELL",-1,0))) | U26: =IFERROR(IF(OR(J26="",N26="",P26=""),"",IF(T26=0,0,T26*Q26-Settings!$B$4/10000-IF(T26<0,Settings!$B$5/10000,0))),"") | W26: =IF($K26="","",$K26*60) | X26: =IF($A26="","",$A26&"|"&$C26&"|"&$D26) | Y26: =IFERROR(IF($X26="","",INDEX(LLM_Data_Entry!$H$3:$H$548,MATCH($X26,INDEX(LLM_Data_Entry!$A$3:$A$548&"|"&LLM_Data_Entry!$C$3:$C$548&"|"&LLM_Data_Entry!$D$3:$D$548,0),0))),"") | Z26: =IFERROR(IF($X26="","",INDEX(LLM_Data_Entry!$R$3:$R$548,MATCH($X26,INDEX(LLM_Data_Entry!$A$3:$A$548&"|"&LLM_Data_Entry!$C$3:$C$548&"|"&LLM_Data_Entry!$D$3:$D$548,0),0))),"") | AB26: release date + stated time in the document (rater worksheet) | AC26: NFLX | AD26: 2025-10-21 | AE26: 124.135 | AF26: 2025-10-22 | AG26: 114.29 | AH26: -0.079308824 | AI26: DOWN | AJ26: NO | AK26: -0.080309 | AL26: =IF($A26="","",IFERROR(INDEX(Company_List!$G$3:$G$207,MATCH($A26,Company_List!$A$3:$A$207,0)),"unassigned")) | AM26: Phase 2/Netflix/2025-Q3/NFLX-2025-Q3-press-release-SEC-EX-99-1.htm | AN26: https://www.sec.gov/Archives/edgar/data/1065280/000106528025000404/ex991_q325.htm | AO26: manifest | AP26: =IF($A26="","",IF(COUNTIFS(LLM_Data_Entry!$A$3:$A$548,$A26)>0,"YES","NO")) | AQ26: =IF($A26="","",IF(COUNTIFS($A$3:$A26,$A26,$C$3:$C26,$C26,$D$3:$D26,$D26)=1,"YES","NO")) | AR26: =IF($A26="","",IF(AND($C26&"-"&$D26>=Settings!$B$19,$C26&"-"&$D26<=Settings!$B$20),"IN","OUT")) | AS26: =IF($A26="","",IF($F26="Financial Results","financials",IF($F26="Outlook/Guidance","guidance",IF($F26="Transcript Q&A","qanda",IF($F26="","unrecorded",IF($E26="All","full",IF($E26="","unrecorded",LOWER($E26)&" only"))))))) | AT26: =IF(AND(OR($J26="BUY",$J26="SELL"),ISNUMBER($U26)),$U26,"") | AU26: =IF(AND(OR($J26="BUY",$J26="SELL"),ISNUMBER($AK26)),$AK26,"") | AV26: =IF(ISNUMBER($AT26),ABS(IF(ISNUMBER($I26),$I26,0)-Settings!$B$24),"") | AW26: =IF(ISNUMBER($AV26),$AV26*$AT26,"") | AX26: =IF(ISNUMBER($AU26),ABS(IF(ISNUMBER($I26),$I26,0)-Settings!$B$24),"") | AY26: FROZEN | AZ26: =IF($A26="","",IFERROR(INDEX(Company_List!$H$3:$H$207,MATCH($A26,Company_List!$A$3:$A$207,0)),"unassigned")) | BC26: =IF($A26="","",IF(COUNTIFS($A$3:$A26,$A26,$C$3:$C26,$C26,$D$3:$D26,$D26,$G$3:$G26,$G26)=1,1,0)) | BG26: no | BK26: =IF(OR($H26<>"Human",$S26="",$J26="",$Y26="",$Z26=""),"",IF(EXACT(UPPER($J26),UPPER($Y26)),1,0)) | BL26: assumed - no rater record | BM26: 1 | BN26: not publisher-identified | BO26: not publisher-identified | BP26: no | BQ26: yes | BR26: filled 11 Aug 2026 from the corpus manifest: the company-quarter holds exactly one document and the manifest carries its release date | BS26: YES
A27: Netflix | B27: =IF(A27="","",_xlfn.XLOOKUP(A27, Company_List!$A:$A, Company_List!$B:$B, "")) | C27: 2025 | D27: Q4 | E27: Transcript | F27: All | G27: David | H27: Human | I27: 0.6 | J27: =IF(OR(I27="",Settings!$B$6=""),"",IF(I27>Settings!$B$6,"BUY",IF(I27<-Settings!$B$6,"SELL","HOLD"))) | K27: 60 | L27: 46042 | M27: 46042 | N27: 87.26 | O27: 46043 | P27: 82.52 | Q27: =IF(OR(N27="",P27=""),"",ROUND((P27-N27)/N27,4)) | R27: =IF(OR(N27="",P27=""),"",IF(Q27>Settings!$B$3/100,"UP",IF(Q27<-Settings!$B$3/100,"DOWN","FLAT"))) | S27: =IF(OR(N27="",P27="",J27=""),"",IF(OR(AND(J27="BUY",R27="UP"),AND(J27="SELL",R27="DOWN"),AND(J27="HOLD",R27="FLAT")),"YES","NO")) | T27: =IF(J27="","",IF(J27="BUY",1,IF(J27="SELL",-1,0))) | U27: =IFERROR(IF(OR(J27="",N27="",P27=""),"",IF(T27=0,0,T27*Q27-Settings!$B$4/10000-IF(T27<0,Settings!$B$5/10000,0))),"") | W27: =IF($K27="","",$K27*60) | X27: =IF($A27="","",$A27&"|"&$C27&"|"&$D27) | Y27: =IFERROR(IF($X27="","",INDEX(LLM_Data_Entry!$H$3:$H$548,MATCH($X27,INDEX(LLM_Data_Entry!$A$3:$A$548&"|"&LLM_Data_Entry!$C$3:$C$548&"|"&LLM_Data_Entry!$D$3:$D$548,0),0))),"") | Z27: =IFERROR(IF($X27="","",INDEX(LLM_Data_Entry!$R$3:$R$548,MATCH($X27,INDEX(LLM_Data_Entry!$A$3:$A$548&"|"&LLM_Data_Entry!$C$3:$C$548&"|"&LLM_Data_Entry!$D$3:$D$548,0),0))),"") | AB27: release date + stated time in the document (rater worksheet) | AC27: NFLX | AD27: 2026-01-20 | AE27: 87.26 | AF27: 2026-01-21 | AG27: 82.52 | AH27: -0.054320478 | AI27: DOWN | AJ27: NO | AK27: -0.05532 | AL27: =IF($A27="","",IFERROR(INDEX(Company_List!$G$3:$G$207,MATCH($A27,Company_List!$A$3:$A$207,0)),"unassigned")) | AM27: Phase 2/Netflix/2025-Q4/NFLX-2025-Q4-press-release-SEC-EX-99-1.htm | AN27: https://www.sec.gov/Archives/edgar/data/1065280/000106528026000033/ex991_q425.htm | AO27: manifest | AP27: =IF($A27="","",IF(COUNTIFS(LLM_Data_Entry!$A$3:$A$548,$A27)>0,"YES","NO")) | AQ27: =IF($A27="","",IF(COUNTIFS($A$3:$A27,$A27,$C$3:$C27,$C27,$D$3:$D27,$D27)=1,"YES","NO")) | AR27: =IF($A27="","",IF(AND($C27&"-"&$D27>=Settings!$B$19,$C27&"-"&$D27<=Settings!$B$20),"IN","OUT")) | AS27: =IF($A27="","",IF($F27="Financial Results","financials",IF($F27="Outlook/Guidance","guidance",IF($F27="Transcript Q&A","qanda",IF($F27="","unrecorded",IF($E27="All","full",IF($E27="","unrecorded",LOWER($E27)&" only"))))))) | AT27: =IF(AND(OR($J27="BUY",$J27="SELL"),ISNUMBER($U27)),$U27,"") | AU27: =IF(AND(OR($J27="BUY",$J27="SELL"),ISNUMBER($AK27)),$AK27,"") | AV27: =IF(ISNUMBER($AT27),ABS(IF(ISNUMBER($I27),$I27,0)-Settings!$B$24),"") | AW27: =IF(ISNUMBER($AV27),$AV27*$AT27,"") | AX27: =IF(ISNUMBER($AU27),ABS(IF(ISNUMBER($I27),$I27,0)-Settings!$B$24),"") | AY27: FROZEN | AZ27: =IF($A27="","",IFERROR(INDEX(Company_List!$H$3:$H$207,MATCH($A27,Company_List!$A$3:$A$207,0)),"unassigned")) | BC27: =IF($A27="","",IF(COUNTIFS($A$3:$A27,$A27,$C$3:$C27,$C27,$D$3:$D27,$D27,$G$3:$G27,$G27)=1,1,0)) | BG27: no | BK27: =IF(OR($H27<>"Human",$S27="",$J27="",$Y27="",$Z27=""),"",IF(EXACT(UPPER($J27),UPPER($Y27)),1,0)) | BL27: assumed - no rater record | BM27: 1 | BN27: not publisher-identified | BO27: not publisher-identified | BP27: no | BQ27: yes | BR27: filled 11 Aug 2026 from the corpus manifest: the company-quarter holds exactly one document and the manifest carries its release date | BS27: YES
A28: Netflix | B28: =IF(A28="","",_xlfn.XLOOKUP(A28, Company_List!$A:$A, Company_List!$B:$B, "")) | C28: 2024 | D28: Q4 | E28: Transcript | F28: All | G28: David | H28: Human | I28: 0.8 | J28: =IF(OR(I28="",Settings!$B$6=""),"",IF(I28>Settings!$B$6,"BUY",IF(I28<-Settings!$B$6,"SELL","HOLD"))) | K28: 47 | L28: 45678 | M28: 45678 | N28: 86.968 | O28: 45679 | P28: 99.8 | Q28: =IF(OR(N28="",P28=""),"",ROUND((P28-N28)/N28,4)) | R28: =IF(OR(N28="",P28=""),"",IF(Q28>Settings!$B$3/100,"UP",IF(Q28<-Settings!$B$3/100,"DOWN","FLAT"))) | S28: =IF(OR(N28="",P28="",J28=""),"",IF(OR(AND(J28="BUY",R28="UP"),AND(J28="SELL",R28="DOWN"),AND(J28="HOLD",R28="FLAT")),"YES","NO")) | T28: =IF(J28="","",IF(J28="BUY",1,IF(J28="SELL",-1,0))) | U28: =IFERROR(IF(OR(J28="",N28="",P28=""),"",IF(T28=0,0,T28*Q28-Settings!$B$4/10000-IF(T28<0,Settings!$B$5/10000,0))),"") | W28: =IF($K28="","",$K28*60) | X28: =IF($A28="","",$A28&"|"&$C28&"|"&$D28) | Y28: =IFERROR(IF($X28="","",INDEX(LLM_Data_Entry!$H$3:$H$548,MATCH($X28,INDEX(LLM_Data_Entry!$A$3:$A$548&"|"&LLM_Data_Entry!$C$3:$C$548&"|"&LLM_Data_Entry!$D$3:$D$548,0),0))),"") | Z28: =IFERROR(IF($X28="","",INDEX(LLM_Data_Entry!$R$3:$R$548,MATCH($X28,INDEX(LLM_Data_Entry!$A$3:$A$548&"|"&LLM_Data_Entry!$C$3:$C$548&"|"&LLM_Data_Entry!$D$3:$D$548,0),0))),"") | AB28: release date + stated time in the document (rater worksheet) | AC28: NFLX | AD28: 2025-01-21 | AE28: 86.968 | AF28: 2025-01-22 | AG28: 99.803 | AH28: 0.147583 | AI28: UP | AJ28: YES | AK28: 0.146583 | AL28: =IF($A28="","",IFERROR(INDEX(Company_List!$G$3:$G$207,MATCH($A28,Company_List!$A$3:$A$207,0)),"unassigned")) | AM28: Phase 2/Netflix/2024-Q4/NFLX-2024-Q4-press-release-SEC-EX-99-1.htm | AN28: https://www.sec.gov/Archives/edgar/data/1065280/000106528025000033/ex991_q424.htm | AO28: manifest | AP28: =IF($A28="","",IF(COUNTIFS(LLM_Data_Entry!$A$3:$A$548,$A28)>0,"YES","NO")) | AQ28: =IF($A28="","",IF(COUNTIFS($A$3:$A28,$A28,$C$3:$C28,$C28,$D$3:$D28,$D28)=1,"YES","NO")) | AR28: =IF($A28="","",IF(AND($C28&"-"&$D28>=Settings!$B$19,$C28&"-"&$D28<=Settings!$B$20),"IN","OUT")) | AS28: =IF($A28="","",IF($F28="Financial Results","financials",IF($F28="Outlook/Guidance","guidance",IF($F28="Transcript Q&A","qanda",IF($F28="","unrecorded",IF($E28="All","full",IF($E28="","unrecorded",LOWER($E28)&" only"))))))) | AT28: =IF(AND(OR($J28="BUY",$J28="SELL"),ISNUMBER($U28)),$U28,"") | AU28: =IF(AND(OR($J28="BUY",$J28="SELL"),ISNUMBER($AK28)),$AK28,"") | AV28: =IF(ISNUMBER($AT28),ABS(IF(ISNUMBER($I28),$I28,0)-Settings!$B$24),"") | AW28: =IF(ISNUMBER($AV28),$AV28*$AT28,"") | AX28: =IF(ISNUMBER($AU28),ABS(IF(ISNUMBER($I28),$I28,0)-Settings!$B$24),"") | AY28: FROZEN | AZ28: =IF($A28="","",IFERROR(INDEX(Company_List!$H$3:$H$207,MATCH($A28,Company_List!$A$3:$A$207,0)),"unassigned")) | BC28: =IF($A28="","",IF(COUNTIFS($A$3:$A28,$A28,$C$3:$C28,$C28,$D$3:$D28,$D28,$G$3:$G28,$G28)=1,1,0)) | BG28: no | BK28: =IF(OR($H28<>"Human",$S28="",$J28="",$Y28="",$Z28=""),"",IF(EXACT(UPPER($J28),UPPER($Y28)),1,0)) | BL28: assumed - no rater record | BM28: 1 | BN28: not publisher-identified | BO28: not publisher-identified | BP28: no | BQ28: yes | BR28: filled 11 Aug 2026 from the corpus manifest: the company-quarter holds exactly one document and the manifest carries its release date | BS28: YES
A29: Amazon | B29: =IF(A29="","",_xlfn.XLOOKUP(A29, Company_List!$A:$A, Company_List!$B:$B, "")) | C29: 2026 | D29: Q1 | E29: All | F29: All | G29: David | H29: Human | I29: 0.8 | J29: =IF(OR(I29="",Settings!$B$6=""),"",IF(I29>Settings!$B$6,"BUY",IF(I29<-Settings!$B$6,"SELL","HOLD"))) | K29: 52 | L29: 46141 | M29: 46141 | N29: 263.04 | O29: 46142 | P29: 273.17 | Q29: =IF(OR(N29="",P29=""),"",ROUND((P29-N29)/N29,4)) | R29: =IF(OR(N29="",P29=""),"",IF(Q29>Settings!$B$3/100,"UP",IF(Q29<-Settings!$B$3/100,"DOWN","FLAT"))) | S29: =IF(OR(N29="",P29="",J29=""),"",IF(OR(AND(J29="BUY",R29="UP"),AND(J29="SELL",R29="DOWN"),AND(J29="HOLD",R29="FLAT")),"YES","NO")) | T29: =IF(J29="","",IF(J29="BUY",1,IF(J29="SELL",-1,0))) | U29: =IFERROR(IF(OR(J29="",N29="",P29=""),"",IF(T29=0,0,T29*Q29-Settings!$B$4/10000-IF(T29<0,Settings!$B$5/10000,0))),"") | W29: =IF($K29="","",$K29*60) | X29: =IF($A29="","",$A29&"|"&$C29&"|"&$D29) | Y29: =IFERROR(IF($X29="","",INDEX(LLM_Data_Entry!$H$3:$H$548,MATCH($X29,INDEX(LLM_Data_Entry!$A$3:$A$548&"|"&LLM_Data_Entry!$C$3:$C$548&"|"&LLM_Data_Entry!$D$3:$D$548,0),0))),"") | Z29: =IFERROR(IF($X29="","",INDEX(LLM_Data_Entry!$R$3:$R$548,MATCH($X29,INDEX(LLM_Data_Entry!$A$3:$A$548&"|"&LLM_Data_Entry!$C$3:$C$548&"|"&LLM_Data_Entry!$D$3:$D$548,0),0))),"") | AB29: release date + stated time in the document (rater worksheet) | AC29: AMZN | AD29: 2026-04-29 | AE29: 263.04 | AF29: 2026-04-30 | AG29: 273.17 | AH29: 0.038511267 | AI29: UP | AJ29: YES | AK29: 0.037511 | AL29: =IF($A29="","",IFERROR(INDEX(Company_List!$G$3:$G$207,MATCH($A29,Company_List!$A$3:$A$207,0)),"unassigned")) | AM29: Phase 2/Amazon/2026-Q1/AMZN-2026-Q1-press-release-SEC-EX-99-1.htm | AN29: https://www.sec.gov/Archives/edgar/data/1018724/000101872426000012/amzn-20260331xex991.htm | AO29: manifest | AP29: =IF($A29="","",IF(COUNTIFS(LLM_Data_Entry!$A$3:$A$548,$A29)>0,"YES","NO")) | AQ29: =IF($A29="","",IF(COUNTIFS($A$3:$A29,$A29,$C$3:$C29,$C29,$D$3:$D29,$D29)=1,"YES","NO")) | AR29: =IF($A29="","",IF(AND($C29&"-"&$D29>=Settings!$B$19,$C29&"-"&$D29<=Settings!$B$20),"IN","OUT")) | AS29: =IF($A29="","",IF($F29="Financial Results","financials",IF($F29="Outlook/Guidance","guidance",IF($F29="Transcript Q&A","qanda",IF($F29="","unrecorded",IF($E29="All","full",IF($E29="","unrecorded",LOWER($E29)&" only"))))))) | AT29: =IF(AND(OR($J29="BUY",$J29="SELL"),ISNUMBER($U29)),$U29,"") | AU29: =IF(AND(OR($J29="BUY",$J29="SELL"),ISNUMBER($AK29)),$AK29,"") | AV29: =IF(ISNUMBER($AT29),ABS(IF(ISNUMBER($I29),$I29,0)-Settings!$B$24),"") | AW29: =IF(ISNUMBER($AV29),$AV29*$AT29,"") | AX29: =IF(ISNUMBER($AU29),ABS(IF(ISNUMBER($I29),$I29,0)-Settings!$B$24),"") | AY29: FROZEN | AZ29: =IF($A29="","",IFERROR(INDEX(Company_List!$H$3:$H$207,MATCH($A29,Company_List!$A$3:$A$207,0)),"unassigned")) | BC29: =IF($A29="","",IF(COUNTIFS($A$3:$A29,$A29,$C$3:$C29,$C29,$D$3:$D29,$D29,$G$3:$G29,$G29)=1,1,0)) | BG29: no | BK29: =IF(OR($H29<>"Human",$S29="",$J29="",$Y29="",$Z29=""),"",IF(EXACT(UPPER($J29),UPPER($Y29)),1,0)) | BL29: assumed - no rater record | BM29: 1 | BN29: not publisher-identified | BO29: not publisher-identified | BP29: no | BQ29: yes | BR29: filled 11 Aug 2026 from the corpus manifest: the company-quarter holds exactly one document and the manifest carries its release date | BS29: YES
A30: Amazon | B30: =IF(A30="","",_xlfn.XLOOKUP(A30, Company_List!$A:$A, Company_List!$B:$B, "")) | C30: 2025 | D30: Q3 | E30: All | F30: All | G30: David | H30: Human | I30: -0.5 | J30: =IF(OR(I30="",Settings!$B$6=""),"",IF(I30>Settings!$B$6,"BUY",IF(I30<-Settings!$B$6,"SELL","HOLD"))) | K30: 47 | L30: 45960 | M30: 45960 | N30: 222.86 | O30: 45961 | P30: 250.1 | Q30: =IF(OR(N30="",P30=""),"",ROUND((P30-N30)/N30,4)) | R30: =IF(OR(N30="",P30=""),"",IF(Q30>Settings!$B$3/100,"UP",IF(Q30<-Settings!$B$3/100,"DOWN","FLAT"))) | S30: =IF(OR(N30="",P30="",J30=""),"",IF(OR(AND(J30="BUY",R30="UP"),AND(J30="SELL",R30="DOWN"),AND(J30="HOLD",R30="FLAT")),"YES","NO")) | T30: =IF(J30="","",IF(J30="BUY",1,IF(J30="SELL",-1,0))) | U30: =IFERROR(IF(OR(J30="",N30="",P30=""),"",IF(T30=0,0,T30*Q30-Settings!$B$4/10000-IF(T30<0,Settings!$B$5/10000,0))),"") | W30: =IF($K30="","",$K30*60) | X30: =IF($A30="","",$A30&"|"&$C30&"|"&$D30) | Y30: =IFERROR(IF($X30="","",INDEX(LLM_Data_Entry!$H$3:$H$548,MATCH($X30,INDEX(LLM_Data_Entry!$A$3:$A$548&"|"&LLM_Data_Entry!$C$3:$C$548&"|"&LLM_Data_Entry!$D$3:$D$548,0),0))),"") | Z30: =IFERROR(IF($X30="","",INDEX(LLM_Data_Entry!$R$3:$R$548,MATCH($X30,INDEX(LLM_Data_Entry!$A$3:$A$548&"|"&LLM_Data_Entry!$C$3:$C$548&"|"&LLM_Data_Entry!$D$3:$D$548,0),0))),"") | AB30: release date + stated time in the document (rater worksheet) | AC30: AMZN | AD30: 2025-10-30 | AE30: 222.86 | AF30: 2025-10-31 | AG30: 250.1 | AH30: 0.12222922 | AI30: UP | AJ30: NO | AK30: -0.123229 | AL30: =IF($A30="","",IFERROR(INDEX(Company_List!$G$3:$G$207,MATCH($A30,Company_List!$A$3:$A$207,0)),"unassigned")) | AM30: Phase 2/Amazon/2025-Q3/AMZN-2025-Q3-press-release-SEC-EX-99-1.htm | AN30: https://www.sec.gov/Archives/edgar/data/1018724/000101872425000121/amzn-20250930xex991.htm | AO30: manifest | AP30: =IF($A30="","",IF(COUNTIFS(LLM_Data_Entry!$A$3:$A$548,$A30)>0,"YES","NO")) | AQ30: =IF($A30="","",IF(COUNTIFS($A$3:$A30,$A30,$C$3:$C30,$C30,$D$3:$D30,$D30)=1,"YES","NO")) | AR30: =IF($A30="","",IF(AND($C30&"-"&$D30>=Settings!$B$19,$C30&"-"&$D30<=Settings!$B$20),"IN","OUT")) | AS30: =IF($A30="","",IF($F30="Financial Results","financials",IF($F30="Outlook/Guidance","guidance",IF($F30="Transcript Q&A","qanda",IF($F30="","unrecorded",IF($E30="All","full",IF($E30="","unrecorded",LOWER($E30)&" only"))))))) | AT30: =IF(AND(OR($J30="BUY",$J30="SELL"),ISNUMBER($U30)),$U30,"") | AU30: =IF(AND(OR($J30="BUY",$J30="SELL"),ISNUMBER($AK30)),$AK30,"") | AV30: =IF(ISNUMBER($AT30),ABS(IF(ISNUMBER($I30),$I30,0)-Settings!$B$24),"") | AW30: =IF(ISNUMBER($AV30),$AV30*$AT30,"") | AX30: =IF(ISNUMBER($AU30),ABS(IF(ISNUMBER($I30),$I30,0)-Settings!$B$24),"") | AY30: FROZEN | AZ30: =IF($A30="","",IFERROR(INDEX(Company_List!$H$3:$H$207,MATCH($A30,Company_List!$A$3:$A$207,0)),"unassigned")) | BC30: =IF($A30="","",IF(COUNTIFS($A$3:$A30,$A30,$C$3:$C30,$C30,$D$3:$D30,$D30,$G$3:$G30,$G30)=1,1,0)) | BG30: no | BK30: =IF(OR($H30<>"Human",$S30="",$J30="",$Y30="",$Z30=""),"",IF(EXACT(UPPER($J30),UPPER($Y30)),1,0)) | BL30: assumed - no rater record | BM30: 1 | BN30: not publisher-identified | BO30: not publisher-identified | BP30: no | BQ30: yes | BR30: filled 11 Aug 2026 from the corpus manifest: the company-quarter holds exactly one document and the manifest carries its release date | BS30: YES
A31: Amazon | B31: =IF(A31="","",_xlfn.XLOOKUP(A31, Company_List!$A:$A, Company_List!$B:$B, "")) | C31: 2025 | D31: Q4 | E31: All | F31: All | G31: David | H31: Human | I31: 0.3 | J31: =IF(OR(I31="",Settings!$B$6=""),"",IF(I31>Settings!$B$6,"BUY",IF(I31<-Settings!$B$6,"SELL","HOLD"))) | K31: 58 | L31: 46058 | M31: 46058 | N31: 222.69 | O31: 46059 | P31: 202.7 | Q31: =IF(OR(N31="",P31=""),"",ROUND((P31-N31)/N31,4)) | R31: =IF(OR(N31="",P31=""),"",IF(Q31>Settings!$B$3/100,"UP",IF(Q31<-Settings!$B$3/100,"DOWN","FLAT"))) | S31: =IF(OR(N31="",P31="",J31=""),"",IF(OR(AND(J31="BUY",R31="UP"),AND(J31="SELL",R31="DOWN"),AND(J31="HOLD",R31="FLAT")),"YES","NO")) | T31: =IF(J31="","",IF(J31="BUY",1,IF(J31="SELL",-1,0))) | U31: =IFERROR(IF(OR(J31="",N31="",P31=""),"",IF(T31=0,0,T31*Q31-Settings!$B$4/10000-IF(T31<0,Settings!$B$5/10000,0))),"") | W31: =IF($K31="","",$K31*60) | X31: =IF($A31="","",$A31&"|"&$C31&"|"&$D31) | Y31: =IFERROR(IF($X31="","",INDEX(LLM_Data_Entry!$H$3:$H$548,MATCH($X31,INDEX(LLM_Data_Entry!$A$3:$A$548&"|"&LLM_Data_Entry!$C$3:$C$548&"|"&LLM_Data_Entry!$D$3:$D$548,0),0))),"") | Z31: =IFERROR(IF($X31="","",INDEX(LLM_Data_Entry!$R$3:$R$548,MATCH($X31,INDEX(LLM_Data_Entry!$A$3:$A$548&"|"&LLM_Data_Entry!$C$3:$C$548&"|"&LLM_Data_Entry!$D$3:$D$548,0),0))),"") | AB31: recorded price identified against every pulled series | AC31: AMZN | AD31: 2026-02-05 | AE31: 222.69 | AF31: 2026-02-06 | AG31: 202.7 | AH31: -0.089766064 | AI31: DOWN | AJ31: NO | AK31: -0.090766 | AL31: =IF($A31="","",IFERROR(INDEX(Company_List!$G$3:$G$207,MATCH($A31,Company_List!$A$3:$A$207,0)),"unassigned")) | AM31: Phase 2/Amazon/2025-Q4/AMZN-2025-Q4-press-release-SEC-EX-99-1.htm | AN31: https://www.sec.gov/Archives/edgar/data/1018724/000101872426000002/amzn-20251231xex991.htm | AO31: manifest | AP31: =IF($A31="","",IF(COUNTIFS(LLM_Data_Entry!$A$3:$A$548,$A31)>0,"YES","NO")) | AQ31: =IF($A31="","",IF(COUNTIFS($A$3:$A31,$A31,$C$3:$C31,$C31,$D$3:$D31,$D31)=1,"YES","NO")) | AR31: =IF($A31="","",IF(AND($C31&"-"&$D31>=Settings!$B$19,$C31&"-"&$D31<=Settings!$B$20),"IN","OUT")) | AS31: =IF($A31="","",IF($F31="Financial Results","financials",IF($F31="Outlook/Guidance","guidance",IF($F31="Transcript Q&A","qanda",IF($F31="","unrecorded",IF($E31="All","full",IF($E31="","unrecorded",LOWER($E31)&" only"))))))) | AT31: =IF(AND(OR($J31="BUY",$J31="SELL"),ISNUMBER($U31)),$U31,"") | AU31: =IF(AND(OR($J31="BUY",$J31="SELL"),ISNUMBER($AK31)),$AK31,"") | AV31: =IF(ISNUMBER($AT31),ABS(IF(ISNUMBER($I31),$I31,0)-Settings!$B$24),"") | AW31: =IF(ISNUMBER($AV31),$AV31*$AT31,"") | AX31: =IF(ISNUMBER($AU31),ABS(IF(ISNUMBER($I31),$I31,0)-Settings!$B$24),"") | AY31: FROZEN | AZ31: =IF($A31="","",IFERROR(INDEX(Company_List!$H$3:$H$207,MATCH($A31,Company_List!$A$3:$A$207,0)),"unassigned")) | BC31: =IF($A31="","",IF(COUNTIFS($A$3:$A31,$A31,$C$3:$C31,$C31,$D$3:$D31,$D31,$G$3:$G31,$G31)=1,1,0)) | BG31: no | BK31: =IF(OR($H31<>"Human",$S31="",$J31="",$Y31="",$Z31=""),"",IF(EXACT(UPPER($J31),UPPER($Y31)),1,0)) | BL31: assumed - no rater record | BM31: 1 | BN31: not publisher-identified | BO31: not publisher-identified | BP31: no | BQ31: yes | BR31: filled 11 Aug 2026 from the corpus manifest: the company-quarter holds exactly one document and the manifest carries its release date | BS31: YES
