Workbook
Name CompanyList: Company_List!$A$3:$A$207
Name DecisionList: Settings!$D$8:$D$10
Name DocumentList: Settings!$I$8:$I$12
Name QuarterList: Settings!$G$8:$G$12
Name RaterList: Settings!$A$8:$A$14
Name SectionList: Settings!$H$8:$H$11
Name TickerList: Company_List!$B$3:$B$207
Name YearList: Settings!$F$8:$F$14

Sheet Human_Data_Entry
A1: HUMAN ARM CORRECTED. Prices M to P re-anchored on release_date from EDGAR filing dates, 2026-08-13. 295 of 420 rows re-anchored; 125 remain on original report_date basis (human-only events not in LLM universe — see column 'Price Basis Corrected'). Columns Q to U and the Summary, Charts and Efficiency sheets recalculate from these. Original basis retained in Master_Data_LOCKED_2026-08-13.xlsx. See Corrections_Log. | W1: Derived from Time (mins). Do not type here. | X1: HELPER KEY | DO NOT EDIT HERE | AB1: SECTION C — re-priced on the declared basis. Values, not formulas. Nothing to the left of here has been changed. | AL1: SECTION D - provenance and classification. Phase is looked up from Company_List column G. Source File is blank where no document matched the event both uniquely and strongly enough to cite, and Source Basis says which. Nothing to the left of here was changed.
A2: Company | B2: Ticker | C2: Year | D2: Quarter | E2: Document | F2: Section | G2: Rater | H2: Type (Human/LLM) | I2: Sentiment Score (−1 to +1) | J2: Decision (BUY/HOLD/SELL) | K2: Time (mins) | L2: Document Date | M2: Prior Closing Date | N2: Prior Close ($) | O2: Next Opening Date | P2: Next Day Open ($) | Q2: Actual % Change | R2: Actual Direction | S2: Prediction Correct? | T2: Position | U2: Net P&L | V2: Notes / Risks Flagged | W2: Time (sec) | X2: Event Key | Y2: LLM Decision | Z2: LLM Correct? | AA2: Helper columns for the Efficiency sheet. Do not type here. | AB2: Re-priced basis | AC2: Re-priced listing | AD2: Re-priced prior close date | AE2: Re-priced prior close | AF2: Re-priced next open date | AG2: Re-priced next open | AH2: Re-priced % change | AI2: Re-priced direction | AJ2: Re-priced correct? | AK2: Re-priced net P&L | AL2: Phase | AM2: Source File | AN2: Source URL | AO2: Source Basis | AP2: In LLM Universe | AQ2: First Rater for Event | AR2: In Window | AS2: Information Set | AT2: Net P&L on trades (helper) | AU2: Net P&L on trades, re-priced (helper) | AV2: Conviction weight (helper) | AW2: Conviction-weighted P&L (helper) | AX2: Conviction weight, re-priced (helper) | AY2: Event Set | AZ2: Sector | BA2: Pass | BB2: Passes Recorded | BC2: First Reading for Rater-Event | BD2: Pass 1 Minutes | BE2: Pass 2 Minutes | BF2: Pass 1 Score | BG2: Peeked | BH2: AI Declared | BI2: Expectation (written before reading) | BJ2: Rater Record | BK2: Decisions Agree | BL2: Peeked - Basis | BM2: Source Documents Cited | BN2: Source Publisher | BO2: Source Licence Class | BP2: Source Is SEC Periodic Filing | BQ2: Source In Provenance Manifest | BR2: Document Date - Basis | BS2: Price Basis Corrected | BT2: Not Corrected Reason
A3: Netflix | B3: =IF(A3="","",_xlfn.XLOOKUP(A3, Company_List!$A:$A, Company_List!$B:$B, "")) -> NFLX | C3: 2026 | D3: Q1 | E3: All | F3: All | G3: Anna | H3: Human | I3: 0.5 | J3: =IF(OR(I3="",Settings!$B$6=""),"",IF(I3>Settings!$B$6,"BUY",IF(I3<-Settings!$B$6,"SELL","HOLD"))) -> BUY | K3: 38 | L3: 46128 | M3: 46128 | N3: 107.79 | O3: 46129 | P3: 96.37 | Q3: =IF(OR(N3="",P3=""),"",ROUND((P3-N3)/N3,4)) -> -0.1059 | R3: =IF(OR(N3="",P3=""),"",IF(Q3>Settings!$B$3/100,"UP",IF(Q3<-Settings!$B$3/100,"DOWN","FLAT"))) -> DOWN | S3: =IF(OR(N3="",P3="",J3=""),"",IF(OR(AND(J3="BUY",R3="UP"),AND(J3="SELL",R3="DOWN"),AND(J3="HOLD",R3="FLAT")),"YES","NO")) -> NO | T3: =IF(J3="","",IF(J3="BUY",1,IF(J3="SELL",-1,0))) -> 1 | U3: =IFERROR(IF(OR(J3="",N3="",P3=""),"",IF(T3=0,0,T3*Q3-Settings!$B$4/10000-IF(T3<0,Settings!$B$5/10000,0))),"") -> -0.1069 | W3: =IF($K3="","",$K3*60) -> 2280 | X3: =IF($A3="","",$A3&"|"&$C3&"|"&$D3) -> Netflix|2026|Q1 | Y3: =IFERROR(IF($X3="","",INDEX(LLM_Data_Entry!$H$3:$H$548,MATCH($X3,INDEX(LLM_Data_Entry!$A$3:$A$548&"|"&LLM_Data_Entry!$C$3:$C$548&"|"&LLM_Data_Entry!$D$3:$D$548,0),0))),"") -> SELL | Z3: =IFERROR(IF($X3="","",INDEX(LLM_Data_Entry!$R$3:$R$548,MATCH($X3,INDEX(LLM_Data_Entry!$A$3:$A$548&"|"&LLM_Data_Entry!$C$3:$C$548&"|"&LLM_Data_Entry!$D$3:$D$548,0),0))),"") -> YES | AB3: price signal — only this window shows an abnormal move | AC3: NFLX | AD3: 2026-04-16 | AE3: 107.79 | AF3: 2026-04-17 | AG3: 96.37 | AH3: -0.10594673 | AI3: DOWN | AJ3: NO | AK3: -0.106947 | AL3: =IF($A3="","",IFERROR(INDEX(Company_List!$G$3:$G$207,MATCH($A3,Company_List!$A$3:$A$207,0)),"unassigned")) -> P2 | AM3: Phase 2/Netflix/Netflix-Inc-_Earnings-Call_2026-04-16T00_00_00_English-1.pdf | AO3: unique filename match | AP3: =IF($A3="","",IF(COUNTIFS(LLM_Data_Entry!$A$3:$A$548,$A3)>0,"YES","NO")) -> YES | AQ3: =IF($A3="","",IF(COUNTIFS($A$3:$A3,$A3,$C$3:$C3,$C3,$D$3:$D3,$D3)=1,"YES","NO")) -> YES | AR3: =IF($A3="","",IF(AND($C3&"-"&$D3>=Settings!$B$19,$C3&"-"&$D3<=Settings!$B$20),"IN","OUT")) -> IN | AS3: =IF($A3="","",IF($F3="Financial Results","financials",IF($F3="Outlook/Guidance","guidance",IF($F3="Transcript Q&A","qanda",IF($F3="","unrecorded",IF($E3="All","full",IF($E3="","unrecorded",LOWER($E3)&" only"))))))) -> full | AT3: =IF(AND(OR($J3="BUY",$J3="SELL"),ISNUMBER($U3)),$U3,"") -> -0.1069 | AU3: =IF(AND(OR($J3="BUY",$J3="SELL"),ISNUMBER($AK3)),$AK3,"") -> -0.106947 | AV3: =IF(ISNUMBER($AT3),ABS(IF(ISNUMBER($I3),$I3,0)-Settings!$B$24),"") -> 0.5 | AW3: =IF(ISNUMBER($AV3),$AV3*$AT3,"") -> -0.05345 | AX3: =IF(ISNUMBER($AU3),ABS(IF(ISNUMBER($I3),$I3,0)-Settings!$B$24),"") -> 0.5 | AY3: FROZEN | AZ3: =IF($A3="","",IFERROR(INDEX(Company_List!$H$3:$H$207,MATCH($A3,Company_List!$A$3:$A$207,0)),"unassigned")) -> Communication Services | BC3: =IF($A3="","",IF(COUNTIFS($A$3:$A3,$A3,$C$3:$C3,$C3,$D$3:$D3,$D3,$G$3:$G3,$G3)=1,1,0)) -> 1 | BG3: no | BK3: =IF(OR($H3<>"Human",$S3="",$J3="",$Y3="",$Z3=""),"",IF(EXACT(UPPER($J3),UPPER($Y3)),1,0)) -> 0 | BL3: assumed - no rater record | BM3: 1 | BN3: S&P Global Market Intelligence (Capital IQ) | BO3: licensed vendor | BP3: no | BQ3: no | BS3: YES
A4: Netflix | B4: =IF(A4="","",_xlfn.XLOOKUP(A4, Company_List!$A:$A, Company_List!$B:$B, "")) -> NFLX | C4: 2025 | D4: Q2 | E4: All | F4: All | G4: Anna | H4: Human | I4: 0.2 | J4: =IF(OR(I4="",Settings!$B$6=""),"",IF(I4>Settings!$B$6,"BUY",IF(I4<-Settings!$B$6,"SELL","HOLD"))) -> HOLD | K4: 26 | L4: 45855 | M4: 45855 | N4: 127.417 | O4: 45856 | P4: 124.2 | Q4: =IF(OR(N4="",P4=""),"",ROUND((P4-N4)/N4,4)) -> -0.0252 | R4: =IF(OR(N4="",P4=""),"",IF(Q4>Settings!$B$3/100,"UP",IF(Q4<-Settings!$B$3/100,"DOWN","FLAT"))) -> DOWN | S4: =IF(OR(N4="",P4="",J4=""),"",IF(OR(AND(J4="BUY",R4="UP"),AND(J4="SELL",R4="DOWN"),AND(J4="HOLD",R4="FLAT")),"YES","NO")) -> NO | T4: =IF(J4="","",IF(J4="BUY",1,IF(J4="SELL",-1,0))) -> 0 | U4: =IFERROR(IF(OR(J4="",N4="",P4=""),"",IF(T4=0,0,T4*Q4-Settings!$B$4/10000-IF(T4<0,Settings!$B$5/10000,0))),"") -> 0 | W4: =IF($K4="","",$K4*60) -> 1560 | X4: =IF($A4="","",$A4&"|"&$C4&"|"&$D4) -> Netflix|2025|Q2 | Y4: =IFERROR(IF($X4="","",INDEX(LLM_Data_Entry!$H$3:$H$548,MATCH($X4,INDEX(LLM_Data_Entry!$A$3:$A$548&"|"&LLM_Data_Entry!$C$3:$C$548&"|"&LLM_Data_Entry!$D$3:$D$548,0),0))),"") -> HOLD | Z4: =IFERROR(IF($X4="","",INDEX(LLM_Data_Entry!$R$3:$R$548,MATCH($X4,INDEX(LLM_Data_Entry!$A$3:$A$548&"|"&LLM_Data_Entry!$C$3:$C$548&"|"&LLM_Data_Entry!$D$3:$D$548,0),0))),"") -> NO | AB4: price signal — only this window shows an abnormal move | AC4: NFLX | AD4: 2025-07-17 | AE4: 127.417 | AF4: 2025-07-18 | AG4: 124.196 | AH4: -0.025279209 | AI4: DOWN | AJ4: NO | AK4: 0 | AL4: =IF($A4="","",IFERROR(INDEX(Company_List!$G$3:$G$207,MATCH($A4,Company_List!$A$3:$A$207,0)),"unassigned")) -> P2 | AM4: Phase 2/Netflix/2025-Q2/NFLX-2025-Q2-press-release-SEC-EX-99-1.htm | AN4: https://www.sec.gov/Archives/edgar/data/1065280/000106528025000322/ex991_q225.htm | AO4: manifest | AP4: =IF($A4="","",IF(COUNTIFS(LLM_Data_Entry!$A$3:$A$548,$A4)>0,"YES","NO")) -> YES | AQ4: =IF($A4="","",IF(COUNTIFS($A$3:$A4,$A4,$C$3:$C4,$C4,$D$3:$D4,$D4)=1,"YES","NO")) -> YES | AR4: =IF($A4="","",IF(AND($C4&"-"&$D4>=Settings!$B$19,$C4&"-"&$D4<=Settings!$B$20),"IN","OUT")) -> IN | AS4: =IF($A4="","",IF($F4="Financial Results","financials",IF($F4="Outlook/Guidance","guidance",IF($F4="Transcript Q&A","qanda",IF($F4="","unrecorded",IF($E4="All","full",IF($E4="","unrecorded",LOWER($E4)&" only"))))))) -> full | AT4: =IF(AND(OR($J4="BUY",$J4="SELL"),ISNUMBER($U4)),$U4,"") | AU4: =IF(AND(OR($J4="BUY",$J4="SELL"),ISNUMBER($AK4)),$AK4,"") | AV4: =IF(ISNUMBER($AT4),ABS(IF(ISNUMBER($I4),$I4,0)-Settings!$B$24),"") | AW4: =IF(ISNUMBER($AV4),$AV4*$AT4,"") | AX4: =IF(ISNUMBER($AU4),ABS(IF(ISNUMBER($I4),$I4,0)-Settings!$B$24),"") | AY4: FROZEN | AZ4: =IF($A4="","",IFERROR(INDEX(Company_List!$H$3:$H$207,MATCH($A4,Company_List!$A$3:$A$207,0)),"unassigned")) -> Communication Services | BC4: =IF($A4="","",IF(COUNTIFS($A$3:$A4,$A4,$C$3:$C4,$C4,$D$3:$D4,$D4,$G$3:$G4,$G4)=1,1,0)) -> 1 | BG4: no | BK4: =IF(OR($H4<>"Human",$S4="",$J4="",$Y4="",$Z4=""),"",IF(EXACT(UPPER($J4),UPPER($Y4)),1,0)) -> 1 | BL4: assumed - no rater record | BM4: 1 | BN4: not publisher-identified | BO4: not publisher-identified | BP4: no | BQ4: yes | BS4: YES
A5: Netflix | B5: =IF(A5="","",_xlfn.XLOOKUP(A5, Company_List!$A:$A, Company_List!$B:$B, "")) -> NFLX | C5: 2025 | D5: Q3 | E5: All | F5: All | G5: Anna | H5: Human | I5: -0.2 | J5: =IF(OR(I5="",Settings!$B$6=""),"",IF(I5>Settings!$B$6,"BUY",IF(I5<-Settings!$B$6,"SELL","HOLD"))) -> HOLD | K5: 24 | L5: 45951 | M5: 45951 | N5: 124.135 | O5: 45952 | P5: 114.29 | Q5: =IF(OR(N5="",P5=""),"",ROUND((P5-N5)/N5,4)) -> -0.0793 | R5: =IF(OR(N5="",P5=""),"",IF(Q5>Settings!$B$3/100,"UP",IF(Q5<-Settings!$B$3/100,"DOWN","FLAT"))) -> DOWN | S5: =IF(OR(N5="",P5="",J5=""),"",IF(OR(AND(J5="BUY",R5="UP"),AND(J5="SELL",R5="DOWN"),AND(J5="HOLD",R5="FLAT")),"YES","NO")) -> NO | T5: =IF(J5="","",IF(J5="BUY",1,IF(J5="SELL",-1,0))) -> 0 | U5: =IFERROR(IF(OR(J5="",N5="",P5=""),"",IF(T5=0,0,T5*Q5-Settings!$B$4/10000-IF(T5<0,Settings!$B$5/10000,0))),"") -> 0 | W5: =IF($K5="","",$K5*60) -> 1440 | X5: =IF($A5="","",$A5&"|"&$C5&"|"&$D5) -> Netflix|2025|Q3 | Y5: =IFERROR(IF($X5="","",INDEX(LLM_Data_Entry!$H$3:$H$548,MATCH($X5,INDEX(LLM_Data_Entry!$A$3:$A$548&"|"&LLM_Data_Entry!$C$3:$C$548&"|"&LLM_Data_Entry!$D$3:$D$548,0),0))),"") -> HOLD | Z5: =IFERROR(IF($X5="","",INDEX(LLM_Data_Entry!$R$3:$R$548,MATCH($X5,INDEX(LLM_Data_Entry!$A$3:$A$548&"|"&LLM_Data_Entry!$C$3:$C$548&"|"&LLM_Data_Entry!$D$3:$D$548,0),0))),"") -> NO | AB5: release date + stated time in the document (rater worksheet) | AC5: NFLX | AD5: 2025-10-21 | AE5: 124.135 | AF5: 2025-10-22 | AG5: 114.29 | AH5: -0.079308824 | AI5: DOWN | AJ5: NO | AK5: 0 | AL5: =IF($A5="","",IFERROR(INDEX(Company_List!$G$3:$G$207,MATCH($A5,Company_List!$A$3:$A$207,0)),"unassigned")) -> P2 | AM5: Phase 2/Netflix/2025-Q3/NFLX-2025-Q3-press-release-SEC-EX-99-1.htm | AN5: https://www.sec.gov/Archives/edgar/data/1065280/000106528025000404/ex991_q325.htm | AO5: manifest | AP5: =IF($A5="","",IF(COUNTIFS(LLM_Data_Entry!$A$3:$A$548,$A5)>0,"YES","NO")) -> YES | AQ5: =IF($A5="","",IF(COUNTIFS($A$3:$A5,$A5,$C$3:$C5,$C5,$D$3:$D5,$D5)=1,"YES","NO")) -> YES | AR5: =IF($A5="","",IF(AND($C5&"-"&$D5>=Settings!$B$19,$C5&"-"&$D5<=Settings!$B$20),"IN","OUT")) -> IN | AS5: =IF($A5="","",IF($F5="Financial Results","financials",IF($F5="Outlook/Guidance","guidance",IF($F5="Transcript Q&A","qanda",IF($F5="","unrecorded",IF($E5="All","full",IF($E5="","unrecorded",LOWER($E5)&" only"))))))) -> full | AT5: =IF(AND(OR($J5="BUY",$J5="SELL"),ISNUMBER($U5)),$U5,"") | AU5: =IF(AND(OR($J5="BUY",$J5="SELL"),ISNUMBER($AK5)),$AK5,"") | AV5: =IF(ISNUMBER($AT5),ABS(IF(ISNUMBER($I5),$I5,0)-Settings!$B$24),"") | AW5: =IF(ISNUMBER($AV5),$AV5*$AT5,"") | AX5: =IF(ISNUMBER($AU5),ABS(IF(ISNUMBER($I5),$I5,0)-Settings!$B$24),"") | AY5: FROZEN | AZ5: =IF($A5="","",IFERROR(INDEX(Company_List!$H$3:$H$207,MATCH($A5,Company_List!$A$3:$A$207,0)),"unassigned")) -> Communication Services | BC5: =IF($A5="","",IF(COUNTIFS($A$3:$A5,$A5,$C$3:$C5,$C5,$D$3:$D5,$D5,$G$3:$G5,$G5)=1,1,0)) -> 1 | BG5: no | BK5: =IF(OR($H5<>"Human",$S5="",$J5="",$Y5="",$Z5=""),"",IF(EXACT(UPPER($J5),UPPER($Y5)),1,0)) -> 1 | BL5: assumed - no rater record | BM5: 1 | BN5: not publisher-identified | BO5: not publisher-identified | BP5: no | BQ5: yes | BS5: YES
A6: Netflix | B6: =IF(A6="","",_xlfn.XLOOKUP(A6, Company_List!$A:$A, Company_List!$B:$B, "")) -> NFLX | C6: 2025 | D6: Q4 | E6: All | F6: All | G6: Anna | H6: Human | I6: 0.6 | J6: =IF(OR(I6="",Settings!$B$6=""),"",IF(I6>Settings!$B$6,"BUY",IF(I6<-Settings!$B$6,"SELL","HOLD"))) -> BUY | K6: 25 | L6: 46042 | M6: 46042 | N6: 87.26 | O6: 46043 | P6: 82.52 | Q6: =IF(OR(N6="",P6=""),"",ROUND((P6-N6)/N6,4)) -> -0.0543 | R6: =IF(OR(N6="",P6=""),"",IF(Q6>Settings!$B$3/100,"UP",IF(Q6<-Settings!$B$3/100,"DOWN","FLAT"))) -> DOWN | S6: =IF(OR(N6="",P6="",J6=""),"",IF(OR(AND(J6="BUY",R6="UP"),AND(J6="SELL",R6="DOWN"),AND(J6="HOLD",R6="FLAT")),"YES","NO")) -> NO | T6: =IF(J6="","",IF(J6="BUY",1,IF(J6="SELL",-1,0))) -> 1 | U6: =IFERROR(IF(OR(J6="",N6="",P6=""),"",IF(T6=0,0,T6*Q6-Settings!$B$4/10000-IF(T6<0,Settings!$B$5/10000,0))),"") -> -0.0553 | W6: =IF($K6="","",$K6*60) -> 1500 | X6: =IF($A6="","",$A6&"|"&$C6&"|"&$D6) -> Netflix|2025|Q4 | Y6: =IFERROR(IF($X6="","",INDEX(LLM_Data_Entry!$H$3:$H$548,MATCH($X6,INDEX(LLM_Data_Entry!$A$3:$A$548&"|"&LLM_Data_Entry!$C$3:$C$548&"|"&LLM_Data_Entry!$D$3:$D$548,0),0))),"") -> BUY | Z6: =IFERROR(IF($X6="","",INDEX(LLM_Data_Entry!$R$3:$R$548,MATCH($X6,INDEX(LLM_Data_Entry!$A$3:$A$548&"|"&LLM_Data_Entry!$C$3:$C$548&"|"&LLM_Data_Entry!$D$3:$D$548,0),0))),"") -> NO | AB6: release date + stated time in the document (rater worksheet) | AC6: NFLX | AD6: 2026-01-20 | AE6: 87.26 | AF6: 2026-01-21 | AG6: 82.52 | AH6: -0.054320478 | AI6: DOWN | AJ6: NO | AK6: -0.05532 | AL6: =IF($A6="","",IFERROR(INDEX(Company_List!$G$3:$G$207,MATCH($A6,Company_List!$A$3:$A$207,0)),"unassigned")) -> P2 | AM6: Phase 2/Netflix/2025-Q4/NFLX-2025-Q4-press-release-SEC-EX-99-1.htm | AN6: https://www.sec.gov/Archives/edgar/data/1065280/000106528026000033/ex991_q425.htm | AO6: manifest | AP6: =IF($A6="","",IF(COUNTIFS(LLM_Data_Entry!$A$3:$A$548,$A6)>0,"YES","NO")) -> YES | AQ6: =IF($A6="","",IF(COUNTIFS($A$3:$A6,$A6,$C$3:$C6,$C6,$D$3:$D6,$D6)=1,"YES","NO")) -> YES | AR6: =IF($A6="","",IF(AND($C6&"-"&$D6>=Settings!$B$19,$C6&"-"&$D6<=Settings!$B$20),"IN","OUT")) -> IN | AS6: =IF($A6="","",IF($F6="Financial Results","financials",IF($F6="Outlook/Guidance","guidance",IF($F6="Transcript Q&A","qanda",IF($F6="","unrecorded",IF($E6="All","full",IF($E6="","unrecorded",LOWER($E6)&" only"))))))) -> full | AT6: =IF(AND(OR($J6="BUY",$J6="SELL"),ISNUMBER($U6)),$U6,"") -> -0.0553 | AU6: =IF(AND(OR($J6="BUY",$J6="SELL"),ISNUMBER($AK6)),$AK6,"") -> -0.05532 | AV6: =IF(ISNUMBER($AT6),ABS(IF(ISNUMBER($I6),$I6,0)-Settings!$B$24),"") -> 0.6 | AW6: =IF(ISNUMBER($AV6),$AV6*$AT6,"") -> -0.03318 | AX6: =IF(ISNUMBER($AU6),ABS(IF(ISNUMBER($I6),$I6,0)-Settings!$B$24),"") -> 0.6 | AY6: FROZEN | AZ6: =IF($A6="","",IFERROR(INDEX(Company_List!$H$3:$H$207,MATCH($A6,Company_List!$A$3:$A$207,0)),"unassigned")) -> Communication Services | BC6: =IF($A6="","",IF(COUNTIFS($A$3:$A6,$A6,$C$3:$C6,$C6,$D$3:$D6,$D6,$G$3:$G6,$G6)=1,1,0)) -> 1 | BG6: no | BK6: =IF(OR($H6<>"Human",$S6="",$J6="",$Y6="",$Z6=""),"",IF(EXACT(UPPER($J6),UPPER($Y6)),1,0)) -> 1 | BL6: assumed - no rater record | BM6: 1 | BN6: not publisher-identified | BO6: not publisher-identified | BP6: no | BQ6: yes | BS6: YES
A7: Netflix | B7: =IF(A7="","",_xlfn.XLOOKUP(A7, Company_List!$A:$A, Company_List!$B:$B, "")) -> NFLX | C7: 2026 | D7: Q1 | E7: All | F7: All | G7: Meriem | H7: Human | I7: 0.6 | J7: =IF(OR(I7="",Settings!$B$6=""),"",IF(I7>Settings!$B$6,"BUY",IF(I7<-Settings!$B$6,"SELL","HOLD"))) -> BUY | K7: 35 | L7: 46128 | M7: 46128 | N7: 107.79 | O7: 46129 | P7: 96.37 | Q7: =IF(OR(N7="",P7=""),"",ROUND((P7-N7)/N7,4)) -> -0.1059 | R7: =IF(OR(N7="",P7=""),"",IF(Q7>Settings!$B$3/100,"UP",IF(Q7<-Settings!$B$3/100,"DOWN","FLAT"))) -> DOWN | S7: =IF(OR(N7="",P7="",J7=""),"",IF(OR(AND(J7="BUY",R7="UP"),AND(J7="SELL",R7="DOWN"),AND(J7="HOLD",R7="FLAT")),"YES","NO")) -> NO | T7: =IF(J7="","",IF(J7="BUY",1,IF(J7="SELL",-1,0))) -> 1 | U7: =IFERROR(IF(OR(J7="",N7="",P7=""),"",IF(T7=0,0,T7*Q7-Settings!$B$4/10000-IF(T7<0,Settings!$B$5/10000,0))),"") -> -0.1069 | W7: =IF($K7="","",$K7*60) -> 2100 | X7: =IF($A7="","",$A7&"|"&$C7&"|"&$D7) -> Netflix|2026|Q1 | Y7: =IFERROR(IF($X7="","",INDEX(LLM_Data_Entry!$H$3:$H$548,MATCH($X7,INDEX(LLM_Data_Entry!$A$3:$A$548&"|"&LLM_Data_Entry!$C$3:$C$548&"|"&LLM_Data_Entry!$D$3:$D$548,0),0))),"") -> SELL | Z7: =IFERROR(IF($X7="","",INDEX(LLM_Data_Entry!$R$3:$R$548,MATCH($X7,INDEX(LLM_Data_Entry!$A$3:$A$548&"|"&LLM_Data_Entry!$C$3:$C$548&"|"&LLM_Data_Entry!$D$3:$D$548,0),0))),"") -> YES | AB7: price signal — only this window shows an abnormal move | AC7: NFLX | AD7: 2026-04-16 | AE7: 107.79 | AF7: 2026-04-17 | AG7: 96.37 | AH7: -0.10594673 | AI7: DOWN | AJ7: NO | AK7: -0.106947 | AL7: =IF($A7="","",IFERROR(INDEX(Company_List!$G$3:$G$207,MATCH($A7,Company_List!$A$3:$A$207,0)),"unassigned")) -> P2 | AM7: Phase 2/Netflix/Netflix-Inc-_Earnings-Call_2026-04-16T00_00_00_English-1.pdf | AO7: unique filename match | AP7: =IF($A7="","",IF(COUNTIFS(LLM_Data_Entry!$A$3:$A$548,$A7)>0,"YES","NO")) -> YES | AQ7: =IF($A7="","",IF(COUNTIFS($A$3:$A7,$A7,$C$3:$C7,$C7,$D$3:$D7,$D7)=1,"YES","NO")) -> NO | AR7: =IF($A7="","",IF(AND($C7&"-"&$D7>=Settings!$B$19,$C7&"-"&$D7<=Settings!$B$20),"IN","OUT")) -> IN | AS7: =IF($A7="","",IF($F7="Financial Results","financials",IF($F7="Outlook/Guidance","guidance",IF($F7="Transcript Q&A","qanda",IF($F7="","unrecorded",IF($E7="All","full",IF($E7="","unrecorded",LOWER($E7)&" only"))))))) -> full | AT7: =IF(AND(OR($J7="BUY",$J7="SELL"),ISNUMBER($U7)),$U7,"") -> -0.1069 | AU7: =IF(AND(OR($J7="BUY",$J7="SELL"),ISNUMBER($AK7)),$AK7,"") -> -0.106947 | AV7: =IF(ISNUMBER($AT7),ABS(IF(ISNUMBER($I7),$I7,0)-Settings!$B$24),"") -> 0.6 | AW7: =IF(ISNUMBER($AV7),$AV7*$AT7,"") -> -0.06414 | AX7: =IF(ISNUMBER($AU7),ABS(IF(ISNUMBER($I7),$I7,0)-Settings!$B$24),"") -> 0.6 | AY7: FROZEN | AZ7: =IF($A7="","",IFERROR(INDEX(Company_List!$H$3:$H$207,MATCH($A7,Company_List!$A$3:$A$207,0)),"unassigned")) -> Communication Services | BC7: =IF($A7="","",IF(COUNTIFS($A$3:$A7,$A7,$C$3:$C7,$C7,$D$3:$D7,$D7,$G$3:$G7,$G7)=1,1,0)) -> 1 | BG7: no | BK7: =IF(OR($H7<>"Human",$S7="",$J7="",$Y7="",$Z7=""),"",IF(EXACT(UPPER($J7),UPPER($Y7)),1,0)) -> 0 | BL7: assumed - no rater record | BM7: 1 | BN7: S&P Global Market Intelligence (Capital IQ) | BO7: licensed vendor | BP7: no | BQ7: no | BS7: YES
A8: Netflix | B8: =IF(A8="","",_xlfn.XLOOKUP(A8, Company_List!$A:$A, Company_List!$B:$B, "")) -> NFLX | C8: 2025 | D8: Q2 | E8: All | F8: All | G8: Meriem | H8: Human | I8: 0.7 | J8: =IF(OR(I8="",Settings!$B$6=""),"",IF(I8>Settings!$B$6,"BUY",IF(I8<-Settings!$B$6,"SELL","HOLD"))) -> BUY | K8: 55 | L8: 45855 | M8: 45855 | N8: 127.417 | O8: 45856 | P8: 124.2 | Q8: =IF(OR(N8="",P8=""),"",ROUND((P8-N8)/N8,4)) -> -0.0252 | R8: =IF(OR(N8="",P8=""),"",IF(Q8>Settings!$B$3/100,"UP",IF(Q8<-Settings!$B$3/100,"DOWN","FLAT"))) -> DOWN | S8: =IF(OR(N8="",P8="",J8=""),"",IF(OR(AND(J8="BUY",R8="UP"),AND(J8="SELL",R8="DOWN"),AND(J8="HOLD",R8="FLAT")),"YES","NO")) -> NO | T8: =IF(J8="","",IF(J8="BUY",1,IF(J8="SELL",-1,0))) -> 1 | U8: =IFERROR(IF(OR(J8="",N8="",P8=""),"",IF(T8=0,0,T8*Q8-Settings!$B$4/10000-IF(T8<0,Settings!$B$5/10000,0))),"") -> -0.0262 | W8: =IF($K8="","",$K8*60) -> 3300 | X8: =IF($A8="","",$A8&"|"&$C8&"|"&$D8) -> Netflix|2025|Q2 | Y8: =IFERROR(IF($X8="","",INDEX(LLM_Data_Entry!$H$3:$H$548,MATCH($X8,INDEX(LLM_Data_Entry!$A$3:$A$548&"|"&LLM_Data_Entry!$C$3:$C$548&"|"&LLM_Data_Entry!$D$3:$D$548,0),0))),"") -> HOLD | Z8: =IFERROR(IF($X8="","",INDEX(LLM_Data_Entry!$R$3:$R$548,MATCH($X8,INDEX(LLM_Data_Entry!$A$3:$A$548&"|"&LLM_Data_Entry!$C$3:$C$548&"|"&LLM_Data_Entry!$D$3:$D$548,0),0))),"") -> NO | AB8: price signal — only this window shows an abnormal move | AC8: NFLX | AD8: 2025-07-17 | AE8: 127.417 | AF8: 2025-07-18 | AG8: 124.196 | AH8: -0.025279209 | AI8: DOWN | AJ8: NO | AK8: -0.026279 | AL8: =IF($A8="","",IFERROR(INDEX(Company_List!$G$3:$G$207,MATCH($A8,Company_List!$A$3:$A$207,0)),"unassigned")) -> P2 | AM8: Phase 2/Netflix/2025-Q2/NFLX-2025-Q2-press-release-SEC-EX-99-1.htm | AN8: https://www.sec.gov/Archives/edgar/data/1065280/000106528025000322/ex991_q225.htm | AO8: manifest | AP8: =IF($A8="","",IF(COUNTIFS(LLM_Data_Entry!$A$3:$A$548,$A8)>0,"YES","NO")) -> YES | AQ8: =IF($A8="","",IF(COUNTIFS($A$3:$A8,$A8,$C$3:$C8,$C8,$D$3:$D8,$D8)=1,"YES","NO")) -> NO | AR8: =IF($A8="","",IF(AND($C8&"-"&$D8>=Settings!$B$19,$C8&"-"&$D8<=Settings!$B$20),"IN","OUT")) -> IN | AS8: =IF($A8="","",IF($F8="Financial Results","financials",IF($F8="Outlook/Guidance","guidance",IF($F8="Transcript Q&A","qanda",IF($F8="","unrecorded",IF($E8="All","full",IF($E8="","unrecorded",LOWER($E8)&" only"))))))) -> full | AT8: =IF(AND(OR($J8="BUY",$J8="SELL"),ISNUMBER($U8)),$U8,"") -> -0.0262 | AU8: =IF(AND(OR($J8="BUY",$J8="SELL"),ISNUMBER($AK8)),$AK8,"") -> -0.026279 | AV8: =IF(ISNUMBER($AT8),ABS(IF(ISNUMBER($I8),$I8,0)-Settings!$B$24),"") -> 0.7 | AW8: =IF(ISNUMBER($AV8),$AV8*$AT8,"") -> -0.01834 | AX8: =IF(ISNUMBER($AU8),ABS(IF(ISNUMBER($I8),$I8,0)-Settings!$B$24),"") -> 0.7 | AY8: FROZEN | AZ8: =IF($A8="","",IFERROR(INDEX(Company_List!$H$3:$H$207,MATCH($A8,Company_List!$A$3:$A$207,0)),"unassigned")) -> Communication Services | BC8: =IF($A8="","",IF(COUNTIFS($A$3:$A8,$A8,$C$3:$C8,$C8,$D$3:$D8,$D8,$G$3:$G8,$G8)=1,1,0)) -> 1 | BG8: no | BK8: =IF(OR($H8<>"Human",$S8="",$J8="",$Y8="",$Z8=""),"",IF(EXACT(UPPER($J8),UPPER($Y8)),1,0)) -> 0 | BL8: assumed - no rater record | BM8: 1 | BN8: not publisher-identified | BO8: not publisher-identified | BP8: no | BQ8: yes | BS8: YES
A9: Netflix | B9: =IF(A9="","",_xlfn.XLOOKUP(A9, Company_List!$A:$A, Company_List!$B:$B, "")) -> NFLX | C9: 2025 | D9: Q3 | E9: All | F9: All | G9: Meriem | H9: Human | I9: -0.5 | J9: =IF(OR(I9="",Settings!$B$6=""),"",IF(I9>Settings!$B$6,"BUY",IF(I9<-Settings!$B$6,"SELL","HOLD"))) -> SELL | K9: 38 | L9: 45951 | M9: 45951 | N9: 124.135 | O9: 45952 | P9: 114.29 | Q9: =IF(OR(N9="",P9=""),"",ROUND((P9-N9)/N9,4)) -> -0.0793 | R9: =IF(OR(N9="",P9=""),"",IF(Q9>Settings!$B$3/100,"UP",IF(Q9<-Settings!$B$3/100,"DOWN","FLAT"))) -> DOWN | S9: =IF(OR(N9="",P9="",J9=""),"",IF(OR(AND(J9="BUY",R9="UP"),AND(J9="SELL",R9="DOWN"),AND(J9="HOLD",R9="FLAT")),"YES","NO")) -> YES | T9: =IF(J9="","",IF(J9="BUY",1,IF(J9="SELL",-1,0))) -> -1 | U9: =IFERROR(IF(OR(J9="",N9="",P9=""),"",IF(T9=0,0,T9*Q9-Settings!$B$4/10000-IF(T9<0,Settings!$B$5/10000,0))),"") -> 0.0783 | W9: =IF($K9="","",$K9*60) -> 2280 | X9: =IF($A9="","",$A9&"|"&$C9&"|"&$D9) -> Netflix|2025|Q3 | Y9: =IFERROR(IF($X9="","",INDEX(LLM_Data_Entry!$H$3:$H$548,MATCH($X9,INDEX(LLM_Data_Entry!$A$3:$A$548&"|"&LLM_Data_Entry!$C$3:$C$548&"|"&LLM_Data_Entry!$D$3:$D$548,0),0))),"") -> HOLD | Z9: =IFERROR(IF($X9="","",INDEX(LLM_Data_Entry!$R$3:$R$548,MATCH($X9,INDEX(LLM_Data_Entry!$A$3:$A$548&"|"&LLM_Data_Entry!$C$3:$C$548&"|"&LLM_Data_Entry!$D$3:$D$548,0),0))),"") -> NO | AB9: release date + stated time in the document (rater worksheet) | AC9: NFLX | AD9: 2025-10-21 | AE9: 124.135 | AF9: 2025-10-22 | AG9: 114.29 | AH9: -0.079308824 | AI9: DOWN | AJ9: YES | AK9: 0.078309 | AL9: =IF($A9="","",IFERROR(INDEX(Company_List!$G$3:$G$207,MATCH($A9,Company_List!$A$3:$A$207,0)),"unassigned")) -> P2 | AM9: Phase 2/Netflix/2025-Q3/NFLX-2025-Q3-press-release-SEC-EX-99-1.htm | AN9: https://www.sec.gov/Archives/edgar/data/1065280/000106528025000404/ex991_q325.htm | AO9: manifest | AP9: =IF($A9="","",IF(COUNTIFS(LLM_Data_Entry!$A$3:$A$548,$A9)>0,"YES","NO")) -> YES | AQ9: =IF($A9="","",IF(COUNTIFS($A$3:$A9,$A9,$C$3:$C9,$C9,$D$3:$D9,$D9)=1,"YES","NO")) -> NO | AR9: =IF($A9="","",IF(AND($C9&"-"&$D9>=Settings!$B$19,$C9&"-"&$D9<=Settings!$B$20),"IN","OUT")) -> IN | AS9: =IF($A9="","",IF($F9="Financial Results","financials",IF($F9="Outlook/Guidance","guidance",IF($F9="Transcript Q&A","qanda",IF($F9="","unrecorded",IF($E9="All","full",IF($E9="","unrecorded",LOWER($E9)&" only"))))))) -> full | AT9: =IF(AND(OR($J9="BUY",$J9="SELL"),ISNUMBER($U9)),$U9,"") -> 0.0783 | AU9: =IF(AND(OR($J9="BUY",$J9="SELL"),ISNUMBER($AK9)),$AK9,"") -> 0.078309 | AV9: =IF(ISNUMBER($AT9),ABS(IF(ISNUMBER($I9),$I9,0)-Settings!$B$24),"") -> 0.5 | AW9: =IF(ISNUMBER($AV9),$AV9*$AT9,"") -> 0.03915 | AX9: =IF(ISNUMBER($AU9),ABS(IF(ISNUMBER($I9),$I9,0)-Settings!$B$24),"") -> 0.5 | AY9: FROZEN | AZ9: =IF($A9="","",IFERROR(INDEX(Company_List!$H$3:$H$207,MATCH($A9,Company_List!$A$3:$A$207,0)),"unassigned")) -> Communication Services | BC9: =IF($A9="","",IF(COUNTIFS($A$3:$A9,$A9,$C$3:$C9,$C9,$D$3:$D9,$D9,$G$3:$G9,$G9)=1,1,0)) -> 1 | BG9: no | BK9: =IF(OR($H9<>"Human",$S9="",$J9="",$Y9="",$Z9=""),"",IF(EXACT(UPPER($J9),UPPER($Y9)),1,0)) -> 0 | BL9: assumed - no rater record | BM9: 1 | BN9: not publisher-identified | BO9: not publisher-identified | BP9: no | BQ9: yes | BS9: YES
A10: Netflix | B10: =IF(A10="","",_xlfn.XLOOKUP(A10, Company_List!$A:$A, Company_List!$B:$B, "")) -> NFLX | C10: 2025 | D10: Q4 | E10: All | F10: All | G10: Meriem | H10: Human | I10: 0.2 | J10: =IF(OR(I10="",Settings!$B$6=""),"",IF(I10>Settings!$B$6,"BUY",IF(I10<-Settings!$B$6,"SELL","HOLD"))) -> HOLD | K10: 40 | L10: 46042 | M10: 46042 | N10: 87.26 | O10: 46043 | P10: 82.52 | Q10: =IF(OR(N10="",P10=""),"",ROUND((P10-N10)/N10,4)) -> -0.0543 | R10: =IF(OR(N10="",P10=""),"",IF(Q10>Settings!$B$3/100,"UP",IF(Q10<-Settings!$B$3/100,"DOWN","FLAT"))) -> DOWN | S10: =IF(OR(N10="",P10="",J10=""),"",IF(OR(AND(J10="BUY",R10="UP"),AND(J10="SELL",R10="DOWN"),AND(J10="HOLD",R10="FLAT")),"YES","NO")) -> NO | T10: =IF(J10="","",IF(J10="BUY",1,IF(J10="SELL",-1,0))) -> 0 | U10: =IFERROR(IF(OR(J10="",N10="",P10=""),"",IF(T10=0,0,T10*Q10-Settings!$B$4/10000-IF(T10<0,Settings!$B$5/10000,0))),"") -> 0 | W10: =IF($K10="","",$K10*60) -> 2400 | X10: =IF($A10="","",$A10&"|"&$C10&"|"&$D10) -> Netflix|2025|Q4 | Y10: =IFERROR(IF($X10="","",INDEX(LLM_Data_Entry!$H$3:$H$548,MATCH($X10,INDEX(LLM_Data_Entry!$A$3:$A$548&"|"&LLM_Data_Entry!$C$3:$C$548&"|"&LLM_Data_Entry!$D$3:$D$548,0),0))),"") -> BUY | Z10: =IFERROR(IF($X10="","",INDEX(LLM_Data_Entry!$R$3:$R$548,MATCH($X10,INDEX(LLM_Data_Entry!$A$3:$A$548&"|"&LLM_Data_Entry!$C$3:$C$548&"|"&LLM_Data_Entry!$D$3:$D$548,0),0))),"") -> NO | AB10: release date + stated time in the document (rater worksheet) | AC10: NFLX | AD10: 2026-01-20 | AE10: 87.26 | AF10: 2026-01-21 | AG10: 82.52 | AH10: -0.054320478 | AI10: DOWN | AJ10: NO | AK10: 0 | AL10: =IF($A10="","",IFERROR(INDEX(Company_List!$G$3:$G$207,MATCH($A10,Company_List!$A$3:$A$207,0)),"unassigned")) -> P2 | AM10: Phase 2/Netflix/2025-Q4/NFLX-2025-Q4-press-release-SEC-EX-99-1.htm | AN10: https://www.sec.gov/Archives/edgar/data/1065280/000106528026000033/ex991_q425.htm | AO10: manifest | AP10: =IF($A10="","",IF(COUNTIFS(LLM_Data_Entry!$A$3:$A$548,$A10)>0,"YES","NO")) -> YES | AQ10: =IF($A10="","",IF(COUNTIFS($A$3:$A10,$A10,$C$3:$C10,$C10,$D$3:$D10,$D10)=1,"YES","NO")) -> NO | AR10: =IF($A10="","",IF(AND($C10&"-"&$D10>=Settings!$B$19,$C10&"-"&$D10<=Settings!$B$20),"IN","OUT")) -> IN | AS10: =IF($A10="","",IF($F10="Financial Results","financials",IF($F10="Outlook/Guidance","guidance",IF($F10="Transcript Q&A","qanda",IF($F10="","unrecorded",IF($E10="All","full",IF($E10="","unrecorded",LOWER($E10)&" only"))))))) -> full | AT10: =IF(AND(OR($J10="BUY",$J10="SELL"),ISNUMBER($U10)),$U10,"") | AU10: =IF(AND(OR($J10="BUY",$J10="SELL"),ISNUMBER($AK10)),$AK10,"") | AV10: =IF(ISNUMBER($AT10),ABS(IF(ISNUMBER($I10),$I10,0)-Settings!$B$24),"") | AW10: =IF(ISNUMBER($AV10),$AV10*$AT10,"") | AX10: =IF(ISNUMBER($AU10),ABS(IF(ISNUMBER($I10),$I10,0)-Settings!$B$24),"") | AY10: FROZEN | AZ10: =IF($A10="","",IFERROR(INDEX(Company_List!$H$3:$H$207,MATCH($A10,Company_List!$A$3:$A$207,0)),"unassigned")) -> Communication Services | BC10: =IF($A10="","",IF(COUNTIFS($A$3:$A10,$A10,$C$3:$C10,$C10,$D$3:$D10,$D10,$G$3:$G10,$G10)=1,1,0)) -> 1 | BG10: no | BK10: =IF(OR($H10<>"Human",$S10="",$J10="",$Y10="",$Z10=""),"",IF(EXACT(UPPER($J10),UPPER($Y10)),1,0)) -> 0 | BL10: assumed - no rater record | BM10: 1 | BN10: not publisher-identified | BO10: not publisher-identified | BP10: no | BQ10: yes | BS10: YES
A11: Netflix | B11: =IF(A11="","",_xlfn.XLOOKUP(A11, Company_List!$A:$A, Company_List!$B:$B, "")) -> NFLX | C11: 2025 | D11: Q1 | E11: All | F11: All | G11: Dragos | H11: Human | I11: 0.65 | J11: =IF(OR(I11="",Settings!$B$6=""),"",IF(I11>Settings!$B$6,"BUY",IF(I11<-Settings!$B$6,"SELL","HOLD"))) -> BUY | K11: 42 | L11: 45764 | M11: 45764 | N11: 97.303 | O11: 45765 | P11: 98.44 | Q11: =IF(OR(N11="",P11=""),"",ROUND((P11-N11)/N11,4)) -> 0.0117 | R11: =IF(OR(N11="",P11=""),"",IF(Q11>Settings!$B$3/100,"UP",IF(Q11<-Settings!$B$3/100,"DOWN","FLAT"))) -> FLAT | S11: =IF(OR(N11="",P11="",J11=""),"",IF(OR(AND(J11="BUY",R11="UP"),AND(J11="SELL",R11="DOWN"),AND(J11="HOLD",R11="FLAT")),"YES","NO")) -> NO | T11: =IF(J11="","",IF(J11="BUY",1,IF(J11="SELL",-1,0))) -> 1 | U11: =IFERROR(IF(OR(J11="",N11="",P11=""),"",IF(T11=0,0,T11*Q11-Settings!$B$4/10000-IF(T11<0,Settings!$B$5/10000,0))),"") -> 0.0107 | V11: CORRECTION: replaces my existing row currently mislabeled '2025 Q4' (it holds this Q1 data). Clean beat, margin expansion, guide tracking above midpoint; valuation full. Sealed 29 Jun, ±1% band (correct under my sealed band). | W11: =IF($K11="","",$K11*60) -> 2520 | X11: =IF($A11="","",$A11&"|"&$C11&"|"&$D11) -> Netflix|2025|Q1 | Y11: =IFERROR(IF($X11="","",INDEX(LLM_Data_Entry!$H$3:$H$548,MATCH($X11,INDEX(LLM_Data_Entry!$A$3:$A$548&"|"&LLM_Data_Entry!$C$3:$C$548&"|"&LLM_Data_Entry!$D$3:$D$548,0),0))),"") -> SELL | Z11: =IFERROR(IF($X11="","",INDEX(LLM_Data_Entry!$R$3:$R$548,MATCH($X11,INDEX(LLM_Data_Entry!$A$3:$A$548&"|"&LLM_Data_Entry!$C$3:$C$548&"|"&LLM_Data_Entry!$D$3:$D$548,0),0))),"") -> NO | AB11: release date + stated time in the document (rater worksheet) | AC11: NFLX | AD11: 2025-04-17 | AE11: 97.303 | AF11: 2025-04-21 | AG11: 98.44 | AH11: 0.011685159 | AI11: FLAT | AJ11: NO | AK11: 0.010685 | AL11: =IF($A11="","",IFERROR(INDEX(Company_List!$G$3:$G$207,MATCH($A11,Company_List!$A$3:$A$207,0)),"unassigned")) -> P2 | AM11: Phase 2/Netflix/2025-Q1/NFLX-2025-Q1-press-release-SEC-EX-99-1.htm | AN11: https://www.sec.gov/Archives/edgar/data/1065280/000106528025000175/ex991_q125.htm | AO11: manifest | AP11: =IF($A11="","",IF(COUNTIFS(LLM_Data_Entry!$A$3:$A$548,$A11)>0,"YES","NO")) -> YES | AQ11: =IF($A11="","",IF(COUNTIFS($A$3:$A11,$A11,$C$3:$C11,$C11,$D$3:$D11,$D11)=1,"YES","NO")) -> YES | AR11: =IF($A11="","",IF(AND($C11&"-"&$D11>=Settings!$B$19,$C11&"-"&$D11<=Settings!$B$20),"IN","OUT")) -> IN | AS11: =IF($A11="","",IF($F11="Financial Results","financials",IF($F11="Outlook/Guidance","guidance",IF($F11="Transcript Q&A","qanda",IF($F11="","unrecorded",IF($E11="All","full",IF($E11="","unrecorded",LOWER($E11)&" only"))))))) -> full | AT11: =IF(AND(OR($J11="BUY",$J11="SELL"),ISNUMBER($U11)),$U11,"") -> 0.0107 | AU11: =IF(AND(OR($J11="BUY",$J11="SELL"),ISNUMBER($AK11)),$AK11,"") -> 0.010685 | AV11: =IF(ISNUMBER($AT11),ABS(IF(ISNUMBER($I11),$I11,0)-Settings!$B$24),"") -> 0.65 | AW11: =IF(ISNUMBER($AV11),$AV11*$AT11,"") -> 0.006955 | AX11: =IF(ISNUMBER($AU11),ABS(IF(ISNUMBER($I11),$I11,0)-Settings!$B$24),"") -> 0.65 | AY11: FROZEN | AZ11: =IF($A11="","",IFERROR(INDEX(Company_List!$H$3:$H$207,MATCH($A11,Company_List!$A$3:$A$207,0)),"unassigned")) -> Communication Services | BC11: =IF($A11="","",IF(COUNTIFS($A$3:$A11,$A11,$C$3:$C11,$C11,$D$3:$D11,$D11,$G$3:$G11,$G11)=1,1,0)) -> 1 | BG11: no | BK11: =IF(OR($H11<>"Human",$S11="",$J11="",$Y11="",$Z11=""),"",IF(EXACT(UPPER($J11),UPPER($Y11)),1,0)) -> 0 | BL11: assumed - no rater record | BM11: 1 | BN11: not publisher-identified | BO11: not publisher-identified | BP11: no | BQ11: yes | BS11: YES
A12: Netflix | B12: =IF(A12="","",_xlfn.XLOOKUP(A12, Company_List!$A:$A, Company_List!$B:$B, "")) -> NFLX | C12: 2025 | D12: Q2 | E12: All | F12: All | G12: Dragos | H12: Human | I12: 0.55 | J12: =IF(OR(I12="",Settings!$B$6=""),"",IF(I12>Settings!$B$6,"BUY",IF(I12<-Settings!$B$6,"SELL","HOLD"))) -> BUY | K12: 38 | L12: 45855 | M12: 45855 | N12: 127.417 | O12: 45856 | P12: 124.2 | Q12: =IF(OR(N12="",P12=""),"",ROUND((P12-N12)/N12,4)) -> -0.0252 | R12: =IF(OR(N12="",P12=""),"",IF(Q12>Settings!$B$3/100,"UP",IF(Q12<-Settings!$B$3/100,"DOWN","FLAT"))) -> DOWN | S12: =IF(OR(N12="",P12="",J12=""),"",IF(OR(AND(J12="BUY",R12="UP"),AND(J12="SELL",R12="DOWN"),AND(J12="HOLD",R12="FLAT")),"YES","NO")) -> NO | T12: =IF(J12="","",IF(J12="BUY",1,IF(J12="SELL",-1,0))) -> 1 | U12: =IFERROR(IF(OR(J12="",N12="",P12=""),"",IF(T12=0,0,T12*Q12-Settings!$B$4/10000-IF(T12<0,Settings!$B$5/10000,0))),"") -> -0.0262 | V12: Beat-and-raise but raise mostly FX; H2 margin step-down guided; stock priced for perfection. NOTE: my sealed next-day open is 124.20 (-2.53%); sheet's existing Q2 rows show 129.92 - flag to Anna/Ben. | W12: =IF($K12="","",$K12*60) -> 2280 | X12: =IF($A12="","",$A12&"|"&$C12&"|"&$D12) -> Netflix|2025|Q2 | Y12: =IFERROR(IF($X12="","",INDEX(LLM_Data_Entry!$H$3:$H$548,MATCH($X12,INDEX(LLM_Data_Entry!$A$3:$A$548&"|"&LLM_Data_Entry!$C$3:$C$548&"|"&LLM_Data_Entry!$D$3:$D$548,0),0))),"") -> HOLD | Z12: =IFERROR(IF($X12="","",INDEX(LLM_Data_Entry!$R$3:$R$548,MATCH($X12,INDEX(LLM_Data_Entry!$A$3:$A$548&"|"&LLM_Data_Entry!$C$3:$C$548&"|"&LLM_Data_Entry!$D$3:$D$548,0),0))),"") -> NO | AB12: price signal — only this window shows an abnormal move | AC12: NFLX | AD12: 2025-07-17 | AE12: 127.417 | AF12: 2025-07-18 | AG12: 124.196 | AH12: -0.025279209 | AI12: DOWN | AJ12: NO | AK12: -0.026279 | AL12: =IF($A12="","",IFERROR(INDEX(Company_List!$G$3:$G$207,MATCH($A12,Company_List!$A$3:$A$207,0)),"unassigned")) -> P2 | AM12: Phase 2/Netflix/2025-Q2/NFLX-2025-Q2-press-release-SEC-EX-99-1.htm | AN12: https://www.sec.gov/Archives/edgar/data/1065280/000106528025000322/ex991_q225.htm | AO12: manifest | AP12: =IF($A12="","",IF(COUNTIFS(LLM_Data_Entry!$A$3:$A$548,$A12)>0,"YES","NO")) -> YES | AQ12: =IF($A12="","",IF(COUNTIFS($A$3:$A12,$A12,$C$3:$C12,$C12,$D$3:$D12,$D12)=1,"YES","NO")) -> NO | AR12: =IF($A12="","",IF(AND($C12&"-"&$D12>=Settings!$B$19,$C12&"-"&$D12<=Settings!$B$20),"IN","OUT")) -> IN | AS12: =IF($A12="","",IF($F12="Financial Results","financials",IF($F12="Outlook/Guidance","guidance",IF($F12="Transcript Q&A","qanda",IF($F12="","unrecorded",IF($E12="All","full",IF($E12="","unrecorded",LOWER($E12)&" only"))))))) -> full | AT12: =IF(AND(OR($J12="BUY",$J12="SELL"),ISNUMBER($U12)),$U12,"") -> -0.0262 | AU12: =IF(AND(OR($J12="BUY",$J12="SELL"),ISNUMBER($AK12)),$AK12,"") -> -0.026279 | AV12: =IF(ISNUMBER($AT12),ABS(IF(ISNUMBER($I12),$I12,0)-Settings!$B$24),"") -> 0.55 | AW12: =IF(ISNUMBER($AV12),$AV12*$AT12,"") -> -0.01441 | AX12: =IF(ISNUMBER($AU12),ABS(IF(ISNUMBER($I12),$I12,0)-Settings!$B$24),"") -> 0.55 | AY12: FROZEN | AZ12: =IF($A12="","",IFERROR(INDEX(Company_List!$H$3:$H$207,MATCH($A12,Company_List!$A$3:$A$207,0)),"unassigned")) -> Communication Services | BC12: =IF($A12="","",IF(COUNTIFS($A$3:$A12,$A12,$C$3:$C12,$C12,$D$3:$D12,$D12,$G$3:$G12,$G12)=1,1,0)) -> 1 | BG12: no | BK12: =IF(OR($H12<>"Human",$S12="",$J12="",$Y12="",$Z12=""),"",IF(EXACT(UPPER($J12),UPPER($Y12)),1,0)) -> 0 | BL12: attested - the note states the score was sealed | BM12: 1 | BN12: not publisher-identified | BO12: not publisher-identified | BP12: no | BQ12: yes | BS12: YES
A13: Netflix | B13: =IF(A13="","",_xlfn.XLOOKUP(A13, Company_List!$A:$A, Company_List!$B:$B, "")) -> NFLX | C13: 2025 | D13: Q3 | E13: All | F13: All | G13: Dragos | H13: Human | I13: 0.45 | J13: =IF(OR(I13="",Settings!$B$6=""),"",IF(I13>Settings!$B$6,"BUY",IF(I13<-Settings!$B$6,"SELL","HOLD"))) -> BUY | K13: 55 | L13: 45951 | M13: 45951 | N13: 124.135 | O13: 45952 | P13: 114.29 | Q13: =IF(OR(N13="",P13=""),"",ROUND((P13-N13)/N13,4)) -> -0.0793 | R13: =IF(OR(N13="",P13=""),"",IF(Q13>Settings!$B$3/100,"UP",IF(Q13<-Settings!$B$3/100,"DOWN","FLAT"))) -> DOWN | S13: =IF(OR(N13="",P13="",J13=""),"",IF(OR(AND(J13="BUY",R13="UP"),AND(J13="SELL",R13="DOWN"),AND(J13="HOLD",R13="FLAT")),"YES","NO")) -> NO | T13: =IF(J13="","",IF(J13="BUY",1,IF(J13="SELL",-1,0))) -> 1 | U13: =IFERROR(IF(OR(J13="",N13="",P13=""),"",IF(T13=0,0,T13*Q13-Settings!$B$4/10000-IF(T13<0,Settings!$B$5/10000,0))),"") -> -0.0803 | V13: Headline EPS miss (Brazil CIDE tax charge), guidance vacuum until January, rich valuation - sold first, reasoned later. | W13: =IF($K13="","",$K13*60) -> 3300 | X13: =IF($A13="","",$A13&"|"&$C13&"|"&$D13) -> Netflix|2025|Q3 | Y13: =IFERROR(IF($X13="","",INDEX(LLM_Data_Entry!$H$3:$H$548,MATCH($X13,INDEX(LLM_Data_Entry!$A$3:$A$548&"|"&LLM_Data_Entry!$C$3:$C$548&"|"&LLM_Data_Entry!$D$3:$D$548,0),0))),"") -> HOLD | Z13: =IFERROR(IF($X13="","",INDEX(LLM_Data_Entry!$R$3:$R$548,MATCH($X13,INDEX(LLM_Data_Entry!$A$3:$A$548&"|"&LLM_Data_Entry!$C$3:$C$548&"|"&LLM_Data_Entry!$D$3:$D$548,0),0))),"") -> NO | AB13: release date + stated time in the document (rater worksheet) | AC13: NFLX | AD13: 2025-10-21 | AE13: 124.135 | AF13: 2025-10-22 | AG13: 114.29 | AH13: -0.079308824 | AI13: DOWN | AJ13: NO | AK13: -0.080309 | AL13: =IF($A13="","",IFERROR(INDEX(Company_List!$G$3:$G$207,MATCH($A13,Company_List!$A$3:$A$207,0)),"unassigned")) -> P2 | AM13: Phase 2/Netflix/2025-Q3/NFLX-2025-Q3-press-release-SEC-EX-99-1.htm | AN13: https://www.sec.gov/Archives/edgar/data/1065280/000106528025000404/ex991_q325.htm | AO13: manifest | AP13: =IF($A13="","",IF(COUNTIFS(LLM_Data_Entry!$A$3:$A$548,$A13)>0,"YES","NO")) -> YES | AQ13: =IF($A13="","",IF(COUNTIFS($A$3:$A13,$A13,$C$3:$C13,$C13,$D$3:$D13,$D13)=1,"YES","NO")) -> NO | AR13: =IF($A13="","",IF(AND($C13&"-"&$D13>=Settings!$B$19,$C13&"-"&$D13<=Settings!$B$20),"IN","OUT")) -> IN | AS13: =IF($A13="","",IF($F13="Financial Results","financials",IF($F13="Outlook/Guidance","guidance",IF($F13="Transcript Q&A","qanda",IF($F13="","unrecorded",IF($E13="All","full",IF($E13="","unrecorded",LOWER($E13)&" only"))))))) -> full | AT13: =IF(AND(OR($J13="BUY",$J13="SELL"),ISNUMBER($U13)),$U13,"") -> -0.0803 | AU13: =IF(AND(OR($J13="BUY",$J13="SELL"),ISNUMBER($AK13)),$AK13,"") -> -0.080309 | AV13: =IF(ISNUMBER($AT13),ABS(IF(ISNUMBER($I13),$I13,0)-Settings!$B$24),"") -> 0.45 | AW13: =IF(ISNUMBER($AV13),$AV13*$AT13,"") -> -0.036135 | AX13: =IF(ISNUMBER($AU13),ABS(IF(ISNUMBER($I13),$I13,0)-Settings!$B$24),"") -> 0.45 | AY13: FROZEN | AZ13: =IF($A13="","",IFERROR(INDEX(Company_List!$H$3:$H$207,MATCH($A13,Company_List!$A$3:$A$207,0)),"unassigned")) -> Communication Services | BC13: =IF($A13="","",IF(COUNTIFS($A$3:$A13,$A13,$C$3:$C13,$C13,$D$3:$D13,$D13,$G$3:$G13,$G13)=1,1,0)) -> 1 | BG13: no | BK13: =IF(OR($H13<>"Human",$S13="",$J13="",$Y13="",$Z13=""),"",IF(EXACT(UPPER($J13),UPPER($Y13)),1,0)) -> 0 | BL13: assumed - no rater record | BM13: 1 | BN13: not publisher-identified | BO13: not publisher-identified | BP13: no | BQ13: yes | BS13: YES
A14: Netflix | B14: =IF(A14="","",_xlfn.XLOOKUP(A14, Company_List!$A:$A, Company_List!$B:$B, "")) -> NFLX | C14: 2025 | D14: Q4 | E14: All | F14: All | G14: Dragos | H14: Human | I14: 0.6 | J14: =IF(OR(I14="",Settings!$B$6=""),"",IF(I14>Settings!$B$6,"BUY",IF(I14<-Settings!$B$6,"SELL","HOLD"))) -> BUY | K14: 45 | L14: 46042 | M14: 46042 | N14: 87.26 | O14: 46043 | P14: 82.52 | Q14: =IF(OR(N14="",P14=""),"",ROUND((P14-N14)/N14,4)) -> -0.0543 | R14: =IF(OR(N14="",P14=""),"",IF(Q14>Settings!$B$3/100,"UP",IF(Q14<-Settings!$B$3/100,"DOWN","FLAT"))) -> DOWN | S14: =IF(OR(N14="",P14="",J14=""),"",IF(OR(AND(J14="BUY",R14="UP"),AND(J14="SELL",R14="DOWN"),AND(J14="HOLD",R14="FLAT")),"YES","NO")) -> NO | T14: =IF(J14="","",IF(J14="BUY",1,IF(J14="SELL",-1,0))) -> 1 | U14: =IFERROR(IF(OR(J14="",N14="",P14=""),"",IF(T14=0,0,T14*Q14-Settings!$B$4/10000-IF(T14<0,Settings!$B$5/10000,0))),"") -> -0.0553 | V14: Clean beat + $51B 2026 guide, but growth decelerating 16%->14% and WBD deal overhang; I under-weighted the forward risk. | W14: =IF($K14="","",$K14*60) -> 2700 | X14: =IF($A14="","",$A14&"|"&$C14&"|"&$D14) -> Netflix|2025|Q4 | Y14: =IFERROR(IF($X14="","",INDEX(LLM_Data_Entry!$H$3:$H$548,MATCH($X14,INDEX(LLM_Data_Entry!$A$3:$A$548&"|"&LLM_Data_Entry!$C$3:$C$548&"|"&LLM_Data_Entry!$D$3:$D$548,0),0))),"") -> BUY | Z14: =IFERROR(IF($X14="","",INDEX(LLM_Data_Entry!$R$3:$R$548,MATCH($X14,INDEX(LLM_Data_Entry!$A$3:$A$548&"|"&LLM_Data_Entry!$C$3:$C$548&"|"&LLM_Data_Entry!$D$3:$D$548,0),0))),"") -> NO | AB14: release date + stated time in the document (rater worksheet) | AC14: NFLX | AD14: 2026-01-20 | AE14: 87.26 | AF14: 2026-01-21 | AG14: 82.52 | AH14: -0.054320478 | AI14: DOWN | AJ14: NO | AK14: -0.05532 | AL14: =IF($A14="","",IFERROR(INDEX(Company_List!$G$3:$G$207,MATCH($A14,Company_List!$A$3:$A$207,0)),"unassigned")) -> P2 | AM14: Phase 2/Netflix/2025-Q4/NFLX-2025-Q4-press-release-SEC-EX-99-1.htm | AN14: https://www.sec.gov/Archives/edgar/data/1065280/000106528026000033/ex991_q425.htm | AO14: manifest | AP14: =IF($A14="","",IF(COUNTIFS(LLM_Data_Entry!$A$3:$A$548,$A14)>0,"YES","NO")) -> YES | AQ14: =IF($A14="","",IF(COUNTIFS($A$3:$A14,$A14,$C$3:$C14,$C14,$D$3:$D14,$D14)=1,"YES","NO")) -> NO | AR14: =IF($A14="","",IF(AND($C14&"-"&$D14>=Settings!$B$19,$C14&"-"&$D14<=Settings!$B$20),"IN","OUT")) -> IN | AS14: =IF($A14="","",IF($F14="Financial Results","financials",IF($F14="Outlook/Guidance","guidance",IF($F14="Transcript Q&A","qanda",IF($F14="","unrecorded",IF($E14="All","full",IF($E14="","unrecorded",LOWER($E14)&" only"))))))) -> full | AT14: =IF(AND(OR($J14="BUY",$J14="SELL"),ISNUMBER($U14)),$U14,"") -> -0.0553 | AU14: =IF(AND(OR($J14="BUY",$J14="SELL"),ISNUMBER($AK14)),$AK14,"") -> -0.05532 | AV14: =IF(ISNUMBER($AT14),ABS(IF(ISNUMBER($I14),$I14,0)-Settings!$B$24),"") -> 0.6 | AW14: =IF(ISNUMBER($AV14),$AV14*$AT14,"") -> -0.03318 | AX14: =IF(ISNUMBER($AU14),ABS(IF(ISNUMBER($I14),$I14,0)-Settings!$B$24),"") -> 0.6 | AY14: FROZEN | AZ14: =IF($A14="","",IFERROR(INDEX(Company_List!$H$3:$H$207,MATCH($A14,Company_List!$A$3:$A$207,0)),"unassigned")) -> Communication Services | BC14: =IF($A14="","",IF(COUNTIFS($A$3:$A14,$A14,$C$3:$C14,$C14,$D$3:$D14,$D14,$G$3:$G14,$G14)=1,1,0)) -> 1 | BG14: no | BK14: =IF(OR($H14<>"Human",$S14="",$J14="",$Y14="",$Z14=""),"",IF(EXACT(UPPER($J14),UPPER($Y14)),1,0)) -> 1 | BL14: assumed - no rater record | BM14: 1 | BN14: not publisher-identified | BO14: not publisher-identified | BP14: no | BQ14: yes | BS14: YES
A15: Nvidia | B15: =IF(A15="","",_xlfn.XLOOKUP(A15, Company_List!$A:$A, Company_List!$B:$B, "")) -> NVDA | C15: 2025 | D15: Q1 | E15: All | F15: All | G15: Dragos | H15: Human | I15: 0.55 | J15: =IF(OR(I15="",Settings!$B$6=""),"",IF(I15>Settings!$B$6,"BUY",IF(I15<-Settings!$B$6,"SELL","HOLD"))) -> BUY | K15: 50 | L15: 45714 | M15: 45714 | N15: 131.28 | O15: 45715 | P15: 135 | Q15: =IF(OR(N15="",P15=""),"",ROUND((P15-N15)/N15,4)) -> 0.0283 | R15: =IF(OR(N15="",P15=""),"",IF(Q15>Settings!$B$3/100,"UP",IF(Q15<-Settings!$B$3/100,"DOWN","FLAT"))) -> UP | S15: =IF(OR(N15="",P15="",J15=""),"",IF(OR(AND(J15="BUY",R15="UP"),AND(J15="SELL",R15="DOWN"),AND(J15="HOLD",R15="FLAT")),"YES","NO")) -> YES | T15: =IF(J15="","",IF(J15="BUY",1,IF(J15="SELL",-1,0))) -> 1 | U15: =IFERROR(IF(OR(J15="",N15="",P15=""),"",IF(T15=0,0,T15*Q15-Settings!$B$4/10000-IF(T15<0,Settings!$B$5/10000,0))),"") -> 0.0273 | V15: NVIDIA fiscal Q4 FY25, released 26 Feb 2025 (calendar label by release date). Beat on every line but margin-trough guide (71%), growth 262%->65%, tariffs unknown. Opened +2.8% then closed -8.5% - overnight window called it BUY. | W15: =IF($K15="","",$K15*60) -> 3000 | X15: =IF($A15="","",$A15&"|"&$C15&"|"&$D15) -> Nvidia|2025|Q1 | Y15: =IFERROR(IF($X15="","",INDEX(LLM_Data_Entry!$H$3:$H$548,MATCH($X15,INDEX(LLM_Data_Entry!$A$3:$A$548&"|"&LLM_Data_Entry!$C$3:$C$548&"|"&LLM_Data_Entry!$D$3:$D$548,0),0))),"") -> SELL | Z15: =IFERROR(IF($X15="","",INDEX(LLM_Data_Entry!$R$3:$R$548,MATCH($X15,INDEX(LLM_Data_Entry!$A$3:$A$548&"|"&LLM_Data_Entry!$C$3:$C$548&"|"&LLM_Data_Entry!$D$3:$D$548,0),0))),"") -> NO | AB15: release date + stated time in the document (rater worksheet) | AC15: NVDA | AD15: 2025-02-26 | AE15: 131.0842 | AF15: 2025-02-27 | AG15: 134.7987 | AH15: 0.028336475 | AI15: UP | AJ15: YES | AK15: 0.027336 | AL15: =IF($A15="","",IFERROR(INDEX(Company_List!$G$3:$G$207,MATCH($A15,Company_List!$A$3:$A$207,0)),"unassigned")) -> P2 | AM15: Phase 2/Nvidia/Q2 2025/NVDA-Q1FY26-press-release-SEC-EX99-1.htm; Phase 2/Nvidia/Q2 2025/NVDA-Q1FY26-earnings-call-transcript-AlphaStreet.html; Phase 2/Nvidia/Q2 2025/NVDA-Q1FY26-CFO-commentary-SEC-EX99-2.htm; Phase 2/Nvidia/Q1 2025/NVDA-Q4FY25-press-release-SEC-EX99-1.htm; Phase 2/Nvidia/Q1 2025/NVDA-Q4FY25-earnings-call-transcript-MotleyFool.html; Phase 2/Nvidia/Q1 2025/NVDA-Q4FY25-CFO-commentary-SEC-EX99-2.htm | AO15: whole bundle (Document = All) | AP15: =IF($A15="","",IF(COUNTIFS(LLM_Data_Entry!$A$3:$A$548,$A15)>0,"YES","NO")) -> YES | AQ15: =IF($A15="","",IF(COUNTIFS($A$3:$A15,$A15,$C$3:$C15,$C15,$D$3:$D15,$D15)=1,"YES","NO")) -> YES | AR15: =IF($A15="","",IF(AND($C15&"-"&$D15>=Settings!$B$19,$C15&"-"&$D15<=Settings!$B$20),"IN","OUT")) -> IN | AS15: =IF($A15="","",IF($F15="Financial Results","financials",IF($F15="Outlook/Guidance","guidance",IF($F15="Transcript Q&A","qanda",IF($F15="","unrecorded",IF($E15="All","full",IF($E15="","unrecorded",LOWER($E15)&" only"))))))) -> full | AT15: =IF(AND(OR($J15="BUY",$J15="SELL"),ISNUMBER($U15)),$U15,"") -> 0.0273 | AU15: =IF(AND(OR($J15="BUY",$J15="SELL"),ISNUMBER($AK15)),$AK15,"") -> 0.027336 | AV15: =IF(ISNUMBER($AT15),ABS(IF(ISNUMBER($I15),$I15,0)-Settings!$B$24),"") -> 0.55 | AW15: =IF(ISNUMBER($AV15),$AV15*$AT15,"") -> 0.015015 | AX15: =IF(ISNUMBER($AU15),ABS(IF(ISNUMBER($I15),$I15,0)-Settings!$B$24),"") -> 0.55 | AY15: FROZEN | AZ15: =IF($A15="","",IFERROR(INDEX(Company_List!$H$3:$H$207,MATCH($A15,Company_List!$A$3:$A$207,0)),"unassigned")) -> Information Technology | BC15: =IF($A15="","",IF(COUNTIFS($A$3:$A15,$A15,$C$3:$C15,$C15,$D$3:$D15,$D15,$G$3:$G15,$G15)=1,1,0)) -> 1 | BG15: no | BK15: =IF(OR($H15<>"Human",$S15="",$J15="",$Y15="",$Z15=""),"",IF(EXACT(UPPER($J15),UPPER($Y15)),1,0)) -> 0 | BL15: assumed - blind unless stated otherwise; the note names the realised move (query E-a, settled 10 Aug 2026) | BM15: 6 | BN15: The Motley Fool | BO15: free to read, copyright asserted | BP15: no | BQ15: yes | BS15: YES
A16: Nvidia | B16: =IF(A16="","",_xlfn.XLOOKUP(A16, Company_List!$A:$A, Company_List!$B:$B, "")) -> NVDA | C16: 2025 | D16: Q2 | E16: All | F16: All | G16: Dragos | H16: Human | I16: 0.35 | J16: =IF(OR(I16="",Settings!$B$6=""),"",IF(I16>Settings!$B$6,"BUY",IF(I16<-Settings!$B$6,"SELL","HOLD"))) -> BUY | K16: 48 | L16: 45805 | M16: 45805 | N16: 134.81 | O16: 45806 | P16: 142.25 | Q16: =IF(OR(N16="",P16=""),"",ROUND((P16-N16)/N16,4)) -> 0.0552 | R16: =IF(OR(N16="",P16=""),"",IF(Q16>Settings!$B$3/100,"UP",IF(Q16<-Settings!$B$3/100,"DOWN","FLAT"))) -> UP | S16: =IF(OR(N16="",P16="",J16=""),"",IF(OR(AND(J16="BUY",R16="UP"),AND(J16="SELL",R16="DOWN"),AND(J16="HOLD",R16="FLAT")),"YES","NO")) -> YES | T16: =IF(J16="","",IF(J16="BUY",1,IF(J16="SELL",-1,0))) -> 1 | U16: =IFERROR(IF(OR(J16="",N16="",P16=""),"",IF(T16=0,0,T16*Q16-Settings!$B$4/10000-IF(T16<0,Settings!$B$5/10000,0))),"") -> 0.0542 | V16: NVIDIA fiscal Q1 FY26, released 28 May 2025. Ugly headline (China/H20 charge) but underlying demand intact; market looked through it. | W16: =IF($K16="","",$K16*60) -> 2880 | X16: =IF($A16="","",$A16&"|"&$C16&"|"&$D16) -> Nvidia|2025|Q2 | Y16: =IFERROR(IF($X16="","",INDEX(LLM_Data_Entry!$H$3:$H$548,MATCH($X16,INDEX(LLM_Data_Entry!$A$3:$A$548&"|"&LLM_Data_Entry!$C$3:$C$548&"|"&LLM_Data_Entry!$D$3:$D$548,0),0))),"") -> HOLD | Z16: =IFERROR(IF($X16="","",INDEX(LLM_Data_Entry!$R$3:$R$548,MATCH($X16,INDEX(LLM_Data_Entry!$A$3:$A$548&"|"&LLM_Data_Entry!$C$3:$C$548&"|"&LLM_Data_Entry!$D$3:$D$548,0),0))),"") -> NO | AB16: release date + stated time in the document (rater worksheet) | AC16: NVDA | AD16: 2025-05-28 | AE16: 134.6213 | AF16: 2025-05-29 | AG16: 142.0509 | AH16: 0.055188774 | AI16: UP | AJ16: YES | AK16: 0.054189 | AL16: =IF($A16="","",IFERROR(INDEX(Company_List!$G$3:$G$207,MATCH($A16,Company_List!$A$3:$A$207,0)),"unassigned")) -> P2 | AM16: Phase 2/Nvidia/Q3 2025/NVDA-Q2FY26-press-release-SEC-EX99-1.htm; Phase 2/Nvidia/Q3 2025/NVDA-Q2FY26-earnings-call-transcript-AlphaStreet.html; Phase 2/Nvidia/Q3 2025/NVDA-Q2FY26-CFO-commentary-SEC-EX99-2.htm; Phase 2/Nvidia/Q2 2025/NVDA-Q1FY26-press-release-SEC-EX99-1.htm; Phase 2/Nvidia/Q2 2025/NVDA-Q1FY26-earnings-call-transcript-AlphaStreet.html; Phase 2/Nvidia/Q2 2025/NVDA-Q1FY26-CFO-commentary-SEC-EX99-2.htm | AO16: whole bundle (Document = All) | AP16: =IF($A16="","",IF(COUNTIFS(LLM_Data_Entry!$A$3:$A$548,$A16)>0,"YES","NO")) -> YES | AQ16: =IF($A16="","",IF(COUNTIFS($A$3:$A16,$A16,$C$3:$C16,$C16,$D$3:$D16,$D16)=1,"YES","NO")) -> YES | AR16: =IF($A16="","",IF(AND($C16&"-"&$D16>=Settings!$B$19,$C16&"-"&$D16<=Settings!$B$20),"IN","OUT")) -> IN | AS16: =IF($A16="","",IF($F16="Financial Results","financials",IF($F16="Outlook/Guidance","guidance",IF($F16="Transcript Q&A","qanda",IF($F16="","unrecorded",IF($E16="All","full",IF($E16="","unrecorded",LOWER($E16)&" only"))))))) -> full | AT16: =IF(AND(OR($J16="BUY",$J16="SELL"),ISNUMBER($U16)),$U16,"") -> 0.0542 | AU16: =IF(AND(OR($J16="BUY",$J16="SELL"),ISNUMBER($AK16)),$AK16,"") -> 0.054189 | AV16: =IF(ISNUMBER($AT16),ABS(IF(ISNUMBER($I16),$I16,0)-Settings!$B$24),"") -> 0.35 | AW16: =IF(ISNUMBER($AV16),$AV16*$AT16,"") -> 0.01897 | AX16: =IF(ISNUMBER($AU16),ABS(IF(ISNUMBER($I16),$I16,0)-Settings!$B$24),"") -> 0.35 | AY16: FROZEN | AZ16: =IF($A16="","",IFERROR(INDEX(Company_List!$H$3:$H$207,MATCH($A16,Company_List!$A$3:$A$207,0)),"unassigned")) -> Information Technology | BC16: =IF($A16="","",IF(COUNTIFS($A$3:$A16,$A16,$C$3:$C16,$C16,$D$3:$D16,$D16,$G$3:$G16,$G16)=1,1,0)) -> 1 | BG16: no | BK16: =IF(OR($H16<>"Human",$S16="",$J16="",$Y16="",$Z16=""),"",IF(EXACT(UPPER($J16),UPPER($Y16)),1,0)) -> 0 | BL16: assumed - no rater record | BM16: 6 | BN16: not publisher-identified | BO16: not publisher-identified | BP16: no | BQ16: yes | BS16: YES
A17: Nvidia | B17: =IF(A17="","",_xlfn.XLOOKUP(A17, Company_List!$A:$A, Company_List!$B:$B, "")) -> NVDA | C17: 2025 | D17: Q3 | E17: All | F17: All | G17: Dragos | H17: Human | I17: 0.6 | J17: =IF(OR(I17="",Settings!$B$6=""),"",IF(I17>Settings!$B$6,"BUY",IF(I17<-Settings!$B$6,"SELL","HOLD"))) -> BUY | K17: 40 | L17: 45896 | M17: 45896 | N17: 181.6 | O17: 45897 | P17: 180.82 | Q17: =IF(OR(N17="",P17=""),"",ROUND((P17-N17)/N17,4)) -> -0.0043 | R17: =IF(OR(N17="",P17=""),"",IF(Q17>Settings!$B$3/100,"UP",IF(Q17<-Settings!$B$3/100,"DOWN","FLAT"))) -> FLAT | S17: =IF(OR(N17="",P17="",J17=""),"",IF(OR(AND(J17="BUY",R17="UP"),AND(J17="SELL",R17="DOWN"),AND(J17="HOLD",R17="FLAT")),"YES","NO")) -> NO | T17: =IF(J17="","",IF(J17="BUY",1,IF(J17="SELL",-1,0))) -> 1 | U17: =IFERROR(IF(OR(J17="",N17="",P17=""),"",IF(T17=0,0,T17*Q17-Settings!$B$4/10000-IF(T17<0,Settings!$B$5/10000,0))),"") -> -0.0053 | V17: NVIDIA fiscal Q2 FY26, released 27 Aug 2025. Strong records but reaction flat (-0.43%) - correct call was HOLD. | W17: =IF($K17="","",$K17*60) -> 2400 | X17: =IF($A17="","",$A17&"|"&$C17&"|"&$D17) -> Nvidia|2025|Q3 | Y17: =IFERROR(IF($X17="","",INDEX(LLM_Data_Entry!$H$3:$H$548,MATCH($X17,INDEX(LLM_Data_Entry!$A$3:$A$548&"|"&LLM_Data_Entry!$C$3:$C$548&"|"&LLM_Data_Entry!$D$3:$D$548,0),0))),"") -> BUY | Z17: =IFERROR(IF($X17="","",INDEX(LLM_Data_Entry!$R$3:$R$548,MATCH($X17,INDEX(LLM_Data_Entry!$A$3:$A$548&"|"&LLM_Data_Entry!$C$3:$C$548&"|"&LLM_Data_Entry!$D$3:$D$548,0),0))),"") -> NO | AB17: release date + stated time in the document (rater worksheet) | AC17: NVDA | AD17: 2025-08-27 | AE17: 181.3585 | AF17: 2025-08-28 | AG17: 180.5795 | AH17: -0.0042951987 | AI17: FLAT | AJ17: NO | AK17: -0.005295 | AL17: =IF($A17="","",IFERROR(INDEX(Company_List!$G$3:$G$207,MATCH($A17,Company_List!$A$3:$A$207,0)),"unassigned")) -> P2 | AM17: Phase 2/Nvidia/Q4 2025/NVDA-Q3FY26-press-release-SEC-EX99-1.htm; Phase 2/Nvidia/Q4 2025/NVDA-Q3FY26-earnings-call-transcript-MotleyFool.html; Phase 2/Nvidia/Q4 2025/NVDA-Q3FY26-CFO-commentary-SEC-EX99-2.htm; Phase 2/Nvidia/Q3 2025/NVDA-Q2FY26-press-release-SEC-EX99-1.htm; Phase 2/Nvidia/Q3 2025/NVDA-Q2FY26-earnings-call-transcript-AlphaStreet.html; Phase 2/Nvidia/Q3 2025/NVDA-Q2FY26-CFO-commentary-SEC-EX99-2.htm | AO17: whole bundle (Document = All) | AP17: =IF($A17="","",IF(COUNTIFS(LLM_Data_Entry!$A$3:$A$548,$A17)>0,"YES","NO")) -> YES | AQ17: =IF($A17="","",IF(COUNTIFS($A$3:$A17,$A17,$C$3:$C17,$C17,$D$3:$D17,$D17)=1,"YES","NO")) -> YES | AR17: =IF($A17="","",IF(AND($C17&"-"&$D17>=Settings!$B$19,$C17&"-"&$D17<=Settings!$B$20),"IN","OUT")) -> IN | AS17: =IF($A17="","",IF($F17="Financial Results","financials",IF($F17="Outlook/Guidance","guidance",IF($F17="Transcript Q&A","qanda",IF($F17="","unrecorded",IF($E17="All","full",IF($E17="","unrecorded",LOWER($E17)&" only"))))))) -> full | AT17: =IF(AND(OR($J17="BUY",$J17="SELL"),ISNUMBER($U17)),$U17,"") -> -0.0053 | AU17: =IF(AND(OR($J17="BUY",$J17="SELL"),ISNUMBER($AK17)),$AK17,"") -> -0.005295 | AV17: =IF(ISNUMBER($AT17),ABS(IF(ISNUMBER($I17),$I17,0)-Settings!$B$24),"") -> 0.6 | AW17: =IF(ISNUMBER($AV17),$AV17*$AT17,"") -> -0.00318 | AX17: =IF(ISNUMBER($AU17),ABS(IF(ISNUMBER($I17),$I17,0)-Settings!$B$24),"") -> 0.6 | AY17: FROZEN | AZ17: =IF($A17="","",IFERROR(INDEX(Company_List!$H$3:$H$207,MATCH($A17,Company_List!$A$3:$A$207,0)),"unassigned")) -> Information Technology | BC17: =IF($A17="","",IF(COUNTIFS($A$3:$A17,$A17,$C$3:$C17,$C17,$D$3:$D17,$D17,$G$3:$G17,$G17)=1,1,0)) -> 1 | BG17: no | BK17: =IF(OR($H17<>"Human",$S17="",$J17="",$Y17="",$Z17=""),"",IF(EXACT(UPPER($J17),UPPER($Y17)),1,0)) -> 1 | BL17: assumed - blind unless stated otherwise; the note names the realised move (query E-a, settled 10 Aug 2026) | BM17: 6 | BN17: The Motley Fool | BO17: free to read, copyright asserted | BP17: no | BQ17: yes | BS17: YES
A18: Nvidia | B18: =IF(A18="","",_xlfn.XLOOKUP(A18, Company_List!$A:$A, Company_List!$B:$B, "")) -> NVDA | C18: 2025 | D18: Q4 | E18: All | F18: All | G18: Dragos | H18: Human | I18: 0.75 | J18: =IF(OR(I18="",Settings!$B$6=""),"",IF(I18>Settings!$B$6,"BUY",IF(I18<-Settings!$B$6,"SELL","HOLD"))) -> BUY | K18: 44 | L18: 45980 | M18: 45980 | N18: 186.52 | O18: 45981 | P18: 195.95 | Q18: =IF(OR(N18="",P18=""),"",ROUND((P18-N18)/N18,4)) -> 0.0506 | R18: =IF(OR(N18="",P18=""),"",IF(Q18>Settings!$B$3/100,"UP",IF(Q18<-Settings!$B$3/100,"DOWN","FLAT"))) -> UP | S18: =IF(OR(N18="",P18="",J18=""),"",IF(OR(AND(J18="BUY",R18="UP"),AND(J18="SELL",R18="DOWN"),AND(J18="HOLD",R18="FLAT")),"YES","NO")) -> YES | T18: =IF(J18="","",IF(J18="BUY",1,IF(J18="SELL",-1,0))) -> 1 | U18: =IFERROR(IF(OR(J18="",N18="",P18=""),"",IF(T18=0,0,T18*Q18-Settings!$B$4/10000-IF(T18<0,Settings!$B$5/10000,0))),"") -> 0.0496 | V18: NVIDIA fiscal Q3 FY26, released 19 Nov 2025. Strongest print of the four; +5.1% overnight. | W18: =IF($K18="","",$K18*60) -> 2640 | X18: =IF($A18="","",$A18&"|"&$C18&"|"&$D18) -> Nvidia|2025|Q4 | Y18: =IFERROR(IF($X18="","",INDEX(LLM_Data_Entry!$H$3:$H$548,MATCH($X18,INDEX(LLM_Data_Entry!$A$3:$A$548&"|"&LLM_Data_Entry!$C$3:$C$548&"|"&LLM_Data_Entry!$D$3:$D$548,0),0))),"") -> BUY | Z18: =IFERROR(IF($X18="","",INDEX(LLM_Data_Entry!$R$3:$R$548,MATCH($X18,INDEX(LLM_Data_Entry!$A$3:$A$548&"|"&LLM_Data_Entry!$C$3:$C$548&"|"&LLM_Data_Entry!$D$3:$D$548,0),0))),"") -> YES | AB18: release date + stated time in the document (rater worksheet) | AC18: NVDA | AD18: 2025-11-19 | AE18: 186.2824 | AF18: 2025-11-20 | AG18: 195.7004 | AH18: 0.050557553 | AI18: UP | AJ18: YES | AK18: 0.049558 | AL18: =IF($A18="","",IFERROR(INDEX(Company_List!$G$3:$G$207,MATCH($A18,Company_List!$A$3:$A$207,0)),"unassigned")) -> P2 | AM18: Phase 2/Nvidia/Q4 2025/NVDA-Q3FY26-press-release-SEC-EX99-1.htm; Phase 2/Nvidia/Q4 2025/NVDA-Q3FY26-earnings-call-transcript-MotleyFool.html; Phase 2/Nvidia/Q4 2025/NVDA-Q3FY26-CFO-commentary-SEC-EX99-2.htm; Phase 2/Nvidia/Q1 2025/NVDA-Q4FY25-press-release-SEC-EX99-1.htm; Phase 2/Nvidia/Q1 2025/NVDA-Q4FY25-earnings-call-transcript-MotleyFool.html; Phase 2/Nvidia/Q1 2025/NVDA-Q4FY25-CFO-commentary-SEC-EX99-2.htm | AO18: whole bundle (Document = All) | AP18: =IF($A18="","",IF(COUNTIFS(LLM_Data_Entry!$A$3:$A$548,$A18)>0,"YES","NO")) -> YES | AQ18: =IF($A18="","",IF(COUNTIFS($A$3:$A18,$A18,$C$3:$C18,$C18,$D$3:$D18,$D18)=1,"YES","NO")) -> YES | AR18: =IF($A18="","",IF(AND($C18&"-"&$D18>=Settings!$B$19,$C18&"-"&$D18<=Settings!$B$20),"IN","OUT")) -> IN | AS18: =IF($A18="","",IF($F18="Financial Results","financials",IF($F18="Outlook/Guidance","guidance",IF($F18="Transcript Q&A","qanda",IF($F18="","unrecorded",IF($E18="All","full",IF($E18="","unrecorded",LOWER($E18)&" only"))))))) -> full | AT18: =IF(AND(OR($J18="BUY",$J18="SELL"),ISNUMBER($U18)),$U18,"") -> 0.0496 | AU18: =IF(AND(OR($J18="BUY",$J18="SELL"),ISNUMBER($AK18)),$AK18,"") -> 0.049558 | AV18: =IF(ISNUMBER($AT18),ABS(IF(ISNUMBER($I18),$I18,0)-Settings!$B$24),"") -> 0.75 | AW18: =IF(ISNUMBER($AV18),$AV18*$AT18,"") -> 0.0372 | AX18: =IF(ISNUMBER($AU18),ABS(IF(ISNUMBER($I18),$I18,0)-Settings!$B$24),"") -> 0.75 | AY18: FROZEN | AZ18: =IF($A18="","",IFERROR(INDEX(Company_List!$H$3:$H$207,MATCH($A18,Company_List!$A$3:$A$207,0)),"unassigned")) -> Information Technology | BC18: =IF($A18="","",IF(COUNTIFS($A$3:$A18,$A18,$C$3:$C18,$C18,$D$3:$D18,$D18,$G$3:$G18,$G18)=1,1,0)) -> 1 | BG18: no | BK18: =IF(OR($H18<>"Human",$S18="",$J18="",$Y18="",$Z18=""),"",IF(EXACT(UPPER($J18),UPPER($Y18)),1,0)) -> 1 | BL18: assumed - no rater record | BM18: 6 | BN18: The Motley Fool | BO18: free to read, copyright asserted | BP18: no | BQ18: yes | BS18: YES
A19: Boeing | B19: =IF(A19="","",_xlfn.XLOOKUP(A19, Company_List!$A:$A, Company_List!$B:$B, "")) -> BA | C19: 2025 | D19: Q1 | E19: All | F19: All | G19: Nigel | H19: Human | I19: -0.5 | J19: =IF(OR(I19="",Settings!$B$6=""),"",IF(I19>Settings!$B$6,"BUY",IF(I19<-Settings!$B$6,"SELL","HOLD"))) -> SELL | K19: 32 | L19: 45770 | M19: 45769 | N19: 162.52 | O19: 45770 | P19: 174 | Q19: =IF(OR(N19="",P19=""),"",ROUND((P19-N19)/N19,4)) -> 0.0706 | R19: =IF(OR(N19="",P19=""),"",IF(Q19>Settings!$B$3/100,"UP",IF(Q19<-Settings!$B$3/100,"DOWN","FLAT"))) -> UP | S19: =IF(OR(N19="",P19="",J19=""),"",IF(OR(AND(J19="BUY",R19="UP"),AND(J19="SELL",R19="DOWN"),AND(J19="HOLD",R19="FLAT")),"YES","NO")) -> NO | T19: =IF(J19="","",IF(J19="BUY",1,IF(J19="SELL",-1,0))) -> -1 | U19: =IFERROR(IF(OR(J19="",N19="",P19=""),"",IF(T19=0,0,T19*Q19-Settings!$B$4/10000-IF(T19<0,Settings!$B$5/10000,0))),"") -> -0.0716 | V19: Recovery plan working as intended though a long road remains; revenue up but operating margin lower and not yet convincing; outlook resting on planned diversification; tariffs a growing concern especially around China deals, with possible supply chain knock-on; more conservative forward plans. Heavy uncertainty, cautious tone. | W19: =IF($K19="","",$K19*60) -> 1920 | X19: =IF($A19="","",$A19&"|"&$C19&"|"&$D19) -> Boeing|2025|Q1 | Y19: =IFERROR(IF($X19="","",INDEX(LLM_Data_Entry!$H$3:$H$548,MATCH($X19,INDEX(LLM_Data_Entry!$A$3:$A$548&"|"&LLM_Data_Entry!$C$3:$C$548&"|"&LLM_Data_Entry!$D$3:$D$548,0),0))),"") -> HOLD | Z19: =IFERROR(IF($X19="","",INDEX(LLM_Data_Entry!$R$3:$R$548,MATCH($X19,INDEX(LLM_Data_Entry!$A$3:$A$548&"|"&LLM_Data_Entry!$C$3:$C$548&"|"&LLM_Data_Entry!$D$3:$D$548,0),0))),"") -> NO | AB19: price signal | AC19: BA | AD19: 2025-04-22 | AE19: 162.52 | AF19: 2025-04-23 | AG19: 174 | AH19: 0.070637434 | AI19: UP | AJ19: NO | AK19: -0.071637 | AL19: =IF($A19="","",IFERROR(INDEX(Company_List!$G$3:$G$207,MATCH($A19,Company_List!$A$3:$A$207,0)),"unassigned")) -> P2 | AM19: Phase 2/Boeing/Q1/Transcript-Q1-2025-Earnings-Call.pdf | AO19: unique filename match | AP19: =IF($A19="","",IF(COUNTIFS(LLM_Data_Entry!$A$3:$A$548,$A19)>0,"YES","NO")) -> YES | AQ19: =IF($A19="","",IF(COUNTIFS($A$3:$A19,$A19,$C$3:$C19,$C19,$D$3:$D19,$D19)=1,"YES","NO")) -> YES | AR19: =IF($A19="","",IF(AND($C19&"-"&$D19>=Settings!$B$19,$C19&"-"&$D19<=Settings!$B$20),"IN","OUT")) -> IN | AS19: =IF($A19="","",IF($F19="Financial Results","financials",IF($F19="Outlook/Guidance","guidance",IF($F19="Transcript Q&A","qanda",IF($F19="","unrecorded",IF($E19="All","full",IF($E19="","unrecorded",LOWER($E19)&" only"))))))) -> full | AT19: =IF(AND(OR($J19="BUY",$J19="SELL"),ISNUMBER($U19)),$U19,"") -> -0.0716 | AU19: =IF(AND(OR($J19="BUY",$J19="SELL"),ISNUMBER($AK19)),$AK19,"") -> -0.071637 | AV19: =IF(ISNUMBER($AT19),ABS(IF(ISNUMBER($I19),$I19,0)-Settings!$B$24),"") -> 0.5 | AW19: =IF(ISNUMBER($AV19),$AV19*$AT19,"") -> -0.0358 | AX19: =IF(ISNUMBER($AU19),ABS(IF(ISNUMBER($I19),$I19,0)-Settings!$B$24),"") -> 0.5 | AY19: FROZEN | AZ19: =IF($A19="","",IFERROR(INDEX(Company_List!$H$3:$H$207,MATCH($A19,Company_List!$A$3:$A$207,0)),"unassigned")) -> Industrials | BC19: =IF($A19="","",IF(COUNTIFS($A$3:$A19,$A19,$C$3:$C19,$C19,$D$3:$D19,$D19,$G$3:$G19,$G19)=1,1,0)) -> 1 | BG19: no | BK19: =IF(OR($H19<>"Human",$S19="",$J19="",$Y19="",$Z19=""),"",IF(EXACT(UPPER($J19),UPPER($Y19)),1,0)) -> 0 | BL19: assumed - no rater record | BM19: 1 | BN19: FactSet CallStreet | BO19: licensed vendor | BP19: no | BQ19: no | BS19: YES
A20: Boeing | B20: =IF(A20="","",_xlfn.XLOOKUP(A20, Company_List!$A:$A, Company_List!$B:$B, "")) -> BA | C20: 2025 | D20: Q2 | E20: All | F20: All | G20: Nigel | H20: Human | I20: 0.6 | J20: =IF(OR(I20="",Settings!$B$6=""),"",IF(I20>Settings!$B$6,"BUY",IF(I20<-Settings!$B$6,"SELL","HOLD"))) -> BUY | K20: 28 | L20: 45867 | M20: 45866 | N20: 236.41 | O20: 45867 | P20: 239.5 | Q20: =IF(OR(N20="",P20=""),"",ROUND((P20-N20)/N20,4)) -> 0.0131 | R20: =IF(OR(N20="",P20=""),"",IF(Q20>Settings!$B$3/100,"UP",IF(Q20<-Settings!$B$3/100,"DOWN","FLAT"))) -> FLAT | S20: =IF(OR(N20="",P20="",J20=""),"",IF(OR(AND(J20="BUY",R20="UP"),AND(J20="SELL",R20="DOWN"),AND(J20="HOLD",R20="FLAT")),"YES","NO")) -> NO | T20: =IF(J20="","",IF(J20="BUY",1,IF(J20="SELL",-1,0))) -> 1 | U20: =IFERROR(IF(OR(J20="",N20="",P20=""),"",IF(T20=0,0,T20*Q20-Settings!$B$4/10000-IF(T20<0,Settings!$B$5/10000,0))),"") -> 0.0121 | V20: Demand growing and finances healthier with stronger revenues; production plan improving as intended; contract wins in defence and space; tariff worries easing and geopolitical risk stabilising; 737 deliveries below last year but in line with the action plan. Improving tone. | W20: =IF($K20="","",$K20*60) -> 1680 | X20: =IF($A20="","",$A20&"|"&$C20&"|"&$D20) -> Boeing|2025|Q2 | Y20: =IFERROR(IF($X20="","",INDEX(LLM_Data_Entry!$H$3:$H$548,MATCH($X20,INDEX(LLM_Data_Entry!$A$3:$A$548&"|"&LLM_Data_Entry!$C$3:$C$548&"|"&LLM_Data_Entry!$D$3:$D$548,0),0))),"") -> HOLD | Z20: =IFERROR(IF($X20="","",INDEX(LLM_Data_Entry!$R$3:$R$548,MATCH($X20,INDEX(LLM_Data_Entry!$A$3:$A$548&"|"&LLM_Data_Entry!$C$3:$C$548&"|"&LLM_Data_Entry!$D$3:$D$548,0),0))),"") -> YES | AB20: price signal | AC20: BA | AD20: 2025-07-28 | AE20: 236.41 | AF20: 2025-07-29 | AG20: 239.5 | AH20: 0.013070496 | AI20: FLAT | AJ20: NO | AK20: 0.01207 | AL20: =IF($A20="","",IFERROR(INDEX(Company_List!$G$3:$G$207,MATCH($A20,Company_List!$A$3:$A$207,0)),"unassigned")) -> P2 | AM20: Phase 2/Boeing/2025-Q2/BA-2025-Q2-press-release-SEC-EX-99-1.htm | AN20: https://www.sec.gov/Archives/edgar/data/12927/000001292725000058/a202506jun308kprex991.htm | AO20: manifest | AP20: =IF($A20="","",IF(COUNTIFS(LLM_Data_Entry!$A$3:$A$548,$A20)>0,"YES","NO")) -> YES | AQ20: =IF($A20="","",IF(COUNTIFS($A$3:$A20,$A20,$C$3:$C20,$C20,$D$3:$D20,$D20)=1,"YES","NO")) -> YES | AR20: =IF($A20="","",IF(AND($C20&"-"&$D20>=Settings!$B$19,$C20&"-"&$D20<=Settings!$B$20),"IN","OUT")) -> IN | AS20: =IF($A20="","",IF($F20="Financial Results","financials",IF($F20="Outlook/Guidance","guidance",IF($F20="Transcript Q&A","qanda",IF($F20="","unrecorded",IF($E20="All","full",IF($E20="","unrecorded",LOWER($E20)&" only"))))))) -> full | AT20: =IF(AND(OR($J20="BUY",$J20="SELL"),ISNUMBER($U20)),$U20,"") -> 0.0121 | AU20: =IF(AND(OR($J20="BUY",$J20="SELL"),ISNUMBER($AK20)),$AK20,"") -> 0.01207 | AV20: =IF(ISNUMBER($AT20),ABS(IF(ISNUMBER($I20),$I20,0)-Settings!$B$24),"") -> 0.6 | AW20: =IF(ISNUMBER($AV20),$AV20*$AT20,"") -> 0.00726 | AX20: =IF(ISNUMBER($AU20),ABS(IF(ISNUMBER($I20),$I20,0)-Settings!$B$24),"") -> 0.6 | AY20: FROZEN | AZ20: =IF($A20="","",IFERROR(INDEX(Company_List!$H$3:$H$207,MATCH($A20,Company_List!$A$3:$A$207,0)),"unassigned")) -> Industrials | BC20: =IF($A20="","",IF(COUNTIFS($A$3:$A20,$A20,$C$3:$C20,$C20,$D$3:$D20,$D20,$G$3:$G20,$G20)=1,1,0)) -> 1 | BG20: no | BK20: =IF(OR($H20<>"Human",$S20="",$J20="",$Y20="",$Z20=""),"",IF(EXACT(UPPER($J20),UPPER($Y20)),1,0)) -> 0 | BL20: assumed - no rater record | BM20: 1 | BN20: not publisher-identified | BO20: not publisher-identified | BP20: no | BQ20: yes | BS20: YES
A21: Boeing | B21: =IF(A21="","",_xlfn.XLOOKUP(A21, Company_List!$A:$A, Company_List!$B:$B, "")) -> BA | C21: 2025 | D21: Q3 | E21: All | F21: All | G21: Nigel | H21: Human | I21: -0.1 | J21: =IF(OR(I21="",Settings!$B$6=""),"",IF(I21>Settings!$B$6,"BUY",IF(I21<-Settings!$B$6,"SELL","HOLD"))) -> HOLD | K21: 26 | L21: 45959 | M21: 45958 | N21: 223.33 | O21: 45959 | P21: 221.36 | Q21: =IF(OR(N21="",P21=""),"",ROUND((P21-N21)/N21,4)) -> -0.0088 | R21: =IF(OR(N21="",P21=""),"",IF(Q21>Settings!$B$3/100,"UP",IF(Q21<-Settings!$B$3/100,"DOWN","FLAT"))) -> FLAT | S21: =IF(OR(N21="",P21="",J21=""),"",IF(OR(AND(J21="BUY",R21="UP"),AND(J21="SELL",R21="DOWN"),AND(J21="HOLD",R21="FLAT")),"YES","NO")) -> YES | T21: =IF(J21="","",IF(J21="BUY",1,IF(J21="SELL",-1,0))) -> 0 | U21: =IFERROR(IF(OR(J21="",N21="",P21=""),"",IF(T21=0,0,T21*Q21-Settings!$B$4/10000-IF(T21<0,Settings!$B$5/10000,0))),"") -> 0 | V21: Good progress on the 737 programme though 777X production delayed; US Space Force contract secured; KPIs being met and demand still strong; finances healthier; supply chain still tough but stable. Steady tone. | W21: =IF($K21="","",$K21*60) -> 1560 | X21: =IF($A21="","",$A21&"|"&$C21&"|"&$D21) -> Boeing|2025|Q3 | Y21: =IFERROR(IF($X21="","",INDEX(LLM_Data_Entry!$H$3:$H$548,MATCH($X21,INDEX(LLM_Data_Entry!$A$3:$A$548&"|"&LLM_Data_Entry!$C$3:$C$548&"|"&LLM_Data_Entry!$D$3:$D$548,0),0))),"") -> SELL | Z21: =IFERROR(IF($X21="","",INDEX(LLM_Data_Entry!$R$3:$R$548,MATCH($X21,INDEX(LLM_Data_Entry!$A$3:$A$548&"|"&LLM_Data_Entry!$C$3:$C$548&"|"&LLM_Data_Entry!$D$3:$D$548,0),0))),"") -> NO | AB21: release time published by the issuer | AC21: BA | AD21: 2025-10-28 | AE21: 223.33 | AF21: 2025-10-29 | AG21: 221.36 | AH21: -0.0088210316 | AI21: FLAT | AJ21: YES | AK21: 0 | AL21: =IF($A21="","",IFERROR(INDEX(Company_List!$G$3:$G$207,MATCH($A21,Company_List!$A$3:$A$207,0)),"unassigned")) -> P2 | AM21: Phase 2/Boeing/2025-Q3/BA-2025-Q3-press-release-SEC-EX-99-1.htm | AN21: https://www.sec.gov/Archives/edgar/data/12927/000162828025046915/a202509sep308kprex991.htm | AO21: manifest | AP21: =IF($A21="","",IF(COUNTIFS(LLM_Data_Entry!$A$3:$A$548,$A21)>0,"YES","NO")) -> YES | AQ21: =IF($A21="","",IF(COUNTIFS($A$3:$A21,$A21,$C$3:$C21,$C21,$D$3:$D21,$D21)=1,"YES","NO")) -> YES | AR21: =IF($A21="","",IF(AND($C21&"-"&$D21>=Settings!$B$19,$C21&"-"&$D21<=Settings!$B$20),"IN","OUT")) -> IN | AS21: =IF($A21="","",IF($F21="Financial Results","financials",IF($F21="Outlook/Guidance","guidance",IF($F21="Transcript Q&A","qanda",IF($F21="","unrecorded",IF($E21="All","full",IF($E21="","unrecorded",LOWER($E21)&" only"))))))) -> full | AT21: =IF(AND(OR($J21="BUY",$J21="SELL"),ISNUMBER($U21)),$U21,"") | AU21: =IF(AND(OR($J21="BUY",$J21="SELL"),ISNUMBER($AK21)),$AK21,"") | AV21: =IF(ISNUMBER($AT21),ABS(IF(ISNUMBER($I21),$I21,0)-Settings!$B$24),"") | AW21: =IF(ISNUMBER($AV21),$AV21*$AT21,"") | AX21: =IF(ISNUMBER($AU21),ABS(IF(ISNUMBER($I21),$I21,0)-Settings!$B$24),"") | AY21: FROZEN | AZ21: =IF($A21="","",IFERROR(INDEX(Company_List!$H$3:$H$207,MATCH($A21,Company_List!$A$3:$A$207,0)),"unassigned")) -> Industrials | BC21: =IF($A21="","",IF(COUNTIFS($A$3:$A21,$A21,$C$3:$C21,$C21,$D$3:$D21,$D21,$G$3:$G21,$G21)=1,1,0)) -> 1 | BG21: no | BK21: =IF(OR($H21<>"Human",$S21="",$J21="",$Y21="",$Z21=""),"",IF(EXACT(UPPER($J21),UPPER($Y21)),1,0)) -> 0 | BL21: assumed - no rater record | BM21: 1 | BN21: not publisher-identified | BO21: not publisher-identified | BP21: no | BQ21: yes | BS21: YES
A22: Boeing | B22: =IF(A22="","",_xlfn.XLOOKUP(A22, Company_List!$A:$A, Company_List!$B:$B, "")) -> BA | C22: 2025 | D22: Q4 | E22: All | F22: All | G22: Nigel | H22: Human | I22: 0.7 | J22: =IF(OR(I22="",Settings!$B$6=""),"",IF(I22>Settings!$B$6,"BUY",IF(I22<-Settings!$B$6,"SELL","HOLD"))) -> BUY | K22: 18 | L22: 46049 | M22: 46048 | N22: 248.43 | O22: 46049 | P22: 242.5 | Q22: =IF(OR(N22="",P22=""),"",ROUND((P22-N22)/N22,4)) -> -0.0239 | R22: =IF(OR(N22="",P22=""),"",IF(Q22>Settings!$B$3/100,"UP",IF(Q22<-Settings!$B$3/100,"DOWN","FLAT"))) -> DOWN | S22: =IF(OR(N22="",P22="",J22=""),"",IF(OR(AND(J22="BUY",R22="UP"),AND(J22="SELL",R22="DOWN"),AND(J22="HOLD",R22="FLAT")),"YES","NO")) -> NO | T22: =IF(J22="","",IF(J22="BUY",1,IF(J22="SELL",-1,0))) -> 1 | U22: =IFERROR(IF(OR(J22="",N22="",P22=""),"",IF(T22=0,0,T22*Q22-Settings!$B$4/10000-IF(T22<0,Settings!$B$5/10000,0))),"") -> -0.0249 | V22: Highest order totals and good progress on delivery plans; leaner production and supply chain; KPIs being met; further defence deals secured; Jeppesen sale completed; finances healthy. Confident tone. | W22: =IF($K22="","",$K22*60) -> 1080 | X22: =IF($A22="","",$A22&"|"&$C22&"|"&$D22) -> Boeing|2025|Q4 | Y22: =IFERROR(IF($X22="","",INDEX(LLM_Data_Entry!$H$3:$H$548,MATCH($X22,INDEX(LLM_Data_Entry!$A$3:$A$548&"|"&LLM_Data_Entry!$C$3:$C$548&"|"&LLM_Data_Entry!$D$3:$D$548,0),0))),"") -> HOLD | Z22: =IFERROR(IF($X22="","",INDEX(LLM_Data_Entry!$R$3:$R$548,MATCH($X22,INDEX(LLM_Data_Entry!$A$3:$A$548&"|"&LLM_Data_Entry!$C$3:$C$548&"|"&LLM_Data_Entry!$D$3:$D$548,0),0))),"") -> NO | AB22: recorded price identified against every pulled series | AC22: BA | AD22: 2026-01-26 | AE22: 248.43 | AF22: 2026-01-27 | AG22: 242.5 | AH22: -0.023869875 | AI22: DOWN | AJ22: NO | AK22: -0.02487 | AL22: =IF($A22="","",IFERROR(INDEX(Company_List!$G$3:$G$207,MATCH($A22,Company_List!$A$3:$A$207,0)),"unassigned")) -> P2 | AM22: Phase 2/Boeing/2025-Q4/BA-2025-Q4-press-release-SEC-EX-99-1.htm | AN22: https://www.sec.gov/Archives/edgar/data/12927/000162828026003518/a202512dec318kprex991.htm | AO22: manifest | AP22: =IF($A22="","",IF(COUNTIFS(LLM_Data_Entry!$A$3:$A$548,$A22)>0,"YES","NO")) -> YES | AQ22: =IF($A22="","",IF(COUNTIFS($A$3:$A22,$A22,$C$3:$C22,$C22,$D$3:$D22,$D22)=1,"YES","NO")) -> YES | AR22: =IF($A22="","",IF(AND($C22&"-"&$D22>=Settings!$B$19,$C22&"-"&$D22<=Settings!$B$20),"IN","OUT")) -> IN | AS22: =IF($A22="","",IF($F22="Financial Results","financials",IF($F22="Outlook/Guidance","guidance",IF($F22="Transcript Q&A","qanda",IF($F22="","unrecorded",IF($E22="All","full",IF($E22="","unrecorded",LOWER($E22)&" only"))))))) -> full | AT22: =IF(AND(OR($J22="BUY",$J22="SELL"),ISNUMBER($U22)),$U22,"") -> -0.0249 | AU22: =IF(AND(OR($J22="BUY",$J22="SELL"),ISNUMBER($AK22)),$AK22,"") -> -0.02487 | AV22: =IF(ISNUMBER($AT22),ABS(IF(ISNUMBER($I22),$I22,0)-Settings!$B$24),"") -> 0.7 | AW22: =IF(ISNUMBER($AV22),$AV22*$AT22,"") -> -0.01743 | AX22: =IF(ISNUMBER($AU22),ABS(IF(ISNUMBER($I22),$I22,0)-Settings!$B$24),"") -> 0.7 | AY22: FROZEN | AZ22: =IF($A22="","",IFERROR(INDEX(Company_List!$H$3:$H$207,MATCH($A22,Company_List!$A$3:$A$207,0)),"unassigned")) -> Industrials | BC22: =IF($A22="","",IF(COUNTIFS($A$3:$A22,$A22,$C$3:$C22,$C22,$D$3:$D22,$D22,$G$3:$G22,$G22)=1,1,0)) -> 1 | BG22: no | BK22: =IF(OR($H22<>"Human",$S22="",$J22="",$Y22="",$Z22=""),"",IF(EXACT(UPPER($J22),UPPER($Y22)),1,0)) -> 0 | BL22: assumed - no rater record | BM22: 1 | BN22: not publisher-identified | BO22: not publisher-identified | BP22: no | BQ22: yes | BS22: YES
A23: Disney | B23: =IF(A23="","",_xlfn.XLOOKUP(A23, Company_List!$A:$A, Company_List!$B:$B, "")) -> DIS | C23: 2025 | D23: Q1 | E23: All | F23: All | G23: Meriem | H23: Human | I23: 0.4 | J23: =IF(OR(I23="",Settings!$B$6=""),"",IF(I23>Settings!$B$6,"BUY",IF(I23<-Settings!$B$6,"SELL","HOLD"))) -> BUY | K23: 60 | L23: 45693 | M23: 45692 | N23: 113.3 | O23: 45693 | P23: 115.7 | Q23: =IF(OR(N23="",P23=""),"",ROUND((P23-N23)/N23,4)) -> 0.0212 | R23: =IF(OR(N23="",P23=""),"",IF(Q23>Settings!$B$3/100,"UP",IF(Q23<-Settings!$B$3/100,"DOWN","FLAT"))) -> UP | S23: =IF(OR(N23="",P23="",J23=""),"",IF(OR(AND(J23="BUY",R23="UP"),AND(J23="SELL",R23="DOWN"),AND(J23="HOLD",R23="FLAT")),"YES","NO")) -> YES | T23: =IF(J23="","",IF(J23="BUY",1,IF(J23="SELL",-1,0))) -> 1 | U23: =IFERROR(IF(OR(J23="",N23="",P23=""),"",IF(T23=0,0,T23*Q23-Settings!$B$4/10000-IF(T23<0,Settings!$B$5/10000,0))),"") -> 0.0202 | W23: =IF($K23="","",$K23*60) -> 3600 | X23: =IF($A23="","",$A23&"|"&$C23&"|"&$D23) -> Disney|2025|Q1 | Y23: =IFERROR(IF($X23="","",INDEX(LLM_Data_Entry!$H$3:$H$548,MATCH($X23,INDEX(LLM_Data_Entry!$A$3:$A$548&"|"&LLM_Data_Entry!$C$3:$C$548&"|"&LLM_Data_Entry!$D$3:$D$548,0),0))),"") -> HOLD | Z23: =IFERROR(IF($X23="","",INDEX(LLM_Data_Entry!$R$3:$R$548,MATCH($X23,INDEX(LLM_Data_Entry!$A$3:$A$548&"|"&LLM_Data_Entry!$C$3:$C$548&"|"&LLM_Data_Entry!$D$3:$D$548,0),0))),"") -> NO | AB23: release date + stated time | AC23: DIS | AD23: 2025-02-04 | AE23: 111.2086 | AF23: 2025-02-05 | AG23: 113.5643 | AH23: 0.021182588 | AI23: UP | AJ23: YES | AK23: 0.020183 | AL23: =IF($A23="","",IFERROR(INDEX(Company_List!$G$3:$G$207,MATCH($A23,Company_List!$A$3:$A$207,0)),"unassigned")) -> P2 | AM23: Phase 2/Disney/q1-fy25-earnings-transcriptpdf.pdf | AO23: unique filename match | AP23: =IF($A23="","",IF(COUNTIFS(LLM_Data_Entry!$A$3:$A$548,$A23)>0,"YES","NO")) -> YES | AQ23: =IF($A23="","",IF(COUNTIFS($A$3:$A23,$A23,$C$3:$C23,$C23,$D$3:$D23,$D23)=1,"YES","NO")) -> YES | AR23: =IF($A23="","",IF(AND($C23&"-"&$D23>=Settings!$B$19,$C23&"-"&$D23<=Settings!$B$20),"IN","OUT")) -> IN | AS23: =IF($A23="","",IF($F23="Financial Results","financials",IF($F23="Outlook/Guidance","guidance",IF($F23="Transcript Q&A","qanda",IF($F23="","unrecorded",IF($E23="All","full",IF($E23="","unrecorded",LOWER($E23)&" only"))))))) -> full | AT23: =IF(AND(OR($J23="BUY",$J23="SELL"),ISNUMBER($U23)),$U23,"") -> 0.0202 | AU23: =IF(AND(OR($J23="BUY",$J23="SELL"),ISNUMBER($AK23)),$AK23,"") -> 0.020183 | AV23: =IF(ISNUMBER($AT23),ABS(IF(ISNUMBER($I23),$I23,0)-Settings!$B$24),"") -> 0.4 | AW23: =IF(ISNUMBER($AV23),$AV23*$AT23,"") -> 0.00808 | AX23: =IF(ISNUMBER($AU23),ABS(IF(ISNUMBER($I23),$I23,0)-Settings!$B$24),"") -> 0.4 | AY23: FROZEN | AZ23: =IF($A23="","",IFERROR(INDEX(Company_List!$H$3:$H$207,MATCH($A23,Company_List!$A$3:$A$207,0)),"unassigned")) -> Communication Services | BC23: =IF($A23="","",IF(COUNTIFS($A$3:$A23,$A23,$C$3:$C23,$C23,$D$3:$D23,$D23,$G$3:$G23,$G23)=1,1,0)) -> 1 | BG23: no | BK23: =IF(OR($H23<>"Human",$S23="",$J23="",$Y23="",$Z23=""),"",IF(EXACT(UPPER($J23),UPPER($Y23)),1,0)) -> 0 | BL23: assumed - no rater record | BM23: 1 | BN23: The Motley Fool | BO23: free to read, copyright asserted | BP23: no | BQ23: no | BS23: YES
A24: Disney | B24: =IF(A24="","",_xlfn.XLOOKUP(A24, Company_List!$A:$A, Company_List!$B:$B, "")) -> DIS | C24: 2025 | D24: Q3 | E24: All | F24: All | G24: Meriem | H24: Human | I24: 0.5 | J24: =IF(OR(I24="",Settings!$B$6=""),"",IF(I24>Settings!$B$6,"BUY",IF(I24<-Settings!$B$6,"SELL","HOLD"))) -> BUY | K24: 45 | L24: 45875 | M24: 45874 | N24: 118.32 | O24: 45875 | P24: 115.78 | Q24: =IF(OR(N24="",P24=""),"",ROUND((P24-N24)/N24,4)) -> -0.0215 | R24: =IF(OR(N24="",P24=""),"",IF(Q24>Settings!$B$3/100,"UP",IF(Q24<-Settings!$B$3/100,"DOWN","FLAT"))) -> DOWN | S24: =IF(OR(N24="",P24="",J24=""),"",IF(OR(AND(J24="BUY",R24="UP"),AND(J24="SELL",R24="DOWN"),AND(J24="HOLD",R24="FLAT")),"YES","NO")) -> NO | T24: =IF(J24="","",IF(J24="BUY",1,IF(J24="SELL",-1,0))) -> 1 | U24: =IFERROR(IF(OR(J24="",N24="",P24=""),"",IF(T24=0,0,T24*Q24-Settings!$B$4/10000-IF(T24<0,Settings!$B$5/10000,0))),"") -> -0.0225 | W24: =IF($K24="","",$K24*60) -> 2700 | X24: =IF($A24="","",$A24&"|"&$C24&"|"&$D24) -> Disney|2025|Q3 | Y24: =IFERROR(IF($X24="","",INDEX(LLM_Data_Entry!$H$3:$H$548,MATCH($X24,INDEX(LLM_Data_Entry!$A$3:$A$548&"|"&LLM_Data_Entry!$C$3:$C$548&"|"&LLM_Data_Entry!$D$3:$D$548,0),0))),"") -> HOLD | Z24: =IFERROR(IF($X24="","",INDEX(LLM_Data_Entry!$R$3:$R$548,MATCH($X24,INDEX(LLM_Data_Entry!$A$3:$A$548&"|"&LLM_Data_Entry!$C$3:$C$548&"|"&LLM_Data_Entry!$D$3:$D$548,0),0))),"") -> NO | AB24: price signal — only this window shows an abnormal move | AC24: DIS | AD24: 2025-08-05 | AE24: 116.6312 | AF24: 2025-08-06 | AG24: 114.1274 | AH24: -0.021467297 | AI24: DOWN | AJ24: NO | AK24: -0.022467 | AL24: =IF($A24="","",IFERROR(INDEX(Company_List!$G$3:$G$207,MATCH($A24,Company_List!$A$3:$A$207,0)),"unassigned")) -> P2 | AM24: Phase 2/Disney/q3-fy25-earnings-transcript.pdf | AO24: unique filename match | AP24: =IF($A24="","",IF(COUNTIFS(LLM_Data_Entry!$A$3:$A$548,$A24)>0,"YES","NO")) -> YES | AQ24: =IF($A24="","",IF(COUNTIFS($A$3:$A24,$A24,$C$3:$C24,$C24,$D$3:$D24,$D24)=1,"YES","NO")) -> YES | AR24: =IF($A24="","",IF(AND($C24&"-"&$D24>=Settings!$B$19,$C24&"-"&$D24<=Settings!$B$20),"IN","OUT")) -> IN | AS24: =IF($A24="","",IF($F24="Financial Results","financials",IF($F24="Outlook/Guidance","guidance",IF($F24="Transcript Q&A","qanda",IF($F24="","unrecorded",IF($E24="All","full",IF($E24="","unrecorded",LOWER($E24)&" only"))))))) -> full | AT24: =IF(AND(OR($J24="BUY",$J24="SELL"),ISNUMBER($U24)),$U24,"") -> -0.0225 | AU24: =IF(AND(OR($J24="BUY",$J24="SELL"),ISNUMBER($AK24)),$AK24,"") -> -0.022467 | AV24: =IF(ISNUMBER($AT24),ABS(IF(ISNUMBER($I24),$I24,0)-Settings!$B$24),"") -> 0.5 | AW24: =IF(ISNUMBER($AV24),$AV24*$AT24,"") -> -0.01125 | AX24: =IF(ISNUMBER($AU24),ABS(IF(ISNUMBER($I24),$I24,0)-Settings!$B$24),"") -> 0.5 | AY24: FROZEN | AZ24: =IF($A24="","",IFERROR(INDEX(Company_List!$H$3:$H$207,MATCH($A24,Company_List!$A$3:$A$207,0)),"unassigned")) -> Communication Services | BC24: =IF($A24="","",IF(COUNTIFS($A$3:$A24,$A24,$C$3:$C24,$C24,$D$3:$D24,$D24,$G$3:$G24,$G24)=1,1,0)) -> 1 | BG24: no | BK24: =IF(OR($H24<>"Human",$S24="",$J24="",$Y24="",$Z24=""),"",IF(EXACT(UPPER($J24),UPPER($Y24)),1,0)) -> 0 | BL24: assumed - no rater record | BM24: 1 | BN24: not publisher-identified | BO24: not publisher-identified | BP24: no | BQ24: no | BS24: YES
A25: Disney | B25: =IF(A25="","",_xlfn.XLOOKUP(A25, Company_List!$A:$A, Company_List!$B:$B, "")) -> DIS | C25: 2025 | D25: Q4 | E25: All | F25: All | G25: Meriem | H25: Human | I25: 0.6 | J25: =IF(OR(I25="",Settings!$B$6=""),"",IF(I25>Settings!$B$6,"BUY",IF(I25<-Settings!$B$6,"SELL","HOLD"))) -> BUY | K25: 60 | L25: 45974 | M25: 45973 | N25: 116.65 | O25: 45974 | P25: 108.89 | Q25: =IF(OR(N25="",P25=""),"",ROUND((P25-N25)/N25,4)) -> -0.0665 | R25: =IF(OR(N25="",P25=""),"",IF(Q25>Settings!$B$3/100,"UP",IF(Q25<-Settings!$B$3/100,"DOWN","FLAT"))) -> DOWN | S25: =IF(OR(N25="",P25="",J25=""),"",IF(OR(AND(J25="BUY",R25="UP"),AND(J25="SELL",R25="DOWN"),AND(J25="HOLD",R25="FLAT")),"YES","NO")) -> NO | T25: =IF(J25="","",IF(J25="BUY",1,IF(J25="SELL",-1,0))) -> 1 | U25: =IFERROR(IF(OR(J25="",N25="",P25=""),"",IF(T25=0,0,T25*Q25-Settings!$B$4/10000-IF(T25<0,Settings!$B$5/10000,0))),"") -> -0.0675 | W25: =IF($K25="","",$K25*60) -> 3600 | X25: =IF($A25="","",$A25&"|"&$C25&"|"&$D25) -> Disney|2025|Q4 | Y25: =IFERROR(IF($X25="","",INDEX(LLM_Data_Entry!$H$3:$H$548,MATCH($X25,INDEX(LLM_Data_Entry!$A$3:$A$548&"|"&LLM_Data_Entry!$C$3:$C$548&"|"&LLM_Data_Entry!$D$3:$D$548,0),0))),"") -> BUY | Z25: =IFERROR(IF($X25="","",INDEX(LLM_Data_Entry!$R$3:$R$548,MATCH($X25,INDEX(LLM_Data_Entry!$A$3:$A$548&"|"&LLM_Data_Entry!$C$3:$C$548&"|"&LLM_Data_Entry!$D$3:$D$548,0),0))),"") -> NO | AB25: price signal — only this window shows an abnormal move | AC25: DIS | AD25: 2025-11-12 | AE25: 114.985 | AF25: 2025-11-13 | AG25: 107.3358 | AH25: -0.066523851 | AI25: DOWN | AJ25: NO | AK25: -0.067524 | AL25: =IF($A25="","",IFERROR(INDEX(Company_List!$G$3:$G$207,MATCH($A25,Company_List!$A$3:$A$207,0)),"unassigned")) -> P2 | AM25: Phase 2/Disney/q4-fy25-earnings-transcript.pdf | AO25: unique filename match | AP25: =IF($A25="","",IF(COUNTIFS(LLM_Data_Entry!$A$3:$A$548,$A25)>0,"YES","NO")) -> YES | AQ25: =IF($A25="","",IF(COUNTIFS($A$3:$A25,$A25,$C$3:$C25,$C25,$D$3:$D25,$D25)=1,"YES","NO")) -> YES | AR25: =IF($A25="","",IF(AND($C25&"-"&$D25>=Settings!$B$19,$C25&"-"&$D25<=Settings!$B$20),"IN","OUT")) -> IN | AS25: =IF($A25="","",IF($F25="Financial Results","financials",IF($F25="Outlook/Guidance","guidance",IF($F25="Transcript Q&A","qanda",IF($F25="","unrecorded",IF($E25="All","full",IF($E25="","unrecorded",LOWER($E25)&" only"))))))) -> full | AT25: =IF(AND(OR($J25="BUY",$J25="SELL"),ISNUMBER($U25)),$U25,"") -> -0.0675 | AU25: =IF(AND(OR($J25="BUY",$J25="SELL"),ISNUMBER($AK25)),$AK25,"") -> -0.067524 | AV25: =IF(ISNUMBER($AT25),ABS(IF(ISNUMBER($I25),$I25,0)-Settings!$B$24),"") -> 0.6 | AW25: =IF(ISNUMBER($AV25),$AV25*$AT25,"") -> -0.0405 | AX25: =IF(ISNUMBER($AU25),ABS(IF(ISNUMBER($I25),$I25,0)-Settings!$B$24),"") -> 0.6 | AY25: FROZEN | AZ25: =IF($A25="","",IFERROR(INDEX(Company_List!$H$3:$H$207,MATCH($A25,Company_List!$A$3:$A$207,0)),"unassigned")) -> Communication Services | BC25: =IF($A25="","",IF(COUNTIFS($A$3:$A25,$A25,$C$3:$C25,$C25,$D$3:$D25,$D25,$G$3:$G25,$G25)=1,1,0)) -> 1 | BG25: no | BK25: =IF(OR($H25<>"Human",$S25="",$J25="",$Y25="",$Z25=""),"",IF(EXACT(UPPER($J25),UPPER($Y25)),1,0)) -> 1 | BL25: assumed - no rater record | BM25: 1 | BN25: not publisher-identified | BO25: not publisher-identified | BP25: no | BQ25: no | BS25: YES
A26: Netflix | B26: =IF(A26="","",_xlfn.XLOOKUP(A26, Company_List!$A:$A, Company_List!$B:$B, "")) -> NFLX | C26: 2025 | D26: Q3 | E26: Transcript | F26: All | G26: David | H26: Human | I26: 0.5 | J26: =IF(OR(I26="",Settings!$B$6=""),"",IF(I26>Settings!$B$6,"BUY",IF(I26<-Settings!$B$6,"SELL","HOLD"))) -> BUY | K26: 62 | L26: 45951 | M26: 45951 | N26: 124.135 | O26: 45952 | P26: 114.29 | Q26: =IF(OR(N26="",P26=""),"",ROUND((P26-N26)/N26,4)) -> -0.0793 | R26: =IF(OR(N26="",P26=""),"",IF(Q26>Settings!$B$3/100,"UP",IF(Q26<-Settings!$B$3/100,"DOWN","FLAT"))) -> DOWN | S26: =IF(OR(N26="",P26="",J26=""),"",IF(OR(AND(J26="BUY",R26="UP"),AND(J26="SELL",R26="DOWN"),AND(J26="HOLD",R26="FLAT")),"YES","NO")) -> NO | T26: =IF(J26="","",IF(J26="BUY",1,IF(J26="SELL",-1,0))) -> 1 | U26: =IFERROR(IF(OR(J26="",N26="",P26=""),"",IF(T26=0,0,T26*Q26-Settings!$B$4/10000-IF(T26<0,Settings!$B$5/10000,0))),"") -> -0.0803 | W26: =IF($K26="","",$K26*60) -> 3720 | X26: =IF($A26="","",$A26&"|"&$C26&"|"&$D26) -> Netflix|2025|Q3 | Y26: =IFERROR(IF($X26="","",INDEX(LLM_Data_Entry!$H$3:$H$548,MATCH($X26,INDEX(LLM_Data_Entry!$A$3:$A$548&"|"&LLM_Data_Entry!$C$3:$C$548&"|"&LLM_Data_Entry!$D$3:$D$548,0),0))),"") -> HOLD | Z26: =IFERROR(IF($X26="","",INDEX(LLM_Data_Entry!$R$3:$R$548,MATCH($X26,INDEX(LLM_Data_Entry!$A$3:$A$548&"|"&LLM_Data_Entry!$C$3:$C$548&"|"&LLM_Data_Entry!$D$3:$D$548,0),0))),"") -> NO | AB26: release date + stated time in the document (rater worksheet) | AC26: NFLX | AD26: 2025-10-21 | AE26: 124.135 | AF26: 2025-10-22 | AG26: 114.29 | AH26: -0.079308824 | AI26: DOWN | AJ26: NO | AK26: -0.080309 | AL26: =IF($A26="","",IFERROR(INDEX(Company_List!$G$3:$G$207,MATCH($A26,Company_List!$A$3:$A$207,0)),"unassigned")) -> P2 | AM26: Phase 2/Netflix/2025-Q3/NFLX-2025-Q3-press-release-SEC-EX-99-1.htm | AN26: https://www.sec.gov/Archives/edgar/data/1065280/000106528025000404/ex991_q325.htm | AO26: manifest | AP26: =IF($A26="","",IF(COUNTIFS(LLM_Data_Entry!$A$3:$A$548,$A26)>0,"YES","NO")) -> YES | AQ26: =IF($A26="","",IF(COUNTIFS($A$3:$A26,$A26,$C$3:$C26,$C26,$D$3:$D26,$D26)=1,"YES","NO")) -> NO | AR26: =IF($A26="","",IF(AND($C26&"-"&$D26>=Settings!$B$19,$C26&"-"&$D26<=Settings!$B$20),"IN","OUT")) -> IN | AS26: =IF($A26="","",IF($F26="Financial Results","financials",IF($F26="Outlook/Guidance","guidance",IF($F26="Transcript Q&A","qanda",IF($F26="","unrecorded",IF($E26="All","full",IF($E26="","unrecorded",LOWER($E26)&" only"))))))) -> transcript only | AT26: =IF(AND(OR($J26="BUY",$J26="SELL"),ISNUMBER($U26)),$U26,"") -> -0.0803 | AU26: =IF(AND(OR($J26="BUY",$J26="SELL"),ISNUMBER($AK26)),$AK26,"") -> -0.080309 | AV26: =IF(ISNUMBER($AT26),ABS(IF(ISNUMBER($I26),$I26,0)-Settings!$B$24),"") -> 0.5 | AW26: =IF(ISNUMBER($AV26),$AV26*$AT26,"") -> -0.04015 | AX26: =IF(ISNUMBER($AU26),ABS(IF(ISNUMBER($I26),$I26,0)-Settings!$B$24),"") -> 0.5 | AY26: FROZEN | AZ26: =IF($A26="","",IFERROR(INDEX(Company_List!$H$3:$H$207,MATCH($A26,Company_List!$A$3:$A$207,0)),"unassigned")) -> Communication Services | BC26: =IF($A26="","",IF(COUNTIFS($A$3:$A26,$A26,$C$3:$C26,$C26,$D$3:$D26,$D26,$G$3:$G26,$G26)=1,1,0)) -> 1 | BG26: no | BK26: =IF(OR($H26<>"Human",$S26="",$J26="",$Y26="",$Z26=""),"",IF(EXACT(UPPER($J26),UPPER($Y26)),1,0)) -> 0 | BL26: assumed - no rater record | BM26: 1 | BN26: not publisher-identified | BO26: not publisher-identified | BP26: no | BQ26: yes | BR26: filled 11 Aug 2026 from the corpus manifest: the company-quarter holds exactly one document and the manifest carries its release date | BS26: YES
A27: Netflix | B27: =IF(A27="","",_xlfn.XLOOKUP(A27, Company_List!$A:$A, Company_List!$B:$B, "")) -> NFLX | C27: 2025 | D27: Q4 | E27: Transcript | F27: All | G27: David | H27: Human | I27: 0.6 | J27: =IF(OR(I27="",Settings!$B$6=""),"",IF(I27>Settings!$B$6,"BUY",IF(I27<-Settings!$B$6,"SELL","HOLD"))) -> BUY | K27: 60 | L27: 46042 | M27: 46042 | N27: 87.26 | O27: 46043 | P27: 82.52 | Q27: =IF(OR(N27="",P27=""),"",ROUND((P27-N27)/N27,4)) -> -0.0543 | R27: =IF(OR(N27="",P27=""),"",IF(Q27>Settings!$B$3/100,"UP",IF(Q27<-Settings!$B$3/100,"DOWN","FLAT"))) -> DOWN | S27: =IF(OR(N27="",P27="",J27=""),"",IF(OR(AND(J27="BUY",R27="UP"),AND(J27="SELL",R27="DOWN"),AND(J27="HOLD",R27="FLAT")),"YES","NO")) -> NO | T27: =IF(J27="","",IF(J27="BUY",1,IF(J27="SELL",-1,0))) -> 1 | U27: =IFERROR(IF(OR(J27="",N27="",P27=""),"",IF(T27=0,0,T27*Q27-Settings!$B$4/10000-IF(T27<0,Settings!$B$5/10000,0))),"") -> -0.0553 | W27: =IF($K27="","",$K27*60) -> 3600 | X27: =IF($A27="","",$A27&"|"&$C27&"|"&$D27) -> Netflix|2025|Q4 | Y27: =IFERROR(IF($X27="","",INDEX(LLM_Data_Entry!$H$3:$H$548,MATCH($X27,INDEX(LLM_Data_Entry!$A$3:$A$548&"|"&LLM_Data_Entry!$C$3:$C$548&"|"&LLM_Data_Entry!$D$3:$D$548,0),0))),"") -> BUY | Z27: =IFERROR(IF($X27="","",INDEX(LLM_Data_Entry!$R$3:$R$548,MATCH($X27,INDEX(LLM_Data_Entry!$A$3:$A$548&"|"&LLM_Data_Entry!$C$3:$C$548&"|"&LLM_Data_Entry!$D$3:$D$548,0),0))),"") -> NO | AB27: release date + stated time in the document (rater worksheet) | AC27: NFLX | AD27: 2026-01-20 | AE27: 87.26 | AF27: 2026-01-21 | AG27: 82.52 | AH27: -0.054320478 | AI27: DOWN | AJ27: NO | AK27: -0.05532 | AL27: =IF($A27="","",IFERROR(INDEX(Company_List!$G$3:$G$207,MATCH($A27,Company_List!$A$3:$A$207,0)),"unassigned")) -> P2 | AM27: Phase 2/Netflix/2025-Q4/NFLX-2025-Q4-press-release-SEC-EX-99-1.htm | AN27: https://www.sec.gov/Archives/edgar/data/1065280/000106528026000033/ex991_q425.htm | AO27: manifest | AP27: =IF($A27="","",IF(COUNTIFS(LLM_Data_Entry!$A$3:$A$548,$A27)>0,"YES","NO")) -> YES | AQ27: =IF($A27="","",IF(COUNTIFS($A$3:$A27,$A27,$C$3:$C27,$C27,$D$3:$D27,$D27)=1,"YES","NO")) -> NO | AR27: =IF($A27="","",IF(AND($C27&"-"&$D27>=Settings!$B$19,$C27&"-"&$D27<=Settings!$B$20),"IN","OUT")) -> IN | AS27: =IF($A27="","",IF($F27="Financial Results","financials",IF($F27="Outlook/Guidance","guidance",IF($F27="Transcript Q&A","qanda",IF($F27="","unrecorded",IF($E27="All","full",IF($E27="","unrecorded",LOWER($E27)&" only"))))))) -> transcript only | AT27: =IF(AND(OR($J27="BUY",$J27="SELL"),ISNUMBER($U27)),$U27,"") -> -0.0553 | AU27: =IF(AND(OR($J27="BUY",$J27="SELL"),ISNUMBER($AK27)),$AK27,"") -> -0.05532 | AV27: =IF(ISNUMBER($AT27),ABS(IF(ISNUMBER($I27),$I27,0)-Settings!$B$24),"") -> 0.6 | AW27: =IF(ISNUMBER($AV27),$AV27*$AT27,"") -> -0.03318 | AX27: =IF(ISNUMBER($AU27),ABS(IF(ISNUMBER($I27),$I27,0)-Settings!$B$24),"") -> 0.6 | AY27: FROZEN | AZ27: =IF($A27="","",IFERROR(INDEX(Company_List!$H$3:$H$207,MATCH($A27,Company_List!$A$3:$A$207,0)),"unassigned")) -> Communication Services | BC27: =IF($A27="","",IF(COUNTIFS($A$3:$A27,$A27,$C$3:$C27,$C27,$D$3:$D27,$D27,$G$3:$G27,$G27)=1,1,0)) -> 1 | BG27: no | BK27: =IF(OR($H27<>"Human",$S27="",$J27="",$Y27="",$Z27=""),"",IF(EXACT(UPPER($J27),UPPER($Y27)),1,0)) -> 1 | BL27: assumed - no rater record | BM27: 1 | BN27: not publisher-identified | BO27: not publisher-identified | BP27: no | BQ27: yes | BR27: filled 11 Aug 2026 from the corpus manifest: the company-quarter holds exactly one document and the manifest carries its release date | BS27: YES
A28: Netflix | B28: =IF(A28="","",_xlfn.XLOOKUP(A28, Company_List!$A:$A, Company_List!$B:$B, "")) -> NFLX | C28: 2024 | D28: Q4 | E28: Transcript | F28: All | G28: David | H28: Human | I28: 0.8 | J28: =IF(OR(I28="",Settings!$B$6=""),"",IF(I28>Settings!$B$6,"BUY",IF(I28<-Settings!$B$6,"SELL","HOLD"))) -> BUY | K28: 47 | L28: 45678 | M28: 45678 | N28: 86.968 | O28: 45679 | P28: 99.8 | Q28: =IF(OR(N28="",P28=""),"",ROUND((P28-N28)/N28,4)) -> 0.1475 | R28: =IF(OR(N28="",P28=""),"",IF(Q28>Settings!$B$3/100,"UP",IF(Q28<-Settings!$B$3/100,"DOWN","FLAT"))) -> UP | S28: =IF(OR(N28="",P28="",J28=""),"",IF(OR(AND(J28="BUY",R28="UP"),AND(J28="SELL",R28="DOWN"),AND(J28="HOLD",R28="FLAT")),"YES","NO")) -> YES | T28: =IF(J28="","",IF(J28="BUY",1,IF(J28="SELL",-1,0))) -> 1 | U28: =IFERROR(IF(OR(J28="",N28="",P28=""),"",IF(T28=0,0,T28*Q28-Settings!$B$4/10000-IF(T28<0,Settings!$B$5/10000,0))),"") -> 0.1465 | W28: =IF($K28="","",$K28*60) -> 2820 | X28: =IF($A28="","",$A28&"|"&$C28&"|"&$D28) -> Netflix|2024|Q4 | Y28: =IFERROR(IF($X28="","",INDEX(LLM_Data_Entry!$H$3:$H$548,MATCH($X28,INDEX(LLM_Data_Entry!$A$3:$A$548&"|"&LLM_Data_Entry!$C$3:$C$548&"|"&LLM_Data_Entry!$D$3:$D$548,0),0))),"") -> BUY | Z28: =IFERROR(IF($X28="","",INDEX(LLM_Data_Entry!$R$3:$R$548,MATCH($X28,INDEX(LLM_Data_Entry!$A$3:$A$548&"|"&LLM_Data_Entry!$C$3:$C$548&"|"&LLM_Data_Entry!$D$3:$D$548,0),0))),"") -> YES | AB28: release date + stated time in the document (rater worksheet) | AC28: NFLX | AD28: 2025-01-21 | AE28: 86.968 | AF28: 2025-01-22 | AG28: 99.803 | AH28: 0.147583 | AI28: UP | AJ28: YES | AK28: 0.146583 | AL28: =IF($A28="","",IFERROR(INDEX(Company_List!$G$3:$G$207,MATCH($A28,Company_List!$A$3:$A$207,0)),"unassigned")) -> P2 | AM28: Phase 2/Netflix/2024-Q4/NFLX-2024-Q4-press-release-SEC-EX-99-1.htm | AN28: https://www.sec.gov/Archives/edgar/data/1065280/000106528025000033/ex991_q424.htm | AO28: manifest | AP28: =IF($A28="","",IF(COUNTIFS(LLM_Data_Entry!$A$3:$A$548,$A28)>0,"YES","NO")) -> YES | AQ28: =IF($A28="","",IF(COUNTIFS($A$3:$A28,$A28,$C$3:$C28,$C28,$D$3:$D28,$D28)=1,"YES","NO")) -> YES | AR28: =IF($A28="","",IF(AND($C28&"-"&$D28>=Settings!$B$19,$C28&"-"&$D28<=Settings!$B$20),"IN","OUT")) -> IN | AS28: =IF($A28="","",IF($F28="Financial Results","financials",IF($F28="Outlook/Guidance","guidance",IF($F28="Transcript Q&A","qanda",IF($F28="","unrecorded",IF($E28="All","full",IF($E28="","unrecorded",LOWER($E28)&" only"))))))) -> transcript only | AT28: =IF(AND(OR($J28="BUY",$J28="SELL"),ISNUMBER($U28)),$U28,"") -> 0.1465 | AU28: =IF(AND(OR($J28="BUY",$J28="SELL"),ISNUMBER($AK28)),$AK28,"") -> 0.146583 | AV28: =IF(ISNUMBER($AT28),ABS(IF(ISNUMBER($I28),$I28,0)-Settings!$B$24),"") -> 0.8 | AW28: =IF(ISNUMBER($AV28),$AV28*$AT28,"") -> 0.1172 | AX28: =IF(ISNUMBER($AU28),ABS(IF(ISNUMBER($I28),$I28,0)-Settings!$B$24),"") -> 0.8 | AY28: FROZEN | AZ28: =IF($A28="","",IFERROR(INDEX(Company_List!$H$3:$H$207,MATCH($A28,Company_List!$A$3:$A$207,0)),"unassigned")) -> Communication Services | BC28: =IF($A28="","",IF(COUNTIFS($A$3:$A28,$A28,$C$3:$C28,$C28,$D$3:$D28,$D28,$G$3:$G28,$G28)=1,1,0)) -> 1 | BG28: no | BK28: =IF(OR($H28<>"Human",$S28="",$J28="",$Y28="",$Z28=""),"",IF(EXACT(UPPER($J28),UPPER($Y28)),1,0)) -> 1 | BL28: assumed - no rater record | BM28: 1 | BN28: not publisher-identified | BO28: not publisher-identified | BP28: no | BQ28: yes | BR28: filled 11 Aug 2026 from the corpus manifest: the company-quarter holds exactly one document and the manifest carries its release date | BS28: YES
A29: Amazon | B29: =IF(A29="","",_xlfn.XLOOKUP(A29, Company_List!$A:$A, Company_List!$B:$B, "")) -> AMZN | C29: 2026 | D29: Q1 | E29: All | F29: All | G29: David | H29: Human | I29: 0.8 | J29: =IF(OR(I29="",Settings!$B$6=""),"",IF(I29>Settings!$B$6,"BUY",IF(I29<-Settings!$B$6,"SELL","HOLD"))) -> BUY | K29: 52 | L29: 46141 | M29: 46141 | N29: 263.04 | O29: 46142 | P29: 273.17 | Q29: =IF(OR(N29="",P29=""),"",ROUND((P29-N29)/N29,4)) -> 0.0385 | R29: =IF(OR(N29="",P29=""),"",IF(Q29>Settings!$B$3/100,"UP",IF(Q29<-Settings!$B$3/100,"DOWN","FLAT"))) -> UP | S29: =IF(OR(N29="",P29="",J29=""),"",IF(OR(AND(J29="BUY",R29="UP"),AND(J29="SELL",R29="DOWN"),AND(J29="HOLD",R29="FLAT")),"YES","NO")) -> YES | T29: =IF(J29="","",IF(J29="BUY",1,IF(J29="SELL",-1,0))) -> 1 | U29: =IFERROR(IF(OR(J29="",N29="",P29=""),"",IF(T29=0,0,T29*Q29-Settings!$B$4/10000-IF(T29<0,Settings!$B$5/10000,0))),"") -> 0.0375 | W29: =IF($K29="","",$K29*60) -> 3120 | X29: =IF($A29="","",$A29&"|"&$C29&"|"&$D29) -> Amazon|2026|Q1 | Y29: =IFERROR(IF($X29="","",INDEX(LLM_Data_Entry!$H$3:$H$548,MATCH($X29,INDEX(LLM_Data_Entry!$A$3:$A$548&"|"&LLM_Data_Entry!$C$3:$C$548&"|"&LLM_Data_Entry!$D$3:$D$548,0),0))),"") -> BUY | Z29: =IFERROR(IF($X29="","",INDEX(LLM_Data_Entry!$R$3:$R$548,MATCH($X29,INDEX(LLM_Data_Entry!$A$3:$A$548&"|"&LLM_Data_Entry!$C$3:$C$548&"|"&LLM_Data_Entry!$D$3:$D$548,0),0))),"") -> YES | AB29: release date + stated time in the document (rater worksheet) | AC29: AMZN | AD29: 2026-04-29 | AE29: 263.04 | AF29: 2026-04-30 | AG29: 273.17 | AH29: 0.038511267 | AI29: UP | AJ29: YES | AK29: 0.037511 | AL29: =IF($A29="","",IFERROR(INDEX(Company_List!$G$3:$G$207,MATCH($A29,Company_List!$A$3:$A$207,0)),"unassigned")) -> P2 | AM29: Phase 2/Amazon/2026-Q1/AMZN-2026-Q1-press-release-SEC-EX-99-1.htm | AN29: https://www.sec.gov/Archives/edgar/data/1018724/000101872426000012/amzn-20260331xex991.htm | AO29: manifest | AP29: =IF($A29="","",IF(COUNTIFS(LLM_Data_Entry!$A$3:$A$548,$A29)>0,"YES","NO")) -> YES | AQ29: =IF($A29="","",IF(COUNTIFS($A$3:$A29,$A29,$C$3:$C29,$C29,$D$3:$D29,$D29)=1,"YES","NO")) -> YES | AR29: =IF($A29="","",IF(AND($C29&"-"&$D29>=Settings!$B$19,$C29&"-"&$D29<=Settings!$B$20),"IN","OUT")) -> IN | AS29: =IF($A29="","",IF($F29="Financial Results","financials",IF($F29="Outlook/Guidance","guidance",IF($F29="Transcript Q&A","qanda",IF($F29="","unrecorded",IF($E29="All","full",IF($E29="","unrecorded",LOWER($E29)&" only"))))))) -> full | AT29: =IF(AND(OR($J29="BUY",$J29="SELL"),ISNUMBER($U29)),$U29,"") -> 0.0375 | AU29: =IF(AND(OR($J29="BUY",$J29="SELL"),ISNUMBER($AK29)),$AK29,"") -> 0.037511 | AV29: =IF(ISNUMBER($AT29),ABS(IF(ISNUMBER($I29),$I29,0)-Settings!$B$24),"") -> 0.8 | AW29: =IF(ISNUMBER($AV29),$AV29*$AT29,"") -> 0.03 | AX29: =IF(ISNUMBER($AU29),ABS(IF(ISNUMBER($I29),$I29,0)-Settings!$B$24),"") -> 0.8 | AY29: FROZEN | AZ29: =IF($A29="","",IFERROR(INDEX(Company_List!$H$3:$H$207,MATCH($A29,Company_List!$A$3:$A$207,0)),"unassigned")) -> Consumer Discretionary | BC29: =IF($A29="","",IF(COUNTIFS($A$3:$A29,$A29,$C$3:$C29,$C29,$D$3:$D29,$D29,$G$3:$G29,$G29)=1,1,0)) -> 1 | BG29: no | BK29: =IF(OR($H29<>"Human",$S29="",$J29="",$Y29="",$Z29=""),"",IF(EXACT(UPPER($J29),UPPER($Y29)),1,0)) -> 1 | BL29: assumed - no rater record | BM29: 1 | BN29: not publisher-identified | BO29: not publisher-identified | BP29: no | BQ29: yes | BR29: filled 11 Aug 2026 from the corpus manifest: the company-quarter holds exactly one document and the manifest carries its release date | BS29: YES
A30: Amazon | B30: =IF(A30="","",_xlfn.XLOOKUP(A30, Company_List!$A:$A, Company_List!$B:$B, "")) -> AMZN | C30: 2025 | D30: Q3 | E30: All | F30: All | G30: David | H30: Human | I30: -0.5 | J30: =IF(OR(I30="",Settings!$B$6=""),"",IF(I30>Settings!$B$6,"BUY",IF(I30<-Settings!$B$6,"SELL","HOLD"))) -> SELL | K30: 47 | L30: 45960 | M30: 45960 | N30: 222.86 | O30: 45961 | P30: 250.1 | Q30: =IF(OR(N30="",P30=""),"",ROUND((P30-N30)/N30,4)) -> 0.1222 | R30: =IF(OR(N30="",P30=""),"",IF(Q30>Settings!$B$3/100,"UP",IF(Q30<-Settings!$B$3/100,"DOWN","FLAT"))) -> UP | S30: =IF(OR(N30="",P30="",J30=""),"",IF(OR(AND(J30="BUY",R30="UP"),AND(J30="SELL",R30="DOWN"),AND(J30="HOLD",R30="FLAT")),"YES","NO")) -> NO | T30: =IF(J30="","",IF(J30="BUY",1,IF(J30="SELL",-1,0))) -> -1 | U30: =IFERROR(IF(OR(J30="",N30="",P30=""),"",IF(T30=0,0,T30*Q30-Settings!$B$4/10000-IF(T30<0,Settings!$B$5/10000,0))),"") -> -0.1232 | W30: =IF($K30="","",$K30*60) -> 2820 | X30: =IF($A30="","",$A30&"|"&$C30&"|"&$D30) -> Amazon|2025|Q3 | Y30: =IFERROR(IF($X30="","",INDEX(LLM_Data_Entry!$H$3:$H$548,MATCH($X30,INDEX(LLM_Data_Entry!$A$3:$A$548&"|"&LLM_Data_Entry!$C$3:$C$548&"|"&LLM_Data_Entry!$D$3:$D$548,0),0))),"") -> SELL | Z30: =IFERROR(IF($X30="","",INDEX(LLM_Data_Entry!$R$3:$R$548,MATCH($X30,INDEX(LLM_Data_Entry!$A$3:$A$548&"|"&LLM_Data_Entry!$C$3:$C$548&"|"&LLM_Data_Entry!$D$3:$D$548,0),0))),"") -> NO | AB30: release date + stated time in the document (rater worksheet) | AC30: AMZN | AD30: 2025-10-30 | AE30: 222.86 | AF30: 2025-10-31 | AG30: 250.1 | AH30: 0.12222922 | AI30: UP | AJ30: NO | AK30: -0.123229 | AL30: =IF($A30="","",IFERROR(INDEX(Company_List!$G$3:$G$207,MATCH($A30,Company_List!$A$3:$A$207,0)),"unassigned")) -> P2 | AM30: Phase 2/Amazon/2025-Q3/AMZN-2025-Q3-press-release-SEC-EX-99-1.htm | AN30: https://www.sec.gov/Archives/edgar/data/1018724/000101872425000121/amzn-20250930xex991.htm | AO30: manifest | AP30: =IF($A30="","",IF(COUNTIFS(LLM_Data_Entry!$A$3:$A$548,$A30)>0,"YES","NO")) -> YES | AQ30: =IF($A30="","",IF(COUNTIFS($A$3:$A30,$A30,$C$3:$C30,$C30,$D$3:$D30,$D30)=1,"YES","NO")) -> YES | AR30: =IF($A30="","",IF(AND($C30&"-"&$D30>=Settings!$B$19,$C30&"-"&$D30<=Settings!$B$20),"IN","OUT")) -> IN | AS30: =IF($A30="","",IF($F30="Financial Results","financials",IF($F30="Outlook/Guidance","guidance",IF($F30="Transcript Q&A","qanda",IF($F30="","unrecorded",IF($E30="All","full",IF($E30="","unrecorded",LOWER($E30)&" only"))))))) -> full | AT30: =IF(AND(OR($J30="BUY",$J30="SELL"),ISNUMBER($U30)),$U30,"") -> -0.1232 | AU30: =IF(AND(OR($J30="BUY",$J30="SELL"),ISNUMBER($AK30)),$AK30,"") -> -0.123229 | AV30: =IF(ISNUMBER($AT30),ABS(IF(ISNUMBER($I30),$I30,0)-Settings!$B$24),"") -> 0.5 | AW30: =IF(ISNUMBER($AV30),$AV30*$AT30,"") -> -0.0616 | AX30: =IF(ISNUMBER($AU30),ABS(IF(ISNUMBER($I30),$I30,0)-Settings!$B$24),"") -> 0.5 | AY30: FROZEN | AZ30: =IF($A30="","",IFERROR(INDEX(Company_List!$H$3:$H$207,MATCH($A30,Company_List!$A$3:$A$207,0)),"unassigned")) -> Consumer Discretionary | BC30: =IF($A30="","",IF(COUNTIFS($A$3:$A30,$A30,$C$3:$C30,$C30,$D$3:$D30,$D30,$G$3:$G30,$G30)=1,1,0)) -> 1 | BG30: no | BK30: =IF(OR($H30<>"Human",$S30="",$J30="",$Y30="",$Z30=""),"",IF(EXACT(UPPER($J30),UPPER($Y30)),1,0)) -> 1 | BL30: assumed - no rater record | BM30: 1 | BN30: not publisher-identified | BO30: not publisher-identified | BP30: no | BQ30: yes | BR30: filled 11 Aug 2026 from the corpus manifest: the company-quarter holds exactly one document and the manifest carries its release date | BS30: YES
A31: Amazon | B31: =IF(A31="","",_xlfn.XLOOKUP(A31, Company_List!$A:$A, Company_List!$B:$B, "")) -> AMZN | C31: 2025 | D31: Q4 | E31: All | F31: All | G31: David | H31: Human | I31: 0.3 | J31: =IF(OR(I31="",Settings!$B$6=""),"",IF(I31>Settings!$B$6,"BUY",IF(I31<-Settings!$B$6,"SELL","HOLD"))) -> BUY | K31: 58 | L31: 46058 | M31: 46058 | N31: 222.69 | O31: 46059 | P31: 202.7 | Q31: =IF(OR(N31="",P31=""),"",ROUND((P31-N31)/N31,4)) -> -0.0898 | R31: =IF(OR(N31="",P31=""),"",IF(Q31>Settings!$B$3/100,"UP",IF(Q31<-Settings!$B$3/100,"DOWN","FLAT"))) -> DOWN | S31: =IF(OR(N31="",P31="",J31=""),"",IF(OR(AND(J31="BUY",R31="UP"),AND(J31="SELL",R31="DOWN"),AND(J31="HOLD",R31="FLAT")),"YES","NO")) -> NO | T31: =IF(J31="","",IF(J31="BUY",1,IF(J31="SELL",-1,0))) -> 1 | U31: =IFERROR(IF(OR(J31="",N31="",P31=""),"",IF(T31=0,0,T31*Q31-Settings!$B$4/10000-IF(T31<0,Settings!$B$5/10000,0))),"") -> -0.0908 | W31: =IF($K31="","",$K31*60) -> 3480 | X31: =IF($A31="","",$A31&"|"&$C31&"|"&$D31) -> Amazon|2025|Q4 | Y31: =IFERROR(IF($X31="","",INDEX(LLM_Data_Entry!$H$3:$H$548,MATCH($X31,INDEX(LLM_Data_Entry!$A$3:$A$548&"|"&LLM_Data_Entry!$C$3:$C$548&"|"&LLM_Data_Entry!$D$3:$D$548,0),0))),"") -> SELL | Z31: =IFERROR(IF($X31="","",INDEX(LLM_Data_Entry!$R$3:$R$548,MATCH($X31,INDEX(LLM_Data_Entry!$A$3:$A$548&"|"&LLM_Data_Entry!$C$3:$C$548&"|"&LLM_Data_Entry!$D$3:$D$548,0),0))),"") -> YES | AB31: recorded price identified against every pulled series | AC31: AMZN | AD31: 2026-02-05 | AE31: 222.69 | AF31: 2026-02-06 | AG31: 202.7 | AH31: -0.089766064 | AI31: DOWN | AJ31: NO | AK31: -0.090766 | AL31: =IF($A31="","",IFERROR(INDEX(Company_List!$G$3:$G$207,MATCH($A31,Company_List!$A$3:$A$207,0)),"unassigned")) -> P2 | AM31: Phase 2/Amazon/2025-Q4/AMZN-2025-Q4-press-release-SEC-EX-99-1.htm | AN31: https://www.sec.gov/Archives/edgar/data/1018724/000101872426000002/amzn-20251231xex991.htm | AO31: manifest | AP31: =IF($A31="","",IF(COUNTIFS(LLM_Data_Entry!$A$3:$A$548,$A31)>0,"YES","NO")) -> YES | AQ31: =IF($A31="","",IF(COUNTIFS($A$3:$A31,$A31,$C$3:$C31,$C31,$D$3:$D31,$D31)=1,"YES","NO")) -> YES | AR31: =IF($A31="","",IF(AND($C31&"-"&$D31>=Settings!$B$19,$C31&"-"&$D31<=Settings!$B$20),"IN","OUT")) -> IN | AS31: =IF($A31="","",IF($F31="Financial Results","financials",IF($F31="Outlook/Guidance","guidance",IF($F31="Transcript Q&A","qanda",IF($F31="","unrecorded",IF($E31="All","full",IF($E31="","unrecorded",LOWER($E31)&" only"))))))) -> full | AT31: =IF(AND(OR($J31="BUY",$J31="SELL"),ISNUMBER($U31)),$U31,"") -> -0.0908 | AU31: =IF(AND(OR($J31="BUY",$J31="SELL"),ISNUMBER($AK31)),$AK31,"") -> -0.090766 | AV31: =IF(ISNUMBER($AT31),ABS(IF(ISNUMBER($I31),$I31,0)-Settings!$B$24),"") -> 0.3 | AW31: =IF(ISNUMBER($AV31),$AV31*$AT31,"") -> -0.02724 | AX31: =IF(ISNUMBER($AU31),ABS(IF(ISNUMBER($I31),$I31,0)-Settings!$B$24),"") -> 0.3 | AY31: FROZEN | AZ31: =IF($A31="","",IFERROR(INDEX(Company_List!$H$3:$H$207,MATCH($A31,Company_List!$A$3:$A$207,0)),"unassigned")) -> Consumer Discretionary | BC31: =IF($A31="","",IF(COUNTIFS($A$3:$A31,$A31,$C$3:$C31,$C31,$D$3:$D31,$D31,$G$3:$G31,$G31)=1,1,0)) -> 1 | BG31: no | BK31: =IF(OR($H31<>"Human",$S31="",$J31="",$Y31="",$Z31=""),"",IF(EXACT(UPPER($J31),UPPER($Y31)),1,0)) -> 0 | BL31: assumed - no rater record | BM31: 1 | BN31: not publisher-identified | BO31: not publisher-identified | BP31: no | BQ31: yes | BR31: filled 11 Aug 2026 from the corpus manifest: the company-quarter holds exactly one document and the manifest carries its release date | BS31: YES
A32: McDonald's | B32: =IF(A32="","",_xlfn.XLOOKUP(A32, Company_List!$A:$A, Company_List!$B:$B, "")) -> MCD | C32: 2024 | D32: Q4 | E32: All | F32: All | G32: Meriem | H32: Human | I32: -0.5 | J32: =IF(OR(I32="",Settings!$B$6=""),"",IF(I32>Settings!$B$6,"BUY",IF(I32<-Settings!$B$6,"SELL","HOLD"))) -> SELL | K32: 30 | L32: 45698 | M32: 45695 | N32: 294.3 | O32: 45698 | P32: 302.27 | Q32: =IF(OR(N32="",P32=""),"",ROUND((P32-N32)/N32,4)) -> 0.0271 | R32: =IF(OR(N32="",P32=""),"",IF(Q32>Settings!$B$3/100,"UP",IF(Q32<-Settings!$B$3/100,"DOWN","FLAT"))) -> UP | S32: =IF(OR(N32="",P32="",J32=""),"",IF(OR(AND(J32="BUY",R32="UP"),AND(J32="SELL",R32="DOWN"),AND(J32="HOLD",R32="FLAT")),"YES","NO")) -> NO | T32: =IF(J32="","",IF(J32="BUY",1,IF(J32="SELL",-1,0))) -> -1 | U32: =IFERROR(IF(OR(J32="",N32="",P32=""),"",IF(T32=0,0,T32*Q32-Settings!$B$4/10000-IF(T32<0,Settings!$B$5/10000,0))),"") -> -0.0281 | V32: sales went down; revenue asw; EPS diluted down; net income and Current +total assets down; long term debt up. No guidance | W32: =IF($K32="","",$K32*60) -> 1800 | X32: =IF($A32="","",$A32&"|"&$C32&"|"&$D32) -> McDonald's|2024|Q4 | Y32: =IFERROR(IF($X32="","",INDEX(LLM_Data_Entry!$H$3:$H$548,MATCH($X32,INDEX(LLM_Data_Entry!$A$3:$A$548&"|"&LLM_Data_Entry!$C$3:$C$548&"|"&LLM_Data_Entry!$D$3:$D$548,0),0))),"") -> SELL | Z32: =IFERROR(IF($X32="","",INDEX(LLM_Data_Entry!$R$3:$R$548,MATCH($X32,INDEX(LLM_Data_Entry!$A$3:$A$548&"|"&LLM_Data_Entry!$C$3:$C$548&"|"&LLM_Data_Entry!$D$3:$D$548,0),0))),"") -> NO | AB32: price signal — only this window shows an abnormal move | AC32: MCD | AD32: 2025-02-07 | AE32: 284.0678 | AF32: 2025-02-10 | AG32: 291.7607 | AH32: 0.027081169 | AI32: UP | AJ32: NO | AK32: -0.028081 | AL32: =IF($A32="","",IFERROR(INDEX(Company_List!$G$3:$G$207,MATCH($A32,Company_List!$A$3:$A$207,0)),"unassigned")) -> P2 | AM32: Phase 2/McDonald's/Q4 2024-numbers.pdf; Phase 2/McDonald's/Q4 2024 Earnings Call Transcript.pdf | AO32: whole bundle (Document = All) | AP32: =IF($A32="","",IF(COUNTIFS(LLM_Data_Entry!$A$3:$A$548,$A32)>0,"YES","NO")) -> YES | AQ32: =IF($A32="","",IF(COUNTIFS($A$3:$A32,$A32,$C$3:$C32,$C32,$D$3:$D32,$D32)=1,"YES","NO")) -> YES | AR32: =IF($A32="","",IF(AND($C32&"-"&$D32>=Settings!$B$19,$C32&"-"&$D32<=Settings!$B$20),"IN","OUT")) -> IN | AS32: =IF($A32="","",IF($F32="Financial Results","financials",IF($F32="Outlook/Guidance","guidance",IF($F32="Transcript Q&A","qanda",IF($F32="","unrecorded",IF($E32="All","full",IF($E32="","unrecorded",LOWER($E32)&" only"))))))) -> full | AT32: =IF(AND(OR($J32="BUY",$J32="SELL"),ISNUMBER($U32)),$U32,"") -> -0.0281 | AU32: =IF(AND(OR($J32="BUY",$J32="SELL"),ISNUMBER($AK32)),$AK32,"") -> -0.028081 | AV32: =IF(ISNUMBER($AT32),ABS(IF(ISNUMBER($I32),$I32,0)-Settings!$B$24),"") -> 0.5 | AW32: =IF(ISNUMBER($AV32),$AV32*$AT32,"") -> -0.01405 | AX32: =IF(ISNUMBER($AU32),ABS(IF(ISNUMBER($I32),$I32,0)-Settings!$B$24),"") -> 0.5 | AY32: FROZEN | AZ32: =IF($A32="","",IFERROR(INDEX(Company_List!$H$3:$H$207,MATCH($A32,Company_List!$A$3:$A$207,0)),"unassigned")) -> Consumer Discretionary | BC32: =IF($A32="","",IF(COUNTIFS($A$3:$A32,$A32,$C$3:$C32,$C32,$D$3:$D32,$D32,$G$3:$G32,$G32)=1,1,0)) -> 1 | BG32: no | BK32: =IF(OR($H32<>"Human",$S32="",$J32="",$Y32="",$Z32=""),"",IF(EXACT(UPPER($J32),UPPER($Y32)),1,0)) -> 1 | BL32: assumed - no rater record | BM32: 2 | BN32: The Motley Fool | BO32: free to read, copyright asserted | BP32: no | BQ32: no | BS32: YES
A33: McDonald's | B33: =IF(A33="","",_xlfn.XLOOKUP(A33, Company_List!$A:$A, Company_List!$B:$B, "")) -> MCD | C33: 2025 | D33: Q4 | E33: All | F33: All | G33: Meriem | H33: Human | I33: 0.3 | J33: =IF(OR(I33="",Settings!$B$6=""),"",IF(I33>Settings!$B$6,"BUY",IF(I33<-Settings!$B$6,"SELL","HOLD"))) -> BUY | K33: 20 | L33: 46064 | M33: 46063 | N33: 325.97 | O33: 46064 | P33: 323.58 | Q33: =IF(OR(N33="",P33=""),"",ROUND((P33-N33)/N33,4)) -> -0.0073 | R33: =IF(OR(N33="",P33=""),"",IF(Q33>Settings!$B$3/100,"UP",IF(Q33<-Settings!$B$3/100,"DOWN","FLAT"))) -> FLAT | S33: =IF(OR(N33="",P33="",J33=""),"",IF(OR(AND(J33="BUY",R33="UP"),AND(J33="SELL",R33="DOWN"),AND(J33="HOLD",R33="FLAT")),"YES","NO")) -> NO | T33: =IF(J33="","",IF(J33="BUY",1,IF(J33="SELL",-1,0))) -> 1 | U33: =IFERROR(IF(OR(J33="",N33="",P33=""),"",IF(T33=0,0,T33*Q33-Settings!$B$4/10000-IF(T33<0,Settings!$B$5/10000,0))),"") -> -0.0083 | V33: good numbers but guidance isn’t great and tone is not as optimistic as needed but still good | W33: =IF($K33="","",$K33*60) -> 1200 | X33: =IF($A33="","",$A33&"|"&$C33&"|"&$D33) -> McDonald's|2025|Q4 | Y33: =IFERROR(IF($X33="","",INDEX(LLM_Data_Entry!$H$3:$H$548,MATCH($X33,INDEX(LLM_Data_Entry!$A$3:$A$548&"|"&LLM_Data_Entry!$C$3:$C$548&"|"&LLM_Data_Entry!$D$3:$D$548,0),0))),"") -> HOLD | Z33: =IFERROR(IF($X33="","",INDEX(LLM_Data_Entry!$R$3:$R$548,MATCH($X33,INDEX(LLM_Data_Entry!$A$3:$A$548&"|"&LLM_Data_Entry!$C$3:$C$548&"|"&LLM_Data_Entry!$D$3:$D$548,0),0))),"") -> YES | AB33: EDGAR acceptance timestamp on the Item 2.02 8-K | AC33: MCD | AD33: 2026-02-11 | AE33: 319.2493 | AF33: 2026-02-12 | AG33: 325.7882 | AH33: 0.020482 | AI33: UP | AJ33: YES | AK33: 0.019482 | AL33: =IF($A33="","",IFERROR(INDEX(Company_List!$G$3:$G$207,MATCH($A33,Company_List!$A$3:$A$207,0)),"unassigned")) -> P2 | AM33: Phase 2/McDonald's/Q4 2025 Earnings Call Transcript.pdf; Phase 2/McDonald's/Q4 2025 - numbers.pdf | AO33: whole bundle (Document = All) | AP33: =IF($A33="","",IF(COUNTIFS(LLM_Data_Entry!$A$3:$A$548,$A33)>0,"YES","NO")) -> YES | AQ33: =IF($A33="","",IF(COUNTIFS($A$3:$A33,$A33,$C$3:$C33,$C33,$D$3:$D33,$D33)=1,"YES","NO")) -> YES | AR33: =IF($A33="","",IF(AND($C33&"-"&$D33>=Settings!$B$19,$C33&"-"&$D33<=Settings!$B$20),"IN","OUT")) -> IN | AS33: =IF($A33="","",IF($F33="Financial Results","financials",IF($F33="Outlook/Guidance","guidance",IF($F33="Transcript Q&A","qanda",IF($F33="","unrecorded",IF($E33="All","full",IF($E33="","unrecorded",LOWER($E33)&" only"))))))) -> full | AT33: =IF(AND(OR($J33="BUY",$J33="SELL"),ISNUMBER($U33)),$U33,"") -> -0.0083 | AU33: =IF(AND(OR($J33="BUY",$J33="SELL"),ISNUMBER($AK33)),$AK33,"") -> 0.019482 | AV33: =IF(ISNUMBER($AT33),ABS(IF(ISNUMBER($I33),$I33,0)-Settings!$B$24),"") -> 0.3 | AW33: =IF(ISNUMBER($AV33),$AV33*$AT33,"") -> -0.00249 | AX33: =IF(ISNUMBER($AU33),ABS(IF(ISNUMBER($I33),$I33,0)-Settings!$B$24),"") -> 0.3 | AY33: FROZEN | AZ33: =IF($A33="","",IFERROR(INDEX(Company_List!$H$3:$H$207,MATCH($A33,Company_List!$A$3:$A$207,0)),"unassigned")) -> Consumer Discretionary | BC33: =IF($A33="","",IF(COUNTIFS($A$3:$A33,$A33,$C$3:$C33,$C33,$D$3:$D33,$D33,$G$3:$G33,$G33)=1,1,0)) -> 1 | BG33: no | BK33: =IF(OR($H33<>"Human",$S33="",$J33="",$Y33="",$Z33=""),"",IF(EXACT(UPPER($J33),UPPER($Y33)),1,0)) -> 0 | BL33: assumed - no rater record | BM33: 2 | BN33: The Motley Fool | BO33: free to read, copyright asserted | BP33: no | BQ33: no | BS33: YES
A34: McDonald's | B34: =IF(A34="","",_xlfn.XLOOKUP(A34, Company_List!$A:$A, Company_List!$B:$B, "")) -> MCD | C34: 2026 | D34: Q1 | E34: All | F34: All | G34: Meriem | H34: Human | I34: 0.2 | J34: =IF(OR(I34="",Settings!$B$6=""),"",IF(I34>Settings!$B$6,"BUY",IF(I34<-Settings!$B$6,"SELL","HOLD"))) -> HOLD | K34: 34 | L34: 46149 | M34: 46148 | N34: 284.1 | O34: 46149 | P34: 287.83 | Q34: =IF(OR(N34="",P34=""),"",ROUND((P34-N34)/N34,4)) -> 0.0131 | R34: =IF(OR(N34="",P34=""),"",IF(Q34>Settings!$B$3/100,"UP",IF(Q34<-Settings!$B$3/100,"DOWN","FLAT"))) -> FLAT | S34: =IF(OR(N34="",P34="",J34=""),"",IF(OR(AND(J34="BUY",R34="UP"),AND(J34="SELL",R34="DOWN"),AND(J34="HOLD",R34="FLAT")),"YES","NO")) -> YES | T34: =IF(J34="","",IF(J34="BUY",1,IF(J34="SELL",-1,0))) -> 0 | U34: =IFERROR(IF(OR(J34="",N34="",P34=""),"",IF(T34=0,0,T34*Q34-Settings!$B$4/10000-IF(T34<0,Settings!$B$5/10000,0))),"") -> 0 | V34: slight increase in sales and revenue and EPS but challenging environment so unsure about future. too many concerns | W34: =IF($K34="","",$K34*60) -> 2040 | X34: =IF($A34="","",$A34&"|"&$C34&"|"&$D34) -> McDonald's|2026|Q1 | Y34: =IFERROR(IF($X34="","",INDEX(LLM_Data_Entry!$H$3:$H$548,MATCH($X34,INDEX(LLM_Data_Entry!$A$3:$A$548&"|"&LLM_Data_Entry!$C$3:$C$548&"|"&LLM_Data_Entry!$D$3:$D$548,0),0))),"") -> SELL | Z34: =IFERROR(IF($X34="","",INDEX(LLM_Data_Entry!$R$3:$R$548,MATCH($X34,INDEX(LLM_Data_Entry!$A$3:$A$548&"|"&LLM_Data_Entry!$C$3:$C$548&"|"&LLM_Data_Entry!$D$3:$D$548,0),0))),"") -> NO | AB34: release date + stated time | AC34: MCD | AD34: 2026-05-06 | AE34: 282.1862 | AF34: 2026-05-07 | AG34: 285.891 | AH34: 0.013129078 | AI34: FLAT | AJ34: YES | AK34: 0 | AL34: =IF($A34="","",IFERROR(INDEX(Company_List!$G$3:$G$207,MATCH($A34,Company_List!$A$3:$A$207,0)),"unassigned")) -> P2 | AM34: Phase 2/McDonald's/Q1 2026- numbers.pdf; Phase 2/McDonald's/Q1 2026 Earnings Transcript.pdf | AO34: whole bundle (Document = All) | AP34: =IF($A34="","",IF(COUNTIFS(LLM_Data_Entry!$A$3:$A$548,$A34)>0,"YES","NO")) -> YES | AQ34: =IF($A34="","",IF(COUNTIFS($A$3:$A34,$A34,$C$3:$C34,$C34,$D$3:$D34,$D34)=1,"YES","NO")) -> YES | AR34: =IF($A34="","",IF(AND($C34&"-"&$D34>=Settings!$B$19,$C34&"-"&$D34<=Settings!$B$20),"IN","OUT")) -> IN | AS34: =IF($A34="","",IF($F34="Financial Results","financials",IF($F34="Outlook/Guidance","guidance",IF($F34="Transcript Q&A","qanda",IF($F34="","unrecorded",IF($E34="All","full",IF($E34="","unrecorded",LOWER($E34)&" only"))))))) -> full | AT34: =IF(AND(OR($J34="BUY",$J34="SELL"),ISNUMBER($U34)),$U34,"") | AU34: =IF(AND(OR($J34="BUY",$J34="SELL"),ISNUMBER($AK34)),$AK34,"") | AV34: =IF(ISNUMBER($AT34),ABS(IF(ISNUMBER($I34),$I34,0)-Settings!$B$24),"") | AW34: =IF(ISNUMBER($AV34),$AV34*$AT34,"") | AX34: =IF(ISNUMBER($AU34),ABS(IF(ISNUMBER($I34),$I34,0)-Settings!$B$24),"") | AY34: FROZEN | AZ34: =IF($A34="","",IFERROR(INDEX(Company_List!$H$3:$H$207,MATCH($A34,Company_List!$A$3:$A$207,0)),"unassigned")) -> Consumer Discretionary | BC34: =IF($A34="","",IF(COUNTIFS($A$3:$A34,$A34,$C$3:$C34,$C34,$D$3:$D34,$D34,$G$3:$G34,$G34)=1,1,0)) -> 1 | BG34: no | BK34: =IF(OR($H34<>"Human",$S34="",$J34="",$Y34="",$Z34=""),"",IF(EXACT(UPPER($J34),UPPER($Y34)),1,0)) -> 0 | BL34: assumed - no rater record | BM34: 2 | BN34: The Motley Fool | BO34: free to read, copyright asserted | BP34: no | BQ34: no | BS34: YES
A35: Apple | B35: =IF(A35="","",_xlfn.XLOOKUP(A35, Company_List!$A:$A, Company_List!$B:$B, "")) -> AAPL | C35: 2025 | D35: Q3 | E35: All | F35: All | G35: Meriem | H35: Human | I35: -0.3 | J35: =IF(OR(I35="",Settings!$B$6=""),"",IF(I35>Settings!$B$6,"BUY",IF(I35<-Settings!$B$6,"SELL","HOLD"))) -> SELL | K35: 25 | L35: 45869 | M35: 45869 | N35: 207.57 | O35: 45870 | P35: 210.87 | Q35: =IF(OR(N35="",P35=""),"",ROUND((P35-N35)/N35,4)) -> 0.0159 | R35: =IF(OR(N35="",P35=""),"",IF(Q35>Settings!$B$3/100,"UP",IF(Q35<-Settings!$B$3/100,"DOWN","FLAT"))) -> FLAT | S35: =IF(OR(N35="",P35="",J35=""),"",IF(OR(AND(J35="BUY",R35="UP"),AND(J35="SELL",R35="DOWN"),AND(J35="HOLD",R35="FLAT")),"YES","NO")) -> NO | T35: =IF(J35="","",IF(J35="BUY",1,IF(J35="SELL",-1,0))) -> -1 | U35: =IFERROR(IF(OR(J35="",N35="",P35=""),"",IF(T35=0,0,T35*Q35-Settings!$B$4/10000-IF(T35<0,Settings!$B$5/10000,0))),"") -> -0.0169 | V35: tariffs costs; revenue and EPS are up but gross profit margin is down and expenses up. selling bcs tariffs | W35: =IF($K35="","",$K35*60) -> 1500 | X35: =IF($A35="","",$A35&"|"&$C35&"|"&$D35) -> Apple|2025|Q3 | Y35: =IFERROR(IF($X35="","",INDEX(LLM_Data_Entry!$H$3:$H$548,MATCH($X35,INDEX(LLM_Data_Entry!$A$3:$A$548&"|"&LLM_Data_Entry!$C$3:$C$548&"|"&LLM_Data_Entry!$D$3:$D$548,0),0))),"") -> HOLD | Z35: =IFERROR(IF($X35="","",INDEX(LLM_Data_Entry!$R$3:$R$548,MATCH($X35,INDEX(LLM_Data_Entry!$A$3:$A$548&"|"&LLM_Data_Entry!$C$3:$C$548&"|"&LLM_Data_Entry!$D$3:$D$548,0),0))),"") -> YES | AB35: price signal — both moved; this one dominates | AC35: AAPL | AD35: 2025-07-31 | AE35: 206.7498 | AF35: 2025-08-01 | AG35: 210.0367 | AH35: 0.015898266 | AI35: FLAT | AJ35: NO | AK35: -0.016898 | AL35: =IF($A35="","",IFERROR(INDEX(Company_List!$G$3:$G$207,MATCH($A35,Company_List!$A$3:$A$207,0)),"unassigned")) -> P2 | AM35: Phase 2/Apple/Q3 2025 Earnings Call Transcript.pdf; Phase 2/Apple/FY25_Q3_Consolidated_Financial_Statements.pdf | AO35: whole bundle (Document = All) | AP35: =IF($A35="","",IF(COUNTIFS(LLM_Data_Entry!$A$3:$A$548,$A35)>0,"YES","NO")) -> YES | AQ35: =IF($A35="","",IF(COUNTIFS($A$3:$A35,$A35,$C$3:$C35,$C35,$D$3:$D35,$D35)=1,"YES","NO")) -> YES | AR35: =IF($A35="","",IF(AND($C35&"-"&$D35>=Settings!$B$19,$C35&"-"&$D35<=Settings!$B$20),"IN","OUT")) -> IN | AS35: =IF($A35="","",IF($F35="Financial Results","financials",IF($F35="Outlook/Guidance","guidance",IF($F35="Transcript Q&A","qanda",IF($F35="","unrecorded",IF($E35="All","full",IF($E35="","unrecorded",LOWER($E35)&" only"))))))) -> full | AT35: =IF(AND(OR($J35="BUY",$J35="SELL"),ISNUMBER($U35)),$U35,"") -> -0.0169 | AU35: =IF(AND(OR($J35="BUY",$J35="SELL"),ISNUMBER($AK35)),$AK35,"") -> -0.016898 | AV35: =IF(ISNUMBER($AT35),ABS(IF(ISNUMBER($I35),$I35,0)-Settings!$B$24),"") -> 0.3 | AW35: =IF(ISNUMBER($AV35),$AV35*$AT35,"") -> -0.00507 | AX35: =IF(ISNUMBER($AU35),ABS(IF(ISNUMBER($I35),$I35,0)-Settings!$B$24),"") -> 0.3 | AY35: FROZEN | AZ35: =IF($A35="","",IFERROR(INDEX(Company_List!$H$3:$H$207,MATCH($A35,Company_List!$A$3:$A$207,0)),"unassigned")) -> Information Technology | BC35: =IF($A35="","",IF(COUNTIFS($A$3:$A35,$A35,$C$3:$C35,$C35,$D$3:$D35,$D35,$G$3:$G35,$G35)=1,1,0)) -> 1 | BG35: no | BK35: =IF(OR($H35<>"Human",$S35="",$J35="",$Y35="",$Z35=""),"",IF(EXACT(UPPER($J35),UPPER($Y35)),1,0)) -> 0 | BL35: assumed - no rater record | BM35: 2 | BN35: The Motley Fool | BO35: free to read, copyright asserted | BP35: no | BQ35: no | BS35: YES
A36: Apple | B36: =IF(A36="","",_xlfn.XLOOKUP(A36, Company_List!$A:$A, Company_List!$B:$B, "")) -> AAPL | C36: 2025 | D36: Q4 | E36: All | F36: All | G36: Meriem | H36: Human | I36: 0.3 | J36: =IF(OR(I36="",Settings!$B$6=""),"",IF(I36>Settings!$B$6,"BUY",IF(I36<-Settings!$B$6,"SELL","HOLD"))) -> BUY | K36: 30 | L36: 45960 | M36: 45960 | N36: 271.4 | O36: 45961 | P36: 276.99 | Q36: =IF(OR(N36="",P36=""),"",ROUND((P36-N36)/N36,4)) -> 0.0206 | R36: =IF(OR(N36="",P36=""),"",IF(Q36>Settings!$B$3/100,"UP",IF(Q36<-Settings!$B$3/100,"DOWN","FLAT"))) -> UP | S36: =IF(OR(N36="",P36="",J36=""),"",IF(OR(AND(J36="BUY",R36="UP"),AND(J36="SELL",R36="DOWN"),AND(J36="HOLD",R36="FLAT")),"YES","NO")) -> YES | T36: =IF(J36="","",IF(J36="BUY",1,IF(J36="SELL",-1,0))) -> 1 | U36: =IFERROR(IF(OR(J36="",N36="",P36=""),"",IF(T36=0,0,T36*Q36-Settings!$B$4/10000-IF(T36<0,Settings!$B$5/10000,0))),"") -> 0.0196 | V36: revenue up; guidance is good and seems more certain than previous quarter. numbers look better | W36: =IF($K36="","",$K36*60) -> 1800 | X36: =IF($A36="","",$A36&"|"&$C36&"|"&$D36) -> Apple|2025|Q4 | Y36: =IFERROR(IF($X36="","",INDEX(LLM_Data_Entry!$H$3:$H$548,MATCH($X36,INDEX(LLM_Data_Entry!$A$3:$A$548&"|"&LLM_Data_Entry!$C$3:$C$548&"|"&LLM_Data_Entry!$D$3:$D$548,0),0))),"") -> BUY | Z36: =IFERROR(IF($X36="","",INDEX(LLM_Data_Entry!$R$3:$R$548,MATCH($X36,INDEX(LLM_Data_Entry!$A$3:$A$548&"|"&LLM_Data_Entry!$C$3:$C$548&"|"&LLM_Data_Entry!$D$3:$D$548,0),0))),"") -> YES | AB36: earnings calendar, seconded independently (section C) | AC36: AAPL | AD36: 2025-10-30 | AE36: 270.6343 | AF36: 2025-10-31 | AG36: 276.2086 | AH36: 0.020596869 | AI36: UP | AJ36: YES | AK36: 0.019597 | AL36: =IF($A36="","",IFERROR(INDEX(Company_List!$G$3:$G$207,MATCH($A36,Company_List!$A$3:$A$207,0)),"unassigned")) -> P2 | AM36: Phase 2/Apple/Q4 2025 Earnings Call Transcript.pdf; Phase 2/Apple/FY25_Q4_Consolidated_Financial_Statements.pdf | AO36: whole bundle (Document = All) | AP36: =IF($A36="","",IF(COUNTIFS(LLM_Data_Entry!$A$3:$A$548,$A36)>0,"YES","NO")) -> YES | AQ36: =IF($A36="","",IF(COUNTIFS($A$3:$A36,$A36,$C$3:$C36,$C36,$D$3:$D36,$D36)=1,"YES","NO")) -> YES | AR36: =IF($A36="","",IF(AND($C36&"-"&$D36>=Settings!$B$19,$C36&"-"&$D36<=Settings!$B$20),"IN","OUT")) -> IN | AS36: =IF($A36="","",IF($F36="Financial Results","financials",IF($F36="Outlook/Guidance","guidance",IF($F36="Transcript Q&A","qanda",IF($F36="","unrecorded",IF($E36="All","full",IF($E36="","unrecorded",LOWER($E36)&" only"))))))) -> full | AT36: =IF(AND(OR($J36="BUY",$J36="SELL"),ISNUMBER($U36)),$U36,"") -> 0.0196 | AU36: =IF(AND(OR($J36="BUY",$J36="SELL"),ISNUMBER($AK36)),$AK36,"") -> 0.019597 | AV36: =IF(ISNUMBER($AT36),ABS(IF(ISNUMBER($I36),$I36,0)-Settings!$B$24),"") -> 0.3 | AW36: =IF(ISNUMBER($AV36),$AV36*$AT36,"") -> 0.00588 | AX36: =IF(ISNUMBER($AU36),ABS(IF(ISNUMBER($I36),$I36,0)-Settings!$B$24),"") -> 0.3 | AY36: FROZEN | AZ36: =IF($A36="","",IFERROR(INDEX(Company_List!$H$3:$H$207,MATCH($A36,Company_List!$A$3:$A$207,0)),"unassigned")) -> Information Technology | BC36: =IF($A36="","",IF(COUNTIFS($A$3:$A36,$A36,$C$3:$C36,$C36,$D$3:$D36,$D36,$G$3:$G36,$G36)=1,1,0)) -> 1 | BG36: no | BK36: =IF(OR($H36<>"Human",$S36="",$J36="",$Y36="",$Z36=""),"",IF(EXACT(UPPER($J36),UPPER($Y36)),1,0)) -> 1 | BL36: assumed - no rater record | BM36: 2 | BN36: The Motley Fool | BO36: free to read, copyright asserted | BP36: no | BQ36: no | BS36: YES
A37: Apple | B37: =IF(A37="","",_xlfn.XLOOKUP(A37, Company_List!$A:$A, Company_List!$B:$B, "")) -> AAPL | C37: 2026 | D37: Q1 | E37: All | F37: All | G37: Meriem | H37: Human | I37: 0.5 | J37: =IF(OR(I37="",Settings!$B$6=""),"",IF(I37>Settings!$B$6,"BUY",IF(I37<-Settings!$B$6,"SELL","HOLD"))) -> BUY | K37: 22 | L37: 46051 | M37: 46051 | N37: 258.28 | O37: 46052 | P37: 255.17 | Q37: =IF(OR(N37="",P37=""),"",ROUND((P37-N37)/N37,4)) -> -0.012 | R37: =IF(OR(N37="",P37=""),"",IF(Q37>Settings!$B$3/100,"UP",IF(Q37<-Settings!$B$3/100,"DOWN","FLAT"))) -> FLAT | S37: =IF(OR(N37="",P37="",J37=""),"",IF(OR(AND(J37="BUY",R37="UP"),AND(J37="SELL",R37="DOWN"),AND(J37="HOLD",R37="FLAT")),"YES","NO")) -> NO | T37: =IF(J37="","",IF(J37="BUY",1,IF(J37="SELL",-1,0))) -> 1 | U37: =IFERROR(IF(OR(J37="",N37="",P37=""),"",IF(T37=0,0,T37*Q37-Settings!$B$4/10000-IF(T37<0,Settings!$B$5/10000,0))),"") -> -0.013 | V37: revenue is up; numbers are great (better than two previous quarters) | W37: =IF($K37="","",$K37*60) -> 1320 | X37: =IF($A37="","",$A37&"|"&$C37&"|"&$D37) -> Apple|2026|Q1 | Y37: =IFERROR(IF($X37="","",INDEX(LLM_Data_Entry!$H$3:$H$548,MATCH($X37,INDEX(LLM_Data_Entry!$A$3:$A$548&"|"&LLM_Data_Entry!$C$3:$C$548&"|"&LLM_Data_Entry!$D$3:$D$548,0),0))),"") -> BUY | Z37: =IFERROR(IF($X37="","",INDEX(LLM_Data_Entry!$R$3:$R$548,MATCH($X37,INDEX(LLM_Data_Entry!$A$3:$A$548&"|"&LLM_Data_Entry!$C$3:$C$548&"|"&LLM_Data_Entry!$D$3:$D$548,0),0))),"") -> NO | AB37: price signal — only this window shows an abnormal move | AC37: AAPL | AD37: 2026-01-29 | AE37: 257.801 | AF37: 2026-01-30 | AG37: 254.6968 | AH37: -0.012041091 | AI37: FLAT | AJ37: NO | AK37: -0.013041 | AL37: =IF($A37="","",IFERROR(INDEX(Company_List!$G$3:$G$207,MATCH($A37,Company_List!$A$3:$A$207,0)),"unassigned")) -> P2 | AM37: Phase 2/Apple/Q1 2026 Earnings Call Transcript.pdf; Phase 2/Apple/FY26_Q1_Consolidated_Financial_Statements.pdf | AO37: whole bundle (Document = All) | AP37: =IF($A37="","",IF(COUNTIFS(LLM_Data_Entry!$A$3:$A$548,$A37)>0,"YES","NO")) -> YES | AQ37: =IF($A37="","",IF(COUNTIFS($A$3:$A37,$A37,$C$3:$C37,$C37,$D$3:$D37,$D37)=1,"YES","NO")) -> YES | AR37: =IF($A37="","",IF(AND($C37&"-"&$D37>=Settings!$B$19,$C37&"-"&$D37<=Settings!$B$20),"IN","OUT")) -> IN | AS37: =IF($A37="","",IF($F37="Financial Results","financials",IF($F37="Outlook/Guidance","guidance",IF($F37="Transcript Q&A","qanda",IF($F37="","unrecorded",IF($E37="All","full",IF($E37="","unrecorded",LOWER($E37)&" only"))))))) -> full | AT37: =IF(AND(OR($J37="BUY",$J37="SELL"),ISNUMBER($U37)),$U37,"") -> -0.013 | AU37: =IF(AND(OR($J37="BUY",$J37="SELL"),ISNUMBER($AK37)),$AK37,"") -> -0.013041 | AV37: =IF(ISNUMBER($AT37),ABS(IF(ISNUMBER($I37),$I37,0)-Settings!$B$24),"") -> 0.5 | AW37: =IF(ISNUMBER($AV37),$AV37*$AT37,"") -> -0.0065 | AX37: =IF(ISNUMBER($AU37),ABS(IF(ISNUMBER($I37),$I37,0)-Settings!$B$24),"") -> 0.5 | AY37: FROZEN | AZ37: =IF($A37="","",IFERROR(INDEX(Company_List!$H$3:$H$207,MATCH($A37,Company_List!$A$3:$A$207,0)),"unassigned")) -> Information Technology | BC37: =IF($A37="","",IF(COUNTIFS($A$3:$A37,$A37,$C$3:$C37,$C37,$D$3:$D37,$D37,$G$3:$G37,$G37)=1,1,0)) -> 1 | BG37: no | BK37: =IF(OR($H37<>"Human",$S37="",$J37="",$Y37="",$Z37=""),"",IF(EXACT(UPPER($J37),UPPER($Y37)),1,0)) -> 1 | BL37: assumed - no rater record | BM37: 2 | BN37: The Motley Fool | BO37: free to read, copyright asserted | BP37: no | BQ37: no | BS37: YES
A38: Coca-Cola | B38: =IF(A38="","",_xlfn.XLOOKUP(A38, Company_List!$A:$A, Company_List!$B:$B, "")) -> KO | C38: 2025 | D38: Q2 | E38: All | F38: All | G38: Meriem | H38: Human | I38: 0.2 | J38: =IF(OR(I38="",Settings!$B$6=""),"",IF(I38>Settings!$B$6,"BUY",IF(I38<-Settings!$B$6,"SELL","HOLD"))) -> HOLD | K38: 35 | L38: 45860 | M38: 45859 | N38: 70.07 | O38: 45860 | P38: 69.45 | Q38: =IF(OR(N38="",P38=""),"",ROUND((P38-N38)/N38,4)) -> -0.0088 | R38: =IF(OR(N38="",P38=""),"",IF(Q38>Settings!$B$3/100,"UP",IF(Q38<-Settings!$B$3/100,"DOWN","FLAT"))) -> FLAT | S38: =IF(OR(N38="",P38="",J38=""),"",IF(OR(AND(J38="BUY",R38="UP"),AND(J38="SELL",R38="DOWN"),AND(J38="HOLD",R38="FLAT")),"YES","NO")) -> YES | T38: =IF(J38="","",IF(J38="BUY",1,IF(J38="SELL",-1,0))) -> 0 | U38: =IFERROR(IF(OR(J38="",N38="",P38=""),"",IF(T38=0,0,T38*Q38-Settings!$B$4/10000-IF(T38<0,Settings!$B$5/10000,0))),"") -> 0 | V38: adverse weather conditions not great so recovery might not be good right now; growth expanded but Asia’s volume is down. so hold | W38: =IF($K38="","",$K38*60) -> 2100 | X38: =IF($A38="","",$A38&"|"&$C38&"|"&$D38) -> Coca-Cola|2025|Q2 | Y38: =IFERROR(IF($X38="","",INDEX(LLM_Data_Entry!$H$3:$H$548,MATCH($X38,INDEX(LLM_Data_Entry!$A$3:$A$548&"|"&LLM_Data_Entry!$C$3:$C$548&"|"&LLM_Data_Entry!$D$3:$D$548,0),0))),"") -> HOLD | Z38: =IFERROR(IF($X38="","",INDEX(LLM_Data_Entry!$R$3:$R$548,MATCH($X38,INDEX(LLM_Data_Entry!$A$3:$A$548&"|"&LLM_Data_Entry!$C$3:$C$548&"|"&LLM_Data_Entry!$D$3:$D$548,0),0))),"") -> YES | AB38: release date + stated time | AC38: KO | AD38: 2025-07-21 | AE38: 68.1402 | AF38: 2025-07-22 | AG38: 67.5373 | AH38: -0.0088483467 | AI38: FLAT | AJ38: YES | AK38: 0 | AL38: =IF($A38="","",IFERROR(INDEX(Company_List!$G$3:$G$207,MATCH($A38,Company_List!$A$3:$A$207,0)),"unassigned")) -> P2 | AM38: Phase 2/Coca-Cola/Q2 2025 Earnings Call Transcript.pdf | AO38: unique filename match | AP38: =IF($A38="","",IF(COUNTIFS(LLM_Data_Entry!$A$3:$A$548,$A38)>0,"YES","NO")) -> YES | AQ38: =IF($A38="","",IF(COUNTIFS($A$3:$A38,$A38,$C$3:$C38,$C38,$D$3:$D38,$D38)=1,"YES","NO")) -> YES | AR38: =IF($A38="","",IF(AND($C38&"-"&$D38>=Settings!$B$19,$C38&"-"&$D38<=Settings!$B$20),"IN","OUT")) -> IN | AS38: =IF($A38="","",IF($F38="Financial Results","financials",IF($F38="Outlook/Guidance","guidance",IF($F38="Transcript Q&A","qanda",IF($F38="","unrecorded",IF($E38="All","full",IF($E38="","unrecorded",LOWER($E38)&" only"))))))) -> full | AT38: =IF(AND(OR($J38="BUY",$J38="SELL"),ISNUMBER($U38)),$U38,"") | AU38: =IF(AND(OR($J38="BUY",$J38="SELL"),ISNUMBER($AK38)),$AK38,"") | AV38: =IF(ISNUMBER($AT38),ABS(IF(ISNUMBER($I38),$I38,0)-Settings!$B$24),"") | AW38: =IF(ISNUMBER($AV38),$AV38*$AT38,"") | AX38: =IF(ISNUMBER($AU38),ABS(IF(ISNUMBER($I38),$I38,0)-Settings!$B$24),"") | AY38: FROZEN | AZ38: =IF($A38="","",IFERROR(INDEX(Company_List!$H$3:$H$207,MATCH($A38,Company_List!$A$3:$A$207,0)),"unassigned")) -> Consumer Staples | BC38: =IF($A38="","",IF(COUNTIFS($A$3:$A38,$A38,$C$3:$C38,$C38,$D$3:$D38,$D38,$G$3:$G38,$G38)=1,1,0)) -> 1 | BG38: no | BK38: =IF(OR($H38<>"Human",$S38="",$J38="",$Y38="",$Z38=""),"",IF(EXACT(UPPER($J38),UPPER($Y38)),1,0)) -> 1 | BL38: assumed - no rater record | BM38: 1 | BN38: The Motley Fool | BO38: free to read, copyright asserted | BP38: no | BQ38: no | BS38: YES
A39: Coca-Cola | B39: =IF(A39="","",_xlfn.XLOOKUP(A39, Company_List!$A:$A, Company_List!$B:$B, "")) -> KO | C39: 2025 | D39: Q4 | E39: All | F39: All | G39: Meriem | H39: Human | I39: -0.3 | J39: =IF(OR(I39="",Settings!$B$6=""),"",IF(I39>Settings!$B$6,"BUY",IF(I39<-Settings!$B$6,"SELL","HOLD"))) -> SELL | K39: 28 | L39: 46063 | M39: 46062 | N39: 77.97 | O39: 46063 | P39: 76.63 | Q39: =IF(OR(N39="",P39=""),"",ROUND((P39-N39)/N39,4)) -> -0.0172 | R39: =IF(OR(N39="",P39=""),"",IF(Q39>Settings!$B$3/100,"UP",IF(Q39<-Settings!$B$3/100,"DOWN","FLAT"))) -> FLAT | S39: =IF(OR(N39="",P39="",J39=""),"",IF(OR(AND(J39="BUY",R39="UP"),AND(J39="SELL",R39="DOWN"),AND(J39="HOLD",R39="FLAT")),"YES","NO")) -> NO | T39: =IF(J39="","",IF(J39="BUY",1,IF(J39="SELL",-1,0))) -> -1 | U39: =IFERROR(IF(OR(J39="",N39="",P39=""),"",IF(T39=0,0,T39*Q39-Settings!$B$4/10000-IF(T39<0,Settings!$B$5/10000,0))),"") -> 0.0162 | V39: leadership transition so added risk; Asia’s volume and revenue still down and uncertainty so sell. | W39: =IF($K39="","",$K39*60) -> 1680 | X39: =IF($A39="","",$A39&"|"&$C39&"|"&$D39) -> Coca-Cola|2025|Q4 | Y39: =IFERROR(IF($X39="","",INDEX(LLM_Data_Entry!$H$3:$H$548,MATCH($X39,INDEX(LLM_Data_Entry!$A$3:$A$548&"|"&LLM_Data_Entry!$C$3:$C$548&"|"&LLM_Data_Entry!$D$3:$D$548,0),0))),"") -> HOLD | Z39: =IFERROR(IF($X39="","",INDEX(LLM_Data_Entry!$R$3:$R$548,MATCH($X39,INDEX(LLM_Data_Entry!$A$3:$A$548&"|"&LLM_Data_Entry!$C$3:$C$548&"|"&LLM_Data_Entry!$D$3:$D$548,0),0))),"") -> YES | AB39: release date + stated time | AC39: KO | AD39: 2026-02-09 | AE39: 76.9408 | AF39: 2026-02-10 | AG39: 75.6185 | AH39: -0.017186253 | AI39: FLAT | AJ39: NO | AK39: 0.016186 | AL39: =IF($A39="","",IFERROR(INDEX(Company_List!$G$3:$G$207,MATCH($A39,Company_List!$A$3:$A$207,0)),"unassigned")) -> P2 | AM39: Phase 2/Coca-Cola/Q4 2025 Earnings Call Transcript.pdf | AO39: unique filename match | AP39: =IF($A39="","",IF(COUNTIFS(LLM_Data_Entry!$A$3:$A$548,$A39)>0,"YES","NO")) -> YES | AQ39: =IF($A39="","",IF(COUNTIFS($A$3:$A39,$A39,$C$3:$C39,$C39,$D$3:$D39,$D39)=1,"YES","NO")) -> YES | AR39: =IF($A39="","",IF(AND($C39&"-"&$D39>=Settings!$B$19,$C39&"-"&$D39<=Settings!$B$20),"IN","OUT")) -> IN | AS39: =IF($A39="","",IF($F39="Financial Results","financials",IF($F39="Outlook/Guidance","guidance",IF($F39="Transcript Q&A","qanda",IF($F39="","unrecorded",IF($E39="All","full",IF($E39="","unrecorded",LOWER($E39)&" only"))))))) -> full | AT39: =IF(AND(OR($J39="BUY",$J39="SELL"),ISNUMBER($U39)),$U39,"") -> 0.0162 | AU39: =IF(AND(OR($J39="BUY",$J39="SELL"),ISNUMBER($AK39)),$AK39,"") -> 0.016186 | AV39: =IF(ISNUMBER($AT39),ABS(IF(ISNUMBER($I39),$I39,0)-Settings!$B$24),"") -> 0.3 | AW39: =IF(ISNUMBER($AV39),$AV39*$AT39,"") -> 0.00486 | AX39: =IF(ISNUMBER($AU39),ABS(IF(ISNUMBER($I39),$I39,0)-Settings!$B$24),"") -> 0.3 | AY39: FROZEN | AZ39: =IF($A39="","",IFERROR(INDEX(Company_List!$H$3:$H$207,MATCH($A39,Company_List!$A$3:$A$207,0)),"unassigned")) -> Consumer Staples | BC39: =IF($A39="","",IF(COUNTIFS($A$3:$A39,$A39,$C$3:$C39,$C39,$D$3:$D39,$D39,$G$3:$G39,$G39)=1,1,0)) -> 1 | BG39: no | BK39: =IF(OR($H39<>"Human",$S39="",$J39="",$Y39="",$Z39=""),"",IF(EXACT(UPPER($J39),UPPER($Y39)),1,0)) -> 0 | BL39: assumed - no rater record | BM39: 1 | BN39: The Motley Fool | BO39: free to read, copyright asserted | BP39: no | BQ39: no | BS39: YES
A40: Coca-Cola | B40: =IF(A40="","",_xlfn.XLOOKUP(A40, Company_List!$A:$A, Company_List!$B:$B, "")) -> KO | C40: 2026 | D40: Q1 | E40: All | F40: All | G40: Meriem | H40: Human | I40: 0.4 | J40: =IF(OR(I40="",Settings!$B$6=""),"",IF(I40>Settings!$B$6,"BUY",IF(I40<-Settings!$B$6,"SELL","HOLD"))) -> BUY | K40: 25 | L40: 46140 | M40: 46139 | N40: 75.44 | O40: 46140 | P40: 79.52 | Q40: =IF(OR(N40="",P40=""),"",ROUND((P40-N40)/N40,4)) -> 0.0541 | R40: =IF(OR(N40="",P40=""),"",IF(Q40>Settings!$B$3/100,"UP",IF(Q40<-Settings!$B$3/100,"DOWN","FLAT"))) -> UP | S40: =IF(OR(N40="",P40="",J40=""),"",IF(OR(AND(J40="BUY",R40="UP"),AND(J40="SELL",R40="DOWN"),AND(J40="HOLD",R40="FLAT")),"YES","NO")) -> YES | T40: =IF(J40="","",IF(J40="BUY",1,IF(J40="SELL",-1,0))) -> 1 | U40: =IFERROR(IF(OR(J40="",N40="",P40=""),"",IF(T40=0,0,T40*Q40-Settings!$B$4/10000-IF(T40<0,Settings!$B$5/10000,0))),"") -> 0.0531 | V40: Asia’s volume and revenue finally up; revenue up as well and EPS up 18%; optimistic tone so buy | W40: =IF($K40="","",$K40*60) -> 1500 | X40: =IF($A40="","",$A40&"|"&$C40&"|"&$D40) -> Coca-Cola|2026|Q1 | Y40: =IFERROR(IF($X40="","",INDEX(LLM_Data_Entry!$H$3:$H$548,MATCH($X40,INDEX(LLM_Data_Entry!$A$3:$A$548&"|"&LLM_Data_Entry!$C$3:$C$548&"|"&LLM_Data_Entry!$D$3:$D$548,0),0))),"") -> HOLD | Z40: =IFERROR(IF($X40="","",INDEX(LLM_Data_Entry!$R$3:$R$548,MATCH($X40,INDEX(LLM_Data_Entry!$A$3:$A$548&"|"&LLM_Data_Entry!$C$3:$C$548&"|"&LLM_Data_Entry!$D$3:$D$548,0),0))),"") -> NO | AB40: release date + stated time | AC40: KO | AD40: 2026-04-27 | AE40: 74.9561 | AF40: 2026-04-28 | AG40: 79.0099 | AH40: 0.054082624 | AI40: UP | AJ40: YES | AK40: 0.053083 | AL40: =IF($A40="","",IFERROR(INDEX(Company_List!$G$3:$G$207,MATCH($A40,Company_List!$A$3:$A$207,0)),"unassigned")) -> P2 | AM40: Phase 2/Coca-Cola/Q1 2026 Earnings Transcript.pdf | AO40: unique filename match | AP40: =IF($A40="","",IF(COUNTIFS(LLM_Data_Entry!$A$3:$A$548,$A40)>0,"YES","NO")) -> YES | AQ40: =IF($A40="","",IF(COUNTIFS($A$3:$A40,$A40,$C$3:$C40,$C40,$D$3:$D40,$D40)=1,"YES","NO")) -> YES | AR40: =IF($A40="","",IF(AND($C40&"-"&$D40>=Settings!$B$19,$C40&"-"&$D40<=Settings!$B$20),"IN","OUT")) -> IN | AS40: =IF($A40="","",IF($F40="Financial Results","financials",IF($F40="Outlook/Guidance","guidance",IF($F40="Transcript Q&A","qanda",IF($F40="","unrecorded",IF($E40="All","full",IF($E40="","unrecorded",LOWER($E40)&" only"))))))) -> full | AT40: =IF(AND(OR($J40="BUY",$J40="SELL"),ISNUMBER($U40)),$U40,"") -> 0.0531 | AU40: =IF(AND(OR($J40="BUY",$J40="SELL"),ISNUMBER($AK40)),$AK40,"") -> 0.053083 | AV40: =IF(ISNUMBER($AT40),ABS(IF(ISNUMBER($I40),$I40,0)-Settings!$B$24),"") -> 0.4 | AW40: =IF(ISNUMBER($AV40),$AV40*$AT40,"") -> 0.02124 | AX40: =IF(ISNUMBER($AU40),ABS(IF(ISNUMBER($I40),$I40,0)-Settings!$B$24),"") -> 0.4 | AY40: FROZEN | AZ40: =IF($A40="","",IFERROR(INDEX(Company_List!$H$3:$H$207,MATCH($A40,Company_List!$A$3:$A$207,0)),"unassigned")) -> Consumer Staples | BC40: =IF($A40="","",IF(COUNTIFS($A$3:$A40,$A40,$C$3:$C40,$C40,$D$3:$D40,$D40,$G$3:$G40,$G40)=1,1,0)) -> 1 | BG40: no | BK40: =IF(OR($H40<>"Human",$S40="",$J40="",$Y40="",$Z40=""),"",IF(EXACT(UPPER($J40),UPPER($Y40)),1,0)) -> 0 | BL40: assumed - no rater record | BM40: 1 | BN40: The Motley Fool | BO40: free to read, copyright asserted | BP40: no | BQ40: no | BS40: YES
A41: Bank of America | B41: =IF(A41="","",_xlfn.XLOOKUP(A41, Company_List!$A:$A, Company_List!$B:$B, "")) -> BAC | C41: 2025 | D41: Q1 | E41: Transcript | F41: All | G41: Abdul | H41: Human | I41: 0.4 | J41: =IF(OR(I41="",Settings!$B$6=""),"",IF(I41>Settings!$B$6,"BUY",IF(I41<-Settings!$B$6,"SELL","HOLD"))) -> BUY | K41: 60 | L41: 45762 | M41: 45761 | N41: 36.67 | O41: 45762 | P41: 37.8 | Q41: =IF(OR(N41="",P41=""),"",ROUND((P41-N41)/N41,4)) -> 0.0308 | R41: =IF(OR(N41="",P41=""),"",IF(Q41>Settings!$B$3/100,"UP",IF(Q41<-Settings!$B$3/100,"DOWN","FLAT"))) -> UP | S41: =IF(OR(N41="",P41="",J41=""),"",IF(OR(AND(J41="BUY",R41="UP"),AND(J41="SELL",R41="DOWN"),AND(J41="HOLD",R41="FLAT")),"YES","NO")) -> YES | T41: =IF(J41="","",IF(J41="BUY",1,IF(J41="SELL",-1,0))) -> 1 | U41: =IFERROR(IF(OR(J41="",N41="",P41=""),"",IF(T41=0,0,T41*Q41-Settings!$B$4/10000-IF(T41<0,Settings!$B$5/10000,0))),"") -> 0.0298 | W41: =IF($K41="","",$K41*60) -> 3600 | X41: =IF($A41="","",$A41&"|"&$C41&"|"&$D41) -> Bank of America|2025|Q1 | Y41: =IFERROR(IF($X41="","",INDEX(LLM_Data_Entry!$H$3:$H$548,MATCH($X41,INDEX(LLM_Data_Entry!$A$3:$A$548&"|"&LLM_Data_Entry!$C$3:$C$548&"|"&LLM_Data_Entry!$D$3:$D$548,0),0))),"") -> SELL | Z41: =IFERROR(IF($X41="","",INDEX(LLM_Data_Entry!$R$3:$R$548,MATCH($X41,INDEX(LLM_Data_Entry!$A$3:$A$548&"|"&LLM_Data_Entry!$C$3:$C$548&"|"&LLM_Data_Entry!$D$3:$D$548,0),0))),"") -> NO | AB41: price signal — only this window shows an abnormal move | AC41: BAC | AD41: 2025-04-14 | AE41: 35.678 | AF41: 2025-04-15 | AG41: 36.7774 | AH41: 0.030815289 | AI41: UP | AJ41: YES | AK41: 0.029815 | AL41: =IF($A41="","",IFERROR(INDEX(Company_List!$G$3:$G$207,MATCH($A41,Company_List!$A$3:$A$207,0)),"unassigned")) -> P2 | AM41: Phase 2/bank of america/2025-Q1/BAC-2025-Q1-earnings-call-transcript-roic-ai.html | AN41: roic.ai API /v2/company/earnings-calls/transcript/BAC?year=2025&quarter=1 | AO41: manifest | AP41: =IF($A41="","",IF(COUNTIFS(LLM_Data_Entry!$A$3:$A$548,$A41)>0,"YES","NO")) -> YES | AQ41: =IF($A41="","",IF(COUNTIFS($A$3:$A41,$A41,$C$3:$C41,$C41,$D$3:$D41,$D41)=1,"YES","NO")) -> YES | AR41: =IF($A41="","",IF(AND($C41&"-"&$D41>=Settings!$B$19,$C41&"-"&$D41<=Settings!$B$20),"IN","OUT")) -> IN | AS41: =IF($A41="","",IF($F41="Financial Results","financials",IF($F41="Outlook/Guidance","guidance",IF($F41="Transcript Q&A","qanda",IF($F41="","unrecorded",IF($E41="All","full",IF($E41="","unrecorded",LOWER($E41)&" only"))))))) -> transcript only | AT41: =IF(AND(OR($J41="BUY",$J41="SELL"),ISNUMBER($U41)),$U41,"") -> 0.0298 | AU41: =IF(AND(OR($J41="BUY",$J41="SELL"),ISNUMBER($AK41)),$AK41,"") -> 0.029815 | AV41: =IF(ISNUMBER($AT41),ABS(IF(ISNUMBER($I41),$I41,0)-Settings!$B$24),"") -> 0.4 | AW41: =IF(ISNUMBER($AV41),$AV41*$AT41,"") -> 0.01192 | AX41: =IF(ISNUMBER($AU41),ABS(IF(ISNUMBER($I41),$I41,0)-Settings!$B$24),"") -> 0.4 | AY41: FROZEN | AZ41: =IF($A41="","",IFERROR(INDEX(Company_List!$H$3:$H$207,MATCH($A41,Company_List!$A$3:$A$207,0)),"unassigned")) -> Financials | BC41: =IF($A41="","",IF(COUNTIFS($A$3:$A41,$A41,$C$3:$C41,$C41,$D$3:$D41,$D41,$G$3:$G41,$G41)=1,1,0)) -> 1 | BG41: no | BK41: =IF(OR($H41<>"Human",$S41="",$J41="",$Y41="",$Z41=""),"",IF(EXACT(UPPER($J41),UPPER($Y41)),1,0)) -> 0 | BL41: assumed - no rater record | BM41: 1 | BN41: not publisher-identified | BO41: not publisher-identified | BP41: no | BQ41: yes | BS41: YES
A42: Bank of America | B42: =IF(A42="","",_xlfn.XLOOKUP(A42, Company_List!$A:$A, Company_List!$B:$B, "")) -> BAC | C42: 2025 | D42: Q2 | E42: Transcript | F42: All | G42: Abdul | H42: Human | I42: 0.6 | J42: =IF(OR(I42="",Settings!$B$6=""),"",IF(I42>Settings!$B$6,"BUY",IF(I42<-Settings!$B$6,"SELL","HOLD"))) -> BUY | K42: 41 | L42: 45854 | M42: 45853 | N42: 46.15 | O42: 45854 | P42: 46.25 | Q42: =IF(OR(N42="",P42=""),"",ROUND((P42-N42)/N42,4)) -> 0.0022 | R42: =IF(OR(N42="",P42=""),"",IF(Q42>Settings!$B$3/100,"UP",IF(Q42<-Settings!$B$3/100,"DOWN","FLAT"))) -> FLAT | S42: =IF(OR(N42="",P42="",J42=""),"",IF(OR(AND(J42="BUY",R42="UP"),AND(J42="SELL",R42="DOWN"),AND(J42="HOLD",R42="FLAT")),"YES","NO")) -> NO | T42: =IF(J42="","",IF(J42="BUY",1,IF(J42="SELL",-1,0))) -> 1 | U42: =IFERROR(IF(OR(J42="",N42="",P42=""),"",IF(T42=0,0,T42*Q42-Settings!$B$4/10000-IF(T42<0,Settings!$B$5/10000,0))),"") -> 0.0012 | W42: =IF($K42="","",$K42*60) -> 2460 | X42: =IF($A42="","",$A42&"|"&$C42&"|"&$D42) -> Bank of America|2025|Q2 | Y42: =IFERROR(IF($X42="","",INDEX(LLM_Data_Entry!$H$3:$H$548,MATCH($X42,INDEX(LLM_Data_Entry!$A$3:$A$548&"|"&LLM_Data_Entry!$C$3:$C$548&"|"&LLM_Data_Entry!$D$3:$D$548,0),0))),"") -> HOLD | Z42: =IFERROR(IF($X42="","",INDEX(LLM_Data_Entry!$R$3:$R$548,MATCH($X42,INDEX(LLM_Data_Entry!$A$3:$A$548&"|"&LLM_Data_Entry!$C$3:$C$548&"|"&LLM_Data_Entry!$D$3:$D$548,0),0))),"") -> YES | AB42: price signal | AC42: BAC | AD42: 2025-07-14 | AE42: 46.0665 | AF42: 2025-07-15 | AG42: 45.8806 | AH42: -0.0040366627 | AI42: FLAT | AJ42: NO | AK42: -0.005037 | AL42: =IF($A42="","",IFERROR(INDEX(Company_List!$G$3:$G$207,MATCH($A42,Company_List!$A$3:$A$207,0)),"unassigned")) -> P2 | AM42: Phase 2/bank of america/2025-Q2/BAC-2025-Q2-earnings-call-transcript-news-alphastreet-com.html | AN42: https://news.alphastreet.com/bank-of-america-corporation-bac-q2-2025-earnings-call-transcript/ | AO42: manifest | AP42: =IF($A42="","",IF(COUNTIFS(LLM_Data_Entry!$A$3:$A$548,$A42)>0,"YES","NO")) -> YES | AQ42: =IF($A42="","",IF(COUNTIFS($A$3:$A42,$A42,$C$3:$C42,$C42,$D$3:$D42,$D42)=1,"YES","NO")) -> YES | AR42: =IF($A42="","",IF(AND($C42&"-"&$D42>=Settings!$B$19,$C42&"-"&$D42<=Settings!$B$20),"IN","OUT")) -> IN | AS42: =IF($A42="","",IF($F42="Financial Results","financials",IF($F42="Outlook/Guidance","guidance",IF($F42="Transcript Q&A","qanda",IF($F42="","unrecorded",IF($E42="All","full",IF($E42="","unrecorded",LOWER($E42)&" only"))))))) -> transcript only | AT42: =IF(AND(OR($J42="BUY",$J42="SELL"),ISNUMBER($U42)),$U42,"") -> 0.0012 | AU42: =IF(AND(OR($J42="BUY",$J42="SELL"),ISNUMBER($AK42)),$AK42,"") -> -0.005037 | AV42: =IF(ISNUMBER($AT42),ABS(IF(ISNUMBER($I42),$I42,0)-Settings!$B$24),"") -> 0.6 | AW42: =IF(ISNUMBER($AV42),$AV42*$AT42,"") -> 0.00072 | AX42: =IF(ISNUMBER($AU42),ABS(IF(ISNUMBER($I42),$I42,0)-Settings!$B$24),"") -> 0.6 | AY42: FROZEN | AZ42: =IF($A42="","",IFERROR(INDEX(Company_List!$H$3:$H$207,MATCH($A42,Company_List!$A$3:$A$207,0)),"unassigned")) -> Financials | BC42: =IF($A42="","",IF(COUNTIFS($A$3:$A42,$A42,$C$3:$C42,$C42,$D$3:$D42,$D42,$G$3:$G42,$G42)=1,1,0)) -> 1 | BG42: no | BK42: =IF(OR($H42<>"Human",$S42="",$J42="",$Y42="",$Z42=""),"",IF(EXACT(UPPER($J42),UPPER($Y42)),1,0)) -> 0 | BL42: assumed - no rater record | BM42: 1 | BN42: not publisher-identified | BO42: not publisher-identified | BP42: no | BQ42: yes | BS42: YES
A43: Bank of America | B43: =IF(A43="","",_xlfn.XLOOKUP(A43, Company_List!$A:$A, Company_List!$B:$B, "")) -> BAC | C43: 2025 | D43: Q3 | E43: Transcript | F43: All | G43: Abdul | H43: Human | I43: 0.7 | J43: =IF(OR(I43="",Settings!$B$6=""),"",IF(I43>Settings!$B$6,"BUY",IF(I43<-Settings!$B$6,"SELL","HOLD"))) -> BUY | K43: 75 | L43: 45945 | M43: 45944 | N43: 50.09 | O43: 45945 | P43: 51.57 | Q43: =IF(OR(N43="",P43=""),"",ROUND((P43-N43)/N43,4)) -> 0.0295 | R43: =IF(OR(N43="",P43=""),"",IF(Q43>Settings!$B$3/100,"UP",IF(Q43<-Settings!$B$3/100,"DOWN","FLAT"))) -> UP | S43: =IF(OR(N43="",P43="",J43=""),"",IF(OR(AND(J43="BUY",R43="UP"),AND(J43="SELL",R43="DOWN"),AND(J43="HOLD",R43="FLAT")),"YES","NO")) -> YES | T43: =IF(J43="","",IF(J43="BUY",1,IF(J43="SELL",-1,0))) -> 1 | U43: =IFERROR(IF(OR(J43="",N43="",P43=""),"",IF(T43=0,0,T43*Q43-Settings!$B$4/10000-IF(T43<0,Settings!$B$5/10000,0))),"") -> 0.0285 | W43: =IF($K43="","",$K43*60) -> 4500 | X43: =IF($A43="","",$A43&"|"&$C43&"|"&$D43) -> Bank of America|2025|Q3 | Y43: =IFERROR(IF($X43="","",INDEX(LLM_Data_Entry!$H$3:$H$548,MATCH($X43,INDEX(LLM_Data_Entry!$A$3:$A$548&"|"&LLM_Data_Entry!$C$3:$C$548&"|"&LLM_Data_Entry!$D$3:$D$548,0),0))),"") -> BUY | Z43: =IFERROR(IF($X43="","",INDEX(LLM_Data_Entry!$R$3:$R$548,MATCH($X43,INDEX(LLM_Data_Entry!$A$3:$A$548&"|"&LLM_Data_Entry!$C$3:$C$548&"|"&LLM_Data_Entry!$D$3:$D$548,0),0))),"") -> YES | AB43: price signal — both moved; this one dominates | AC43: BAC | AD43: 2025-10-14 | AE43: 49.2948 | AF43: 2025-10-15 | AG43: 50.7513 | AH43: 0.029546883 | AI43: UP | AJ43: YES | AK43: 0.028547 | AL43: =IF($A43="","",IFERROR(INDEX(Company_List!$G$3:$G$207,MATCH($A43,Company_List!$A$3:$A$207,0)),"unassigned")) -> P2 | AM43: Phase 2/bank of america/2025-Q3/BAC-2025-Q3-earnings-call-transcript-news-alphastreet-com.html | AN43: https://news.alphastreet.com/bank-of-america-corporation-bac-q3-2025-earnings-call-transcript/ | AO43: manifest | AP43: =IF($A43="","",IF(COUNTIFS(LLM_Data_Entry!$A$3:$A$548,$A43)>0,"YES","NO")) -> YES | AQ43: =IF($A43="","",IF(COUNTIFS($A$3:$A43,$A43,$C$3:$C43,$C43,$D$3:$D43,$D43)=1,"YES","NO")) -> YES | AR43: =IF($A43="","",IF(AND($C43&"-"&$D43>=Settings!$B$19,$C43&"-"&$D43<=Settings!$B$20),"IN","OUT")) -> IN | AS43: =IF($A43="","",IF($F43="Financial Results","financials",IF($F43="Outlook/Guidance","guidance",IF($F43="Transcript Q&A","qanda",IF($F43="","unrecorded",IF($E43="All","full",IF($E43="","unrecorded",LOWER($E43)&" only"))))))) -> transcript only | AT43: =IF(AND(OR($J43="BUY",$J43="SELL"),ISNUMBER($U43)),$U43,"") -> 0.0285 | AU43: =IF(AND(OR($J43="BUY",$J43="SELL"),ISNUMBER($AK43)),$AK43,"") -> 0.028547 | AV43: =IF(ISNUMBER($AT43),ABS(IF(ISNUMBER($I43),$I43,0)-Settings!$B$24),"") -> 0.7 | AW43: =IF(ISNUMBER($AV43),$AV43*$AT43,"") -> 0.01995 | AX43: =IF(ISNUMBER($AU43),ABS(IF(ISNUMBER($I43),$I43,0)-Settings!$B$24),"") -> 0.7 | AY43: FROZEN | AZ43: =IF($A43="","",IFERROR(INDEX(Company_List!$H$3:$H$207,MATCH($A43,Company_List!$A$3:$A$207,0)),"unassigned")) -> Financials | BC43: =IF($A43="","",IF(COUNTIFS($A$3:$A43,$A43,$C$3:$C43,$C43,$D$3:$D43,$D43,$G$3:$G43,$G43)=1,1,0)) -> 1 | BG43: no | BK43: =IF(OR($H43<>"Human",$S43="",$J43="",$Y43="",$Z43=""),"",IF(EXACT(UPPER($J43),UPPER($Y43)),1,0)) -> 1 | BL43: assumed - no rater record | BM43: 1 | BN43: not publisher-identified | BO43: not publisher-identified | BP43: no | BQ43: yes | BS43: YES
A44: Bank of America | B44: =IF(A44="","",_xlfn.XLOOKUP(A44, Company_List!$A:$A, Company_List!$B:$B, "")) -> BAC | C44: 2025 | D44: Q4 | E44: Transcript | F44: All | G44: Abdul | H44: Human | I44: 0.1 | J44: =IF(OR(I44="",Settings!$B$6=""),"",IF(I44>Settings!$B$6,"BUY",IF(I44<-Settings!$B$6,"SELL","HOLD"))) -> HOLD | K44: 55 | L44: 46036 | M44: 46035 | N44: 54.54 | O44: 46036 | P44: 52.88 | Q44: =IF(OR(N44="",P44=""),"",ROUND((P44-N44)/N44,4)) -> -0.0304 | R44: =IF(OR(N44="",P44=""),"",IF(Q44>Settings!$B$3/100,"UP",IF(Q44<-Settings!$B$3/100,"DOWN","FLAT"))) -> DOWN | S44: =IF(OR(N44="",P44="",J44=""),"",IF(OR(AND(J44="BUY",R44="UP"),AND(J44="SELL",R44="DOWN"),AND(J44="HOLD",R44="FLAT")),"YES","NO")) -> NO | T44: =IF(J44="","",IF(J44="BUY",1,IF(J44="SELL",-1,0))) -> 0 | U44: =IFERROR(IF(OR(J44="",N44="",P44=""),"",IF(T44=0,0,T44*Q44-Settings!$B$4/10000-IF(T44<0,Settings!$B$5/10000,0))),"") -> 0 | W44: =IF($K44="","",$K44*60) -> 3300 | X44: =IF($A44="","",$A44&"|"&$C44&"|"&$D44) -> Bank of America|2025|Q4 | Y44: =IFERROR(IF($X44="","",INDEX(LLM_Data_Entry!$H$3:$H$548,MATCH($X44,INDEX(LLM_Data_Entry!$A$3:$A$548&"|"&LLM_Data_Entry!$C$3:$C$548&"|"&LLM_Data_Entry!$D$3:$D$548,0),0))),"") -> HOLD | Z44: =IFERROR(IF($X44="","",INDEX(LLM_Data_Entry!$R$3:$R$548,MATCH($X44,INDEX(LLM_Data_Entry!$A$3:$A$548&"|"&LLM_Data_Entry!$C$3:$C$548&"|"&LLM_Data_Entry!$D$3:$D$548,0),0))),"") -> NO | AB44: price signal — only this window shows an abnormal move | AC44: BAC | AD44: 2026-01-13 | AE44: 53.9531 | AF44: 2026-01-14 | AG44: 52.3109 | AH44: -0.030436323 | AI44: DOWN | AJ44: NO | AK44: 0 | AL44: =IF($A44="","",IFERROR(INDEX(Company_List!$G$3:$G$207,MATCH($A44,Company_List!$A$3:$A$207,0)),"unassigned")) -> P2 | AM44: Phase 2/bank of america/2025-Q4/BAC-2025-Q4-earnings-call-transcript-news-alphastreet-com.html | AN44: https://news.alphastreet.com/bank-of-america-corporation-bac-q4-2025-earnings-call-transcript/ | AO44: manifest | AP44: =IF($A44="","",IF(COUNTIFS(LLM_Data_Entry!$A$3:$A$548,$A44)>0,"YES","NO")) -> YES | AQ44: =IF($A44="","",IF(COUNTIFS($A$3:$A44,$A44,$C$3:$C44,$C44,$D$3:$D44,$D44)=1,"YES","NO")) -> YES | AR44: =IF($A44="","",IF(AND($C44&"-"&$D44>=Settings!$B$19,$C44&"-"&$D44<=Settings!$B$20),"IN","OUT")) -> IN | AS44: =IF($A44="","",IF($F44="Financial Results","financials",IF($F44="Outlook/Guidance","guidance",IF($F44="Transcript Q&A","qanda",IF($F44="","unrecorded",IF($E44="All","full",IF($E44="","unrecorded",LOWER($E44)&" only"))))))) -> transcript only | AT44: =IF(AND(OR($J44="BUY",$J44="SELL"),ISNUMBER($U44)),$U44,"") | AU44: =IF(AND(OR($J44="BUY",$J44="SELL"),ISNUMBER($AK44)),$AK44,"") | AV44: =IF(ISNUMBER($AT44),ABS(IF(ISNUMBER($I44),$I44,0)-Settings!$B$24),"") | AW44: =IF(ISNUMBER($AV44),$AV44*$AT44,"") | AX44: =IF(ISNUMBER($AU44),ABS(IF(ISNUMBER($I44),$I44,0)-Settings!$B$24),"") | AY44: FROZEN | AZ44: =IF($A44="","",IFERROR(INDEX(Company_List!$H$3:$H$207,MATCH($A44,Company_List!$A$3:$A$207,0)),"unassigned")) -> Financials | BC44: =IF($A44="","",IF(COUNTIFS($A$3:$A44,$A44,$C$3:$C44,$C44,$D$3:$D44,$D44,$G$3:$G44,$G44)=1,1,0)) -> 1 | BG44: no | BK44: =IF(OR($H44<>"Human",$S44="",$J44="",$Y44="",$Z44=""),"",IF(EXACT(UPPER($J44),UPPER($Y44)),1,0)) -> 1 | BL44: assumed - no rater record | BM44: 1 | BN44: not publisher-identified | BO44: not publisher-identified | BP44: no | BQ44: yes | BS44: YES
A45: AMD | B45: =IF(A45="","",_xlfn.XLOOKUP(A45, Company_List!$A:$A, Company_List!$B:$B, "")) -> AMD | C45: 2026 | D45: Q1 | E45: All | F45: All | G45: David | H45: Human | I45: 0.8 | J45: =IF(OR(I45="",Settings!$B$6=""),"",IF(I45>Settings!$B$6,"BUY",IF(I45<-Settings!$B$6,"SELL","HOLD"))) -> BUY | K45: 51 | L45: 46147 | M45: 46147 | N45: 355.26 | O45: 46148 | P45: 409.49 | Q45: =IF(OR(N45="",P45=""),"",ROUND((P45-N45)/N45,4)) -> 0.1526 | R45: =IF(OR(N45="",P45=""),"",IF(Q45>Settings!$B$3/100,"UP",IF(Q45<-Settings!$B$3/100,"DOWN","FLAT"))) -> UP | S45: =IF(OR(N45="",P45="",J45=""),"",IF(OR(AND(J45="BUY",R45="UP"),AND(J45="SELL",R45="DOWN"),AND(J45="HOLD",R45="FLAT")),"YES","NO")) -> YES | T45: =IF(J45="","",IF(J45="BUY",1,IF(J45="SELL",-1,0))) -> 1 | U45: =IFERROR(IF(OR(J45="",N45="",P45=""),"",IF(T45=0,0,T45*Q45-Settings!$B$4/10000-IF(T45<0,Settings!$B$5/10000,0))),"") -> 0.1516 | W45: =IF($K45="","",$K45*60) -> 3060 | X45: =IF($A45="","",$A45&"|"&$C45&"|"&$D45) -> AMD|2026|Q1 | Y45: =IFERROR(IF($X45="","",INDEX(LLM_Data_Entry!$H$3:$H$548,MATCH($X45,INDEX(LLM_Data_Entry!$A$3:$A$548&"|"&LLM_Data_Entry!$C$3:$C$548&"|"&LLM_Data_Entry!$D$3:$D$548,0),0))),"") -> BUY | Z45: =IFERROR(IF($X45="","",INDEX(LLM_Data_Entry!$R$3:$R$548,MATCH($X45,INDEX(LLM_Data_Entry!$A$3:$A$548&"|"&LLM_Data_Entry!$C$3:$C$548&"|"&LLM_Data_Entry!$D$3:$D$548,0),0))),"") -> YES | AB45: release date + stated time in the document (rater worksheet) | AC45: AMD | AD45: 2026-05-05 | AE45: 355.26 | AF45: 2026-05-06 | AG45: 409.49 | AH45: 0.1526487 | AI45: UP | AJ45: YES | AK45: 0.151649 | AL45: =IF($A45="","",IFERROR(INDEX(Company_List!$G$3:$G$207,MATCH($A45,Company_List!$A$3:$A$207,0)),"unassigned")) -> P2 | AM45: Phase 2/AMD/2026-Q1/AMD-2026-Q1-press-release-SEC-EX-99-1.htm | AN45: https://www.sec.gov/Archives/edgar/data/2488/000000248826000072/q12026991.htm | AO45: manifest | AP45: =IF($A45="","",IF(COUNTIFS(LLM_Data_Entry!$A$3:$A$548,$A45)>0,"YES","NO")) -> YES | AQ45: =IF($A45="","",IF(COUNTIFS($A$3:$A45,$A45,$C$3:$C45,$C45,$D$3:$D45,$D45)=1,"YES","NO")) -> YES | AR45: =IF($A45="","",IF(AND($C45&"-"&$D45>=Settings!$B$19,$C45&"-"&$D45<=Settings!$B$20),"IN","OUT")) -> IN | AS45: =IF($A45="","",IF($F45="Financial Results","financials",IF($F45="Outlook/Guidance","guidance",IF($F45="Transcript Q&A","qanda",IF($F45="","unrecorded",IF($E45="All","full",IF($E45="","unrecorded",LOWER($E45)&" only"))))))) -> full | AT45: =IF(AND(OR($J45="BUY",$J45="SELL"),ISNUMBER($U45)),$U45,"") -> 0.1516 | AU45: =IF(AND(OR($J45="BUY",$J45="SELL"),ISNUMBER($AK45)),$AK45,"") -> 0.151649 | AV45: =IF(ISNUMBER($AT45),ABS(IF(ISNUMBER($I45),$I45,0)-Settings!$B$24),"") -> 0.8 | AW45: =IF(ISNUMBER($AV45),$AV45*$AT45,"") -> 0.12128 | AX45: =IF(ISNUMBER($AU45),ABS(IF(ISNUMBER($I45),$I45,0)-Settings!$B$24),"") -> 0.8 | AY45: FROZEN | AZ45: =IF($A45="","",IFERROR(INDEX(Company_List!$H$3:$H$207,MATCH($A45,Company_List!$A$3:$A$207,0)),"unassigned")) -> Information Technology | BC45: =IF($A45="","",IF(COUNTIFS($A$3:$A45,$A45,$C$3:$C45,$C45,$D$3:$D45,$D45,$G$3:$G45,$G45)=1,1,0)) -> 1 | BG45: no | BK45: =IF(OR($H45<>"Human",$S45="",$J45="",$Y45="",$Z45=""),"",IF(EXACT(UPPER($J45),UPPER($Y45)),1,0)) -> 1 | BL45: assumed - no rater record | BM45: 1 | BN45: not publisher-identified | BO45: not publisher-identified | BP45: no | BQ45: yes | BR45: filled 11 Aug 2026 from the corpus manifest: the company-quarter holds exactly one document and the manifest carries its release date | BS45: YES
A46: AMD | B46: =IF(A46="","",_xlfn.XLOOKUP(A46, Company_List!$A:$A, Company_List!$B:$B, "")) -> AMD | C46: 2025 | D46: Q2 | E46: All | F46: All | G46: David | H46: Human | I46: 0.65 | J46: =IF(OR(I46="",Settings!$B$6=""),"",IF(I46>Settings!$B$6,"BUY",IF(I46<-Settings!$B$6,"SELL","HOLD"))) -> BUY | K46: 44 | L46: 45874 | M46: 45874 | N46: 174.31 | O46: 45875 | P46: 165.05 | Q46: =IF(OR(N46="",P46=""),"",ROUND((P46-N46)/N46,4)) -> -0.0531 | R46: =IF(OR(N46="",P46=""),"",IF(Q46>Settings!$B$3/100,"UP",IF(Q46<-Settings!$B$3/100,"DOWN","FLAT"))) -> DOWN | S46: =IF(OR(N46="",P46="",J46=""),"",IF(OR(AND(J46="BUY",R46="UP"),AND(J46="SELL",R46="DOWN"),AND(J46="HOLD",R46="FLAT")),"YES","NO")) -> NO | T46: =IF(J46="","",IF(J46="BUY",1,IF(J46="SELL",-1,0))) -> 1 | U46: =IFERROR(IF(OR(J46="",N46="",P46=""),"",IF(T46=0,0,T46*Q46-Settings!$B$4/10000-IF(T46<0,Settings!$B$5/10000,0))),"") -> -0.0541 | W46: =IF($K46="","",$K46*60) -> 2640 | X46: =IF($A46="","",$A46&"|"&$C46&"|"&$D46) -> AMD|2025|Q2 | Y46: =IFERROR(IF($X46="","",INDEX(LLM_Data_Entry!$H$3:$H$548,MATCH($X46,INDEX(LLM_Data_Entry!$A$3:$A$548&"|"&LLM_Data_Entry!$C$3:$C$548&"|"&LLM_Data_Entry!$D$3:$D$548,0),0))),"") -> HOLD | Z46: =IFERROR(IF($X46="","",INDEX(LLM_Data_Entry!$R$3:$R$548,MATCH($X46,INDEX(LLM_Data_Entry!$A$3:$A$548&"|"&LLM_Data_Entry!$C$3:$C$548&"|"&LLM_Data_Entry!$D$3:$D$548,0),0))),"") -> NO | AB46: release date + stated time in the document (rater worksheet) | AC46: AMD | AD46: 2025-08-05 | AE46: 174.31 | AF46: 2025-08-06 | AG46: 165.05 | AH46: -0.053123717 | AI46: DOWN | AJ46: NO | AK46: -0.054124 | AL46: =IF($A46="","",IFERROR(INDEX(Company_List!$G$3:$G$207,MATCH($A46,Company_List!$A$3:$A$207,0)),"unassigned")) -> P2 | AM46: Phase 2/AMD/2025-Q2/AMD-2025-Q2-press-release-SEC-EX-99-1.htm | AN46: https://www.sec.gov/Archives/edgar/data/2488/000000248825000106/q22025991.htm | AO46: manifest | AP46: =IF($A46="","",IF(COUNTIFS(LLM_Data_Entry!$A$3:$A$548,$A46)>0,"YES","NO")) -> YES | AQ46: =IF($A46="","",IF(COUNTIFS($A$3:$A46,$A46,$C$3:$C46,$C46,$D$3:$D46,$D46)=1,"YES","NO")) -> YES | AR46: =IF($A46="","",IF(AND($C46&"-"&$D46>=Settings!$B$19,$C46&"-"&$D46<=Settings!$B$20),"IN","OUT")) -> IN | AS46: =IF($A46="","",IF($F46="Financial Results","financials",IF($F46="Outlook/Guidance","guidance",IF($F46="Transcript Q&A","qanda",IF($F46="","unrecorded",IF($E46="All","full",IF($E46="","unrecorded",LOWER($E46)&" only"))))))) -> full | AT46: =IF(AND(OR($J46="BUY",$J46="SELL"),ISNUMBER($U46)),$U46,"") -> -0.0541 | AU46: =IF(AND(OR($J46="BUY",$J46="SELL"),ISNUMBER($AK46)),$AK46,"") -> -0.054124 | AV46: =IF(ISNUMBER($AT46),ABS(IF(ISNUMBER($I46),$I46,0)-Settings!$B$24),"") -> 0.65 | AW46: =IF(ISNUMBER($AV46),$AV46*$AT46,"") -> -0.035165 | AX46: =IF(ISNUMBER($AU46),ABS(IF(ISNUMBER($I46),$I46,0)-Settings!$B$24),"") -> 0.65 | AY46: FROZEN | AZ46: =IF($A46="","",IFERROR(INDEX(Company_List!$H$3:$H$207,MATCH($A46,Company_List!$A$3:$A$207,0)),"unassigned")) -> Information Technology | BC46: =IF($A46="","",IF(COUNTIFS($A$3:$A46,$A46,$C$3:$C46,$C46,$D$3:$D46,$D46,$G$3:$G46,$G46)=1,1,0)) -> 1 | BG46: no | BK46: =IF(OR($H46<>"Human",$S46="",$J46="",$Y46="",$Z46=""),"",IF(EXACT(UPPER($J46),UPPER($Y46)),1,0)) -> 0 | BL46: assumed - no rater record | BM46: 1 | BN46: not publisher-identified | BO46: not publisher-identified | BP46: no | BQ46: yes | BR46: filled 11 Aug 2026 from the corpus manifest: the company-quarter holds exactly one document and the manifest carries its release date | BS46: YES
A47: AMD | B47: =IF(A47="","",_xlfn.XLOOKUP(A47, Company_List!$A:$A, Company_List!$B:$B, "")) -> AMD | C47: 2025 | D47: Q4 | E47: All | F47: All | G47: David | H47: Human | I47: 0.75 | J47: =IF(OR(I47="",Settings!$B$6=""),"",IF(I47>Settings!$B$6,"BUY",IF(I47<-Settings!$B$6,"SELL","HOLD"))) -> BUY | K47: 55 | L47: 46056 | M47: 46056 | N47: 242.11 | O47: 46057 | P47: 215 | Q47: =IF(OR(N47="",P47=""),"",ROUND((P47-N47)/N47,4)) -> -0.112 | R47: =IF(OR(N47="",P47=""),"",IF(Q47>Settings!$B$3/100,"UP",IF(Q47<-Settings!$B$3/100,"DOWN","FLAT"))) -> DOWN | S47: =IF(OR(N47="",P47="",J47=""),"",IF(OR(AND(J47="BUY",R47="UP"),AND(J47="SELL",R47="DOWN"),AND(J47="HOLD",R47="FLAT")),"YES","NO")) -> NO | T47: =IF(J47="","",IF(J47="BUY",1,IF(J47="SELL",-1,0))) -> 1 | U47: =IFERROR(IF(OR(J47="",N47="",P47=""),"",IF(T47=0,0,T47*Q47-Settings!$B$4/10000-IF(T47<0,Settings!$B$5/10000,0))),"") -> -0.113 | W47: =IF($K47="","",$K47*60) -> 3300 | X47: =IF($A47="","",$A47&"|"&$C47&"|"&$D47) -> AMD|2025|Q4 | Y47: =IFERROR(IF($X47="","",INDEX(LLM_Data_Entry!$H$3:$H$548,MATCH($X47,INDEX(LLM_Data_Entry!$A$3:$A$548&"|"&LLM_Data_Entry!$C$3:$C$548&"|"&LLM_Data_Entry!$D$3:$D$548,0),0))),"") -> BUY | Z47: =IFERROR(IF($X47="","",INDEX(LLM_Data_Entry!$R$3:$R$548,MATCH($X47,INDEX(LLM_Data_Entry!$A$3:$A$548&"|"&LLM_Data_Entry!$C$3:$C$548&"|"&LLM_Data_Entry!$D$3:$D$548,0),0))),"") -> NO | AB47: release date + stated time in the document (rater worksheet) | AC47: AMD | AD47: 2026-02-03 | AE47: 242.11 | AF47: 2026-02-04 | AG47: 215 | AH47: -0.1119739 | AI47: DOWN | AJ47: NO | AK47: -0.112974 | AL47: =IF($A47="","",IFERROR(INDEX(Company_List!$G$3:$G$207,MATCH($A47,Company_List!$A$3:$A$207,0)),"unassigned")) -> P2 | AM47: Phase 2/AMD/2025-Q4/AMD-2025-Q4-press-release-SEC-EX-99-1.htm | AN47: https://www.sec.gov/Archives/edgar/data/2488/000000248826000014/q42025991.htm | AO47: manifest | AP47: =IF($A47="","",IF(COUNTIFS(LLM_Data_Entry!$A$3:$A$548,$A47)>0,"YES","NO")) -> YES | AQ47: =IF($A47="","",IF(COUNTIFS($A$3:$A47,$A47,$C$3:$C47,$C47,$D$3:$D47,$D47)=1,"YES","NO")) -> YES | AR47: =IF($A47="","",IF(AND($C47&"-"&$D47>=Settings!$B$19,$C47&"-"&$D47<=Settings!$B$20),"IN","OUT")) -> IN | AS47: =IF($A47="","",IF($F47="Financial Results","financials",IF($F47="Outlook/Guidance","guidance",IF($F47="Transcript Q&A","qanda",IF($F47="","unrecorded",IF($E47="All","full",IF($E47="","unrecorded",LOWER($E47)&" only"))))))) -> full | AT47: =IF(AND(OR($J47="BUY",$J47="SELL"),ISNUMBER($U47)),$U47,"") -> -0.113 | AU47: =IF(AND(OR($J47="BUY",$J47="SELL"),ISNUMBER($AK47)),$AK47,"") -> -0.112974 | AV47: =IF(ISNUMBER($AT47),ABS(IF(ISNUMBER($I47),$I47,0)-Settings!$B$24),"") -> 0.75 | AW47: =IF(ISNUMBER($AV47),$AV47*$AT47,"") -> -0.08475 | AX47: =IF(ISNUMBER($AU47),ABS(IF(ISNUMBER($I47),$I47,0)-Settings!$B$24),"") -> 0.75 | AY47: FROZEN | AZ47: =IF($A47="","",IFERROR(INDEX(Company_List!$H$3:$H$207,MATCH($A47,Company_List!$A$3:$A$207,0)),"unassigned")) -> Information Technology | BC47: =IF($A47="","",IF(COUNTIFS($A$3:$A47,$A47,$C$3:$C47,$C47,$D$3:$D47,$D47,$G$3:$G47,$G47)=1,1,0)) -> 1 | BG47: no | BK47: =IF(OR($H47<>"Human",$S47="",$J47="",$Y47="",$Z47=""),"",IF(EXACT(UPPER($J47),UPPER($Y47)),1,0)) -> 1 | BL47: assumed - no rater record | BM47: 1 | BN47: not publisher-identified | BO47: not publisher-identified | BP47: no | BQ47: yes | BR47: filled 11 Aug 2026 from the corpus manifest: the company-quarter holds exactly one document and the manifest carries its release date | BS47: YES
A48: Airbnb | B48: =IF(A48="","",_xlfn.XLOOKUP(A48, Company_List!$A:$A, Company_List!$B:$B, "")) -> ABNB | C48: 2025 | D48: Q2 | E48: Transcript | F48: All | G48: Anna | H48: Human | I48: 0.6 | J48: =IF(OR(I48="",Settings!$B$6=""),"",IF(I48>Settings!$B$6,"BUY",IF(I48<-Settings!$B$6,"SELL","HOLD"))) -> BUY | K48: 30 | L48: 45875 | M48: 45875 | N48: 130.5 | O48: 45876 | P48: 120.38 | Q48: =IF(OR(N48="",P48=""),"",ROUND((P48-N48)/N48,4)) -> -0.0775 | R48: =IF(OR(N48="",P48=""),"",IF(Q48>Settings!$B$3/100,"UP",IF(Q48<-Settings!$B$3/100,"DOWN","FLAT"))) -> DOWN | S48: =IF(OR(N48="",P48="",J48=""),"",IF(OR(AND(J48="BUY",R48="UP"),AND(J48="SELL",R48="DOWN"),AND(J48="HOLD",R48="FLAT")),"YES","NO")) -> NO | T48: =IF(J48="","",IF(J48="BUY",1,IF(J48="SELL",-1,0))) -> 1 | U48: =IFERROR(IF(OR(J48="",N48="",P48=""),"",IF(T48=0,0,T48*Q48-Settings!$B$4/10000-IF(T48<0,Settings!$B$5/10000,0))),"") -> -0.0785 | W48: =IF($K48="","",$K48*60) -> 1800 | X48: =IF($A48="","",$A48&"|"&$C48&"|"&$D48) -> Airbnb|2025|Q2 | Y48: =IFERROR(IF($X48="","",INDEX(LLM_Data_Entry!$H$3:$H$548,MATCH($X48,INDEX(LLM_Data_Entry!$A$3:$A$548&"|"&LLM_Data_Entry!$C$3:$C$548&"|"&LLM_Data_Entry!$D$3:$D$548,0),0))),"") -> HOLD | Z48: =IFERROR(IF($X48="","",INDEX(LLM_Data_Entry!$R$3:$R$548,MATCH($X48,INDEX(LLM_Data_Entry!$A$3:$A$548&"|"&LLM_Data_Entry!$C$3:$C$548&"|"&LLM_Data_Entry!$D$3:$D$548,0),0))),"") -> NO | AB48: price signal — only this window shows an abnormal move | AC48: ABNB | AD48: 2025-08-06 | AE48: 130.5 | AF48: 2025-08-07 | AG48: 120.38 | AH48: -0.077547916 | AI48: DOWN | AJ48: NO | AK48: -0.078548 | AL48: =IF($A48="","",IFERROR(INDEX(Company_List!$G$3:$G$207,MATCH($A48,Company_List!$A$3:$A$207,0)),"unassigned")) -> P2 | AM48: Phase 2/Airbnb/Airbnb-Q2-25-Earnings-Call-Transcript.pdf | AO48: unique filename match | AP48: =IF($A48="","",IF(COUNTIFS(LLM_Data_Entry!$A$3:$A$548,$A48)>0,"YES","NO")) -> YES | AQ48: =IF($A48="","",IF(COUNTIFS($A$3:$A48,$A48,$C$3:$C48,$C48,$D$3:$D48,$D48)=1,"YES","NO")) -> YES | AR48: =IF($A48="","",IF(AND($C48&"-"&$D48>=Settings!$B$19,$C48&"-"&$D48<=Settings!$B$20),"IN","OUT")) -> IN | AS48: =IF($A48="","",IF($F48="Financial Results","financials",IF($F48="Outlook/Guidance","guidance",IF($F48="Transcript Q&A","qanda",IF($F48="","unrecorded",IF($E48="All","full",IF($E48="","unrecorded",LOWER($E48)&" only"))))))) -> transcript only | AT48: =IF(AND(OR($J48="BUY",$J48="SELL"),ISNUMBER($U48)),$U48,"") -> -0.0785 | AU48: =IF(AND(OR($J48="BUY",$J48="SELL"),ISNUMBER($AK48)),$AK48,"") -> -0.078548 | AV48: =IF(ISNUMBER($AT48),ABS(IF(ISNUMBER($I48),$I48,0)-Settings!$B$24),"") -> 0.6 | AW48: =IF(ISNUMBER($AV48),$AV48*$AT48,"") -> -0.0471 | AX48: =IF(ISNUMBER($AU48),ABS(IF(ISNUMBER($I48),$I48,0)-Settings!$B$24),"") -> 0.6 | AY48: FROZEN | AZ48: =IF($A48="","",IFERROR(INDEX(Company_List!$H$3:$H$207,MATCH($A48,Company_List!$A$3:$A$207,0)),"unassigned")) -> Consumer Discretionary | BC48: =IF($A48="","",IF(COUNTIFS($A$3:$A48,$A48,$C$3:$C48,$C48,$D$3:$D48,$D48,$G$3:$G48,$G48)=1,1,0)) -> 1 | BG48: no | BK48: =IF(OR($H48<>"Human",$S48="",$J48="",$Y48="",$Z48=""),"",IF(EXACT(UPPER($J48),UPPER($Y48)),1,0)) -> 0 | BL48: assumed - no rater record | BM48: 1 | BN48: FactSet CallStreet | BO48: licensed vendor | BP48: no | BQ48: no | BS48: YES
A49: Airbnb | B49: =IF(A49="","",_xlfn.XLOOKUP(A49, Company_List!$A:$A, Company_List!$B:$B, "")) -> ABNB | C49: 2025 | D49: Q3 | E49: Transcript | F49: All | G49: Anna | H49: Human | I49: 0.4 | J49: =IF(OR(I49="",Settings!$B$6=""),"",IF(I49>Settings!$B$6,"BUY",IF(I49<-Settings!$B$6,"SELL","HOLD"))) -> BUY | K49: 31 | L49: 45967 | M49: 45967 | N49: 120.53 | O49: 45968 | P49: 125.49 | Q49: =IF(OR(N49="",P49=""),"",ROUND((P49-N49)/N49,4)) -> 0.0412 | R49: =IF(OR(N49="",P49=""),"",IF(Q49>Settings!$B$3/100,"UP",IF(Q49<-Settings!$B$3/100,"DOWN","FLAT"))) -> UP | S49: =IF(OR(N49="",P49="",J49=""),"",IF(OR(AND(J49="BUY",R49="UP"),AND(J49="SELL",R49="DOWN"),AND(J49="HOLD",R49="FLAT")),"YES","NO")) -> YES | T49: =IF(J49="","",IF(J49="BUY",1,IF(J49="SELL",-1,0))) -> 1 | U49: =IFERROR(IF(OR(J49="",N49="",P49=""),"",IF(T49=0,0,T49*Q49-Settings!$B$4/10000-IF(T49<0,Settings!$B$5/10000,0))),"") -> 0.0402 | W49: =IF($K49="","",$K49*60) -> 1860 | X49: =IF($A49="","",$A49&"|"&$C49&"|"&$D49) -> Airbnb|2025|Q3 | Y49: =IFERROR(IF($X49="","",INDEX(LLM_Data_Entry!$H$3:$H$548,MATCH($X49,INDEX(LLM_Data_Entry!$A$3:$A$548&"|"&LLM_Data_Entry!$C$3:$C$548&"|"&LLM_Data_Entry!$D$3:$D$548,0),0))),"") -> BUY | Z49: =IFERROR(IF($X49="","",INDEX(LLM_Data_Entry!$R$3:$R$548,MATCH($X49,INDEX(LLM_Data_Entry!$A$3:$A$548&"|"&LLM_Data_Entry!$C$3:$C$548&"|"&LLM_Data_Entry!$D$3:$D$548,0),0))),"") -> YES | AB49: price signal — only this window shows an abnormal move | AC49: ABNB | AD49: 2025-11-06 | AE49: 120.53 | AF49: 2025-11-07 | AG49: 125.495 | AH49: 0.041193097 | AI49: UP | AJ49: YES | AK49: 0.040193 | AL49: =IF($A49="","",IFERROR(INDEX(Company_List!$G$3:$G$207,MATCH($A49,Company_List!$A$3:$A$207,0)),"unassigned")) -> P2 | AM49: Phase 2/Airbnb/Airbnb-Q3-2025-Earnings-Call-6-November-2025-5_00-PM-ET.pdf | AO49: unique filename match | AP49: =IF($A49="","",IF(COUNTIFS(LLM_Data_Entry!$A$3:$A$548,$A49)>0,"YES","NO")) -> YES | AQ49: =IF($A49="","",IF(COUNTIFS($A$3:$A49,$A49,$C$3:$C49,$C49,$D$3:$D49,$D49)=1,"YES","NO")) -> YES | AR49: =IF($A49="","",IF(AND($C49&"-"&$D49>=Settings!$B$19,$C49&"-"&$D49<=Settings!$B$20),"IN","OUT")) -> IN | AS49: =IF($A49="","",IF($F49="Financial Results","financials",IF($F49="Outlook/Guidance","guidance",IF($F49="Transcript Q&A","qanda",IF($F49="","unrecorded",IF($E49="All","full",IF($E49="","unrecorded",LOWER($E49)&" only"))))))) -> transcript only | AT49: =IF(AND(OR($J49="BUY",$J49="SELL"),ISNUMBER($U49)),$U49,"") -> 0.0402 | AU49: =IF(AND(OR($J49="BUY",$J49="SELL"),ISNUMBER($AK49)),$AK49,"") -> 0.040193 | AV49: =IF(ISNUMBER($AT49),ABS(IF(ISNUMBER($I49),$I49,0)-Settings!$B$24),"") -> 0.4 | AW49: =IF(ISNUMBER($AV49),$AV49*$AT49,"") -> 0.01608 | AX49: =IF(ISNUMBER($AU49),ABS(IF(ISNUMBER($I49),$I49,0)-Settings!$B$24),"") -> 0.4 | AY49: FROZEN | AZ49: =IF($A49="","",IFERROR(INDEX(Company_List!$H$3:$H$207,MATCH($A49,Company_List!$A$3:$A$207,0)),"unassigned")) -> Consumer Discretionary | BC49: =IF($A49="","",IF(COUNTIFS($A$3:$A49,$A49,$C$3:$C49,$C49,$D$3:$D49,$D49,$G$3:$G49,$G49)=1,1,0)) -> 1 | BG49: no | BK49: =IF(OR($H49<>"Human",$S49="",$J49="",$Y49="",$Z49=""),"",IF(EXACT(UPPER($J49),UPPER($Y49)),1,0)) -> 1 | BL49: assumed - no rater record | BM49: 1 | BN49: FactSet CallStreet | BO49: licensed vendor | BP49: no | BQ49: no | BS49: YES
A50: JPMorgan | B50: =IF(A50="","",_xlfn.XLOOKUP(A50, Company_List!$A:$A, Company_List!$B:$B, "")) -> JPM | C50: 2025 | D50: Q1 | E50: All | F50: All | G50: Nigel | H50: Human | I50: 0.2 | J50: =IF(OR(I50="",Settings!$B$6=""),"",IF(I50>Settings!$B$6,"BUY",IF(I50<-Settings!$B$6,"SELL","HOLD"))) -> HOLD | K50: 32 | L50: 45758 | M50: 45757 | N50: 227.11 | O50: 45758 | P50: 226.31 | Q50: =IF(OR(N50="",P50=""),"",ROUND((P50-N50)/N50,4)) -> -0.0035 | R50: =IF(OR(N50="",P50=""),"",IF(Q50>Settings!$B$3/100,"UP",IF(Q50<-Settings!$B$3/100,"DOWN","FLAT"))) -> FLAT | S50: =IF(OR(N50="",P50="",J50=""),"",IF(OR(AND(J50="BUY",R50="UP"),AND(J50="SELL",R50="DOWN"),AND(J50="HOLD",R50="FLAT")),"YES","NO")) -> YES | T50: =IF(J50="","",IF(J50="BUY",1,IF(J50="SELL",-1,0))) -> 0 | U50: =IFERROR(IF(OR(J50="",N50="",P50=""),"",IF(T50=0,0,T50*Q50-Settings!$B$4/10000-IF(T50<0,Settings!$B$5/10000,0))),"") -> 0 | W50: =IF($K50="","",$K50*60) -> 1920 | X50: =IF($A50="","",$A50&"|"&$C50&"|"&$D50) -> JPMorgan|2025|Q1 | Y50: =IFERROR(IF($X50="","",INDEX(LLM_Data_Entry!$H$3:$H$548,MATCH($X50,INDEX(LLM_Data_Entry!$A$3:$A$548&"|"&LLM_Data_Entry!$C$3:$C$548&"|"&LLM_Data_Entry!$D$3:$D$548,0),0))),"") -> SELL | Z50: =IFERROR(IF($X50="","",INDEX(LLM_Data_Entry!$R$3:$R$548,MATCH($X50,INDEX(LLM_Data_Entry!$A$3:$A$548&"|"&LLM_Data_Entry!$C$3:$C$548&"|"&LLM_Data_Entry!$D$3:$D$548,0),0))),"") -> NO | AB50: document date + price signal | AC50: JPM | AD50: 2025-03-31 | AE50: 238.0749 | AF50: 2025-04-01 | AG50: 235.4738 | AH50: -0.010925476 | AI50: FLAT | AJ50: YES | AK50: 0 | AL50: =IF($A50="","",IFERROR(INDEX(Company_List!$G$3:$G$207,MATCH($A50,Company_List!$A$3:$A$207,0)),"unassigned")) -> P2 | AM50: Phase 2/JPMC Documents/2025-Q1/JPM-2025-Q1-press-release-SEC-EX-99-1.htm; Phase 2/JPMC Documents/2025-Q1/JPM-2025-Q1-earnings-call-transcript-jpmorganchase-com.pdf | AN50: https://www.jpmorganchase.com/content/dam/jpmc/jpmorgan-chase-and-co/investor-relations/documents/quarterly-earnings/2025/1st-quarter/1q25-earnings-transcript.pdf; https://www.sec.gov/Archives/edgar/data/19617/000001961725000332/a1q25erfexhibit991narrative.htm | AO50: manifest (whole bundle) | AP50: =IF($A50="","",IF(COUNTIFS(LLM_Data_Entry!$A$3:$A$548,$A50)>0,"YES","NO")) -> YES | AQ50: =IF($A50="","",IF(COUNTIFS($A$3:$A50,$A50,$C$3:$C50,$C50,$D$3:$D50,$D50)=1,"YES","NO")) -> YES | AR50: =IF($A50="","",IF(AND($C50&"-"&$D50>=Settings!$B$19,$C50&"-"&$D50<=Settings!$B$20),"IN","OUT")) -> IN | AS50: =IF($A50="","",IF($F50="Financial Results","financials",IF($F50="Outlook/Guidance","guidance",IF($F50="Transcript Q&A","qanda",IF($F50="","unrecorded",IF($E50="All","full",IF($E50="","unrecorded",LOWER($E50)&" only"))))))) -> full | AT50: =IF(AND(OR($J50="BUY",$J50="SELL"),ISNUMBER($U50)),$U50,"") | AU50: =IF(AND(OR($J50="BUY",$J50="SELL"),ISNUMBER($AK50)),$AK50,"") | AV50: =IF(ISNUMBER($AT50),ABS(IF(ISNUMBER($I50),$I50,0)-Settings!$B$24),"") | AW50: =IF(ISNUMBER($AV50),$AV50*$AT50,"") | AX50: =IF(ISNUMBER($AU50),ABS(IF(ISNUMBER($I50),$I50,0)-Settings!$B$24),"") | AY50: FROZEN | AZ50: =IF($A50="","",IFERROR(INDEX(Company_List!$H$3:$H$207,MATCH($A50,Company_List!$A$3:$A$207,0)),"unassigned")) -> Financials | BC50: =IF($A50="","",IF(COUNTIFS($A$3:$A50,$A50,$C$3:$C50,$C50,$D$3:$D50,$D50,$G$3:$G50,$G50)=1,1,0)) -> 1 | BG50: no | BK50: =IF(OR($H50<>"Human",$S50="",$J50="",$Y50="",$Z50=""),"",IF(EXACT(UPPER($J50),UPPER($Y50)),1,0)) -> 0 | BL50: assumed - no rater record | BM50: 2 | BN50: not publisher-identified | BO50: not publisher-identified | BP50: no | BQ50: yes | BS50: YES
A51: JPMorgan | B51: =IF(A51="","",_xlfn.XLOOKUP(A51, Company_List!$A:$A, Company_List!$B:$B, "")) -> JPM | C51: 2025 | D51: Q2 | E51: All | F51: All | G51: Nigel | H51: Human | I51: 0.6 | J51: =IF(OR(I51="",Settings!$B$6=""),"",IF(I51>Settings!$B$6,"BUY",IF(I51<-Settings!$B$6,"SELL","HOLD"))) -> BUY | K51: 31 | L51: 45853 | M51: 45852 | N51: 288.7 | O51: 45853 | P51: 288 | Q51: =IF(OR(N51="",P51=""),"",ROUND((P51-N51)/N51,4)) -> -0.0024 | R51: =IF(OR(N51="",P51=""),"",IF(Q51>Settings!$B$3/100,"UP",IF(Q51<-Settings!$B$3/100,"DOWN","FLAT"))) -> FLAT | S51: =IF(OR(N51="",P51="",J51=""),"",IF(OR(AND(J51="BUY",R51="UP"),AND(J51="SELL",R51="DOWN"),AND(J51="HOLD",R51="FLAT")),"YES","NO")) -> NO | T51: =IF(J51="","",IF(J51="BUY",1,IF(J51="SELL",-1,0))) -> 1 | U51: =IFERROR(IF(OR(J51="",N51="",P51=""),"",IF(T51=0,0,T51*Q51-Settings!$B$4/10000-IF(T51<0,Settings!$B$5/10000,0))),"") -> -0.0034 | W51: =IF($K51="","",$K51*60) -> 1860 | X51: =IF($A51="","",$A51&"|"&$C51&"|"&$D51) -> JPMorgan|2025|Q2 | Y51: =IFERROR(IF($X51="","",INDEX(LLM_Data_Entry!$H$3:$H$548,MATCH($X51,INDEX(LLM_Data_Entry!$A$3:$A$548&"|"&LLM_Data_Entry!$C$3:$C$548&"|"&LLM_Data_Entry!$D$3:$D$548,0),0))),"") -> HOLD | Z51: =IFERROR(IF($X51="","",INDEX(LLM_Data_Entry!$R$3:$R$548,MATCH($X51,INDEX(LLM_Data_Entry!$A$3:$A$548&"|"&LLM_Data_Entry!$C$3:$C$548&"|"&LLM_Data_Entry!$D$3:$D$548,0),0))),"") -> YES | AB51: release time published by the issuer | AC51: JPM | AD51: 2025-07-14 | AE51: 283.2807 | AF51: 2025-07-15 | AG51: 282.5938 | AH51: -0.0024247578 | AI51: FLAT | AJ51: NO | AK51: -0.003425 | AL51: =IF($A51="","",IFERROR(INDEX(Company_List!$G$3:$G$207,MATCH($A51,Company_List!$A$3:$A$207,0)),"unassigned")) -> P2 | AM51: Phase 2/JPMC Documents/Q2/corp-q2-2025.pdf | AO51: unique filename match | AP51: =IF($A51="","",IF(COUNTIFS(LLM_Data_Entry!$A$3:$A$548,$A51)>0,"YES","NO")) -> YES | AQ51: =IF($A51="","",IF(COUNTIFS($A$3:$A51,$A51,$C$3:$C51,$C51,$D$3:$D51,$D51)=1,"YES","NO")) -> YES | AR51: =IF($A51="","",IF(AND($C51&"-"&$D51>=Settings!$B$19,$C51&"-"&$D51<=Settings!$B$20),"IN","OUT")) -> IN | AS51: =IF($A51="","",IF($F51="Financial Results","financials",IF($F51="Outlook/Guidance","guidance",IF($F51="Transcript Q&A","qanda",IF($F51="","unrecorded",IF($E51="All","full",IF($E51="","unrecorded",LOWER($E51)&" only"))))))) -> full | AT51: =IF(AND(OR($J51="BUY",$J51="SELL"),ISNUMBER($U51)),$U51,"") -> -0.0034 | AU51: =IF(AND(OR($J51="BUY",$J51="SELL"),ISNUMBER($AK51)),$AK51,"") -> -0.003425 | AV51: =IF(ISNUMBER($AT51),ABS(IF(ISNUMBER($I51),$I51,0)-Settings!$B$24),"") -> 0.6 | AW51: =IF(ISNUMBER($AV51),$AV51*$AT51,"") -> -0.00204 | AX51: =IF(ISNUMBER($AU51),ABS(IF(ISNUMBER($I51),$I51,0)-Settings!$B$24),"") -> 0.6 | AY51: FROZEN | AZ51: =IF($A51="","",IFERROR(INDEX(Company_List!$H$3:$H$207,MATCH($A51,Company_List!$A$3:$A$207,0)),"unassigned")) -> Financials | BC51: =IF($A51="","",IF(COUNTIFS($A$3:$A51,$A51,$C$3:$C51,$C51,$D$3:$D51,$D51,$G$3:$G51,$G51)=1,1,0)) -> 1 | BG51: no | BK51: =IF(OR($H51<>"Human",$S51="",$J51="",$Y51="",$Z51=""),"",IF(EXACT(UPPER($J51),UPPER($Y51)),1,0)) -> 0 | BL51: assumed - no rater record | BM51: 1 | BN51: not publisher-identified | BO51: not publisher-identified | BP51: sole source | BQ51: no | BS51: YES
A52: JPMorgan | B52: =IF(A52="","",_xlfn.XLOOKUP(A52, Company_List!$A:$A, Company_List!$B:$B, "")) -> JPM | C52: 2025 | D52: Q3 | E52: All | F52: All | G52: Nigel | H52: Human | I52: 0.7 | J52: =IF(OR(I52="",Settings!$B$6=""),"",IF(I52>Settings!$B$6,"BUY",IF(I52<-Settings!$B$6,"SELL","HOLD"))) -> BUY | K52: 28 | L52: 45944 | M52: 45943 | N52: 307.97 | O52: 45944 | P52: 305.84 | Q52: =IF(OR(N52="",P52=""),"",ROUND((P52-N52)/N52,4)) -> -0.0069 | R52: =IF(OR(N52="",P52=""),"",IF(Q52>Settings!$B$3/100,"UP",IF(Q52<-Settings!$B$3/100,"DOWN","FLAT"))) -> FLAT | S52: =IF(OR(N52="",P52="",J52=""),"",IF(OR(AND(J52="BUY",R52="UP"),AND(J52="SELL",R52="DOWN"),AND(J52="HOLD",R52="FLAT")),"YES","NO")) -> NO | T52: =IF(J52="","",IF(J52="BUY",1,IF(J52="SELL",-1,0))) -> 1 | U52: =IFERROR(IF(OR(J52="",N52="",P52=""),"",IF(T52=0,0,T52*Q52-Settings!$B$4/10000-IF(T52<0,Settings!$B$5/10000,0))),"") -> -0.0079 | W52: =IF($K52="","",$K52*60) -> 1680 | X52: =IF($A52="","",$A52&"|"&$C52&"|"&$D52) -> JPMorgan|2025|Q3 | Y52: =IFERROR(IF($X52="","",INDEX(LLM_Data_Entry!$H$3:$H$548,MATCH($X52,INDEX(LLM_Data_Entry!$A$3:$A$548&"|"&LLM_Data_Entry!$C$3:$C$548&"|"&LLM_Data_Entry!$D$3:$D$548,0),0))),"") -> HOLD | Z52: =IFERROR(IF($X52="","",INDEX(LLM_Data_Entry!$R$3:$R$548,MATCH($X52,INDEX(LLM_Data_Entry!$A$3:$A$548&"|"&LLM_Data_Entry!$C$3:$C$548&"|"&LLM_Data_Entry!$D$3:$D$548,0),0))),"") -> YES | AB52: release time published by the issuer | AC52: JPM | AD52: 2025-10-13 | AE52: 303.6581 | AF52: 2025-10-14 | AG52: 301.5579 | AH52: -0.0069162052 | AI52: FLAT | AJ52: NO | AK52: -0.007916 | AL52: =IF($A52="","",IFERROR(INDEX(Company_List!$G$3:$G$207,MATCH($A52,Company_List!$A$3:$A$207,0)),"unassigned")) -> P2 | AM52: Phase 2/JPMC Documents/2025-Q3/JPM-2025-Q3-press-release-SEC-EX-99-1.htm; Phase 2/JPMC Documents/2025-Q3/JPM-2025-Q3-earnings-call-transcript-jpmorganchase-com.pdf | AN52: https://www.jpmorganchase.com/content/dam/jpmc/jpmorgan-chase-and-co/investor-relations/documents/quarterly-earnings/2025/3rd-quarter/jpm-3q25-earnings-call-transcript.pdf; https://www.sec.gov/Archives/edgar/data/19617/000162828025044845/a3q25erfexhibit991narrative.htm | AO52: manifest (whole bundle) | AP52: =IF($A52="","",IF(COUNTIFS(LLM_Data_Entry!$A$3:$A$548,$A52)>0,"YES","NO")) -> YES | AQ52: =IF($A52="","",IF(COUNTIFS($A$3:$A52,$A52,$C$3:$C52,$C52,$D$3:$D52,$D52)=1,"YES","NO")) -> YES | AR52: =IF($A52="","",IF(AND($C52&"-"&$D52>=Settings!$B$19,$C52&"-"&$D52<=Settings!$B$20),"IN","OUT")) -> IN | AS52: =IF($A52="","",IF($F52="Financial Results","financials",IF($F52="Outlook/Guidance","guidance",IF($F52="Transcript Q&A","qanda",IF($F52="","unrecorded",IF($E52="All","full",IF($E52="","unrecorded",LOWER($E52)&" only"))))))) -> full | AT52: =IF(AND(OR($J52="BUY",$J52="SELL"),ISNUMBER($U52)),$U52,"") -> -0.0079 | AU52: =IF(AND(OR($J52="BUY",$J52="SELL"),ISNUMBER($AK52)),$AK52,"") -> -0.007916 | AV52: =IF(ISNUMBER($AT52),ABS(IF(ISNUMBER($I52),$I52,0)-Settings!$B$24),"") -> 0.7 | AW52: =IF(ISNUMBER($AV52),$AV52*$AT52,"") -> -0.00553 | AX52: =IF(ISNUMBER($AU52),ABS(IF(ISNUMBER($I52),$I52,0)-Settings!$B$24),"") -> 0.7 | AY52: FROZEN | AZ52: =IF($A52="","",IFERROR(INDEX(Company_List!$H$3:$H$207,MATCH($A52,Company_List!$A$3:$A$207,0)),"unassigned")) -> Financials | BC52: =IF($A52="","",IF(COUNTIFS($A$3:$A52,$A52,$C$3:$C52,$C52,$D$3:$D52,$D52,$G$3:$G52,$G52)=1,1,0)) -> 1 | BG52: no | BK52: =IF(OR($H52<>"Human",$S52="",$J52="",$Y52="",$Z52=""),"",IF(EXACT(UPPER($J52),UPPER($Y52)),1,0)) -> 0 | BL52: assumed - no rater record | BM52: 2 | BN52: not publisher-identified | BO52: not publisher-identified | BP52: no | BQ52: yes | BS52: YES
A53: JPMorgan | B53: =IF(A53="","",_xlfn.XLOOKUP(A53, Company_List!$A:$A, Company_List!$B:$B, "")) -> JPM | C53: 2025 | D53: Q4 | E53: All | F53: All | G53: Nigel | H53: Human | I53: -0.4 | J53: =IF(OR(I53="",Settings!$B$6=""),"",IF(I53>Settings!$B$6,"BUY",IF(I53<-Settings!$B$6,"SELL","HOLD"))) -> SELL | K53: 24 | L53: 46035 | M53: 46034 | N53: 324.49 | O53: 46035 | P53: 324.3 | Q53: =IF(OR(N53="",P53=""),"",ROUND((P53-N53)/N53,4)) -> -0.0006 | R53: =IF(OR(N53="",P53=""),"",IF(Q53>Settings!$B$3/100,"UP",IF(Q53<-Settings!$B$3/100,"DOWN","FLAT"))) -> FLAT | S53: =IF(OR(N53="",P53="",J53=""),"",IF(OR(AND(J53="BUY",R53="UP"),AND(J53="SELL",R53="DOWN"),AND(J53="HOLD",R53="FLAT")),"YES","NO")) -> NO | T53: =IF(J53="","",IF(J53="BUY",1,IF(J53="SELL",-1,0))) -> -1 | U53: =IFERROR(IF(OR(J53="",N53="",P53=""),"",IF(T53=0,0,T53*Q53-Settings!$B$4/10000-IF(T53<0,Settings!$B$5/10000,0))),"") -> -0.0004 | W53: =IF($K53="","",$K53*60) -> 1440 | X53: =IF($A53="","",$A53&"|"&$C53&"|"&$D53) -> JPMorgan|2025|Q4 | Y53: =IFERROR(IF($X53="","",INDEX(LLM_Data_Entry!$H$3:$H$548,MATCH($X53,INDEX(LLM_Data_Entry!$A$3:$A$548&"|"&LLM_Data_Entry!$C$3:$C$548&"|"&LLM_Data_Entry!$D$3:$D$548,0),0))),"") -> HOLD | Z53: =IFERROR(IF($X53="","",INDEX(LLM_Data_Entry!$R$3:$R$548,MATCH($X53,INDEX(LLM_Data_Entry!$A$3:$A$548&"|"&LLM_Data_Entry!$C$3:$C$548&"|"&LLM_Data_Entry!$D$3:$D$548,0),0))),"") -> YES | AB53: release time published by the issuer | AC53: JPM | AD53: 2026-01-12 | AE53: 321.39 | AF53: 2026-01-13 | AG53: 321.2018 | AH53: -0.00058557171 | AI53: FLAT | AJ53: NO | AK53: -0.000414 | AL53: =IF($A53="","",IFERROR(INDEX(Company_List!$G$3:$G$207,MATCH($A53,Company_List!$A$3:$A$207,0)),"unassigned")) -> P2 | AM53: Phase 2/JPMC Documents/Q4/corp-10k-2025.pdf | AO53: unique filename match | AP53: =IF($A53="","",IF(COUNTIFS(LLM_Data_Entry!$A$3:$A$548,$A53)>0,"YES","NO")) -> YES | AQ53: =IF($A53="","",IF(COUNTIFS($A$3:$A53,$A53,$C$3:$C53,$C53,$D$3:$D53,$D53)=1,"YES","NO")) -> YES | AR53: =IF($A53="","",IF(AND($C53&"-"&$D53>=Settings!$B$19,$C53&"-"&$D53<=Settings!$B$20),"IN","OUT")) -> IN | AS53: =IF($A53="","",IF($F53="Financial Results","financials",IF($F53="Outlook/Guidance","guidance",IF($F53="Transcript Q&A","qanda",IF($F53="","unrecorded",IF($E53="All","full",IF($E53="","unrecorded",LOWER($E53)&" only"))))))) -> full | AT53: =IF(AND(OR($J53="BUY",$J53="SELL"),ISNUMBER($U53)),$U53,"") -> -0.0004 | AU53: =IF(AND(OR($J53="BUY",$J53="SELL"),ISNUMBER($AK53)),$AK53,"") -> -0.000414 | AV53: =IF(ISNUMBER($AT53),ABS(IF(ISNUMBER($I53),$I53,0)-Settings!$B$24),"") -> 0.4 | AW53: =IF(ISNUMBER($AV53),$AV53*$AT53,"") -> -0.00016 | AX53: =IF(ISNUMBER($AU53),ABS(IF(ISNUMBER($I53),$I53,0)-Settings!$B$24),"") -> 0.4 | AY53: FROZEN | AZ53: =IF($A53="","",IFERROR(INDEX(Company_List!$H$3:$H$207,MATCH($A53,Company_List!$A$3:$A$207,0)),"unassigned")) -> Financials | BC53: =IF($A53="","",IF(COUNTIFS($A$3:$A53,$A53,$C$3:$C53,$C53,$D$3:$D53,$D53,$G$3:$G53,$G53)=1,1,0)) -> 1 | BG53: no | BK53: =IF(OR($H53<>"Human",$S53="",$J53="",$Y53="",$Z53=""),"",IF(EXACT(UPPER($J53),UPPER($Y53)),1,0)) -> 0 | BL53: assumed - no rater record | BM53: 1 | BN53: not publisher-identified | BO53: not publisher-identified | BP53: sole source | BQ53: no | BS53: YES
A54: JPMorgan | B54: =IF(A54="","",_xlfn.XLOOKUP(A54, Company_List!$A:$A, Company_List!$B:$B, "")) -> JPM | C54: 2025 | D54: Q1 | E54: Transcript | F54: All | G54: Abdul | H54: Human | I54: 0.1 | J54: =IF(OR(I54="",Settings!$B$6=""),"",IF(I54>Settings!$B$6,"BUY",IF(I54<-Settings!$B$6,"SELL","HOLD"))) -> HOLD | K54: 72 | L54: 45758 | M54: 45757 | N54: 227.11 | O54: 45758 | P54: 226.31 | Q54: =IF(OR(N54="",P54=""),"",ROUND((P54-N54)/N54,4)) -> -0.0035 | R54: =IF(OR(N54="",P54=""),"",IF(Q54>Settings!$B$3/100,"UP",IF(Q54<-Settings!$B$3/100,"DOWN","FLAT"))) -> FLAT | S54: =IF(OR(N54="",P54="",J54=""),"",IF(OR(AND(J54="BUY",R54="UP"),AND(J54="SELL",R54="DOWN"),AND(J54="HOLD",R54="FLAT")),"YES","NO")) -> YES | T54: =IF(J54="","",IF(J54="BUY",1,IF(J54="SELL",-1,0))) -> 0 | U54: =IFERROR(IF(OR(J54="",N54="",P54=""),"",IF(T54=0,0,T54*Q54-Settings!$B$4/10000-IF(T54<0,Settings!$B$5/10000,0))),"") -> 0 | W54: =IF($K54="","",$K54*60) -> 4320 | X54: =IF($A54="","",$A54&"|"&$C54&"|"&$D54) -> JPMorgan|2025|Q1 | Y54: =IFERROR(IF($X54="","",INDEX(LLM_Data_Entry!$H$3:$H$548,MATCH($X54,INDEX(LLM_Data_Entry!$A$3:$A$548&"|"&LLM_Data_Entry!$C$3:$C$548&"|"&LLM_Data_Entry!$D$3:$D$548,0),0))),"") -> SELL | Z54: =IFERROR(IF($X54="","",INDEX(LLM_Data_Entry!$R$3:$R$548,MATCH($X54,INDEX(LLM_Data_Entry!$A$3:$A$548&"|"&LLM_Data_Entry!$C$3:$C$548&"|"&LLM_Data_Entry!$D$3:$D$548,0),0))),"") -> NO | AB54: document date + price signal | AC54: JPM | AD54: 2025-03-31 | AE54: 238.0749 | AF54: 2025-04-01 | AG54: 235.4738 | AH54: -0.010925476 | AI54: FLAT | AJ54: YES | AK54: 0 | AL54: =IF($A54="","",IFERROR(INDEX(Company_List!$G$3:$G$207,MATCH($A54,Company_List!$A$3:$A$207,0)),"unassigned")) -> P2 | AM54: Phase 2/JPMC Documents/2025-Q1/JPM-2025-Q1-earnings-call-transcript-jpmorganchase-com.pdf | AN54: https://www.jpmorganchase.com/content/dam/jpmc/jpmorgan-chase-and-co/investor-relations/documents/quarterly-earnings/2025/1st-quarter/1q25-earnings-transcript.pdf | AO54: manifest | AP54: =IF($A54="","",IF(COUNTIFS(LLM_Data_Entry!$A$3:$A$548,$A54)>0,"YES","NO")) -> YES | AQ54: =IF($A54="","",IF(COUNTIFS($A$3:$A54,$A54,$C$3:$C54,$C54,$D$3:$D54,$D54)=1,"YES","NO")) -> NO | AR54: =IF($A54="","",IF(AND($C54&"-"&$D54>=Settings!$B$19,$C54&"-"&$D54<=Settings!$B$20),"IN","OUT")) -> IN | AS54: =IF($A54="","",IF($F54="Financial Results","financials",IF($F54="Outlook/Guidance","guidance",IF($F54="Transcript Q&A","qanda",IF($F54="","unrecorded",IF($E54="All","full",IF($E54="","unrecorded",LOWER($E54)&" only"))))))) -> transcript only | AT54: =IF(AND(OR($J54="BUY",$J54="SELL"),ISNUMBER($U54)),$U54,"") | AU54: =IF(AND(OR($J54="BUY",$J54="SELL"),ISNUMBER($AK54)),$AK54,"") | AV54: =IF(ISNUMBER($AT54),ABS(IF(ISNUMBER($I54),$I54,0)-Settings!$B$24),"") | AW54: =IF(ISNUMBER($AV54),$AV54*$AT54,"") | AX54: =IF(ISNUMBER($AU54),ABS(IF(ISNUMBER($I54),$I54,0)-Settings!$B$24),"") | AY54: FROZEN | AZ54: =IF($A54="","",IFERROR(INDEX(Company_List!$H$3:$H$207,MATCH($A54,Company_List!$A$3:$A$207,0)),"unassigned")) -> Financials | BC54: =IF($A54="","",IF(COUNTIFS($A$3:$A54,$A54,$C$3:$C54,$C54,$D$3:$D54,$D54,$G$3:$G54,$G54)=1,1,0)) -> 1 | BG54: no | BK54: =IF(OR($H54<>"Human",$S54="",$J54="",$Y54="",$Z54=""),"",IF(EXACT(UPPER($J54),UPPER($Y54)),1,0)) -> 0 | BL54: assumed - no rater record | BM54: 1 | BN54: not publisher-identified | BO54: not publisher-identified | BP54: no | BQ54: yes | BS54: YES
A55: JPMorgan | B55: =IF(A55="","",_xlfn.XLOOKUP(A55, Company_List!$A:$A, Company_List!$B:$B, "")) -> JPM | C55: 2025 | D55: Q3 | E55: Transcript | F55: All | G55: Abdul | H55: Human | I55: 0.4 | J55: =IF(OR(I55="",Settings!$B$6=""),"",IF(I55>Settings!$B$6,"BUY",IF(I55<-Settings!$B$6,"SELL","HOLD"))) -> BUY | K55: 55 | L55: 45944 | M55: 45943 | N55: 307.97 | O55: 45944 | P55: 305.84 | Q55: =IF(OR(N55="",P55=""),"",ROUND((P55-N55)/N55,4)) -> -0.0069 | R55: =IF(OR(N55="",P55=""),"",IF(Q55>Settings!$B$3/100,"UP",IF(Q55<-Settings!$B$3/100,"DOWN","FLAT"))) -> FLAT | S55: =IF(OR(N55="",P55="",J55=""),"",IF(OR(AND(J55="BUY",R55="UP"),AND(J55="SELL",R55="DOWN"),AND(J55="HOLD",R55="FLAT")),"YES","NO")) -> NO | T55: =IF(J55="","",IF(J55="BUY",1,IF(J55="SELL",-1,0))) -> 1 | U55: =IFERROR(IF(OR(J55="",N55="",P55=""),"",IF(T55=0,0,T55*Q55-Settings!$B$4/10000-IF(T55<0,Settings!$B$5/10000,0))),"") -> -0.0079 | W55: =IF($K55="","",$K55*60) -> 3300 | X55: =IF($A55="","",$A55&"|"&$C55&"|"&$D55) -> JPMorgan|2025|Q3 | Y55: =IFERROR(IF($X55="","",INDEX(LLM_Data_Entry!$H$3:$H$548,MATCH($X55,INDEX(LLM_Data_Entry!$A$3:$A$548&"|"&LLM_Data_Entry!$C$3:$C$548&"|"&LLM_Data_Entry!$D$3:$D$548,0),0))),"") -> HOLD | Z55: =IFERROR(IF($X55="","",INDEX(LLM_Data_Entry!$R$3:$R$548,MATCH($X55,INDEX(LLM_Data_Entry!$A$3:$A$548&"|"&LLM_Data_Entry!$C$3:$C$548&"|"&LLM_Data_Entry!$D$3:$D$548,0),0))),"") -> YES | AB55: release time published by the issuer | AC55: JPM | AD55: 2025-10-13 | AE55: 303.6581 | AF55: 2025-10-14 | AG55: 301.5579 | AH55: -0.0069162052 | AI55: FLAT | AJ55: NO | AK55: -0.007916 | AL55: =IF($A55="","",IFERROR(INDEX(Company_List!$G$3:$G$207,MATCH($A55,Company_List!$A$3:$A$207,0)),"unassigned")) -> P2 | AM55: Phase 2/JPMC Documents/2025-Q3/JPM-2025-Q3-earnings-call-transcript-jpmorganchase-com.pdf | AN55: https://www.jpmorganchase.com/content/dam/jpmc/jpmorgan-chase-and-co/investor-relations/documents/quarterly-earnings/2025/3rd-quarter/jpm-3q25-earnings-call-transcript.pdf | AO55: manifest | AP55: =IF($A55="","",IF(COUNTIFS(LLM_Data_Entry!$A$3:$A$548,$A55)>0,"YES","NO")) -> YES | AQ55: =IF($A55="","",IF(COUNTIFS($A$3:$A55,$A55,$C$3:$C55,$C55,$D$3:$D55,$D55)=1,"YES","NO")) -> NO | AR55: =IF($A55="","",IF(AND($C55&"-"&$D55>=Settings!$B$19,$C55&"-"&$D55<=Settings!$B$20),"IN","OUT")) -> IN | AS55: =IF($A55="","",IF($F55="Financial Results","financials",IF($F55="Outlook/Guidance","guidance",IF($F55="Transcript Q&A","qanda",IF($F55="","unrecorded",IF($E55="All","full",IF($E55="","unrecorded",LOWER($E55)&" only"))))))) -> transcript only | AT55: =IF(AND(OR($J55="BUY",$J55="SELL"),ISNUMBER($U55)),$U55,"") -> -0.0079 | AU55: =IF(AND(OR($J55="BUY",$J55="SELL"),ISNUMBER($AK55)),$AK55,"") -> -0.007916 | AV55: =IF(ISNUMBER($AT55),ABS(IF(ISNUMBER($I55),$I55,0)-Settings!$B$24),"") -> 0.4 | AW55: =IF(ISNUMBER($AV55),$AV55*$AT55,"") -> -0.00316 | AX55: =IF(ISNUMBER($AU55),ABS(IF(ISNUMBER($I55),$I55,0)-Settings!$B$24),"") -> 0.4 | AY55: FROZEN | AZ55: =IF($A55="","",IFERROR(INDEX(Company_List!$H$3:$H$207,MATCH($A55,Company_List!$A$3:$A$207,0)),"unassigned")) -> Financials | BC55: =IF($A55="","",IF(COUNTIFS($A$3:$A55,$A55,$C$3:$C55,$C55,$D$3:$D55,$D55,$G$3:$G55,$G55)=1,1,0)) -> 1 | BG55: no | BK55: =IF(OR($H55<>"Human",$S55="",$J55="",$Y55="",$Z55=""),"",IF(EXACT(UPPER($J55),UPPER($Y55)),1,0)) -> 0 | BL55: assumed - no rater record | BM55: 1 | BN55: not publisher-identified | BO55: not publisher-identified | BP55: no | BQ55: yes | BS55: YES
A56: JPMorgan | B56: =IF(A56="","",_xlfn.XLOOKUP(A56, Company_List!$A:$A, Company_List!$B:$B, "")) -> JPM | C56: 2026 | D56: Q1 | E56: Transcript | F56: All | G56: Abdul | H56: Human | I56: 0.5 | J56: =IF(OR(I56="",Settings!$B$6=""),"",IF(I56>Settings!$B$6,"BUY",IF(I56<-Settings!$B$6,"SELL","HOLD"))) -> BUY | K56: 74 | L56: 46126 | M56: 46125 | N56: 313.68 | O56: 46126 | P56: 309.82 | Q56: =IF(OR(N56="",P56=""),"",ROUND((P56-N56)/N56,4)) -> -0.0123 | R56: =IF(OR(N56="",P56=""),"",IF(Q56>Settings!$B$3/100,"UP",IF(Q56<-Settings!$B$3/100,"DOWN","FLAT"))) -> FLAT | S56: =IF(OR(N56="",P56="",J56=""),"",IF(OR(AND(J56="BUY",R56="UP"),AND(J56="SELL",R56="DOWN"),AND(J56="HOLD",R56="FLAT")),"YES","NO")) -> NO | T56: =IF(J56="","",IF(J56="BUY",1,IF(J56="SELL",-1,0))) -> 1 | U56: =IFERROR(IF(OR(J56="",N56="",P56=""),"",IF(T56=0,0,T56*Q56-Settings!$B$4/10000-IF(T56<0,Settings!$B$5/10000,0))),"") -> -0.0133 | W56: =IF($K56="","",$K56*60) -> 4440 | X56: =IF($A56="","",$A56&"|"&$C56&"|"&$D56) -> JPMorgan|2026|Q1 | Y56: =IFERROR(IF($X56="","",INDEX(LLM_Data_Entry!$H$3:$H$548,MATCH($X56,INDEX(LLM_Data_Entry!$A$3:$A$548&"|"&LLM_Data_Entry!$C$3:$C$548&"|"&LLM_Data_Entry!$D$3:$D$548,0),0))),"") -> SELL | Z56: =IFERROR(IF($X56="","",INDEX(LLM_Data_Entry!$R$3:$R$548,MATCH($X56,INDEX(LLM_Data_Entry!$A$3:$A$548&"|"&LLM_Data_Entry!$C$3:$C$548&"|"&LLM_Data_Entry!$D$3:$D$548,0),0))),"") -> NO | AB56: release time published by the issuer | AC56: JPM | AD56: 2026-04-13 | AE56: 312.2732 | AF56: 2026-04-14 | AG56: 308.4305 | AH56: -0.012305509 | AI56: FLAT | AJ56: NO | AK56: -0.013306 | AL56: =IF($A56="","",IFERROR(INDEX(Company_List!$G$3:$G$207,MATCH($A56,Company_List!$A$3:$A$207,0)),"unassigned")) -> P2 | AM56: Phase 2/JPMC Documents/2026-Q1/JPM-2026-Q1-earnings-call-transcript-jpmorganchase-com.pdf | AN56: https://www.jpmorganchase.com/content/dam/jpmc/jpmorgan-chase-and-co/investor-relations/documents/quarterly-earnings/2026/1st-quarter/1q26-earnings-transcript.pdf | AO56: manifest | AP56: =IF($A56="","",IF(COUNTIFS(LLM_Data_Entry!$A$3:$A$548,$A56)>0,"YES","NO")) -> YES | AQ56: =IF($A56="","",IF(COUNTIFS($A$3:$A56,$A56,$C$3:$C56,$C56,$D$3:$D56,$D56)=1,"YES","NO")) -> YES | AR56: =IF($A56="","",IF(AND($C56&"-"&$D56>=Settings!$B$19,$C56&"-"&$D56<=Settings!$B$20),"IN","OUT")) -> IN | AS56: =IF($A56="","",IF($F56="Financial Results","financials",IF($F56="Outlook/Guidance","guidance",IF($F56="Transcript Q&A","qanda",IF($F56="","unrecorded",IF($E56="All","full",IF($E56="","unrecorded",LOWER($E56)&" only"))))))) -> transcript only | AT56: =IF(AND(OR($J56="BUY",$J56="SELL"),ISNUMBER($U56)),$U56,"") -> -0.0133 | AU56: =IF(AND(OR($J56="BUY",$J56="SELL"),ISNUMBER($AK56)),$AK56,"") -> -0.013306 | AV56: =IF(ISNUMBER($AT56),ABS(IF(ISNUMBER($I56),$I56,0)-Settings!$B$24),"") -> 0.5 | AW56: =IF(ISNUMBER($AV56),$AV56*$AT56,"") -> -0.00665 | AX56: =IF(ISNUMBER($AU56),ABS(IF(ISNUMBER($I56),$I56,0)-Settings!$B$24),"") -> 0.5 | AY56: FROZEN | AZ56: =IF($A56="","",IFERROR(INDEX(Company_List!$H$3:$H$207,MATCH($A56,Company_List!$A$3:$A$207,0)),"unassigned")) -> Financials | BC56: =IF($A56="","",IF(COUNTIFS($A$3:$A56,$A56,$C$3:$C56,$C56,$D$3:$D56,$D56,$G$3:$G56,$G56)=1,1,0)) -> 1 | BG56: no | BK56: =IF(OR($H56<>"Human",$S56="",$J56="",$Y56="",$Z56=""),"",IF(EXACT(UPPER($J56),UPPER($Y56)),1,0)) -> 0 | BL56: assumed - no rater record | BM56: 1 | BN56: not publisher-identified | BO56: not publisher-identified | BP56: no | BQ56: yes | BS56: YES
A57: IBM | B57: =IF(A57="","",_xlfn.XLOOKUP(A57, Company_List!$A:$A, Company_List!$B:$B, "")) -> IBM | C57: 2025 | D57: Q2 | E57: All | F57: All | G57: Meriem | H57: Human | I57: 0.4 | J57: =IF(OR(I57="",Settings!$B$6=""),"",IF(I57>Settings!$B$6,"BUY",IF(I57<-Settings!$B$6,"SELL","HOLD"))) -> BUY | K57: 40 | L57: 45861 | M57: 45861 | N57: 282.01 | O57: 45862 | P57: 261.25 | Q57: =IF(OR(N57="",P57=""),"",ROUND((P57-N57)/N57,4)) -> -0.0736 | R57: =IF(OR(N57="",P57=""),"",IF(Q57>Settings!$B$3/100,"UP",IF(Q57<-Settings!$B$3/100,"DOWN","FLAT"))) -> DOWN | S57: =IF(OR(N57="",P57="",J57=""),"",IF(OR(AND(J57="BUY",R57="UP"),AND(J57="SELL",R57="DOWN"),AND(J57="HOLD",R57="FLAT")),"YES","NO")) -> NO | T57: =IF(J57="","",IF(J57="BUY",1,IF(J57="SELL",-1,0))) -> 1 | U57: =IFERROR(IF(OR(J57="",N57="",P57=""),"",IF(T57=0,0,T57*Q57-Settings!$B$4/10000-IF(T57<0,Settings!$B$5/10000,0))),"") -> -0.0746 | V57: revenue up 8% you; profit is up and G profit margin + EPS asw. numbers look great and tone is optimistic | W57: =IF($K57="","",$K57*60) -> 2400 | X57: =IF($A57="","",$A57&"|"&$C57&"|"&$D57) -> IBM|2025|Q2 | Y57: =IFERROR(IF($X57="","",INDEX(LLM_Data_Entry!$H$3:$H$548,MATCH($X57,INDEX(LLM_Data_Entry!$A$3:$A$548&"|"&LLM_Data_Entry!$C$3:$C$548&"|"&LLM_Data_Entry!$D$3:$D$548,0),0))),"") -> BUY | Z57: =IFERROR(IF($X57="","",INDEX(LLM_Data_Entry!$R$3:$R$548,MATCH($X57,INDEX(LLM_Data_Entry!$A$3:$A$548&"|"&LLM_Data_Entry!$C$3:$C$548&"|"&LLM_Data_Entry!$D$3:$D$548,0),0))),"") -> NO | AB57: price signal — only this window shows an abnormal move | AC57: IBM | AD57: 2025-07-23 | AE57: 274.977 | AF57: 2025-07-24 | AG57: 254.7347 | AH57: -0.073614474 | AI57: DOWN | AJ57: NO | AK57: -0.074614 | AL57: =IF($A57="","",IFERROR(INDEX(Company_List!$G$3:$G$207,MATCH($A57,Company_List!$A$3:$A$207,0)),"unassigned")) -> P2 | AM57: Phase 2/IBM/Q2 2025 Earnings Call Transcript.pdf; Phase 2/IBM/Q2 2025 - numbers.pdf | AO57: whole bundle (Document = All) | AP57: =IF($A57="","",IF(COUNTIFS(LLM_Data_Entry!$A$3:$A$548,$A57)>0,"YES","NO")) -> YES | AQ57: =IF($A57="","",IF(COUNTIFS($A$3:$A57,$A57,$C$3:$C57,$C57,$D$3:$D57,$D57)=1,"YES","NO")) -> YES | AR57: =IF($A57="","",IF(AND($C57&"-"&$D57>=Settings!$B$19,$C57&"-"&$D57<=Settings!$B$20),"IN","OUT")) -> IN | AS57: =IF($A57="","",IF($F57="Financial Results","financials",IF($F57="Outlook/Guidance","guidance",IF($F57="Transcript Q&A","qanda",IF($F57="","unrecorded",IF($E57="All","full",IF($E57="","unrecorded",LOWER($E57)&" only"))))))) -> full | AT57: =IF(AND(OR($J57="BUY",$J57="SELL"),ISNUMBER($U57)),$U57,"") -> -0.0746 | AU57: =IF(AND(OR($J57="BUY",$J57="SELL"),ISNUMBER($AK57)),$AK57,"") -> -0.074614 | AV57: =IF(ISNUMBER($AT57),ABS(IF(ISNUMBER($I57),$I57,0)-Settings!$B$24),"") -> 0.4 | AW57: =IF(ISNUMBER($AV57),$AV57*$AT57,"") -> -0.02984 | AX57: =IF(ISNUMBER($AU57),ABS(IF(ISNUMBER($I57),$I57,0)-Settings!$B$24),"") -> 0.4 | AY57: FROZEN | AZ57: =IF($A57="","",IFERROR(INDEX(Company_List!$H$3:$H$207,MATCH($A57,Company_List!$A$3:$A$207,0)),"unassigned")) -> Information Technology | BC57: =IF($A57="","",IF(COUNTIFS($A$3:$A57,$A57,$C$3:$C57,$C57,$D$3:$D57,$D57,$G$3:$G57,$G57)=1,1,0)) -> 1 | BG57: no | BK57: =IF(OR($H57<>"Human",$S57="",$J57="",$Y57="",$Z57=""),"",IF(EXACT(UPPER($J57),UPPER($Y57)),1,0)) -> 1 | BL57: assumed - no rater record | BM57: 2 | BN57: The Motley Fool | BO57: free to read, copyright asserted | BP57: no | BQ57: no | BS57: YES
A58: IBM | B58: =IF(A58="","",_xlfn.XLOOKUP(A58, Company_List!$A:$A, Company_List!$B:$B, "")) -> IBM | C58: 2025 | D58: Q4 | E58: All | F58: All | G58: Meriem | H58: Human | I58: 0.5 | J58: =IF(OR(I58="",Settings!$B$6=""),"",IF(I58>Settings!$B$6,"BUY",IF(I58<-Settings!$B$6,"SELL","HOLD"))) -> BUY | K58: 30 | L58: 46050 | M58: 46050 | N58: 294.16 | O58: 46051 | P58: 317.86 | Q58: =IF(OR(N58="",P58=""),"",ROUND((P58-N58)/N58,4)) -> 0.0806 | R58: =IF(OR(N58="",P58=""),"",IF(Q58>Settings!$B$3/100,"UP",IF(Q58<-Settings!$B$3/100,"DOWN","FLAT"))) -> UP | S58: =IF(OR(N58="",P58="",J58=""),"",IF(OR(AND(J58="BUY",R58="UP"),AND(J58="SELL",R58="DOWN"),AND(J58="HOLD",R58="FLAT")),"YES","NO")) -> YES | T58: =IF(J58="","",IF(J58="BUY",1,IF(J58="SELL",-1,0))) -> 1 | U58: =IFERROR(IF(OR(J58="",N58="",P58=""),"",IF(T58=0,0,T58*Q58-Settings!$B$4/10000-IF(T58<0,Settings!$B$5/10000,0))),"") -> 0.0796 | V58: same as Q2; numbers look great; tone is optimistic and growth is seen and expected; good guidance so buy | W58: =IF($K58="","",$K58*60) -> 1800 | X58: =IF($A58="","",$A58&"|"&$C58&"|"&$D58) -> IBM|2025|Q4 | Y58: =IFERROR(IF($X58="","",INDEX(LLM_Data_Entry!$H$3:$H$548,MATCH($X58,INDEX(LLM_Data_Entry!$A$3:$A$548&"|"&LLM_Data_Entry!$C$3:$C$548&"|"&LLM_Data_Entry!$D$3:$D$548,0),0))),"") -> BUY | Z58: =IFERROR(IF($X58="","",INDEX(LLM_Data_Entry!$R$3:$R$548,MATCH($X58,INDEX(LLM_Data_Entry!$A$3:$A$548&"|"&LLM_Data_Entry!$C$3:$C$548&"|"&LLM_Data_Entry!$D$3:$D$548,0),0))),"") -> YES | AB58: price signal — only this window shows an abnormal move | AC58: IBM | AD58: 2026-01-28 | AE58: 290.3553 | AF58: 2026-01-29 | AG58: 313.7488 | AH58: 0.080568354 | AI58: UP | AJ58: YES | AK58: 0.079568 | AL58: =IF($A58="","",IFERROR(INDEX(Company_List!$G$3:$G$207,MATCH($A58,Company_List!$A$3:$A$207,0)),"unassigned")) -> P2 | AM58: Phase 2/IBM/Q4 2025 Earnings Call Transcript.pdf; Phase 2/IBM/Q4 2025 - numbers.pdf | AO58: whole bundle (Document = All) | AP58: =IF($A58="","",IF(COUNTIFS(LLM_Data_Entry!$A$3:$A$548,$A58)>0,"YES","NO")) -> YES | AQ58: =IF($A58="","",IF(COUNTIFS($A$3:$A58,$A58,$C$3:$C58,$C58,$D$3:$D58,$D58)=1,"YES","NO")) -> YES | AR58: =IF($A58="","",IF(AND($C58&"-"&$D58>=Settings!$B$19,$C58&"-"&$D58<=Settings!$B$20),"IN","OUT")) -> IN | AS58: =IF($A58="","",IF($F58="Financial Results","financials",IF($F58="Outlook/Guidance","guidance",IF($F58="Transcript Q&A","qanda",IF($F58="","unrecorded",IF($E58="All","full",IF($E58="","unrecorded",LOWER($E58)&" only"))))))) -> full | AT58: =IF(AND(OR($J58="BUY",$J58="SELL"),ISNUMBER($U58)),$U58,"") -> 0.0796 | AU58: =IF(AND(OR($J58="BUY",$J58="SELL"),ISNUMBER($AK58)),$AK58,"") -> 0.079568 | AV58: =IF(ISNUMBER($AT58),ABS(IF(ISNUMBER($I58),$I58,0)-Settings!$B$24),"") -> 0.5 | AW58: =IF(ISNUMBER($AV58),$AV58*$AT58,"") -> 0.0398 | AX58: =IF(ISNUMBER($AU58),ABS(IF(ISNUMBER($I58),$I58,0)-Settings!$B$24),"") -> 0.5 | AY58: FROZEN | AZ58: =IF($A58="","",IFERROR(INDEX(Company_List!$H$3:$H$207,MATCH($A58,Company_List!$A$3:$A$207,0)),"unassigned")) -> Information Technology | BC58: =IF($A58="","",IF(COUNTIFS($A$3:$A58,$A58,$C$3:$C58,$C58,$D$3:$D58,$D58,$G$3:$G58,$G58)=1,1,0)) -> 1 | BG58: no | BK58: =IF(OR($H58<>"Human",$S58="",$J58="",$Y58="",$Z58=""),"",IF(EXACT(UPPER($J58),UPPER($Y58)),1,0)) -> 1 | BL58: assumed - no rater record | BM58: 2 | BN58: The Motley Fool | BO58: free to read, copyright asserted | BP58: no | BQ58: no | BS58: YES
A59: IBM | B59: =IF(A59="","",_xlfn.XLOOKUP(A59, Company_List!$A:$A, Company_List!$B:$B, "")) -> IBM | C59: 2026 | D59: Q1 | E59: All | F59: All | G59: Meriem | H59: Human | I59: 0.2 | J59: =IF(OR(I59="",Settings!$B$6=""),"",IF(I59>Settings!$B$6,"BUY",IF(I59<-Settings!$B$6,"SELL","HOLD"))) -> HOLD | K59: 42 | L59: 46134 | M59: 46134 | N59: 251.86 | O59: 46135 | P59: 232.27 | Q59: =IF(OR(N59="",P59=""),"",ROUND((P59-N59)/N59,4)) -> -0.0778 | R59: =IF(OR(N59="",P59=""),"",IF(Q59>Settings!$B$3/100,"UP",IF(Q59<-Settings!$B$3/100,"DOWN","FLAT"))) -> DOWN | S59: =IF(OR(N59="",P59="",J59=""),"",IF(OR(AND(J59="BUY",R59="UP"),AND(J59="SELL",R59="DOWN"),AND(J59="HOLD",R59="FLAT")),"YES","NO")) -> NO | T59: =IF(J59="","",IF(J59="BUY",1,IF(J59="SELL",-1,0))) -> 0 | U59: =IFERROR(IF(OR(J59="",N59="",P59=""),"",IF(T59=0,0,T59*Q59-Settings!$B$4/10000-IF(T59<0,Settings!$B$5/10000,0))),"") -> 0 | V59: numbers are great but Middle East worries even though didnt affect Q1 as we saw higher growth in the ME than in decades so uncertainty but some confidence so hold | W59: =IF($K59="","",$K59*60) -> 2520 | X59: =IF($A59="","",$A59&"|"&$C59&"|"&$D59) -> IBM|2026|Q1 | Y59: =IFERROR(IF($X59="","",INDEX(LLM_Data_Entry!$H$3:$H$548,MATCH($X59,INDEX(LLM_Data_Entry!$A$3:$A$548&"|"&LLM_Data_Entry!$C$3:$C$548&"|"&LLM_Data_Entry!$D$3:$D$548,0),0))),"") -> HOLD | Z59: =IFERROR(IF($X59="","",INDEX(LLM_Data_Entry!$R$3:$R$548,MATCH($X59,INDEX(LLM_Data_Entry!$A$3:$A$548&"|"&LLM_Data_Entry!$C$3:$C$548&"|"&LLM_Data_Entry!$D$3:$D$548,0),0))),"") -> NO | AB59: price signal — both moved; this one dominates | AC59: IBM | AD59: 2026-04-22 | AE59: 250.0199 | AF59: 2026-04-23 | AG59: 230.573 | AH59: -0.077781289 | AI59: DOWN | AJ59: NO | AK59: 0 | AL59: =IF($A59="","",IFERROR(INDEX(Company_List!$G$3:$G$207,MATCH($A59,Company_List!$A$3:$A$207,0)),"unassigned")) -> P2 | AM59: Phase 2/IBM/Q1 2026 Earnings Call Transcript.pdf; Phase 2/IBM/Q1 2026 0 numbers.pdf | AO59: whole bundle (Document = All) | AP59: =IF($A59="","",IF(COUNTIFS(LLM_Data_Entry!$A$3:$A$548,$A59)>0,"YES","NO")) -> YES | AQ59: =IF($A59="","",IF(COUNTIFS($A$3:$A59,$A59,$C$3:$C59,$C59,$D$3:$D59,$D59)=1,"YES","NO")) -> YES | AR59: =IF($A59="","",IF(AND($C59&"-"&$D59>=Settings!$B$19,$C59&"-"&$D59<=Settings!$B$20),"IN","OUT")) -> IN | AS59: =IF($A59="","",IF($F59="Financial Results","financials",IF($F59="Outlook/Guidance","guidance",IF($F59="Transcript Q&A","qanda",IF($F59="","unrecorded",IF($E59="All","full",IF($E59="","unrecorded",LOWER($E59)&" only"))))))) -> full | AT59: =IF(AND(OR($J59="BUY",$J59="SELL"),ISNUMBER($U59)),$U59,"") | AU59: =IF(AND(OR($J59="BUY",$J59="SELL"),ISNUMBER($AK59)),$AK59,"") | AV59: =IF(ISNUMBER($AT59),ABS(IF(ISNUMBER($I59),$I59,0)-Settings!$B$24),"") | AW59: =IF(ISNUMBER($AV59),$AV59*$AT59,"") | AX59: =IF(ISNUMBER($AU59),ABS(IF(ISNUMBER($I59),$I59,0)-Settings!$B$24),"") | AY59: FROZEN | AZ59: =IF($A59="","",IFERROR(INDEX(Company_List!$H$3:$H$207,MATCH($A59,Company_List!$A$3:$A$207,0)),"unassigned")) -> Information Technology | BC59: =IF($A59="","",IF(COUNTIFS($A$3:$A59,$A59,$C$3:$C59,$C59,$D$3:$D59,$D59,$G$3:$G59,$G59)=1,1,0)) -> 1 | BG59: no | BK59: =IF(OR($H59<>"Human",$S59="",$J59="",$Y59="",$Z59=""),"",IF(EXACT(UPPER($J59),UPPER($Y59)),1,0)) -> 1 | BL59: assumed - no rater record | BM59: 2 | BN59: The Motley Fool | BO59: free to read, copyright asserted | BP59: no | BQ59: no | BS59: YES
